Workbook
Name __bookmark_1: '[2]1502000 FX'!#REF!
Name __bookmark_1: '[2]1502000 FX'!#REF!
Name __bookmark_1: '[2]1502000 FX'!#REF!
Name _FTE1: #REF!
Name _FTE1: #REF!
Name _FTE1: #REF!
Name _ORG1: #REF!
Name _ORG1: #REF!
Name _ORG1: #REF!
Name Additional_Costs_1_Cost: #REF!
Name Additional_Costs_1_Cost: #REF!
Name Additional_Costs_1_Cost: #REF!
Name Additional_Costs_2_Cost: #REF!
Name Additional_Costs_2_Cost: #REF!
Name Additional_Costs_2_Cost: #REF!
Name Additional_Costs_3_Cost: #REF!
Name Additional_Costs_3_Cost: #REF!
Name Additional_Costs_3_Cost: #REF!
Name Additional_Costs_4_Cost: #REF!
Name Additional_Costs_4_Cost: #REF!
Name Additional_Costs_4_Cost: #REF!
Name Additional_Costs_5_Cost: #REF!
Name Additional_Costs_5_Cost: #REF!
Name Additional_Costs_5_Cost: #REF!
Name Additional_Costs_6_Cost: #REF!
Name Additional_Costs_6_Cost: #REF!
Name Additional_Costs_6_Cost: #REF!
Name Allocated_Labor_Cost_per_Production_Man_Hour: #REF!
Name Allocated_Labor_Cost_per_Production_Man_Hour: #REF!
Name Allocated_Labor_Cost_per_Production_Man_Hour: #REF!
Name annex: #REF!
Name annex: #REF!
Name annex: #REF!
Name ANNEX1: #REF!
Name ANNEX1: #REF!
Name ANNEX1: #REF!
Name Area_of_Country_List: #REF!
Name Area_of_Country_List: #REF!
Name Area_of_Country_List: #REF!
Name AREA1: #REF!
Name AREA1: #REF!
Name AREA1: #REF!
Name ARRA_Compliant: #REF!
Name ARRA_Compliant: #REF!
Name ARRA_Compliant: #REF!
Name Ballast_Codes: #REF!
Name Ballast_Codes: #REF!
Name Ballast_Codes: #REF!
Name Ballast_Specs: #REF!
Name Ballast_Specs: #REF!
Name Ballast_Specs: #REF!
Name BASE_ST_MP: '[5]BASE WAGES & BENEFITS - ST'!$A$4:$AM$33
Name BASE_ST_TCNJ: '[5]BASE WAGES & BENEFITS - ST'!$A$258:$AN$295
Name BASE_ST_TCNP: '[5]BASE WAGES & BENEFITS - ST'!$A$38:$AM$253
Name BBB_Charge: #REF!
Name BBB_Charge: #REF!
Name BBB_Charge: #REF!
Name BBB_Labor_Charge: #REF!
Name BBB_Labor_Charge: #REF!
Name BBB_Labor_Charge: #REF!

Sheet CLIN 0001 Base Period RW
C1: Attachment J-0200000-17
C2: Exhibit Line Item Numbers - NAVSTA Mayport
C3: Contract No.: N6945025R0003
C4: CLIN 0001 - Recurring Work - Base Period
C5: Provide Prices for Recurring Work in accordance with Section C, Spec Item 3
C6: ELINs A001 through A014
A7: Customer | B7: Funding Source | C7: Category | D7: Sub-Category | E7: ELIN | F7: Sub-ELIN | G7: Annex/Sub-annex | H7: Spec Item | I7: Description | J7: Quantity | K7: Unit of Measure | L7: Unit Price | M7: Extended Price
A8: CNRSE | B8: Port Ops | C8: Port Operations | D8: Port Ops Equipment Work Order | E8: A001 | F8: A001AA | G8: 0600000 | H8: 3.1 | I8: Port Ops Equipment Work Order | J8: 20 | K8: EA
A9: CNRSE | B9: Port Ops | C9: Port Operations | D9: Recurring Work | E9: A001 | F9: A001AB | G9: 0600000 | H9: 3.2 | I9: Ship Movements - Berthing and Hotel Services | J9: 12 | K9: MO
A10: CNRSE | B10: CNRSE FP | C10: Facility Management | D10: Recurring Work | E10: A001 | F10: A001AC | G10: 1501000 | H10: 3.1 | I10: NAVFAC Maximo Data Entry | J10: 12 | K10: MO
A11: CNRSE | B11: CNRSE FP | C11: Facility Management | D11: Recurring Work | E11: A001 | F11: A001AD | G11: 1501000 | H11: 3.2 | I11: Infrastructure Condition Assessment Program (ICAP) Services | J11: 12 | K11: MO
A12: CNRSE | B12: CNRSE FP | C12: Facility Management | D12: Recurring Work | E12: A001 | F12: A001AE | G12: 1501000 | H12: 3.3 | I12: Technical Library Operations | J12: 12 | K12: MO
A13: CNRSE | B13: CNRSE ST-FAC | C13: Facility Investment | D13: E/U/R Work Orders | E13: A001 | F13: A001AF | G13: 1502000 | H13: 3.1 | I13: Emergency, Urgent and Routine (E/U/R) Work | J13: 3658 | K13: EA
A14: CNRSE | B14: CNRSE ST-FAC | C14: Facility Investment | D14: Recurring Work | E14: A001 | F14: A001AG | G14: 1502000 | H14: 3.2 | I14: Project Work Orders | J14: 50 | K14: EA
A15: CNRSE | B15: CNRSE ST-FAC | C15: Facility Investment | D15: Preventive Maintenance (PM) Program | E15: A001 | F15: A001AH | G15: 1502000 | H15: 3.3.1 | I15: Airfield Lighting Systems | J15: 12 | K15: MO
A16: CNRSE | B16: CNRSE ST-FAC | C16: Facility Investment | D16: Preventive Maintenance (PM) Program | E16: A001 | F16: A001AJ | G16: 1502000 | H16: 3.3.2 | I16: Auxiliary Generator Systems | J16: 12 | K16: MO
A17: CNRSE | B17: CNRSE ST-FAC | C17: Facility Investment | D17: Preventive Maintenance (PM) Program | E17: A001 | F17: A001AK | G17: 1502000 | H17: 3.3.3 | I17: Boiler and Unfired Pressure Vessel (UPV) Systems | J17: 12 | K17: MO
A18: CNRSE | B18: CNRSE ST-FAC | C18: Facility Investment | D18: Preventive Maintenance (PM) Program | E18: A001 | F18: A001AL | G18: 1502000 | H18: 3.3.4 | I18: Compressed Air Systems | J18: 12 | K18: MO
A19: CNRSE | B19: CNRSE ST-FAC | C19: Facility Investment | D19: Preventive Maintenance (PM) Program | E19: A001 | F19: A001AM | G19: 1502000 | H19: 3.3.5 | I19: Door and Gate Systems | J19: 12 | K19: MO
A20: CNRSE | B20: CNRSE ST-FAC | C20: Facility Investment | D20: Preventive Maintenance (PM) Program | E20: A001 | F20: A001AN | G20: 1502000 | H20: 3.3.6 | I20: Fire Protection Systems | J20: 12 | K20: MO
A21: CNRSE | B21: CNRSE ST-FAC | C21: Facility Investment | D21: Preventive Maintenance (PM) Program | E21: A001 | F21: A001AP | G21: 1502000 | H21: 3.3.7 | I21: Frequency Converter (400 HZ) Systems | J21: 12 | K21: MO
A22: CNRSE | B22: CNRSE ST-FAC | C22: Facility Investment | D22: Preventive Maintenance (PM) Program | E22: A001 | F22: A001AQ | G22: 1502000 | H22: 3.3.8 | I22: Galley Equipment and Systems | J22: 12 | K22: MO
A23: CNRSE | B23: CNRSE ST-FAC | C23: Facility Investment | D23: Preventive Maintenance (PM) Program | E23: A001 | F23: A001AR | G23: 1502000 | H23: 3.3.9 | I23: HVAC and Refrigeration Systems | J23: 12 | K23: MO
A24: CNRSE | B24: CNRSE ST-FAC | C24: Facility Investment | D24: Preventive Maintenance (PM) Program | E24: A001 | F24: A001AS | G24: 1502000 | H24: 3.3.10 | I24: Security Systems and Equipment | J24: 12 | K24: MO
A25: CNRSE | B25: CNRSE ST-FAC | C25: Facility Investment | D25: Preventive Maintenance (PM) Program | E25: A001 | F25: A001AT | G25: 1502000 | H25: 3.3.11 | I25: Uninterruptible Power Supplies (UPS) | J25: 12 | K25: MO
A26: CNRSE | B26: CNRSE ST-FAC | C26: Facility Investment | D26: Preventive Maintenance (PM) Program | E26: A001 | F26: A001AU | G26: 1502000 | H26: 3.3.12 | I26: Vertical Transportation Equipment (VTE) | J26: 12 | K26: MO
... A42: CNRSE | B42: CNRSE ST-FAC | C42: Facility Investment | D42: Other Recurring Services Program | E42: A001 | F42: A001BL | G42: 1502000 | H42: 3.5.11 | I42: Spot Coolers | J42: 12 | K42: MO
A43: CNRSE | B43: CNRSE ST-FAC | C43: Facility Investment | D43: Other (Swimming Pools) | E43: A001 | F43: A001BM | G43: 1503040 | H43: 3.1 | I43: Pool Operator Maintenance | J43: 12 | K43: MO
A44: CNRSE | B44: CNRSE ST-FAC | C44: Facility Investment | D44: Other (Swimming Pools) | E44: A001 | F44: A001BN | G44: 1503040 | H44: 3.2 | I44: Preventive Maintenance (PM) Program | J44: 12 | K44: MO
A45: CNRSE | B45: CNRSE FX | C45: Facility Investment | D45: Other (Swimming Pools) | E45: A001 | F45: A001BP | G45: 1503040 | H45: 3.3 | I45: Water Treatment | J45: 12 | K45: MO
A46: CNRSE | B46: CNRSE UT | C46: Utilities Management | D46: Utility Operations Support | E46: A001 | F46: A001BQ | G46: 1601000 | H46: 3.1 | I46: Utility Operations Support | J46: 12 | K46: MO
A47: CNRSE | B47: CNRSE UT | C47: Utilities Management | D47: Recurring Work | E47: A001 | F47: A001BR | G47: 1601000 | H47: 3.2 | I47: Utility Infrastructure Condition Assessment Program (UICAP) Support | J47: 12 | K47: MO
A48: CNRSE | B48: CNRSE UT | C48: Utilities Management | D48: Recurring Work | E48: A001 | F48: A001BS | G48: 1601000 | H48: 3.3 | I48: Operation and Management of Facility Related Control Systems (FRCS) | J48: 12 | K48: MO
A49: CNRSE | B49: CNRSE UT | C49: Utilities Management | D49: Recurring Work | E49: A001 | F49: A001BT | G49: 1601000 | H49: 3.4 | I49: NAVFAC Maximo Data Entry | J49: 12 | K49: MO
A50: CNRSE | B50: CNRSE UT | C50: Electrical | D50: Recurring Work | E50: A001 | F50: A001BU | G50: 1602000 | H50: 3.1 | I50: Operate Electrical Power Transmission and Distribution Systems | J50: 12 | K50: MO
A51: CNRSE | B51: CNRSE ST | C51: Electrical | D51: E/U/R Work Orders | E51: A001 | F51: A001BV | G51: 1602000 | H51: 3.2 | I51: Emergency, Urgent and Routine (E/U/R) Work | J51: 220 | K51: EA
A52: CNRSE | B52: CNRSE ST | C52: Electrical | D52: Recurring Work | E52: A001 | F52: A001BW | G52: 1602000 | H52: 3.3 | I52: Preventive Maintenance (PM) Program | J52: 12 | K52: MO
A53: CNRSE | B53: CNRSE UT | C53: Electrical | D53: Other Recurring Services Program | E53: A001 | F53: A001BX | G53: 1602000 | H53: 3.4 | I53: Other Recurring Services | J53: 12 | K53: MO
A54: CNRSE | B54: CNRSE UT | C54: Electrical | D54: Other Recurring Services Program | E54: A001 | F54: A001BY | G54: 1602000 | H54: 3.5 | I54: Utility Right of Way Clearance | J54: 12 | K54: MO
A55: CNRSE | B55: CNRSE TR | C55: Transportation | D55: Operations | E55: A001 | F55: A001BZ | G55: 1700000 | H55: 3.1.1 | I55: WHE/MHE/NTVE Services | J55: 12 | K55: MO
A56: CNRSE | B56: CNRSE TR | C56: Transportation | D56: Operations | E56: A001 | F56: A001CA | G56: 1700000 | H56: 3.1.2 | I56: Fuel Delivery Services | J56: 12 | K56: MO
A57: CNRSE | B57: CNRSE TR | C57: Transportation | D57: Support Services | E57: A001 | F57: A001CB | G57: 1700000 | H57: 3.2.1 | I57: Dispatching Services | J57: 12 | K57: MO
A58: CNRSE | B58: CNRSE TR | C58: Transportation | D58: Support Services | E58: A001 | F58: A001CC | G58: 1700000 | H58: 3.2.2 | I58: Non-Government Owned Leased Vehicles | J58: 12 | K58: MO
A59: CNRSE | B59: CNRSE TR | C59: Transportation | D59: Maintenance of NTVE | E59: A001 | F59: A001CD | G59: 1700000 | H59: 3.3.1.1 | I59: New and Reassigned Vehicles and Equipment Services | J59: 12 | K59: MO
A60: CNRSE | B60: CNRSE TR | C60: Transportation | D60: Maintenance of CESE | E60: A001 | F60: A001CE | G60: 1700000 | H60: 3.3.1.2 | I60: Preventive Maintenance, Inspection, Load Test and Certification of WHE, MHE and AWP | J60: 12 | K60: MO
A61: CNRSE | B61: CNRSE TR | C61: Transportation | D61: Maintenance of CESE | E61: A001 | F61: A001CF | G61: 1700000 | H61: 3.3.1.3 | I61: Preventive Maintenance Inspection of NTVE | J61: 12 | K61: MO
A62: CNRSE | B62: CNRSE TR | C62: Transportation | D62: Maintenance of CESE | E62: A001 | F62: A001CG | G62: 1700000 | H62: 3.3.1.4 | I62: Repair (NTVE, WHE, MHE and AWP) | J62: 12 | K62: MO
A63: CNRSE | B63: CNRSE TR | C63: Transportation | D63: Maintenance of CESE | E63: A001 | F63: A001CH | G63: 1700000 | H63: 3.3.1.5 | I63: NTVE Trouble Calls | J63: 150 | K63: EA
A64: CNRSE | B64: CNRSE TR | C64: Transportation | D64: Maintenance of CESE | E64: A001 | F64: A001CJ | G64: 1700000 | H64: 3.3.2 | I64: BSVE Accessories Installation and Removal | J64: 12 | K64: MO
A65: CNRSE | B65: CNRSE EC | C65: Environmental | D65: Recurring Work | E65: A001 | F65: A001CK | G65: 1800000 | H65: 3.1 | I65: Oil and Regulated Substance Spill Response and Cleanup Ashore | J65: 12 | K65: MO
A66: CNRSE | B66: CNRSE EC | C66: Environmental | D66: Recurring Work | E66: A001 | F66: A001CL | G66: 1800000 | H66: 3.2 | I66: Used Oil Management Services | J66: 12 | K66: MO
A67: CNRSE | B67: CNRSE EC | C67: Environmental | D67: Recurring Work | E67: A001 | F67: A001CM | G67: 1800000 | H67: 3.3 | I67: Storm Water Monitoring | J67: 12 | K67: MO
A68: CNRSE | B68: CNRSE ST-UH | C68: Facility Investment | D68: E/U/R Work Orders | E68: A001 | F68: A001CN | G68: 1502000 | H68: 3.1 | I68: Emergency, Urgent and Routine (E/U/R) Work | J68: 1350 | K68: EA
A69: CNRSE | B69: CNRSE ST-UH | C69: Facility Investment | D69: Preventive Maintenance (PM) Program | E69: A001 | F69: A001CP | G69: 1502000 | H69: 3.3.3 | I69: Boiler and Unfired Pressure Vessel (UPV) Systems | J69: 12 | K69: MO
A70: CNRSE | B70: CNRSE ST-UH | C70: Facility Investment | D70: Preventive Maintenance (PM) Program | E70: A001 | F70: A001CQ | G70: 1502000 | H70: 3.3.6 | I70: Fire Protection Systems | J70: 12 | K70: MO
A71: CNRSE | B71: CNRSE ST-UH | C71: Facility Investment | D71: Preventive Maintenance (PM) Program | E71: A001 | F71: A001CR | G71: 1502000 | H71: 3.3.9 | I71: HVAC and Refrigeration Systems | J71: 12 | K71: MO
A72: CNRSE | B72: CNRSE ST-UH | C72: Facility Investment | D72: Inspection, Testing, and Certification | E72: A001 | F72: A001CS | G72: 1502000 | H72: 3.4.1 | I72: Backflow Prevention Devices | J72: 12 | K72: MO
A73: CNRSE | B73: CNRSE ST-UH | C73: Facility Investment | D73: Inspection, Testing, and Certification | E73: A001 | F73: A001CT | G73: 1502000 | H73: 3.4.2 | I73: Boilers and UPVs | J73: 12 | K73: MO
A74: CNRSE | B74: CNRSE ST-UH | C74: Facility Investment | D74: Other Recurring Services Program | E74: A001 | F74: A001CU | G74: 1502000 | H74: 3.5.1 & 3.5.7 | I74: Boiler & HVAC Seasonal Startup and Shutdown | J74: 12 | K74: MO
A75: CNRSE | B75: CNRSE ST-UH | C75: Facility Investment | D75: Other Recurring Services Program | E75: A001 | F75: A001CV | G75: 1502000 | H75: 3.5.2 | I75: Boiler Systems Water Testing and Treatment Services | J75: 12 | K75: MO
A76: CNRSE | B76: CNRSE ST-UH | C76: Facility Investment | D76: Other Recurring Services Program | E76: A001 | F76: A001CW | G76: 1502000 | H76: 3.5.8 | I76: HVAC Water Testing and Treatment Services | J76: 12 | K76: MO
A77: CNRSE | B77: CNRSE ST-UH | C77: Facility Investment | D77: Other Recurring Services Program | E77: A001 | F77: A001CX | G77: 1502000 | H77: 3.5.9 | I77: HVAC Condenser Tube Inspections | J77: 12 | K77: MO
A78: CNRSE | B78: CNRSE ST-UH | C78: Facility Investment | D78: Other Recurring Services Program | E78: A001 | F78: A001CY | G78: 1502000 | H78: 3.5.3 | I78: Change of Occupancy Maintenance (COM) | J78: 50 | K78: EA
A79: CNRSE | B79: CNRSE ST-UH | C79: Facility Investment | D79: Other Recurring Services Program | E79: A001 | F79: A001CZ | G79: 1502000 | H79: 3.5.10 | I79: Lint Traps | J79: 12 | K79: MO
A80: CNRSE | B80: Family Housing | C80: Facility Invetment | D80: Preventive Maintenance (PM) Program | E80: A001 | F80: A001DA | G80: 1502000 | H80: 3.3.9 | I80: HVAC and Refrigeration Systems | J80: 12 | K80: MO
... A87: FRC VRT | B87: FRC VRT | C87: Transportation | D87: Maintenance (Government Owned) | E87: A002 | F87: A002AB | G87: 1700000 | H87: 3.3.1.4 | I87: Repair (NTVE, WHE, MHE and AWP) | J87: 12 | K87: MO
A88: FRC VRT | B88: FRC VRT | C88: Environmental | D88: Recurring Work | E88: A002 | F88: A002AC | G88: 1800000 | H88: 3.2 | I88: Used Oil Management Services | J88: 12 | K88: MO
A89: MCSF-BI | B89: MCSF-BI | C89: Facility Management | D89: Recurring Work | E89: A003 | F89: A003AA | G89: 1501000(MCSF-BI) | H89: 3.1,3.2,3.3 | I89: USMC Maximo, ICAP and Tech Library | J89: 12 | K89: MO
A90: MCSF-BI | B90: MCSF-BI | C90: Facility Investment - MCSF-BI | D90: E/U/R Work Orders | E90: A003 | F90: A003AB | G90: 1502000(MCSF-BI) | H90: 3.1 | I90: Emergency, Urgent and Routine (E/U/R) Work | J90: 750 | K90: EA
A91: MCSF-BI | B91: MCSF-BI | C91: Facility Investment - MCSF-BI | D91: Recurring Work | E91: A003 | F91: A003AC | G91: 1502000(MCSF-BI) | H91: 3.2 | I91: Urgent and Routine Project Work Orders | J91: 48 | K91: EA
A92: MCSF-BI | B92: MCSF-BI | C92: Facility Investment - MCSF-BI | D92: Preventive Maintenance (PM) Program | E92: A003 | F92: A003AD | G92: 1502000(MCSF-BI) | H92: 3.3.1 | I92: Auxiliary Generator Systems | J92: 12 | K92: MO
A93: MCSF-BI | B93: MCSF-BI | C93: Facility Investment - MCSF-BI | D93: Preventive Maintenance (PM) Program | E93: A003 | F93: A003AE | G93: 1502000(MCSF-BI) | H93: 3.3.2 | I93: Cathodic Protection | J93: 12 | K93: MO
A94: MCSF-BI | B94: MCSF-BI | C94: Facility Investment - MCSF-BI | D94: Preventive Maintenance (PM) Program | E94: A003 | F94: A003AF | G94: 1502000(MCSF-BI) | H94: 3.3.3 | I94: Compressed Air Systems | J94: 12 | K94: MO
A95: MCSF-BI | B95: MCSF-BI | C95: Facility Investment - MCSF-BI | D95: Preventive Maintenance (PM) Program | E95: A003 | F95: A003AG | G95: 1502000(MCSF-BI) | H95: 3.3.4 | I95: Facilities, Systems, and Equipment | J95: 12 | K95: MO
A96: MCSF-BI | B96: MCSF-BI | C96: Facility Investment - MCSF-BI | D96: Preventive Maintenance (PM) Program | E96: A003 | F96: A003AH | G96: 1502000(MCSF-BI) | H96: 3.3.5 | I96: Fire Protection Systems | J96: 12 | K96: MO
A97: MCSF-BI | B97: MCSF-BI | C97: Facility Investment - MCSF-BI | D97: Preventive Maintenance (PM) Program | E97: A003 | F97: A003AJ | G97: 1502000(MCSF-BI) | H97: 3.3.6 | I97: Irrigation Equipment and Systems | J97: 12 | K97: MO
A98: MCSF-BI | B98: MCSF-BI | C98: Facility Investment - MCSF-BI | D98: Preventive Maintenance (PM) Program | E98: A003 | F98: A003AK | G98: 1502000(MCSF-BI) | H98: 3.3.7 | I98: Unfired Pressure Vessels (UPVs) | J98: 12 | K98: MO
A99: MCSF-BI | B99: MCSF-BI | C99: Facility Investment - MCSF-BI | D99: Preventive Maintenance (PM) Program | E99: A003 | F99: A003AL | G99: 1502000(MCSF-BI) | H99: 3.3.8 | I99: Vertical Transportation Equipment (VTE) | J99: 12 | K99: MO
A100: MCSF-BI | B100: MCSF-BI | C100: Facility Investment - MCSF-BI | D100: Integrated Maintenance Program (IMP) | E100: A003 | F100: A003AM | G100: 1502000(MCSF-BI) | H100: 3.4.1 | I100: Blast, Paint, and Drying Systems | J100: 12 | K100: MO
A101: MCSF-BI | B101: MCSF-BI | C101: Facility Investment - MCSF-BI | D101: Integrated Maintenance Program (IMP) | E101: A003 | F101: A003AN | G101: 1502000(MCSF-BI) | H101: 3.4.2 | I101: Boiler Systems | J101: 12 | K101: MO
A102: MCSF-BI | B102: MCSF-BI | C102: Facility Investment - MCSF-BI | D102: Integrated Maintenance Program (IMP) | E102: A003 | F102: A003AP | G102: 1502000(MCSF-BI) | H102: 3.4.3 | I102: HVAC and Refrigeration Systems | J102: 12 | K102: MO
A103: MCSF-BI | B103: MCSF-BI | C103: Facility Investment - MCSF-BI | D103: Integrated Maintenance Program (IMP) | E103: A003 | F103: A003AQ | G103: 1502000(MCSF-BI) | H103: 3.4.4 | I103: Railroad Signal and Battery House Systems and Equipment | J103: 12 | K103: MO
... A119: MCSF-BI | B119: MCSF-BI | C119: Facility Investment - MCSF-BI | D119: Other Recurring Services Program | E119: A003 | F119: A003BG | G119: 1502000(MCSF-BI) | H119: 3.6.10 | I119: Fuel Storage Tanks and Berms | J119: 12 | K119: MO
A120: MCSF-BI | B120: MCSF-BI | C120: Custodial - MCSF-BI | D120: Recurring Work | E120: A003 | F120: A003BH | G120: 1503010(MCSF-BI) | H120: 3.1 | I120: Scheduled Services | J120: 12 | K120: MO
A121: MCSF-BI | B121: MCSF-BI | C121: Custodial - MCSF-BI | D121: Recurring Work | E121: A003 | F121: A003BJ | G121: 1503010(MCSF-BI) | H121: 3.2 | I121: Custodial Service Orders | J121: 12 | K121: EA
A122: MCSF-BI | B122: MCSF-BI | C122: Pest Control - MCSF-BI | D122: Recurring Work | E122: A003 | F122: A003BK | G122: 1503020(MCSF-BI) | H122: 3.1 | I122: Scheduled Pest Control Services | J122: 12 | K122: MO
A123: MCSF-BI | B123: MCSF-BI | C123: Pest Control - MCSF-BI | D123: Recurring Work | E123: A003 | F123: A003BL | G123: 1503020(MCSF-BI) | H123: 3.2 | I123: Pest Control Service Orders | J123: 100 | K123: EA
A124: MCSF-BI | B124: MCSF-BI | C124: Pest Control - MCSF-BI | D124: Recurring Work | E124: A003 | F124: A003BM | G124: 1503020(MCSF-BI) | H124: 3.3 | I124: Pest Management Reporting | J124: 12 | K124: MO
A125: MCSF-BI | B125: MCSF-BI | C125: Integrated Solid Waste Management - MCSF-BI | D125: Recurring Work | E125: A003 | F125: A003BN | G125: 1503030(MCSF-BI) | H125: 3 | I125: Recurring Work ISWM | J125: 12 | K125: MO
A126: MCSF-BI | B126: MCSF-BI | C126: Grounds Maintenance and Landscaping - MCSF-BI | D126: Recurring Work | E126: A003 | F126: A003BP | G126: 1503050(MCSF-BI) | H126: 3.1 | I126: Improved Grounds | J126: 12 | K126: MO
A127: MCSF-BI | B127: MCSF-BI | C127: Grounds Maintenance and Landscaping - MCSF-BI | D127: Recurring Work | E127: A003 | F127: A003BQ | G127: 1503050(MCSF-BI) | H127: 3.2 | I127: Operational Areas | J127: 12 | K127: MO
A128: MCSF-BI | B128: MCSF-BI | C128: Grounds Maintenance and Landscaping - MCSF-BI | D128: Recurring Work | E128: A003 | F128: A003BR | G128: 1503050(MCSF-BI) | H128: 3.3 | I128: Storm Drainage Systems | J128: 12 | K128: MO
A129: MCSF-BI | B129: MCSF-BI | C129: Grounds Maintenance and Landscaping - MCSF-BI | D129: Recurring Work | E129: A003 | F129: A003BS | G129: 1503050(MCSF-BI) | H129: 3.4 | I129: Street Sweeping | J129: 12 | K129: MO
A130: MCSF-BI | B130: MCSF-BI | C130: Grounds Maintenance and Landscaping - MCSF-BI | D130: Recurring Work | E130: A003 | F130: A003BT | G130: 1503050(MCSF-BI) | H130: 3.5 | I130: Grounds Maintenance Service Orders | J130: 12 | K130: EA
A131: MCSF-BI | B131: MCSF-BI | C131: Environmental - MCSF-BI | D131: Recurring Work | E131: A003 | F131: A003BU | G131: 1800000(MCSF-BI) | H131: 3.1 | I131: Sampling, Field Testing and Laboratory Services | J131: 12 | K131: MO
... A136: MCSF-BI | B136: MCSF-BI | C136: Environmental - MCSF-BI | D136: Recurring Work | E136: A003 | F136: A003BZ | G136: 1800000(MCSF-BI) | H136: 3.6 | I136: Inspection of POL Tanks and Systems | J136: 12 | K136: MO
A137: NCIS | B137: NCIS | C137: Facility Investment | D137: Preventive Maintenance (PM) Program | E137: A004 | F137: A004AA | G137: 1502000 | H137: 3.3.10 | I137: Security Systems and Equipment | J137: 12 | K137: MO
A138: FLCJ | B138: FLCJ | C138: Facility Investment | D138: E/U/R Work Orders | E138: A005 | F138: A005AA | G138: 1502000 | H138: 3.1 | I138: Emergency, Urgent and Routine (E/U/R) Work | J138: 50 | K138: EA
A139: FLCJ | B139: FLCJ | C139: Facility Investment | D139: Recurring Work | E139: A005 | F139: A005AB | G139: 1502000 | H139: 3.2 | I139: Project Work Orders | J139: 10 | K139: EA
A140: FLCJ | B140: FLCJ | C140: Transportation | D140: Maintenance (Government Owned) | E140: A005 | F140: A005AC | G140: 1700000 | H140: 3.3.1.2 | I140: Preventive Maintenance, Inspection, Load Test and Certification of WHE, MHE and AWP | J140: 12 | K140: MO
...

Sheet CLIN 0002 Base Period N-RW
B1: Attachment J-0200000-17
B2: Exhibit Line Item Numbers - NAVSTA Mayport
B3: Contract No.: N6945025R0003
B5: CLIN 0002 - Non-Recurring Work - Base Period
B6: Provide Prices for Recurring Work in accordance with Section C, Spec Item 4
B7: ELINs A700 through A718
A8: ELIN | B8: Product Name (120 Characters) | C8: Description Extended | D8: Estimated Quantity | E8: Unit of Measure | F8: Unit Price | G8: Extended Price
A9: A700 | B9: Unit Priced Labor Hour Work - MUST BE NEGOTIATED BY KO. | C9: The Contractor shall perform all UPL work in accordance with the scope and delivery schedule negotiated per each task order. Refer to: Section C, Annex 0200000 Managmenent and Administration, Specification Item 2.15.2 Unit Priced Labor (UPL)Work (Negotiated) for description of UPL Work. Refer to: Section J, Annex 0200000 Managmenent and Administration, Attachment J-0200000-01 Definitions and Acronyms for description of Unit Priced Labor (UPL) Hour and Universal Equipment. Task order completion times will be specified on each task order. For self-performed work: the unit price proposed for Sub-ELIN A700AA will be used to determine the labor cost to the Governent. For subcontracted labor: the FBR proposed for Sub-ELIN A700AB will be used to determine the labor cost to the Governmnet. The estimated quantity of each Sub-ELIN is used to establish the ELIN Extended Price. During administration the labor Sub-ELINs may be used in any combination and quantity provided the ELIN extended price is not exceeded. The contract will not be modified to re-allocate capacity among labor SLINs. | D9: =G10+G11 -> 0 | E9: DO | F9: 1
A10: A700AA | B10: Self-Performed Unit Priced Labor Hour Work - MUST BE NEGOTIATED BY KO. | C10: The Contractor shall self-perform all UPL work in accordance with the scope and delivery schedule negotiated per each task order. Refer to: Section C, Annex 0200000 Managmenent and Administration, Specification Item 2.15.2 Unit Priced Labor (UPL)Work (Negotiated) for description of UPL Work. Refer to: Section J, Annex 0200000 Managmenent and Administration, Attachment J-0200000-01 Definitions and Acronyms for description of Unit Priced Labor (UPL) Hour and Universal Equipment. | D10: 16000 | E10: LH
A11: A700AB | B11: Subcontractor Labor (Fixed Burden Rate) - MUST BE NEGOTIATED BY KO. | C11: The Contractor shall perform management and oversight of subcontracted non-recurring work in accordance with the scope and delivery schedule negotiated per each task order. Refer to: Section C, Annex 0200000 Management and Administration, Specification Item 2.15.2.1.2 Subcontractor Requirements description of Sub. Refer to: Section J, Annex 0200000 Management and Administration, Attachment J-0200000-01 Definitions and Acronyms for definition of Sub-Contractor Fixed Burden Rate. The estimated quantity (in dollars) is provided. A Fixed Burdened Rate (FBR) shall be entered in the Unit Price column. The FBR shall include all direct and indirect factors for management and oversight of subcontracted non-recurring work. Similar to FBR example in J-0200000-01, if a 15% markup is the Contractor's proposed FBR, the Unit Price should be $1.15. During performance, if the lowest subcontractor labor proposal is $1,000.00 and the FBR is $1.15, the labor cost to the Government will be $1,150.00. (DO - Dollars). | D11: 1600000 | E11: DO
A12: A701 | B12: Material and Equipment - MUST BE NEGOTIATED BY KO. | C12: Provide all materials and construction equipment to perform Unit Priced Labor work per the scope and delivery schedule specified in the order. Pre-expended bin supplies and materials will not be included in the list of materials since the cost for these items were included in the labor hour unit price bid. Material prices provided by the Contractor shall be the lowest price available considering the availability of materials and the time constraints of the job. The direct material price shall be adjusted by all discounts and rebates for core value or salvage value that accrue to the Contractor. Contractor owned equipment rental rates shall be based on calculations set forth in US Army Corp of Engineers “Construction Equipment Ownership and Operating Expense Schedule (EP 1110-1-8 (Vol. 11) July 03 or latest revision) Chapter 2. The estitmate quantity (in dollars) is provided. A Fixed burdened rate (FBR) shall be entered in the Unit Price column. The FBR shall include factors for ordering, handling, and stockpiling materials and repair parts. Similar to FBR example in J-0200000-01, if a 10% markup is the Contractor's proposed FBR, the Unit Price should be $1.10. When multiplying the proposed Unit Price by the Estimated Quantity, the Extended Price should be During administration, if the vendor's invoice on material is $1,000.00 and the unit price is $1.10, the cost of the material to the government will be $1,050.00. (DO - Dollars) | D12: 2000000 | E12: DO
A13: A702 | B13: Category I Calls - MUST BE NEGOTIATED BY KO. | C13: The Contractor shall perform Category I Calls to accomplish any work identified within the entire boundary of the installation and will include a wide variety of work. Category I Calls shall be completed within two weeks of receipt of call order, unless otherwise agreed to by the customer and contractor and annotated on the CAT call request. As part of the Category I Call, the Contractor has full responsibility for any work identified up to the Category I Call Threshold of $5,000 in direct labor and direct material, per Category I Call. A Blanket Task Order (BTO) may be issued on a DD Form 1155 with a Not To Exceed (NTE) quantity and value for Non-recurring Work Category Calls. | D13: 115 | E13: EA
A14: A703 | B14: Category II Calls - MUST BE NEGOTIATED BY KO. | C14: The Contractor shall perform Category II Calls to accomplish any work identified within the entire boundary of the installation and will include a wide variety of work. Category II Calls shall be completed within three weeks of receipt of call order, unless otherwise agreed to by the customer and contractor and annotated on the CAT call request. As part of the Category II Call, the Contractor has full responsibility for any work identified up to the Category II Call Threshold of $7,500 in direct labor and direct material, per Category II Call. A Blanket Task Order (BTO) may be issued on a DD Form 1155 with a Not To Exceed (NTE) quantity and value for Non-recurring Work Category Calls. | D14: 130 | E14: EA
A15: A704 | B15: Category III Calls - MUST BE NEGOTIATED BY KO. | C15: The Contractor shall perform Category III Calls to accomplish any work identified within the entire boundary of the installation and will include a wide variety of work. Category III Calls shall be completed within 30 days of receipt of call order, unless otherwise agreed to by the customer and contractor and annotated on the CAT call request. As part of the Category III Call, the Contractor has full responsibility for any work identified up to the Category III Call Threshold of $10,000 in direct labor and direct material, per Category III Call. A Blanket Task Order (BTO) may be issued on a DD Form 1155 with a Not To Exceed (NTE) quantity and value for Non-recurring Work Category Calls. | D15: 95 | E15: EA
A16: A705 | B16: Category IV Calls - MUST BE NEGOTIATED BY KO. | C16: The Contractor shall perform Category IV Calls to accomplish any work identified within the entire boundary of the installation and will include a wide variety of work. Category IV Calls shall be completed within 30 days of receipt of call order, unless otherwise agreed to by the customer and contractor and annotated on the CAT call request. As part of the Category IV Call, the Contractor has full responsibility for any work identified up to the Category IV Call Threshold of $12,500 in direct labor and direct material, per Category IV Call. A Blanket Task Order (BTO) may be issued on a DD Form 1155 with a Not To Exceed (NTE) quantity and value for Non-recurring Work Category Calls. | D16: 50 | E16: EA
A17: A706 | B17: Category V Calls - MUST BE NEGOTIATED BY KO. | C17: The Contractor shall perform Category V Calls to accomplish any work identified within the entire boundary of the installation and will include a wide variety of work. Category V Calls shall be completed within 30 days of receipt of call order, unless otherwise agreed to by the customer and contractor and annotated on the CAT call request. As part of the Category V Call, the Contractor has full responsibility for any work identified up to the Category V Call Threshold of $15,000 in direct labor and direct material, per Category V Call. A Blanket Task Order (BTO) may be issued on a DD Form 1155 with a Not To Exceed (NTE) quantity and value for Non-recurring Work Category Calls. | D17: 40 | E17: EA
A18: A707 | B18: Category VI Calls - MUST BE NEGOTIATED BY KO. | C18: The Contractor shall perform Category VI Calls to accomplish any work identified within the entire boundary of the installation and will include a wide variety of work. Category VI Calls shall be completed within 30 days of receipt of call order, unless otherwise agreed to by the customer and contractor and annotated on the CAT call request. As part of the Category VI Call, the Contractor has full responsibility for any work identified up to the Category VI Call Threshold of $17,500 in direct labor and direct material, per Category VI Call. A Blanket Task Order (BTO) may be issued on a DD Form 1155 with a Not To Exceed (NTE) quantity and value for Non-recurring Work Category Calls. | D18: 30 | E18: EA
A19: A708 | B19: Category VII Calls - MUST BE NEGOTIATED BY KO. | C19: The Contractor shall perform Category VII Calls to accomplish any work identified within the entire boundary of the installation and will include a wide variety of work. Category VII Calls shall be completed within 30 days of receipt of call order, unless otherwise agreed to by the customer and contractor and annotated on the CAT call request. As part of the Category VII Call, the Contractor has full responsibility for any work identified up to the Category VII Call Threshold of $20,000 in direct labor and direct material, per Category VII Call. A Blanket Task Order (BTO) may be issued on a DD Form 1155 with a Not To Exceed (NTE) quantity and value for Non-recurring Work Category Calls. | D19: 20 | E19: EA
A20: A709 | B20: Water Damage Removal available on FEDMALL | C20: The Contractor shall carefully remove and dispose of damaged interior finishes to include drywall, carpeting, etc. to prevent further damage or mold/mildew development in the event of water intrusion into a facility. In addition to the removal of the interior finishes, the Contractor shall dry the effected areas by providing dehumidifaction and airflow to remove any moisture from the space. Work shall begin within 12 hours of notification. Task order completion times will be specified on each task order. | D20: 20000 | E20: SF
A21: A710 | B21: Temporary Roof Repairs available on FEDMALL | C21: The Contractor shall provide all labor, material, and equipment to perform temporary roof repairs (i.e. tarping, roof patches, polyethylene film, etc.) to minimize water intrusion into a facility. Roof repairs shall be sufficient to last for a period no less than six months before requiring replacement or further repair.Within six months from the date of the original installation, the Contractor shall provide repairs and maintenance of the temporary repair at no additional cost to the Government. Work shall begin within 12 hours of notification. Task order completion times will be specified on each task order. | D21: 30000 | E21: SF
... A29: A718 | B29: Blount Island Shoreline Cleanup available on FEDMALL | C29: The Contractor shall perfrome shore cleanup, following the MCSF-BI Integrated Natural Resources Management Plan (INRMP). The shoreline clean up covers approximately 5 acres, and includes removal of debris, separation of recycling and not recycling materials, and proper disposal of the removed materials. The Contractor shall submit a report to the contracting Officer within 2 days after each service. Work shall begin within 12 hours of notification. | D29: 2 | E29: EA
A30: Total Non-recurring Work - Base Period:

Sheet CLIN 0003 Base Water RW
B1: Attachment J-0200000-17
B2: Exhibit Line Item Numbers - NAVSTA Mayport
B3: Contract No.: N6945025R0003
B6: CLIN 0003 - UT Recurring Work - Base Period
B7: Provide Prices for Recurring Work in accordance with Section C, Spec Item 3
B8: ELIN A015
A9: Customer/ Program | B9: Category | C9: Sub-Category | D9: ELIN | E9: Sub-ELIN | F9: Annex/Sub-annex | G9: Spec Item | H9: Description | I9: Quantity | J9: Unit of Measure | K9: Unit Price | L9: Extended Price
A10: CNRSE UT | B10: Water | C10: Recurring Services | D10: A015 | E10: A015AA | F10: 1606000 | G10: 3.1 | H10: Operation | I10: 12 | J10: MO
A11: CNRSE ST | B11: Water | C11: E/U/R Work Orders | D11: A015 | E11: A015AC | F11: 1606000 | G11: 3.2.2 | H11: E/U/R Work Orders | I11: 80 | J11: EA
A12: CNRSE ST | B12: Water | C12: Recurring Services | D12: A015 | E12: A015AE | F12: 1606000 | G12: 3.3 | H12: Preventive Maintenance (PM) | I12: 12 | J12: MO
A13: CNRSE UT | B13: Water | C13: Recurring Services | D13: A015 | E13: A015AF | F13: 1606000 | G13: 3.4 | H13: Inspection, Testing, and Certification of Fire Hydrants | I13: 12 | J13: MO

Sheet CLIN 0004 1st Period Opt RW
C1: Attachment J-0200000-17
C2: Exhibit Line Item Numbers - NAVSTA Mayport
C3: Contract No.: N6945025R0003
C4: CLIN 0004 - Recurring Work - First Option Period
C5: Provide Prices for Recurring Work in accordance with Section C, Spec Item 3
C6: ELINs B001 through B014
A7: Customer | B7: Funding Source | C7: Category | D7: Sub-Category | E7: ELIN | F7: Sub-ELIN | G7: Annex/Sub-annex | H7: Spec Item | I7: Description | J7: Quantity | K7: Unit of Measure | L7: Unit Price | M7: Extended Price
A8: CNRSE | B8: Port Ops | C8: Port Operations | D8: Port Ops Equipment Work Order | E8: B001 | F8: B001AA | G8: 0600000 | H8: 3.1 | I8: Port Ops Equipment Work Order | J8: 20 | K8: EA
A9: CNRSE | B9: Port Ops | C9: Port Operations | D9: Recurring Work | E9: B001 | F9: B001AB | G9: 0600000 | H9: 3.2 | I9: Ship Movements - Berthing and Hotel Services | J9: 12 | K9: MO
A10: CNRSE | B10: CNRSE FP | C10: Facility Management | D10: Recurring Work | E10: B001 | F10: B001AC | G10: 1501000 | H10: 3.1 | I10: NAVFAC Maximo Data Entry | J10: 12 | K10: MO
A11: CNRSE | B11: CNRSE FP | C11: Facility Management | D11: Recurring Work | E11: B001 | F11: B001AD | G11: 1501000 | H11: 3.2 | I11: Infrastructure Condition Assessment Program (ICAP) Services | J11: 12 | K11: MO
A12: CNRSE | B12: CNRSE FP | C12: Facility Management | D12: Recurring Work | E12: B001 | F12: B001AE | G12: 1501000 | H12: 3.3 | I12: Technical Library Operations | J12: 12 | K12: MO
A13: CNRSE | B13: CNRSE ST-FAC | C13: Facility Investment | D13: E/U/R Work Orders | E13: B001 | F13: B001AF | G13: 1502000 | H13: 3.1 | I13: Emergency, Urgent and Routine (E/U/R) Work | J13: 3658 | K13: EA
A14: CNRSE | B14: CNRSE ST-FAC | C14: Facility Investment | D14: Recurring Work | E14: B001 | F14: B001AG | G14: 1502000 | H14: 3.2 | I14: Project Work Orders | J14: 50 | K14: EA
A15: CNRSE | B15: CNRSE ST-FAC | C15: Facility Investment | D15: Preventive Maintenance (PM) Program | E15: B001 | F15: B001AH | G15: 1502000 | H15: 3.3.1 | I15: Airfield Lighting Systems | J15: 12 | K15: MO
A16: CNRSE | B16: CNRSE ST-FAC | C16: Facility Investment | D16: Preventive Maintenance (PM) Program | E16: B001 | F16: B001AJ | G16: 1502000 | H16: 3.3.2 | I16: Auxiliary Generator Systems | J16: 12 | K16: MO
A17: CNRSE | B17: CNRSE ST-FAC | C17: Facility Investment | D17: Preventive Maintenance (PM) Program | E17: B001 | F17: B001AK | G17: 1502000 | H17: 3.3.3 | I17: Boiler and Unfired Pressure Vessel (UPV) Systems | J17: 12 | K17: MO
A18: CNRSE | B18: CNRSE ST-FAC | C18: Facility Investment | D18: Preventive Maintenance (PM) Program | E18: B001 | F18: B001AL | G18: 1502000 | H18: 3.3.4 | I18: Compressed Air Systems | J18: 12 | K18: MO
A19: CNRSE | B19: CNRSE ST-FAC | C19: Facility Investment | D19: Preventive Maintenance (PM) Program | E19: B001 | F19: B001AM | G19: 1502000 | H19: 3.3.5 | I19: Door and Gate Systems | J19: 12 | K19: MO
A20: CNRSE | B20: CNRSE ST-FAC | C20: Facility Investment | D20: Preventive Maintenance (PM) Program | E20: B001 | F20: B001AN | G20: 1502000 | H20: 3.3.6 | I20: Fire Protection Systems | J20: 12 | K20: MO
A21: CNRSE | B21: CNRSE ST-FAC | C21: Facility Investment | D21: Preventive Maintenance (PM) Program | E21: B001 | F21: B001AP | G21: 1502000 | H21: 3.3.7 | I21: Frequency Converter (400 HZ) Systems | J21: 12 | K21: MO
A22: CNRSE | B22: CNRSE ST-FAC | C22: Facility Investment | D22: Preventive Maintenance (PM) Program | E22: B001 | F22: B001AQ | G22: 1502000 | H22: 3.3.8 | I22: Galley Equipment and Systems | J22: 12 | K22: MO
A23: CNRSE | B23: CNRSE ST-FAC | C23: Facility Investment | D23: Preventive Maintenance (PM) Program | E23: B001 | F23: B001AR | G23: 1502000 | H23: 3.3.9 | I23: HVAC and Refrigeration Systems | J23: 12 | K23: MO
A24: CNRSE | B24: CNRSE ST-FAC | C24: Facility Investment | D24: Preventive Maintenance (PM) Program | E24: B001 | F24: B001AS | G24: 1502000 | H24: 3.3.10 | I24: Security Systems and Equipment | J24: 12 | K24: MO
A25: CNRSE | B25: CNRSE ST-FAC | C25: Facility Investment | D25: Preventive Maintenance (PM) Program | E25: B001 | F25: B001AT | G25: 1502000 | H25: 3.3.11 | I25: Uninterruptible Power Supplies (UPS) | J25: 12 | K25: MO
A26: CNRSE | B26: CNRSE ST-FAC | C26: Facility Investment | D26: Preventive Maintenance (PM) Program | E26: B001 | F26: B001AU | G26: 1502000 | H26: 3.3.12 | I26: Vertical Transportation Equipment (VTE) | J26: 12 | K26: MO
... A42: CNRSE | B42: CNRSE ST-FAC | C42: Facility Investment | D42: Other Recurring Services Program | E42: B001 | F42: B001BL | G42: 1502000 | H42: 3.5.11 | I42: Spot Coolers | J42: 12 | K42: MO
A43: CNRSE | B43: CNRSE ST-FAC | C43: Facility Investment | D43: Other (Swimming Pools) | E43: B001 | F43: B001BM | G43: 1503040 | H43: 3.1 | I43: Pool Operator Maintenance | J43: 12 | K43: MO
A44: CNRSE | B44: CNRSE ST-FAC | C44: Facility Investment | D44: Other (Swimming Pools) | E44: B001 | F44: B001BN | G44: 1503040 | H44: 3.2 | I44: Preventive Maintenance (PM) Program | J44: 12 | K44: MO
A45: CNRSE | B45: CNRSE FX | C45: Facility Investment | D45: Other (Swimming Pools) | E45: B001 | F45: B001BP | G45: 1503040 | H45: 3.3 | I45: Water Treatment | J45: 12 | K45: MO
A46: CNRSE | B46: CNRSE UT | C46: Utilities Management | D46: Utility Operations Support | E46: B001 | F46: B001BQ | G46: 1601000 | H46: 3.1 | I46: Utility Operations Support | J46: 12 | K46: MO
A47: CNRSE | B47: CNRSE UT | C47: Utilities Management | D47: Recurring Work | E47: B001 | F47: B001BR | G47: 1601000 | H47: 3.2 | I47: Utility Infrastructure Condition Assessment Program (UICAP) Support | J47: 12 | K47: MO
A48: CNRSE | B48: CNRSE UT | C48: Utilities Management | D48: Recurring Work | E48: B001 | F48: B001BS | G48: 1601000 | H48: 3.3 | I48: Operation and Management of Facility Related Control Systems (FRCS) | J48: 12 | K48: MO
A49: CNRSE | B49: CNRSE UT | C49: Utilities Management | D49: Recurring Work | E49: B001 | F49: B001BT | G49: 1601000 | H49: 3.4 | I49: NAVFAC Maximo Data Entry | J49: 12 | K49: MO
A50: CNRSE | B50: CNRSE UT | C50: Electrical | D50: Recurring Work | E50: B001 | F50: B001BU | G50: 1602000 | H50: 3.1 | I50: Operate Electrical Power Transmission and Distribution Systems | J50: 12 | K50: MO
A51: CNRSE | B51: CNRSE ST | C51: Electrical | D51: E/U/R Work Orders | E51: B001 | F51: B001BV | G51: 1602000 | H51: 3.2 | I51: Emergency, Urgent and Routine (E/U/R) Work | J51: 220 | K51: EA
A52: CNRSE | B52: CNRSE ST | C52: Electrical | D52: Recurring Work | E52: B001 | F52: B001BW | G52: 1602000 | H52: 3.3 | I52: Preventive Maintenance (PM) Program | J52: 12 | K52: MO
A53: CNRSE | B53: CNRSE UT | C53: Electrical | D53: Other Recurring Services Program | E53: B001 | F53: B001BX | G53: 1602000 | H53: 3.4 | I53: Other Recurring Services | J53: 12 | K53: MO
A54: CNRSE | B54: CNRSE UT | C54: Electrical | D54: Other Recurring Services Program | E54: B001 | F54: B001BY | G54: 1602000 | H54: 3.5 | I54: Utility Right of Way Clearance | J54: 12 | K54: MO
A55: CNRSE | B55: CNRSE TR | C55: Transportation | D55: Operations | E55: B001 | F55: B001BZ | G55: 1700000 | H55: 3.1.1 | I55: WHE/MHE/NTVE Services | J55: 12 | K55: MO
A56: CNRSE | B56: CNRSE TR | C56: Transportation | D56: Operations | E56: B001 | F56: B001CA | G56: 1700000 | H56: 3.1.2 | I56: Fuel Delivery Services | J56: 12 | K56: MO
A57: CNRSE | B57: CNRSE TR | C57: Transportation | D57: Support Services | E57: B001 | F57: B001CB | G57: 1700000 | H57: 3.2.1 | I57: Dispatching Services | J57: 12 | K57: MO
A58: CNRSE | B58: CNRSE TR | C58: Transportation | D58: Support Services | E58: B001 | F58: B001CC | G58: 1700000 | H58: 3.2.2 | I58: Non-Government Owned Leased Vehicles | J58: 12 | K58: MO
A59: CNRSE | B59: CNRSE TR | C59: Transportation | D59: Maintenance of NTVE | E59: B001 | F59: B001CD | G59: 1700000 | H59: 3.3.1.1 | I59: New and Reassigned Vehicles and Equipment Services | J59: 12 | K59: MO
A60: CNRSE | B60: CNRSE TR | C60: Transportation | D60: Maintenance of CESE | E60: B001 | F60: B001CE | G60: 1700000 | H60: 3.3.1.2 | I60: Preventive Maintenance, Inspection, Load Test and Certification of WHE, MHE and AWP | J60: 12 | K60: MO
A61: CNRSE | B61: CNRSE TR | C61: Transportation | D61: Maintenance of CESE | E61: B001 | F61: B001CF | G61: 1700000 | H61: 3.3.1.3 | I61: Preventive Maintenance Inspection of NTVE | J61: 12 | K61: MO
A62: CNRSE | B62: CNRSE TR | C62: Transportation | D62: Maintenance of CESE | E62: B001 | F62: B001CG | G62: 1700000 | H62: 3.3.1.4 | I62: Repair (NTVE, WHE, MHE and AWP) | J62: 12 | K62: MO
A63: CNRSE | B63: CNRSE TR | C63: Transportation | D63: Maintenance of CESE | E63: B001 | F63: B001CH | G63: 1700000 | H63: 3.3.1.5 | I63: NTVE Trouble Calls | J63: 150 | K63: EA
A64: CNRSE | B64: CNRSE TR | C64: Transportation | D64: Maintenance of CESE | E64: B001 | F64: B001CJ | G64: 1700000 | H64: 3.3.2 | I64: BSVE Accessories Installation and Removal | J64: 12 | K64: MO
A65: CNRSE | B65: CNRSE EC | C65: Environmental | D65: Recurring Work | E65: B001 | F65: B001CK | G65: 1800000 | H65: 3.1 | I65: Oil and Regulated Substance Spill Response and Cleanup Ashore | J65: 12 | K65: MO
A66: CNRSE | B66: CNRSE EC | C66: Environmental | D66: Recurring Work | E66: B001 | F66: B001CL | G66: 1800000 | H66: 3.2 | I66: Used Oil Management Services | J66: 12 | K66: MO
A67: CNRSE | B67: CNRSE EC | C67: Environmental | D67: Recurring Work | E67: B001 | F67: B001CM | G67: 1800000 | H67: 3.3 | I67: Storm Water Monitoring | J67: 12 | K67: MO
A68: CNRSE | B68: CNRSE ST-UH | C68: Facility Investment | D68: E/U/R Work Orders | E68: B001 | F68: B001CN | G68: 1502000 | H68: 3.1 | I68: Emergency, Urgent and Routine (E/U/R) Work | J68: 1350 | K68: EA
A69: CNRSE | B69: CNRSE ST-UH | C69: Facility Investment | D69: Preventive Maintenance (PM) Program | E69: B001 | F69: B001CP | G69: 1502000 | H69: 3.3.3 | I69: Boiler and Unfired Pressure Vessel (UPV) Systems | J69: 12 | K69: MO
A70: CNRSE | B70: CNRSE ST-UH | C70: Facility Investment | D70: Preventive Maintenance (PM) Program | E70: B001 | F70: B001CQ | G70: 1502000 | H70: 3.3.6 | I70: Fire Protection Systems | J70: 12 | K70: MO
A71: CNRSE | B71: CNRSE ST-UH | C71: Facility Investment | D71: Preventive Maintenance (PM) Program | E71: B001 | F71: B001CR | G71: 1502000 | H71: 3.3.9 | I71: HVAC and Refrigeration Systems | J71: 12 | K71: MO
A72: CNRSE | B72: CNRSE ST-UH | C72: Facility Investment | D72: Inspection, Testing, and Certification | E72: B001 | F72: B001CS | G72: 1502000 | H72: 3.4.1 | I72: Backflow Prevention Devices | J72: 12 | K72: MO
A73: CNRSE | B73: CNRSE ST-UH | C73: Facility Investment | D73: Inspection, Testing, and Certification | E73: B001 | F73: B001CT | G73: 1502000 | H73: 3.4.2 | I73: Boilers and UPVs | J73: 12 | K73: MO
A74: CNRSE | B74: CNRSE ST-UH | C74: Facility Investment | D74: Other Recurring Services Program | E74: B001 | F74: B001CU | G74: 1502000 | H74: 3.5.1 & 3.5.7 | I74: Boiler & HVAC Seasonal Startup and Shutdown | J74: 12 | K74: MO
A75: CNRSE | B75: CNRSE ST-UH | C75: Facility Investment | D75: Other Recurring Services Program | E75: B001 | F75: B001CV | G75: 1502000 | H75: 3.5.2 | I75: Boiler Systems Water Testing and Treatment Services | J75: 12 | K75: MO
A76: CNRSE | B76: CNRSE ST-UH | C76: Facility Investment | D76: Other Recurring Services Program | E76: B001 | F76: B001CW | G76: 1502000 | H76: 3.5.8 | I76: HVAC Water Testing and Treatment Services | J76: 12 | K76: MO
A77: CNRSE | B77: CNRSE ST-UH | C77: Facility Investment | D77: Other Recurring Services Program | E77: B001 | F77: B001CX | G77: 1502000 | H77: 3.5.9 | I77: HVAC Condenser Tube Inspections | J77: 12 | K77: MO
A78: CNRSE | B78: CNRSE ST-UH | C78: Facility Investment | D78: Other Recurring Services Program | E78: B001 | F78: B001CY | G78: 1502000 | H78: 3.5.3 | I78: Change of Occupancy Maintenance (COM) | J78: 50 | K78: EA
A79: CNRSE | B79: CNRSE ST-UH | C79: Facility Investment | D79: Other Recurring Services Program | E79: B001 | F79: B001CZ | G79: 1502000 | H79: 3.5.10 | I79: Lint Traps | J79: 12 | K79: MO
A80: CNRSE | B80: Family Housing | C80: Facility Invetment | D80: Preventive Maintenance (PM) Program | E80: B001 | F80: B001DA | G80: 1502000 | H80: 3.3.9 | I80: HVAC and Refrigeration Systems | J80: 12 | K80: MO
... A87: FRC VRT | B87: FRC VRT | C87: Transportation | D87: Maintenance (Government Owned) | E87: B002 | F87: B002AB | G87: 1700000 | H87: 3.3.1.4 | I87: Repair (NTVE, WHE, MHE and AWP) | J87: 12 | K87: MO
A88: FRC VRT | B88: FRC VRT | C88: Environmental | D88: Recurring Work | E88: B002 | F88: B002AC | G88: 1800000 | H88: 3.2 | I88: Used Oil Management Services | J88: 12 | K88: MO
A89: MCSF-BI | B89: MCSF-BI | C89: Facility Management | D89: Recurring Work | E89: B003 | F89: B003AA | G89: 1501000(MCSF-BI) | H89: 3.1,3.2,3.3 | I89: USMC Maximo, ICAP and Tech Library | J89: 12 | K89: MO
A90: MCSF-BI | B90: MCSF-BI | C90: Facility Investment - MCSF-BI | D90: E/U/R Work Orders | E90: B003 | F90: B003AB | G90: 1502000(MCSF-BI) | H90: 3.1 | I90: Emergency, Urgent and Routine (E/U/R) Work | J90: 750 | K90: EA
A91: MCSF-BI | B91: MCSF-BI | C91: Facility Investment - MCSF-BI | D91: Recurring Work | E91: B003 | F91: B003AC | G91: 1502000(MCSF-BI) | H91: 3.2 | I91: Urgent and Routine Project Work Orders | J91: 48 | K91: EA
A92: MCSF-BI | B92: MCSF-BI | C92: Facility Investment - MCSF-BI | D92: Preventive Maintenance (PM) Program | E92: B003 | F92: B003AD | G92: 1502000(MCSF-BI) | H92: 3.3.1 | I92: Auxiliary Generator Systems | J92: 12 | K92: MO
A93: MCSF-BI | B93: MCSF-BI | C93: Facility Investment - MCSF-BI | D93: Preventive Maintenance (PM) Program | E93: B003 | F93: B003AE | G93: 1502000(MCSF-BI) | H93: 3.3.2 | I93: Cathodic Protection | J93: 12 | K93: MO
A94: MCSF-BI | B94: MCSF-BI | C94: Facility Investment - MCSF-BI | D94: Preventive Maintenance (PM) Program | E94: B003 | F94: B003AF | G94: 1502000(MCSF-BI) | H94: 3.3.3 | I94: Compressed Air Systems | J94: 12 | K94: MO
A95: MCSF-BI | B95: MCSF-BI | C95: Facility Investment - MCSF-BI | D95: Preventive Maintenance (PM) Program | E95: B003 | F95: B003AG | G95: 1502000(MCSF-BI) | H95: 3.3.4 | I95: Facilities, Systems, and Equipment | J95: 12 | K95: MO
A96: MCSF-BI | B96: MCSF-BI | C96: Facility Investment - MCSF-BI | D96: Preventive Maintenance (PM) Program | E96: B003 | F96: B003AH | G96: 1502000(MCSF-BI) | H96: 3.3.5 | I96: Fire Protection Systems | J96: 12 | K96: MO
A97: MCSF-BI | B97: MCSF-BI | C97: Facility Investment - MCSF-BI | D97: Preventive Maintenance (PM) Program | E97: B003 | F97: B003AJ | G97: 1502000(MCSF-BI) | H97: 3.3.6 | I97: Irrigation Equipment and Systems | J97: 12 | K97: MO
A98: MCSF-BI | B98: MCSF-BI | C98: Facility Investment - MCSF-BI | D98: Preventive Maintenance (PM) Program | E98: B003 | F98: B003AK | G98: 1502000(MCSF-BI) | H98: 3.3.7 | I98: Unfired Pressure Vessels (UPVs) | J98: 12 | K98: MO
A99: MCSF-BI | B99: MCSF-BI | C99: Facility Investment - MCSF-BI | D99: Preventive Maintenance (PM) Program | E99: B003 | F99: B003AL | G99: 1502000(MCSF-BI) | H99: 3.3.8 | I99: Vertical Transportation Equipment (VTE) | J99: 12 | K99: MO
A100: MCSF-BI | B100: MCSF-BI | C100: Facility Investment - MCSF-BI | D100: Integrated Maintenance Program (IMP) | E100: B003 | F100: B003AM | G100: 1502000(MCSF-BI) | H100: 3.4.1 | I100: Blast, Paint, and Drying Systems | J100: 12 | K100: MO
A101: MCSF-BI | B101: MCSF-BI | C101: Facility Investment - MCSF-BI | D101: Integrated Maintenance Program (IMP) | E101: B003 | F101: B003AN | G101: 1502000(MCSF-BI) | H101: 3.4.2 | I101: Boiler Systems | J101: 12 | K101: MO
A102: MCSF-BI | B102: MCSF-BI | C102: Facility Investment - MCSF-BI | D102: Integrated Maintenance Program (IMP) | E102: B003 | F102: B003AP | G102: 1502000(MCSF-BI) | H102: 3.4.3 | I102: HVAC and Refrigeration Systems | J102: 12 | K102: MO
A103: MCSF-BI | B103: MCSF-BI | C103: Facility Investment - MCSF-BI | D103: Integrated Maintenance Program (IMP) | E103: B003 | F103: B003AQ | G103: 1502000(MCSF-BI) | H103: 3.4.4 | I103: Railroad Signal and Battery House Systems and Equipment | J103: 12 | K103: MO
... A119: MCSF-BI | B119: MCSF-BI | C119: Facility Investment - MCSF-BI | D119: Other Recurring Services Program | E119: B003 | F119: B003BG | G119: 1502000(MCSF-BI) | H119: 3.6.10 | I119: Fuel Storage Tanks and Berms | J119: 12 | K119: MO
A120: MCSF-BI | B120: MCSF-BI | C120: Custodial - MCSF-BI | D120: Recurring Work | E120: B003 | F120: B003BH | G120: 1503010(MCSF-BI) | H120: 3.1 | I120: Scheduled Services | J120: 12 | K120: MO
A121: MCSF-BI | B121: MCSF-BI | C121: Custodial - MCSF-BI | D121: Recurring Work | E121: B003 | F121: B003BJ | G121: 1503010(MCSF-BI) | H121: 3.2 | I121: Custodial Service Orders | J121: 12 | K121: EA
A122: MCSF-BI | B122: MCSF-BI | C122: Pest Control - MCSF-BI | D122: Recurring Work | E122: B003 | F122: B003BK | G122: 1503020(MCSF-BI) | H122: 3.1 | I122: Scheduled Pest Control Services | J122: 12 | K122: MO
A123: MCSF-BI | B123: MCSF-BI | C123: Pest Control - MCSF-BI | D123: Recurring Work | E123: B003 | F123: B003BL | G123: 1503020(MCSF-BI) | H123: 3.2 | I123: Pest Control Service Orders | J123: 100 | K123: EA
A124: MCSF-BI | B124: MCSF-BI | C124: Pest Control - MCSF-BI | D124: Recurring Work | E124: B003 | F124: B003BM | G124: 1503020(MCSF-BI) | H124: 3.3 | I124: Pest Management Reporting | J124: 12 | K124: MO
A125: MCSF-BI | B125: MCSF-BI | C125: Integrated Solid Waste Management - MCSF-BI | D125: Recurring Work | E125: B003 | F125: B003BN | G125: 1503030(MCSF-BI) | H125: 3 | I125: Recurring Work ISWM | J125: 12 | K125: MO
A126: MCSF-BI | B126: MCSF-BI | C126: Grounds Maintenance and Landscaping - MCSF-BI | D126: Recurring Work | E126: B003 | F126: B003BP | G126: 1503050(MCSF-BI) | H126: 3.1 | I126: Improved Grounds | J126: 12 | K126: MO
A127: MCSF-BI | B127: MCSF-BI | C127: Grounds Maintenance and Landscaping - MCSF-BI | D127: Recurring Work | E127: B003 | F127: B003BQ | G127: 1503050(MCSF-BI) | H127: 3.2 | I127: Operational Areas | J127: 12 | K127: MO
A128: MCSF-BI | B128: MCSF-BI | C128: Grounds Maintenance and Landscaping - MCSF-BI | D128: Recurring Work | E128: B003 | F128: B003BR | G128: 1503050(MCSF-BI) | H128: 3.3 | I128: Storm Drainage Systems | J128: 12 | K128: MO
A129: MCSF-BI | B129: MCSF-BI | C129: Grounds Maintenance and Landscaping - MCSF-BI | D129: Recurring Work | E129: B003 | F129: B003BS | G129: 1503050(MCSF-BI) | H129: 3.4 | I129: Street Sweeping | J129: 12 | K129: MO
A130: MCSF-BI | B130: MCSF-BI | C130: Grounds Maintenance and Landscaping - MCSF-BI | D130: Recurring Work | E130: B003 | F130: B003BT | G130: 1503050(MCSF-BI) | H130: 3.5 | I130: Grounds Maintenance Service Orders | J130: 12 | K130: EA
A131: MCSF-BI | B131: MCSF-BI | C131: Environmental - MCSF-BI | D131: Recurring Work | E131: B003 | F131: B003BU | G131: 1800000(MCSF-BI) | H131: 3.1 | I131: Sampling, Field Testing and Laboratory Services | J131: 12 | K131: MO
... A136: MCSF-BI | B136: MCSF-BI | C136: Environmental - MCSF-BI | D136: Recurring Work | E136: B003 | F136: B003BZ | G136: 1800000(MCSF-BI) | H136: 3.6 | I136: Inspection of POL Tanks and Systems | J136: 12 | K136: MO
A137: NCIS | B137: NCIS | C137: Facility Investment | D137: Preventive Maintenance (PM) Program | E137: B004 | F137: B004AA | G137: 1502000 | H137: 3.3.10 | I137: Security Systems and Equipment | J137: 12 | K137: MO
A138: FLCJ | B138: FLCJ | C138: Facility Investment | D138: E/U/R Work Orders | E138: B005 | F138: B005AA | G138: 1502000 | H138: 3.1 | I138: Emergency, Urgent and Routine (E/U/R) Work | J138: 50 | K138: EA
A139: FLCJ | B139: FLCJ | C139: Facility Investment | D139: Recurring Work | E139: B005 | F139: B005AB | G139: 1502000 | H139: 3.2 | I139: Project Work Orders | J139: 10 | K139: EA
A140: FLCJ | B140: FLCJ | C140: Transportation | D140: Maintenance (Government Owned) | E140: B005 | F140: B005AC | G140: 1700000 | H140: 3.3.1.2 | I140: Preventive Maintenance, Inspection, Load Test and Certification of WHE, MHE and AWP | J140: 12 | K140: MO
...

Sheet CLIN 0005 1st Period Opt N-RW
B1: Attachment J-0200000-17
B2: Exhibit Line Item Numbers - NAVSTA Mayport
B3: Contract No.: N6945025R0003
B5: CLIN 0005 - Non-Recurring Work - Option Period 1
B6: Provide Prices for Recurring Work in accordance with Section C, Spec Item 4
B7: ELINs B700 through B718
A8: ELIN | B8: Product Name (120 Characters) | C8: Description Extended | D8: Estimated Quantity | E8: Unit of Measure | F8: Unit Price | G8: Extended Price
A9: B700 | B9: Unit Priced Labor Hour Work - MUST BE NEGOTIATED BY KO. | C9: The Contractor shall perform all UPL work in accordance with the scope and delivery schedule negotiated per each task order. Refer to: Section C, Annex 0200000 Managmenent and Administration, Specification Item 2.15.2 Unit Priced Labor (UPL)Work (Negotiated) for description of UPL Work. Refer to: Section J, Annex 0200000 Managmenent and Administration, Attachment J-0200000-01 Definitions and Acronyms for description of Unit Priced Labor (UPL) Hour and Universal Equipment. Task order completion times will be specified on each task order. For self-performed work: the unit price proposed for Sub-ELIN B700AA will be used to determine the labor cost to the Governent. For subcontracted labor: the FBR proposed for Sub-ELIN B700AB will be used to determine the labor cost to the Governmnet. The estimated quantity of each Sub-ELIN is used to establish the ELIN Extended Price. During administration the labor Sub-ELINs may be used in any combination and quantity provided the ELIN extended price is not exceeded. The contract will not be modified to re-allocate capacity among labor SLINs. | D9: =G10+G11 -> 0 | E9: DO | F9: 1
A10: B700AA | B10: Self-Performed Unit Priced Labor Hour Work - MUST BE NEGOTIATED BY KO. | C10: The Contractor shall self-perform all UPL work in accordance with the scope and delivery schedule negotiated per each task order. Refer to: Section C, Annex 0200000 Managmenent and Administration, Specification Item 2.15.2 Unit Priced Labor (UPL)Work (Negotiated) for description of UPL Work. Refer to: Section J, Annex 0200000 Managmenent and Administration, Attachment J-0200000-01 Definitions and Acronyms for description of Unit Priced Labor (UPL) Hour and Universal Equipment. | D10: ='CLIN 0002 Base Period N-RW'!D10 -> 16000 | E10: LH
A11: B700AB | B11: Subcontractor Labor (Fixed Burden Rate) - MUST BE NEGOTIATED BY KO. | C11: The Contractor shall perform management and oversight of subcontracted non-recurring work in accordance with the scope and delivery schedule negotiated per each task order. Refer to: Section C, Annex 0200000 Management and Administration, Specification Item 2.15.2.1.2 Subcontractor Requirements description of Sub. Refer to: Section J, Annex 0200000 Management and Administration, Attachment J-0200000-01 Definitions and Acronyms for definition of Sub-Contractor Fixed Burden Rate. The estimated quantity (in dollars) is provided. A Fixed Burdened Rate (FBR) shall be entered in the Unit Price column. The FBR shall include all direct and indirect factors for management and oversight of subcontracted non-recurring work. Similar to FBR example in J-0200000-01, if a 15% markup is the Contractor's proposed FBR, the Unit Price should be $1.15. During performance, if the lowest subcontractor labor proposal is $1,000.00 and the FBR is $1.15, the labor cost to the Government will be $1,150.00. (DO - Dollars). | D11: ='CLIN 0002 Base Period N-RW'!D11 -> 1600000 | E11: DO
A12: B701 | B12: Material and Equipment - MUST BE NEGOTIATED BY KO. | C12: Provide all materials and construction equipment to perform Unit Priced Labor work per the scope and delivery schedule specified in the order. Pre-expended bin supplies and materials will not be included in the list of materials since the cost for these items were included in the labor hour unit price bid. Material prices provided by the Contractor shall be the lowest price available considering the availability of materials and the time constraints of the job. The direct material price shall be adjusted by all discounts and rebates for core value or salvage value that accrue to the Contractor. Contractor owned equipment rental rates shall be based on calculations set forth in US Army Corp of Engineers “Construction Equipment Ownership and Operating Expense Schedule (EP 1110-1-8 (Vol. 11) July 03 or latest revision) Chapter 2. The estitmate quantity (in dollars) is provided. A Fixed burdened rate (FBR) shall be entered in the Unit Price column. The FBR shall include factors for ordering, handling, and stockpiling materials and repair parts. Similar to FBR example in J-0200000-01, if a 10% markup is the Contractor's proposed FBR, the Unit Price should be $1.10. When multiplying the proposed Unit Price by the Estimated Quantity, the Extended Price should be During administration, if the vendor's invoice on material is $1,000.00 and the unit price is $1.10, the cost of the material to the government will be $1,050.00. (DO - Dollars) | D12: ='CLIN 0002 Base Period N-RW'!D12 -> 2000000 | E12: DO
A13: B702 | B13: Category I Calls - MUST BE NEGOTIATED BY KO. | C13: The Contractor shall perform Category I Calls to accomplish any work identified within the entire boundary of the installation and will include a wide variety of work. Category I Calls shall be completed within two weeks of receipt of call order, unless otherwise agreed to by the customer and contractor and annotated on the CAT call request. As part of the Category I Call, the Contractor has full responsibility for any work identified up to the Category I Call Threshold of $5,000 in direct labor and direct material, per Category I Call. A Blanket Task Order (BTO) may be issued on a DD Form 1155 with a Not To Exceed (NTE) quantity and value for Non-recurring Work Category Calls. | D13: ='CLIN 0002 Base Period N-RW'!D13 -> 115 | E13: EA
A14: B703 | B14: Category II Calls - MUST BE NEGOTIATED BY KO. | C14: The Contractor shall perform Category II Calls to accomplish any work identified within the entire boundary of the installation and will include a wide variety of work. Category II Calls shall be completed within three weeks of receipt of call order, unless otherwise agreed to by the customer and contractor and annotated on the CAT call request. As part of the Category II Call, the Contractor has full responsibility for any work identified up to the Category II Call Threshold of $7,500 in direct labor and direct material, per Category II Call. A Blanket Task Order (BTO) may be issued on a DD Form 1155 with a Not To Exceed (NTE) quantity and value for Non-recurring Work Category Calls. | D14: ='CLIN 0002 Base Period N-RW'!D14 -> 130 | E14: EA
A15: B704 | B15: Category III Calls - MUST BE NEGOTIATED BY KO. | C15: The Contractor shall perform Category III Calls to accomplish any work identified within the entire boundary of the installation and will include a wide variety of work. Category III Calls shall be completed within 30 days of receipt of call order, unless otherwise agreed to by the customer and contractor and annotated on the CAT call request. As part of the Category III Call, the Contractor has full responsibility for any work identified up to the Category III Call Threshold of $10,000 in direct labor and direct material, per Category III Call. A Blanket Task Order (BTO) may be issued on a DD Form 1155 with a Not To Exceed (NTE) quantity and value for Non-recurring Work Category Calls. | D15: ='CLIN 0002 Base Period N-RW'!D15 -> 95 | E15: EA
A16: B705 | B16: Category IV Calls - MUST BE NEGOTIATED BY KO. | C16: The Contractor shall perform Category IV Calls to accomplish any work identified within the entire boundary of the installation and will include a wide variety of work. Category IV Calls shall be completed within 30 days of receipt of call order, unless otherwise agreed to by the customer and contractor and annotated on the CAT call request. As part of the Category IV Call, the Contractor has full responsibility for any work identified up to the Category IV Call Threshold of $12,500 in direct labor and direct material, per Category IV Call. A Blanket Task Order (BTO) may be issued on a DD Form 1155 with a Not To Exceed (NTE) quantity and value for Non-recurring Work Category Calls. | D16: ='CLIN 0002 Base Period N-RW'!D16 -> 50 | E16: EA
A17: B706 | B17: Category V Calls - MUST BE NEGOTIATED BY KO. | C17: The Contractor shall perform Category V Calls to accomplish any work identified within the entire boundary of the installation and will include a wide variety of work. Category V Calls shall be completed within 30 days of receipt of call order, unless otherwise agreed to by the customer and contractor and annotated on the CAT call request. As part of the Category V Call, the Contractor has full responsibility for any work identified up to the Category V Call Threshold of $15,000 in direct labor and direct material, per Category V Call. A Blanket Task Order (BTO) may be issued on a DD Form 1155 with a Not To Exceed (NTE) quantity and value for Non-recurring Work Category Calls. | D17: ='CLIN 0002 Base Period N-RW'!D17 -> 40 | E17: EA
A18: B707 | B18: Category VI Calls - MUST BE NEGOTIATED BY KO. | C18: The Contractor shall perform Category VI Calls to accomplish any work identified within the entire boundary of the installation and will include a wide variety of work. Category VI Calls shall be completed within 30 days of receipt of call order, unless otherwise agreed to by the customer and contractor and annotated on the CAT call request. As part of the Category VI Call, the Contractor has full responsibility for any work identified up to the Category VI Call Threshold of $17,500 in direct labor and direct material, per Category VI Call. A Blanket Task Order (BTO) may be issued on a DD Form 1155 with a Not To Exceed (NTE) quantity and value for Non-recurring Work Category Calls. | D18: ='CLIN 0002 Base Period N-RW'!D18 -> 30 | E18: EA
A19: B708 | B19: Category VII Calls - MUST BE NEGOTIATED BY KO. | C19: The Contractor shall perform Category VII Calls to accomplish any work identified within the entire boundary of the installation and will include a wide variety of work. Category VII Calls shall be completed within 30 days of receipt of call order, unless otherwise agreed to by the customer and contractor and annotated on the CAT call request. As part of the Category VII Call, the Contractor has full responsibility for any work identified up to the Category VII Call Threshold of $20,000 in direct labor and direct material, per Category VII Call. A Blanket Task Order (BTO) may be issued on a DD Form 1155 with a Not To Exceed (NTE) quantity and value for Non-recurring Work Category Calls. | D19: ='CLIN 0002 Base Period N-RW'!D19 -> 20 | E19: EA
A20: B709 | B20: Water Damage Removal available on FEDMALL | C20: The Contractor shall carefully remove and dispose of damaged interior finishes to include drywall, carpeting, etc. to prevent further damage or mold/mildew development in the event of water intrusion into a facility. In addition to the removal of the interior finishes, the Contractor shall dry the effected areas by providing dehumidifaction and airflow to remove any moisture from the space. Work shall begin within 12 hours of notification. Task order completion times will be specified on each task order. | D20: ='CLIN 0002 Base Period N-RW'!D20 -> 20000 | E20: SF
A21: B710 | B21: Temporary Roof Repairs available on FEDMALL | C21: The Contractor shall provide all labor, material, and equipment to perform temporary roof repairs (i.e. tarping, roof patches, polyethylene film, etc.) to minimize water intrusion into a facility. Roof repairs shall be sufficient to last for a period no less than six months before requiring replacement or further repair.Within six months from the date of the original installation, the Contractor shall provide repairs and maintenance of the temporary repair at no additional cost to the Government. Work shall begin within 12 hours of notification. Task order completion times will be specified on each task order. | D21: ='CLIN 0002 Base Period N-RW'!D21 -> 30000 | E21: SF
... A29: B718 | B29: Blount Island Shoreline Cleanup available on FEDMALL | C29: The Contractor shall perfrome shore cleanup, following the MCSF-BI Integrated Natural Resources Management Plan (INRMP). The shoreline clean up covers approximately 5 acres, and includes removal of debris, separation of recycling and not recycling materials, and proper disposal of the removed materials. The Contractor shall submit a report to the contracting Officer within 2 days after each service. Work shall begin within 12 hours of notification. | D29: ='CLIN 0002 Base Period N-RW'!D29 -> 2 | E29: EA
A30: Total Non-recurring Work - Base Period:

Sheet CLIN 0006 -1st Period Water RW
B1: Attachment J-0200000-17
B2: Exhibit Line Item Numbers - NAVSTA Mayport
B3: Contract No.: N6945025R0003
B6: CLIN 0006 - UT Recurring Work - First Option Period
B7: Provide Prices for Recurring Work in accordance with Section C, Spec Item 3
B8: ELIN B015
A9: Customer/ Program | B9: Category | C9: Sub-Category | D9: ELIN | E9: Sub-ELIN | F9: Annex/Sub-annex | G9: Spec Item | H9: Description | I9: Quantity | J9: Unit of Measure | K9: Unit Price | L9: Extended Price
A10: CNRSE UT | B10: Water | C10: Recurring Services | D10: B015 | E10: B015AA | F10: 1606000 | G10: 3.1 | H10: Operation | I10: 12 | J10: MO
A11: CNRSE ST | B11: Water | C11: E/U/R Work Orders | D11: B015 | E11: B015AC | F11: 1606000 | G11: 3.2.2 | H11: E/U/R Work Orders | I11: 80 | J11: EA
A12: CNRSE ST | B12: Water | C12: Recurring Services | D12: B015 | E12: B015AE | F12: 1606000 | G12: 3.3 | H12: Preventive Maintenance (PM) | I12: 12 | J12: MO
A13: CNRSE UT | B13: Water | C13: Recurring Services | D13: B015 | E13: B015AF | F13: 1606000 | G13: 3.4 | H13: Inspection, Testing, and Certification of Fire Hydrants | I13: 12 | J13: MO

Sheet CLIN 0007 2nd Period Opt RW
C1: Attachment J-0200000-17
C2: Exhibit Line Item Numbers - NAVSTA Mayport
C3: Contract No.: N6945025R0003
C4: CLIN 0007 - Recurring Work - Second Period
C5: Provide Prices for Recurring Work in accordance with Section C, Spec Item 3
C6: ELINs C001 through C014
A7: Customer | B7: Funding Source | C7: Category | D7: Sub-Category | E7: ELIN | F7: Sub-ELIN | G7: Annex/Sub-annex | H7: Spec Item | I7: Description | J7: Quantity | K7: Unit of Measure | L7: Unit Price | M7: Extended Price
A8: CNRSE | B8: Port Ops | C8: Port Operations | D8: Port Ops Equipment Work Order | E8: C001 | F8: C001AA | G8: 0600000 | H8: 3.1 | I8: Port Ops Equipment Work Order | J8: 20 | K8: EA
A9: CNRSE | B9: Port Ops | C9: Port Operations | D9: Recurring Work | E9: C001 | F9: C001AB | G9: 0600000 | H9: 3.2 | I9: Ship Movements - Berthing and Hotel Services | J9: 12 | K9: MO
A10: CNRSE | B10: CNRSE FP | C10: Facility Management | D10: Recurring Work | E10: C001 | F10: C001AC | G10: 1501000 | H10: 3.1 | I10: NAVFAC Maximo Data Entry | J10: 12 | K10: MO
A11: CNRSE | B11: CNRSE FP | C11: Facility Management | D11: Recurring Work | E11: C001 | F11: C001AD | G11: 1501000 | H11: 3.2 | I11: Infrastructure Condition Assessment Program (ICAP) Services | J11: 12 | K11: MO
A12: CNRSE | B12: CNRSE FP | C12: Facility Management | D12: Recurring Work | E12: C001 | F12: C001AE | G12: 1501000 | H12: 3.3 | I12: Technical Library Operations | J12: 12 | K12: MO
A13: CNRSE | B13: CNRSE ST-FAC | C13: Facility Investment | D13: E/U/R Work Orders | E13: C001 | F13: C001AF | G13: 1502000 | H13: 3.1 | I13: Emergency, Urgent and Routine (E/U/R) Work | J13: 3658 | K13: EA
A14: CNRSE | B14: CNRSE ST-FAC | C14: Facility Investment | D14: Recurring Work | E14: C001 | F14: C001AG | G14: 1502000 | H14: 3.2 | I14: Project Work Orders | J14: 50 | K14: EA
A15: CNRSE | B15: CNRSE ST-FAC | C15: Facility Investment | D15: Preventive Maintenance (PM) Program | E15: C001 | F15: C001AH | G15: 1502000 | H15: 3.3.1 | I15: Airfield Lighting Systems | J15: 12 | K15: MO
A16: CNRSE | B16: CNRSE ST-FAC | C16: Facility Investment | D16: Preventive Maintenance (PM) Program | E16: C001 | F16: C001AJ | G16: 1502000 | H16: 3.3.2 | I16: Auxiliary Generator Systems | J16: 12 | K16: MO
A17: CNRSE | B17: CNRSE ST-FAC | C17: Facility Investment | D17: Preventive Maintenance (PM) Program | E17: C001 | F17: C001AK | G17: 1502000 | H17: 3.3.3 | I17: Boiler and Unfired Pressure Vessel (UPV) Systems | J17: 12 | K17: MO
A18: CNRSE | B18: CNRSE ST-FAC | C18: Facility Investment | D18: Preventive Maintenance (PM) Program | E18: C001 | F18: C001AL | G18: 1502000 | H18: 3.3.4 | I18: Compressed Air Systems | J18: 12 | K18: MO
A19: CNRSE | B19: CNRSE ST-FAC | C19: Facility Investment | D19: Preventive Maintenance (PM) Program | E19: C001 | F19: C001AM | G19: 1502000 | H19: 3.3.5 | I19: Door and Gate Systems | J19: 12 | K19: MO
A20: CNRSE | B20: CNRSE ST-FAC | C20: Facility Investment | D20: Preventive Maintenance (PM) Program | E20: C001 | F20: C001AN | G20: 1502000 | H20: 3.3.6 | I20: Fire Protection Systems | J20: 12 | K20: MO
A21: CNRSE | B21: CNRSE ST-FAC | C21: Facility Investment | D21: Preventive Maintenance (PM) Program | E21: C001 | F21: C001AP | G21: 1502000 | H21: 3.3.7 | I21: Frequency Converter (400 HZ) Systems | J21: 12 | K21: MO
A22: CNRSE | B22: CNRSE ST-FAC | C22: Facility Investment | D22: Preventive Maintenance (PM) Program | E22: C001 | F22: C001AQ | G22: 1502000 | H22: 3.3.8 | I22: Galley Equipment and Systems | J22: 12 | K22: MO
A23: CNRSE | B23: CNRSE ST-FAC | C23: Facility Investment | D23: Preventive Maintenance (PM) Program | E23: C001 | F23: C001AR | G23: 1502000 | H23: 3.3.9 | I23: HVAC and Refrigeration Systems | J23: 12 | K23: MO
A24: CNRSE | B24: CNRSE ST-FAC | C24: Facility Investment | D24: Preventive Maintenance (PM) Program | E24: C001 | F24: C001AS | G24: 1502000 | H24: 3.3.10 | I24: Security Systems and Equipment | J24: 12 | K24: MO
A25: CNRSE | B25: CNRSE ST-FAC | C25: Facility Investment | D25: Preventive Maintenance (PM) Program | E25: C001 | F25: C001AT | G25: 1502000 | H25: 3.3.11 | I25: Uninterruptible Power Supplies (UPS) | J25: 12 | K25: MO
A26: CNRSE | B26: CNRSE ST-FAC | C26: Facility Investment | D26: Preventive Maintenance (PM) Program | E26: C001 | F26: C001AU | G26: 1502000 | H26: 3.3.12 | I26: Vertical Transportation Equipment (VTE) | J26: 12 | K26: MO
... A42: CNRSE | B42: CNRSE ST-FAC | C42: Facility Investment | D42: Other Recurring Services Program | E42: C001 | F42: C001BL | G42: 1502000 | H42: 3.5.11 | I42: Spot Coolers | J42: 12 | K42: MO
A43: CNRSE | B43: CNRSE ST-FAC | C43: Facility Investment | D43: Other (Swimming Pools) | E43: C001 | F43: C001BM | G43: 1503040 | H43: 3.1 | I43: Pool Operator Maintenance | J43: 12 | K43: MO
A44: CNRSE | B44: CNRSE ST-FAC | C44: Facility Investment | D44: Other (Swimming Pools) | E44: C001 | F44: C001BN | G44: 1503040 | H44: 3.2 | I44: Preventive Maintenance (PM) Program | J44: 12 | K44: MO
A45: CNRSE | B45: CNRSE FX | C45: Facility Investment | D45: Other (Swimming Pools) | E45: C001 | F45: C001BP | G45: 1503040 | H45: 3.3 | I45: Water Treatment | J45: 12 | K45: MO
A46: CNRSE | B46: CNRSE UT | C46: Utilities Management | D46: Utility Operations Support | E46: C001 | F46: C001BQ | G46: 1601000 | H46: 3.1 | I46: Utility Operations Support | J46: 12 | K46: MO
A47: CNRSE | B47: CNRSE UT | C47: Utilities Management | D47: Recurring Work | E47: C001 | F47: C001BR | G47: 1601000 | H47: 3.2 | I47: Utility Infrastructure Condition Assessment Program (UICAP) Support | J47: 12 | K47: MO
A48: CNRSE | B48: CNRSE UT | C48: Utilities Management | D48: Recurring Work | E48: C001 | F48: C001BS | G48: 1601000 | H48: 3.3 | I48: Operation and Management of Facility Related Control Systems (FRCS) | J48: 12 | K48: MO
A49: CNRSE | B49: CNRSE UT | C49: Utilities Management | D49: Recurring Work | E49: C001 | F49: C001BT | G49: 1601000 | H49: 3.4 | I49: NAVFAC Maximo Data Entry | J49: 12 | K49: MO
A50: CNRSE | B50: CNRSE UT | C50: Electrical | D50: Recurring Work | E50: C001 | F50: C001BU | G50: 1602000 | H50: 3.1 | I50: Operate Electrical Power Transmission and Distribution Systems | J50: 12 | K50: MO
A51: CNRSE | B51: CNRSE ST | C51: Electrical | D51: E/U/R Work Orders | E51: C001 | F51: C001BV | G51: 1602000 | H51: 3.2 | I51: Emergency, Urgent and Routine (E/U/R) Work | J51: 220 | K51: EA
A52: CNRSE | B52: CNRSE ST | C52: Electrical | D52: Recurring Work | E52: C001 | F52: C001BW | G52: 1602000 | H52: 3.3 | I52: Preventive Maintenance (PM) Program | J52: 12 | K52: MO
A53: CNRSE | B53: CNRSE UT | C53: Electrical | D53: Other Recurring Services Program | E53: C001 | F53: C001BX | G53: 1602000 | H53: 3.4 | I53: Other Recurring Services | J53: 12 | K53: MO
A54: CNRSE | B54: CNRSE UT | C54: Electrical | D54: Other Recurring Services Program | E54: C001 | F54: C001BY | G54: 1602000 | H54: 3.5 | I54: Utility Right of Way Clearance | J54: 12 | K54: MO
A55: CNRSE | B55: CNRSE TR | C55: Transportation | D55: Operations | E55: C001 | F55: C001BZ | G55: 1700000 | H55: 3.1.1 | I55: WHE/MHE/NTVE Services | J55: 12 | K55: MO
A56: CNRSE | B56: CNRSE TR | C56: Transportation | D56: Operations | E56: C001 | F56: C001CA | G56: 1700000 | H56: 3.1.2 | I56: Fuel Delivery Services | J56: 12 | K56: MO
A57: CNRSE | B57: CNRSE TR | C57: Transportation | D57: Support Services | E57: C001 | F57: C001CB | G57: 1700000 | H57: 3.2.1 | I57: Dispatching Services | J57: 12 | K57: MO
A58: CNRSE | B58: CNRSE TR | C58: Transportation | D58: Support Services | E58: C001 | F58: C001CC | G58: 1700000 | H58: 3.2.2 | I58: Non-Government Owned Leased Vehicles | J58: 12 | K58: MO
A59: CNRSE | B59: CNRSE TR | C59: Transportation | D59: Maintenance of NTVE | E59: C001 | F59: C001CD | G59: 1700000 | H59: 3.3.1.1 | I59: New and Reassigned Vehicles and Equipment Services | J59: 12 | K59: MO
A60: CNRSE | B60: CNRSE TR | C60: Transportation | D60: Maintenance of CESE | E60: C001 | F60: C001CE | G60: 1700000 | H60: 3.3.1.2 | I60: Preventive Maintenance, Inspection, Load Test and Certification of WHE, MHE and AWP | J60: 12 | K60: MO
A61: CNRSE | B61: CNRSE TR | C61: Transportation | D61: Maintenance of CESE | E61: C001 | F61: C001CF | G61: 1700000 | H61: 3.3.1.3 | I61: Preventive Maintenance Inspection of NTVE | J61: 12 | K61: MO
A62: CNRSE | B62: CNRSE TR | C62: Transportation | D62: Maintenance of CESE | E62: C001 | F62: C001CG | G62: 1700000 | H62: 3.3.1.4 | I62: Repair (NTVE, WHE, MHE and AWP) | J62: 12 | K62: MO
A63: CNRSE | B63: CNRSE TR | C63: Transportation | D63: Maintenance of CESE | E63: C001 | F63: C001CH | G63: 1700000 | H63: 3.3.1.5 | I63: NTVE Trouble Calls | J63: 150 | K63: EA
A64: CNRSE | B64: CNRSE TR | C64: Transportation | D64: Maintenance of CESE | E64: C001 | F64: C001CJ | G64: 1700000 | H64: 3.3.2 | I64: BSVE Accessories Installation and Removal | J64: 12 | K64: MO
A65: CNRSE | B65: CNRSE EC | C65: Environmental | D65: Recurring Work | E65: C001 | F65: C001CK | G65: 1800000 | H65: 3.1 | I65: Oil and Regulated Substance Spill Response and Cleanup Ashore | J65: 12 | K65: MO
A66: CNRSE | B66: CNRSE EC | C66: Environmental | D66: Recurring Work | E66: C001 | F66: C001CL | G66: 1800000 | H66: 3.2 | I66: Used Oil Management Services | J66: 12 | K66: MO
A67: CNRSE | B67: CNRSE EC | C67: Environmental | D67: Recurring Work | E67: C001 | F67: C001CM | G67: 1800000 | H67: 3.3 | I67: Storm Water Monitoring | J67: 12 | K67: MO
A68: CNRSE | B68: CNRSE ST-UH | C68: Facility Investment | D68: E/U/R Work Orders | E68: C001 | F68: C001CN | G68: 1502000 | H68: 3.1 | I68: Emergency, Urgent and Routine (E/U/R) Work | J68: 1350 | K68: EA
A69: CNRSE | B69: CNRSE ST-UH | C69: Facility Investment | D69: Preventive Maintenance (PM) Program | E69: C001 | F69: C001CP | G69: 1502000 | H69: 3.3.3 | I69: Boiler and Unfired Pressure Vessel (UPV) Systems | J69: 12 | K69: MO
A70: CNRSE | B70: CNRSE ST-UH | C70: Facility Investment | D70: Preventive Maintenance (PM) Program | E70: C001 | F70: C001CQ | G70: 1502000 | H70: 3.3.6 | I70: Fire Protection Systems | J70: 12 | K70: MO
A71: CNRSE | B71: CNRSE ST-UH | C71: Facility Investment | D71: Preventive Maintenance (PM) Program | E71: C001 | F71: C001CR | G71: 1502000 | H71: 3.3.9 | I71: HVAC and Refrigeration Systems | J71: 12 | K71: MO
A72: CNRSE | B72: CNRSE ST-UH | C72: Facility Investment | D72: Inspection, Testing, and Certification | E72: C001 | F72: C001CS | G72: 1502000 | H72: 3.4.1 | I72: Backflow Prevention Devices | J72: 12 | K72: MO
A73: CNRSE | B73: CNRSE ST-UH | C73: Facility Investment | D73: Inspection, Testing, and Certification | E73: C001 | F73: C001CT | G73: 1502000 | H73: 3.4.2 | I73: Boilers and UPVs | J73: 12 | K73: MO
A74: CNRSE | B74: CNRSE ST-UH | C74: Facility Investment | D74: Other Recurring Services Program | E74: C001 | F74: C001CU | G74: 1502000 | H74: 3.5.1 & 3.5.7 | I74: Boiler & HVAC Seasonal Startup and Shutdown | J74: 12 | K74: MO
A75: CNRSE | B75: CNRSE ST-UH | C75: Facility Investment | D75: Other Recurring Services Program | E75: C001 | F75: C001CV | G75: 1502000 | H75: 3.5.2 | I75: Boiler Systems Water Testing and Treatment Services | J75: 12 | K75: MO
A76: CNRSE | B76: CNRSE ST-UH | C76: Facility Investment | D76: Other Recurring Services Program | E76: C001 | F76: C001CW | G76: 1502000 | H76: 3.5.8 | I76: HVAC Water Testing and Treatment Services | J76: 12 | K76: MO
A77: CNRSE | B77: CNRSE ST-UH | C77: Facility Investment | D77: Other Recurring Services Program | E77: C001 | F77: C001CX | G77: 1502000 | H77: 3.5.9 | I77: HVAC Condenser Tube Inspections | J77: 12 | K77: MO
A78: CNRSE | B78: CNRSE ST-UH | C78: Facility Investment | D78: Other Recurring Services Program | E78: C001 | F78: C001CY | G78: 1502000 | H78: 3.5.3 | I78: Change of Occupancy Maintenance (COM) | J78: 50 | K78: EA
A79: CNRSE | B79: CNRSE ST-UH | C79: Facility Investment | D79: Other Recurring Services Program | E79: C001 | F79: C001CZ | G79: 1502000 | H79: 3.5.10 | I79: Lint Traps | J79: 12 | K79: MO
A80: CNRSE | B80: Family Housing | C80: Facility Invetment | D80: Preventive Maintenance (PM) Program | E80: C001 | F80: C001DA | G80: 1502000 | H80: 3.3.9 | I80: HVAC and Refrigeration Systems | J80: 12 | K80: MO
... A87: FRC VRT | B87: FRC VRT | C87: Transportation | D87: Maintenance (Government Owned) | E87: C002 | F87: C002AB | G87: 1700000 | H87: 3.3.1.4 | I87: Repair (NTVE, WHE, MHE and AWP) | J87: 12 | K87: MO
A88: FRC VRT | B88: FRC VRT | C88: Environmental | D88: Recurring Work | E88: C002 | F88: C002AC | G88: 1800000 | H88: 3.2 | I88: Used Oil Management Services | J88: 12 | K88: MO
A89: MCSF-BI | B89: MCSF-BI | C89: Facility Management | D89: Recurring Work | E89: C003 | F89: C003AA | G89: 1501000(MCSF-BI) | H89: 3.1,3.2,3.3 | I89: USMC Maximo, ICAP and Tech Library | J89: 12 | K89: MO
A90: MCSF-BI | B90: MCSF-BI | C90: Facility Investment - MCSF-BI | D90: E/U/R Work Orders | E90: C003 | F90: C003AB | G90: 1502000(MCSF-BI) | H90: 3.1 | I90: Emergency, Urgent and Routine (E/U/R) Work | J90: 750 | K90: EA
A91: MCSF-BI | B91: MCSF-BI | C91: Facility Investment - MCSF-BI | D91: Recurring Work | E91: C003 | F91: C003AC | G91: 1502000(MCSF-BI) | H91: 3.2 | I91: Urgent and Routine Project Work Orders | J91: 48 | K91: EA
A92: MCSF-BI | B92: MCSF-BI | C92: Facility Investment - MCSF-BI | D92: Preventive Maintenance (PM) Program | E92: C003 | F92: C003AD | G92: 1502000(MCSF-BI) | H92: 3.3.1 | I92: Auxiliary Generator Systems | J92: 12 | K92: MO
A93: MCSF-BI | B93: MCSF-BI | C93: Facility Investment - MCSF-BI | D93: Preventive Maintenance (PM) Program | E93: C003 | F93: C003AE | G93: 1502000(MCSF-BI) | H93: 3.3.2 | I93: Cathodic Protection | J93: 12 | K93: MO
A94: MCSF-BI | B94: MCSF-BI | C94: Facility Investment - MCSF-BI | D94: Preventive Maintenance (PM) Program | E94: C003 | F94: C003AF | G94: 1502000(MCSF-BI) | H94: 3.3.3 | I94: Compressed Air Systems | J94: 12 | K94: MO
A95: MCSF-BI | B95: MCSF-BI | C95: Facility Investment - MCSF-BI | D95: Preventive Maintenance (PM) Program | E95: C003 | F95: C003AG | G95: 1502000(MCSF-BI) | H95: 3.3.4 | I95: Facilities, Systems, and Equipment | J95: 12 | K95: MO
A96: MCSF-BI | B96: MCSF-BI | C96: Facility Investment - MCSF-BI | D96: Preventive Maintenance (PM) Program | E96: C003 | F96: C003AH | G96: 1502000(MCSF-BI) | H96: 3.3.5 | I96: Fire Protection Systems | J96: 12 | K96: MO
A97: MCSF-BI | B97: MCSF-BI | C97: Facility Investment - MCSF-BI | D97: Preventive Maintenance (PM) Program | E97: C003 | F97: C003AJ | G97: 1502000(MCSF-BI) | H97: 3.3.6 | I97: Irrigation Equipment and Systems | J97: 12 | K97: MO
A98: MCSF-BI | B98: MCSF-BI | C98: Facility Investment - MCSF-BI | D98: Preventive Maintenance (PM) Program | E98: C003 | F98: C003AK | G98: 1502000(MCSF-BI) | H98: 3.3.7 | I98: Unfired Pressure Vessels (UPVs) | J98: 12 | K98: MO
A99: MCSF-BI | B99: MCSF-BI | C99: Facility Investment - MCSF-BI | D99: Preventive Maintenance (PM) Program | E99: C003 | F99: C003AL | G99: 1502000(MCSF-BI) | H99: 3.3.8 | I99: Vertical Transportation Equipment (VTE) | J99: 12 | K99: MO
A100: MCSF-BI | B100: MCSF-BI | C100: Facility Investment - MCSF-BI | D100: Integrated Maintenance Program (IMP) | E100: C003 | F100: C003AM | G100: 1502000(MCSF-BI) | H100: 3.4.1 | I100: Blast, Paint, and Drying Systems | J100: 12 | K100: MO
A101: MCSF-BI | B101: MCSF-BI | C101: Facility Investment - MCSF-BI | D101: Integrated Maintenance Program (IMP) | E101: C003 | F101: C003AN | G101: 1502000(MCSF-BI) | H101: 3.4.2 | I101: Boiler Systems | J101: 12 | K101: MO
A102: MCSF-BI | B102: MCSF-BI | C102: Facility Investment - MCSF-BI | D102: Integrated Maintenance Program (IMP) | E102: C003 | F102: C003AP | G102: 1502000(MCSF-BI) | H102: 3.4.3 | I102: HVAC and Refrigeration Systems | J102: 12 | K102: MO
A103: MCSF-BI | B103: MCSF-BI | C103: Facility Investment - MCSF-BI | D103: Integrated Maintenance Program (IMP) | E103: C003 | F103: C003AQ | G103: 1502000(MCSF-BI) | H103: 3.4.4 | I103: Railroad Signal and Battery House Systems and Equipment | J103: 12 | K103: MO
... A119: MCSF-BI | B119: MCSF-BI | C119: Facility Investment - MCSF-BI | D119: Other Recurring Services Program | E119: C003 | F119: C003BG | G119: 1502000(MCSF-BI) | H119: 3.6.10 | I119: Fuel Storage Tanks and Berms | J119: 12 | K119: MO
A120: MCSF-BI | B120: MCSF-BI | C120: Custodial - MCSF-BI | D120: Recurring Work | E120: C003 | F120: C003BH | G120: 1503010(MCSF-BI) | H120: 3.1 | I120: Scheduled Services | J120: 12 | K120: MO
A121: MCSF-BI | B121: MCSF-BI | C121: Custodial - MCSF-BI | D121: Recurring Work | E121: C003 | F121: C003BJ | G121: 1503010(MCSF-BI) | H121: 3.2 | I121: Custodial Service Orders | J121: 12 | K121: EA
A122: MCSF-BI | B122: MCSF-BI | C122: Pest Control - MCSF-BI | D122: Recurring Work | E122: C003 | F122: C003BK | G122: 1503020(MCSF-BI) | H122: 3.1 | I122: Scheduled Pest Control Services | J122: 12 | K122: MO
A123: MCSF-BI | B123: MCSF-BI | C123: Pest Control - MCSF-BI | D123: Recurring Work | E123: C003 | F123: C003BL | G123: 1503020(MCSF-BI) | H123: 3.2 | I123: Pest Control Service Orders | J123: 100 | K123: EA
A124: MCSF-BI | B124: MCSF-BI | C124: Pest Control - MCSF-BI | D124: Recurring Work | E124: C003 | F124: C003BM | G124: 1503020(MCSF-BI) | H124: 3.3 | I124: Pest Management Reporting | J124: 12 | K124: MO
A125: MCSF-BI | B125: MCSF-BI | C125: Integrated Solid Waste Management - MCSF-BI | D125: Recurring Work | E125: C003 | F125: C003BN | G125: 1503030(MCSF-BI) | H125: 3 | I125: Recurring Work ISWM | J125: 12 | K125: MO
A126: MCSF-BI | B126: MCSF-BI | C126: Grounds Maintenance and Landscaping - MCSF-BI | D126: Recurring Work | E126: C003 | F126: C003BP | G126: 1503050(MCSF-BI) | H126: 3.1 | I126: Improved Grounds | J126: 12 | K126: MO
A127: MCSF-BI | B127: MCSF-BI | C127: Grounds Maintenance and Landscaping - MCSF-BI | D127: Recurring Work | E127: C003 | F127: C003BQ | G127: 1503050(MCSF-BI) | H127: 3.2 | I127: Operational Areas | J127: 12 | K127: MO
A128: MCSF-BI | B128: MCSF-BI | C128: Grounds Maintenance and Landscaping - MCSF-BI | D128: Recurring Work | E128: C003 | F128: C003BR | G128: 1503050(MCSF-BI) | H128: 3.3 | I128: Storm Drainage Systems | J128: 12 | K128: MO
A129: MCSF-BI | B129: MCSF-BI | C129: Grounds Maintenance and Landscaping - MCSF-BI | D129: Recurring Work | E129: C003 | F129: C003BS | G129: 1503050(MCSF-BI) | H129: 3.4 | I129: Street Sweeping | J129: 12 | K129: MO
A130: MCSF-BI | B130: MCSF-BI | C130: Grounds Maintenance and Landscaping - MCSF-BI | D130: Recurring Work | E130: C003 | F130: C003BT | G130: 1503050(MCSF-BI) | H130: 3.5 | I130: Grounds Maintenance Service Orders | J130: 12 | K130: EA
A131: MCSF-BI | B131: MCSF-BI | C131: Environmental - MCSF-BI | D131: Recurring Work | E131: C003 | F131: C003BU | G131: 1800000(MCSF-BI) | H131: 3.1 | I131: Sampling, Field Testing and Laboratory Services | J131: 12 | K131: MO
... A136: MCSF-BI | B136: MCSF-BI | C136: Environmental - MCSF-BI | D136: Recurring Work | E136: C003 | F136: C003BZ | G136: 1800000(MCSF-BI) | H136: 3.6 | I136: Inspection of POL Tanks and Systems | J136: 12 | K136: MO
A137: NCIS | B137: NCIS | C137: Facility Investment | D137: Preventive Maintenance (PM) Program | E137: C004 | F137: C004AA | G137: 1502000 | H137: 3.3.10 | I137: Security Systems and Equipment | J137: 12 | K137: MO
A138: FLCJ | B138: FLCJ | C138: Facility Investment | D138: E/U/R Work Orders | E138: C005 | F138: C005AA | G138: 1502000 | H138: 3.1 | I138: Emergency, Urgent and Routine (E/U/R) Work | J138: 50 | K138: MO
A139: FLCJ | B139: FLCJ | C139: Facility Investment | D139: Recurring Work | E139: C005 | F139: C005AB | G139: 1502000 | H139: 3.2 | I139: Project Work Orders | J139: 10 | K139: MO
A140: FLCJ | B140: FLCJ | C140: Transportation | D140: Maintenance (Government Owned) | E140: C005 | F140: C005AC | G140: 1700000 | H140: 3.3.1.2 | I140: Preventive Maintenance, Inspection, Load Test and Certification of WHE, MHE and AWP | J140: 12 | K140: MO
...

Sheet CLIN 0008 2nd Period Opt N-RW
B1: Attachment J-0200000-17
B2: Exhibit Line Item Numbers - NAVSTA Mayport
B3: Contract No.: N6945025R0003
B5: CLIN 0008 - Non-Recurring Work - Option Period 2
B6: Provide Prices for Recurring Work in accordance with Section C, Spec Item 4
B7: ELINs C700 through C718
A8: ELIN | B8: Product Name (120 Characters) | C8: Description Extended | D8: Estimated Quantity | E8: Unit of Measure | F8: Unit Price | G8: Extended Price
A9: C700 | B9: Unit Priced Labor Hour Work - MUST BE NEGOTIATED BY KO. | C9: The Contractor shall perform all UPL work in accordance with the scope and delivery schedule negotiated per each task order. Refer to: Section C, Annex 0200000 Managmenent and Administration, Specification Item 2.15.2 Unit Priced Labor (UPL)Work (Negotiated) for description of UPL Work. Refer to: Section J, Annex 0200000 Managmenent and Administration, Attachment J-0200000-01 Definitions and Acronyms for description of Unit Priced Labor (UPL) Hour and Universal Equipment. Task order completion times will be specified on each task order. For self-performed work: the unit price proposed for Sub-ELIN C700AA will be used to determine the labor cost to the Governent. For subcontracted labor: the FBR proposed for Sub-ELIN C700AB will be used to determine the labor cost to the Governmnet. The estimated quantity of each Sub-ELIN is used to establish the ELIN Extended Price. During administration the labor Sub-ELINs may be used in any combination and quantity provided the ELIN extended price is not exceeded. The contract will not be modified to re-allocate capacity among labor SLINs. | D9: =G10+G11 -> 0 | E9: DO | F9: 1
A10: C700AA | B10: Self-Performed Unit Priced Labor Hour Work - MUST BE NEGOTIATED BY KO. | C10: The Contractor shall self-perform all UPL work in accordance with the scope and delivery schedule negotiated per each task order. Refer to: Section C, Annex 0200000 Managmenent and Administration, Specification Item 2.15.2 Unit Priced Labor (UPL)Work (Negotiated) for description of UPL Work. Refer to: Section J, Annex 0200000 Managmenent and Administration, Attachment J-0200000-01 Definitions and Acronyms for description of Unit Priced Labor (UPL) Hour and Universal Equipment. | D10: ='CLIN 0002 Base Period N-RW'!D10 -> 16000 | E10: LH
A11: C700AB | B11: Subcontractor Labor (Fixed Burden Rate) - MUST BE NEGOTIATED BY KO. | C11: The Contractor shall perform management and oversight of subcontracted non-recurring work in accordance with the scope and delivery schedule negotiated per each task order. Refer to: Section C, Annex 0200000 Management and Administration, Specification Item 2.15.2.1.2 Subcontractor Requirements description of Sub. Refer to: Section J, Annex 0200000 Management and Administration, Attachment J-0200000-01 Definitions and Acronyms for definition of Sub-Contractor Fixed Burden Rate. The estimated quantity (in dollars) is provided. A Fixed Burdened Rate (FBR) shall be entered in the Unit Price column. The FBR shall include all direct and indirect factors for management and oversight of subcontracted non-recurring work. Similar to FBR example in J-0200000-01, if a 15% markup is the Contractor's proposed FBR, the Unit Price should be $1.15. During performance, if the lowest subcontractor labor proposal is $1,000.00 and the FBR is $1.15, the labor cost to the Government will be $1,150.00. (DO - Dollars). | D11: ='CLIN 0002 Base Period N-RW'!D11 -> 1600000 | E11: DO
A12: C701 | B12: Material and Equipment - MUST BE NEGOTIATED BY KO. | C12: Provide all materials and construction equipment to perform Unit Priced Labor work per the scope and delivery schedule specified in the order. Pre-expended bin supplies and materials will not be included in the list of materials since the cost for these items were included in the labor hour unit price bid. Material prices provided by the Contractor shall be the lowest price available considering the availability of materials and the time constraints of the job. The direct material price shall be adjusted by all discounts and rebates for core value or salvage value that accrue to the Contractor. Contractor owned equipment rental rates shall be based on calculations set forth in US Army Corp of Engineers “Construction Equipment Ownership and Operating Expense Schedule (EP 1110-1-8 (Vol. 11) July 03 or latest revision) Chapter 2. The estitmate quantity (in dollars) is provided. A Fixed burdened rate (FBR) shall be entered in the Unit Price column. The FBR shall include factors for ordering, handling, and stockpiling materials and repair parts. Similar to FBR example in J-0200000-01, if a 10% markup is the Contractor's proposed FBR, the Unit Price should be $1.10. When multiplying the proposed Unit Price by the Estimated Quantity, the Extended Price should be During administration, if the vendor's invoice on material is $1,000.00 and the unit price is $1.10, the cost of the material to the government will be $1,050.00. (DO - Dollars) | D12: 2000000 | E12: DO
A13: C702 | B13: Category I Calls - MUST BE NEGOTIATED BY KO. | C13: The Contractor shall perform Category I Calls to accomplish any work identified within the entire boundary of the installation and will include a wide variety of work. Category I Calls shall be completed within two weeks of receipt of call order, unless otherwise agreed to by the customer and contractor and annotated on the CAT call request. As part of the Category I Call, the Contractor has full responsibility for any work identified up to the Category I Call Threshold of $5,000 in direct labor and direct material, per Category I Call. A Blanket Task Order (BTO) may be issued on a DD Form 1155 with a Not To Exceed (NTE) quantity and value for Non-recurring Work Category Calls. | D13: 115 | E13: EA
A14: C703 | B14: Category II Calls - MUST BE NEGOTIATED BY KO. | C14: The Contractor shall perform Category II Calls to accomplish any work identified within the entire boundary of the installation and will include a wide variety of work. Category II Calls shall be completed within three weeks of receipt of call order, unless otherwise agreed to by the customer and contractor and annotated on the CAT call request. As part of the Category II Call, the Contractor has full responsibility for any work identified up to the Category II Call Threshold of $7,500 in direct labor and direct material, per Category II Call. A Blanket Task Order (BTO) may be issued on a DD Form 1155 with a Not To Exceed (NTE) quantity and value for Non-recurring Work Category Calls. | D14: 130 | E14: EA
A15: C704 | B15: Category III Calls - MUST BE NEGOTIATED BY KO. | C15: The Contractor shall perform Category III Calls to accomplish any work identified within the entire boundary of the installation and will include a wide variety of work. Category III Calls shall be completed within 30 days of receipt of call order, unless otherwise agreed to by the customer and contractor and annotated on the CAT call request. As part of the Category III Call, the Contractor has full responsibility for any work identified up to the Category III Call Threshold of $10,000 in direct labor and direct material, per Category III Call. A Blanket Task Order (BTO) may be issued on a DD Form 1155 with a Not To Exceed (NTE) quantity and value for Non-recurring Work Category Calls. | D15: 95 | E15: EA
A16: C705 | B16: Category IV Calls - MUST BE NEGOTIATED BY KO. | C16: The Contractor shall perform Category IV Calls to accomplish any work identified within the entire boundary of the installation and will include a wide variety of work. Category IV Calls shall be completed within 30 days of receipt of call order, unless otherwise agreed to by the customer and contractor and annotated on the CAT call request. As part of the Category IV Call, the Contractor has full responsibility for any work identified up to the Category IV Call Threshold of $12,500 in direct labor and direct material, per Category IV Call. A Blanket Task Order (BTO) may be issued on a DD Form 1155 with a Not To Exceed (NTE) quantity and value for Non-recurring Work Category Calls. | D16: 50 | E16: EA
A17: C706 | B17: Category V Calls - MUST BE NEGOTIATED BY KO. | C17: The Contractor shall perform Category V Calls to accomplish any work identified within the entire boundary of the installation and will include a wide variety of work. Category V Calls shall be completed within 30 days of receipt of call order, unless otherwise agreed to by the customer and contractor and annotated on the CAT call request. As part of the Category V Call, the Contractor has full responsibility for any work identified up to the Category V Call Threshold of $15,000 in direct labor and direct material, per Category V Call. A Blanket Task Order (BTO) may be issued on a DD Form 1155 with a Not To Exceed (NTE) quantity and value for Non-recurring Work Category Calls. | D17: 40 | E17: EA
A18: C707 | B18: Category VI Calls - MUST BE NEGOTIATED BY KO. | C18: The Contractor shall perform Category VI Calls to accomplish any work identified within the entire boundary of the installation and will include a wide variety of work. Category VI Calls shall be completed within 30 days of receipt of call order, unless otherwise agreed to by the customer and contractor and annotated on the CAT call request. As part of the Category VI Call, the Contractor has full responsibility for any work identified up to the Category VI Call Threshold of $17,500 in direct labor and direct material, per Category VI Call. A Blanket Task Order (BTO) may be issued on a DD Form 1155 with a Not To Exceed (NTE) quantity and value for Non-recurring Work Category Calls. | D18: 30 | E18: EA
A19: C708 | B19: Category VII Calls - MUST BE NEGOTIATED BY KO. | C19: The Contractor shall perform Category VII Calls to accomplish any work identified within the entire boundary of the installation and will include a wide variety of work. Category VII Calls shall be completed within 30 days of receipt of call order, unless otherwise agreed to by the customer and contractor and annotated on the CAT call request. As part of the Category VII Call, the Contractor has full responsibility for any work identified up to the Category VII Call Threshold of $20,000 in direct labor and direct material, per Category VII Call. A Blanket Task Order (BTO) may be issued on a DD Form 1155 with a Not To Exceed (NTE) quantity and value for Non-recurring Work Category Calls. | D19: 20 | E19: EA
A20: C709 | B20: Water Damage Removal available on FEDMALL | C20: The Contractor shall carefully remove and dispose of damaged interior finishes to include drywall, carpeting, etc. to prevent further damage or mold/mildew development in the event of water intrusion into a facility. In addition to the removal of the interior finishes, the Contractor shall dry the effected areas by providing dehumidifaction and airflow to remove any moisture from the space. Work shall begin within 12 hours of notification. Task order completion times will be specified on each task order. | D20: 20000 | E20: SF
A21: C710 | B21: Temporary Roof Repairs available on FEDMALL | C21: The Contractor shall provide all labor, material, and equipment to perform temporary roof repairs (i.e. tarping, roof patches, polyethylene film, etc.) to minimize water intrusion into a facility. Roof repairs shall be sufficient to last for a period no less than six months before requiring replacement or further repair.Within six months from the date of the original installation, the Contractor shall provide repairs and maintenance of the temporary repair at no additional cost to the Government. Work shall begin within 12 hours of notification. Task order completion times will be specified on each task order. | D21: 30000 | E21: SF
A22: C711 | B22: Temporary HVAC 100 ton Chiller available on FEDMALL | C22: Includes monthly rental rate, delivery, set-up, periodic monitoring, and demobilization, as well as ancillary components necessary to operate (such as but not limited to: hoses, flanges, fittings, transformers, power cables, temporary ducting, etc.). Work shall be delivered within 12 hours of receipt of order. Work shall be delivered within 12 hours of receipt of order. | D22: 18 | E22: MO
A23: C712 | B23: Temporary HVAC 40 ton package unit available on FEDMALL | C23: Includes monthly rental rate, delivery, set-up, periodic monitoring, and demobilization, as well as ancillary components necessary to operate (such as but not limited to: hoses, flanges, fittings, transformers, power cables, temporary ducting, etc.). Work shall be delivered within 12 hours of receipt of order. Work shall be delivered within 12 hours of receipt of order. | D23: 18 | E23: MO
... A29: C718 | B29: Blount Island Shoreline Cleanup available on FEDMALL | C29: The Contractor shall perfrome shore cleanup, following the MCSF-BI Integrated Natural Resources Management Plan (INRMP). The shoreline clean up covers approximately 5 acres, and includes removal of debris, separation of recycling and not recycling materials, and proper disposal of the removed materials. The Contractor shall submit a report to the contracting Officer within 2 days after each service. Work shall begin within 12 hours of notification. | D29: 2 | E29: EA
A30: Total Non-recurring Work - Base Period:

Sheet CLIN 0009 -2nd Period Water RW
B1: Attachment J-0200000-17
B2: Exhibit Line Item Numbers - NAVSTA Mayport
B3: Contract No.: N6945025R0003
B6: CLIN 0009 - UT Recurring Work -Second Option Period
B7: Provide Prices for Recurring Work in accordance with Section C, Spec Item 3
B8: ELIN C015
A9: Customer/ Program | B9: Category | C9: Sub-Category | D9: ELIN | E9: Sub-ELIN | F9: Annex/Sub-annex | G9: Spec Item | H9: Description | I9: Quantity | J9: Unit of Measure | K9: Unit Price | L9: Extended Price
A10: CNRSE UT | B10: Water | C10: Recurring Services | D10: C015 | E10: C015AA | F10: 1606000 | G10: 3.1 | H10: Operation | I10: 12 | J10: MO
A11: CNRSE ST | B11: Water | C11: E/U/R Work Orders | D11: C015 | E11: C015AC | F11: 1606000 | G11: 3.2.2 | H11: E/U/R Work Orders | I11: 80 | J11: EA
A12: CNRSE ST | B12: Water | C12: Recurring Services | D12: C015 | E12: C015AE | F12: 1606000 | G12: 3.3 | H12: Preventive Maintenance (PM) | I12: 12 | J12: MO
A13: CNRSE UT | B13: Water | C13: Recurring Services | D13: C015 | E13: C015AF | F13: 1606000 | G13: 3.4 | H13: Inspection, Testing, and Certification of Fire Hydrants | I13: 12 | J13: MO

Sheet CLIN 0010 3rd Period Opt RW
C1: Attachment J-0200000-17
C2: Exhibit Line Item Numbers - NAVSTA Mayport
C3: Contract No.: N6945025R0003
C4: CLIN 0010 - Recurring Work -Third Option Period
C5: Provide Prices for Recurring Work in accordance with Section C, Spec Item 3
C6: ELINs D001 through D014
A7: Customer | B7: Funding Source | C7: Category | D7: Sub-Category | E7: ELIN | F7: Sub-ELIN | G7: Annex/Sub-annex | H7: Spec Item | I7: Description | J7: Quantity | K7: Unit of Measure | L7: Unit Price | M7: Extended Price
A8: CNRSE | B8: Port Ops | C8: Port Operations | D8: Port Ops Equipment Work Order | E8: D001 | F8: D001AA | G8: 0600000 | H8: 3.1 | I8: Port Ops Equipment Work Order | J8: 20 | K8: EA
A9: CNRSE | B9: Port Ops | C9: Port Operations | D9: Recurring Work | E9: D001 | F9: D001AB | G9: 0600000 | H9: 3.2 | I9: Ship Movements - Berthing and Hotel Services | J9: 12 | K9: MO
A10: CNRSE | B10: CNRSE FP | C10: Facility Management | D10: Recurring Work | E10: D001 | F10: D001AC | G10: 1501000 | H10: 3.1 | I10: NAVFAC Maximo Data Entry | J10: 12 | K10: MO
A11: CNRSE | B11: CNRSE FP | C11: Facility Management | D11: Recurring Work | E11: D001 | F11: D001AD | G11: 1501000 | H11: 3.2 | I11: Infrastructure Condition Assessment Program (ICAP) Services | J11: 12 | K11: MO
A12: CNRSE | B12: CNRSE FP | C12: Facility Management | D12: Recurring Work | E12: D001 | F12: D001AE | G12: 1501000 | H12: 3.3 | I12: Technical Library Operations | J12: 12 | K12: MO
A13: CNRSE | B13: CNRSE ST-FAC | C13: Facility Investment | D13: E/U/R Work Orders | E13: D001 | F13: D001AF | G13: 1502000 | H13: 3.1 | I13: Emergency, Urgent and Routine (E/U/R) Work | J13: 3658 | K13: EA
A14: CNRSE | B14: CNRSE ST-FAC | C14: Facility Investment | D14: Recurring Work | E14: D001 | F14: D001AG | G14: 1502000 | H14: 3.2 | I14: Project Work Orders | J14: 50 | K14: EA
A15: CNRSE | B15: CNRSE ST-FAC | C15: Facility Investment | D15: Preventive Maintenance (PM) Program | E15: D001 | F15: D001AH | G15: 1502000 | H15: 3.3.1 | I15: Airfield Lighting Systems | J15: 12 | K15: MO
A16: CNRSE | B16: CNRSE ST-FAC | C16: Facility Investment | D16: Preventive Maintenance (PM) Program | E16: D001 | F16: D001AJ | G16: 1502000 | H16: 3.3.2 | I16: Auxiliary Generator Systems | J16: 12 | K16: MO
A17: CNRSE | B17: CNRSE ST-FAC | C17: Facility Investment | D17: Preventive Maintenance (PM) Program | E17: D001 | F17: D001AK | G17: 1502000 | H17: 3.3.3 | I17: Boiler and Unfired Pressure Vessel (UPV) Systems | J17: 12 | K17: MO
A18: CNRSE | B18: CNRSE ST-FAC | C18: Facility Investment | D18: Preventive Maintenance (PM) Program | E18: D001 | F18: D001AL | G18: 1502000 | H18: 3.3.4 | I18: Compressed Air Systems | J18: 12 | K18: MO
A19: CNRSE | B19: CNRSE ST-FAC | C19: Facility Investment | D19: Preventive Maintenance (PM) Program | E19: D001 | F19: D001AM | G19: 1502000 | H19: 3.3.5 | I19: Door and Gate Systems | J19: 12 | K19: MO
A20: CNRSE | B20: CNRSE ST-FAC | C20: Facility Investment | D20: Preventive Maintenance (PM) Program | E20: D001 | F20: D001AN | G20: 1502000 | H20: 3.3.6 | I20: Fire Protection Systems | J20: 12 | K20: MO
A21: CNRSE | B21: CNRSE ST-FAC | C21: Facility Investment | D21: Preventive Maintenance (PM) Program | E21: D001 | F21: D001AP | G21: 1502000 | H21: 3.3.7 | I21: Frequency Converter (400 HZ) Systems | J21: 12 | K21: MO
A22: CNRSE | B22: CNRSE ST-FAC | C22: Facility Investment | D22: Preventive Maintenance (PM) Program | E22: D001 | F22: D001AQ | G22: 1502000 | H22: 3.3.8 | I22: Galley Equipment and Systems | J22: 12 | K22: MO
A23: CNRSE | B23: CNRSE ST-FAC | C23: Facility Investment | D23: Preventive Maintenance (PM) Program | E23: D001 | F23: D001AR | G23: 1502000 | H23: 3.3.9 | I23: HVAC and Refrigeration Systems | J23: 12 | K23: MO
A24: CNRSE | B24: CNRSE ST-FAC | C24: Facility Investment | D24: Preventive Maintenance (PM) Program | E24: D001 | F24: D001AS | G24: 1502000 | H24: 3.3.10 | I24: Security Systems and Equipment | J24: 12 | K24: MO
A25: CNRSE | B25: CNRSE ST-FAC | C25: Facility Investment | D25: Preventive Maintenance (PM) Program | E25: D001 | F25: D001AT | G25: 1502000 | H25: 3.3.11 | I25: Uninterruptible Power Supplies (UPS) | J25: 12 | K25: MO
A26: CNRSE | B26: CNRSE ST-FAC | C26: Facility Investment | D26: Preventive Maintenance (PM) Program | E26: D001 | F26: D001AU | G26: 1502000 | H26: 3.3.12 | I26: Vertical Transportation Equipment (VTE) | J26: 12 | K26: MO
... A42: CNRSE | B42: CNRSE ST-FAC | C42: Facility Investment | D42: Other Recurring Services Program | E42: D001 | F42: D001BL | G42: 1502000 | H42: 3.5.11 | I42: Spot Coolers | J42: 12 | K42: MO
A43: CNRSE | B43: CNRSE ST-FAC | C43: Facility Investment | D43: Other (Swimming Pools) | E43: D001 | F43: D001BM | G43: 1503040 | H43: 3.1 | I43: Pool Operator Maintenance | J43: 12 | K43: MO
A44: CNRSE | B44: CNRSE ST-FAC | C44: Facility Investment | D44: Other (Swimming Pools) | E44: D001 | F44: D001BN | G44: 1503040 | H44: 3.2 | I44: Preventive Maintenance (PM) Program | J44: 12 | K44: MO
A45: CNRSE | B45: CNRSE FX | C45: Facility Investment | D45: Other (Swimming Pools) | E45: D001 | F45: D001BP | G45: 1503040 | H45: 3.3 | I45: Water Treatment | J45: 12 | K45: MO
A46: CNRSE | B46: CNRSE UT | C46: Utilities Management | D46: Utility Operations Support | E46: D001 | F46: D001BQ | G46: 1601000 | H46: 3.1 | I46: Utility Operations Support | J46: 12 | K46: MO
A47: CNRSE | B47: CNRSE UT | C47: Utilities Management | D47: Recurring Work | E47: D001 | F47: D001BR | G47: 1601000 | H47: 3.2 | I47: Utility Infrastructure Condition Assessment Program (UICAP) Support | J47: 12 | K47: MO
A48: CNRSE | B48: CNRSE UT | C48: Utilities Management | D48: Recurring Work | E48: D001 | F48: D001BS | G48: 1601000 | H48: 3.3 | I48: Operation and Management of Facility Related Control Systems (FRCS) | J48: 12 | K48: MO
A49: CNRSE | B49: CNRSE UT | C49: Utilities Management | D49: Recurring Work | E49: D001 | F49: D001BT | G49: 1601000 | H49: 3.4 | I49: NAVFAC Maximo Data Entry | J49: 12 | K49: MO
A50: CNRSE | B50: CNRSE UT | C50: Electrical | D50: Recurring Work | E50: D001 | F50: D001BU | G50: 1602000 | H50: 3.1 | I50: Operate Electrical Power Transmission and Distribution Systems | J50: 12 | K50: MO
A51: CNRSE | B51: CNRSE ST | C51: Electrical | D51: E/U/R Work Orders | E51: D001 | F51: D001BV | G51: 1602000 | H51: 3.2 | I51: Emergency, Urgent and Routine (E/U/R) Work | J51: 220 | K51: EA
A52: CNRSE | B52: CNRSE ST | C52: Electrical | D52: Recurring Work | E52: D001 | F52: D001BW | G52: 1602000 | H52: 3.3 | I52: Preventive Maintenance (PM) Program | J52: 12 | K52: MO
A53: CNRSE | B53: CNRSE UT | C53: Electrical | D53: Other Recurring Services Program | E53: D001 | F53: D001BX | G53: 1602000 | H53: 3.4 | I53: Other Recurring Services | J53: 12 | K53: MO
A54: CNRSE | B54: CNRSE UT | C54: Electrical | D54: Other Recurring Services Program | E54: D001 | F54: D001BY | G54: 1602000 | H54: 3.5 | I54: Utility Right of Way Clearance | J54: 12 | K54: MO
A55: CNRSE | B55: CNRSE TR | C55: Transportation | D55: Operations | E55: D001 | F55: D001BZ | G55: 1700000 | H55: 3.1.1 | I55: WHE/MHE/NTVE Services | J55: 12 | K55: MO
A56: CNRSE | B56: CNRSE TR | C56: Transportation | D56: Operations | E56: D001 | F56: D001CA | G56: 1700000 | H56: 3.1.2 | I56: Fuel Delivery Services | J56: 12 | K56: MO
A57: CNRSE | B57: CNRSE TR | C57: Transportation | D57: Support Services | E57: D001 | F57: D001CB | G57: 1700000 | H57: 3.2.1 | I57: Dispatching Services | J57: 12 | K57: MO
A58: CNRSE | B58: CNRSE TR | C58: Transportation | D58: Support Services | E58: D001 | F58: D001CC | G58: 1700000 | H58: 3.2.2 | I58: Non-Government Owned Leased Vehicles | J58: 12 | K58: MO
A59: CNRSE | B59: CNRSE TR | C59: Transportation | D59: Maintenance of NTVE | E59: D001 | F59: D001CD | G59: 1700000 | H59: 3.3.1.1 | I59: New and Reassigned Vehicles and Equipment Services | J59: 12 | K59: MO
A60: CNRSE | B60: CNRSE TR | C60: Transportation | D60: Maintenance of CESE | E60: D001 | F60: D001CE | G60: 1700000 | H60: 3.3.1.2 | I60: Preventive Maintenance, Inspection, Load Test and Certification of WHE, MHE and AWP | J60: 12 | K60: MO
A61: CNRSE | B61: CNRSE TR | C61: Transportation | D61: Maintenance of CESE | E61: D001 | F61: D001CF | G61: 1700000 | H61: 3.3.1.3 | I61: Preventive Maintenance Inspection of NTVE | J61: 12 | K61: MO
A62: CNRSE | B62: CNRSE TR | C62: Transportation | D62: Maintenance of CESE | E62: D001 | F62: D001CG | G62: 1700000 | H62: 3.3.1.4 | I62: Repair (NTVE, WHE, MHE and AWP) | J62: 12 | K62: MO
A63: CNRSE | B63: CNRSE TR | C63: Transportation | D63: Maintenance of CESE | E63: D001 | F63: D001CH | G63: 1700000 | H63: 3.3.1.5 | I63: NTVE Trouble Calls | J63: 150 | K63: EA
A64: CNRSE | B64: CNRSE TR | C64: Transportation | D64: Maintenance of CESE | E64: D001 | F64: D001CJ | G64: 1700000 | H64: 3.3.2 | I64: BSVE Accessories Installation and Removal | J64: 12 | K64: MO
A65: CNRSE | B65: CNRSE EC | C65: Environmental | D65: Recurring Work | E65: D001 | F65: D001CK | G65: 1800000 | H65: 3.1 | I65: Oil and Regulated Substance Spill Response and Cleanup Ashore | J65: 12 | K65: MO
A66: CNRSE | B66: CNRSE EC | C66: Environmental | D66: Recurring Work | E66: D001 | F66: D001CL | G66: 1800000 | H66: 3.2 | I66: Used Oil Management Services | J66: 12 | K66: MO
A67: CNRSE | B67: CNRSE EC | C67: Environmental | D67: Recurring Work | E67: D001 | F67: D001CM | G67: 1800000 | H67: 3.3 | I67: Storm Water Monitoring | J67: 12 | K67: MO
A68: CNRSE | B68: CNRSE ST-UH | C68: Facility Investment | D68: E/U/R Work Orders | E68: D001 | F68: D001CN | G68: 1502000 | H68: 3.1 | I68: Emergency, Urgent and Routine (E/U/R) Work | J68: 1350 | K68: EA
A69: CNRSE | B69: CNRSE ST-UH | C69: Facility Investment | D69: Preventive Maintenance (PM) Program | E69: D001 | F69: D001CP | G69: 1502000 | H69: 3.3.3 | I69: Boiler and Unfired Pressure Vessel (UPV) Systems | J69: 12 | K69: MO
A70: CNRSE | B70: CNRSE ST-UH | C70: Facility Investment | D70: Preventive Maintenance (PM) Program | E70: D001 | F70: D001CQ | G70: 1502000 | H70: 3.3.6 | I70: Fire Protection Systems | J70: 12 | K70: MO
A71: CNRSE | B71: CNRSE ST-UH | C71: Facility Investment | D71: Preventive Maintenance (PM) Program | E71: D001 | F71: D001CR | G71: 1502000 | H71: 3.3.9 | I71: HVAC and Refrigeration Systems | J71: 12 | K71: MO
A72: CNRSE | B72: CNRSE ST-UH | C72: Facility Investment | D72: Inspection, Testing, and Certification | E72: D001 | F72: D001CS | G72: 1502000 | H72: 3.4.1 | I72: Backflow Prevention Devices | J72: 12 | K72: MO
A73: CNRSE | B73: CNRSE ST-UH | C73: Facility Investment | D73: Inspection, Testing, and Certification | E73: D001 | F73: D001CT | G73: 1502000 | H73: 3.4.2 | I73: Boilers and UPVs | J73: 12 | K73: MO
A74: CNRSE | B74: CNRSE ST-UH | C74: Facility Investment | D74: Other Recurring Services Program | E74: D001 | F74: D001CU | G74: 1502000 | H74: 3.5.1 & 3.5.7 | I74: Boiler & HVAC Seasonal Startup and Shutdown | J74: 12 | K74: MO
A75: CNRSE | B75: CNRSE ST-UH | C75: Facility Investment | D75: Other Recurring Services Program | E75: D001 | F75: D001CV | G75: 1502000 | H75: 3.5.2 | I75: Boiler Systems Water Testing and Treatment Services | J75: 12 | K75: MO
A76: CNRSE | B76: CNRSE ST-UH | C76: Facility Investment | D76: Other Recurring Services Program | E76: D001 | F76: D001CW | G76: 1502000 | H76: 3.5.8 | I76: HVAC Water Testing and Treatment Services | J76: 12 | K76: MO
A77: CNRSE | B77: CNRSE ST-UH | C77: Facility Investment | D77: Other Recurring Services Program | E77: D001 | F77: D001CX | G77: 1502000 | H77: 3.5.9 | I77: HVAC Condenser Tube Inspections | J77: 12 | K77: MO
A78: CNRSE | B78: CNRSE ST-UH | C78: Facility Investment | D78: Other Recurring Services Program | E78: D001 | F78: D001CY | G78: 1502000 | H78: 3.5.3 | I78: Change of Occupancy Maintenance (COM) | J78: 50 | K78: EA
A79: CNRSE | B79: CNRSE ST-UH | C79: Facility Investment | D79: Other Recurring Services Program | E79: D001 | F79: D001CZ | G79: 1502000 | H79: 3.5.10 | I79: Lint Traps | J79: 12 | K79: MO
A80: CNRSE | B80: Family Housing | C80: Facility Invetment | D80: Preventive Maintenance (PM) Program | E80: D001 | F80: D001DA | G80: 1502000 | H80: 3.3.9 | I80: HVAC and Refrigeration Systems | J80: 12 | K80: MO
... A87: FRC VRT | B87: FRC VRT | C87: Transportation | D87: Maintenance (Government Owned) | E87: D002 | F87: D002AB | G87: 1700000 | H87: 3.3.1.4 | I87: Repair (NTVE, WHE, MHE and AWP) | J87: 12 | K87: MO
A88: FRC VRT | B88: FRC VRT | C88: Environmental | D88: Recurring Work | E88: D002 | F88: D002AC | G88: 1800000 | H88: 3.2 | I88: Used Oil Management Services | J88: 12 | K88: MO
A89: MCSF-BI | B89: MCSF-BI | C89: Facility Management | D89: Recurring Work | E89: D003 | F89: D003AA | G89: 1501000(MCSF-BI) | H89: 3.1,3.2,3.3 | I89: USMC Maximo, ICAP and Tech Library | J89: 12 | K89: MO
A90: MCSF-BI | B90: MCSF-BI | C90: Facility Investment - MCSF-BI | D90: E/U/R Work Orders | E90: D003 | F90: D003AB | G90: 1502000(MCSF-BI) | H90: 3.1 | I90: Emergency, Urgent and Routine (E/U/R) Work | J90: 750 | K90: EA
A91: MCSF-BI | B91: MCSF-BI | C91: Facility Investment - MCSF-BI | D91: Recurring Work | E91: D003 | F91: D003AC | G91: 1502000(MCSF-BI) | H91: 3.2 | I91: Urgent and Routine Project Work Orders | J91: 48 | K91: EA
A92: MCSF-BI | B92: MCSF-BI | C92: Facility Investment - MCSF-BI | D92: Preventive Maintenance (PM) Program | E92: D003 | F92: D003AD | G92: 1502000(MCSF-BI) | H92: 3.3.1 | I92: Auxiliary Generator Systems | J92: 12 | K92: MO
A93: MCSF-BI | B93: MCSF-BI | C93: Facility Investment - MCSF-BI | D93: Preventive Maintenance (PM) Program | E93: D003 | F93: D003AE | G93: 1502000(MCSF-BI) | H93: 3.3.2 | I93: Cathodic Protection | J93: 12 | K93: MO
A94: MCSF-BI | B94: MCSF-BI | C94: Facility Investment - MCSF-BI | D94: Preventive Maintenance (PM) Program | E94: D003 | F94: D003AF | G94: 1502000(MCSF-BI) | H94: 3.3.3 | I94: Compressed Air Systems | J94: 12 | K94: MO
A95: MCSF-BI | B95: MCSF-BI | C95: Facility Investment - MCSF-BI | D95: Preventive Maintenance (PM) Program | E95: D003 | F95: D003AG | G95: 1502000(MCSF-BI) | H95: 3.3.4 | I95: Facilities, Systems, and Equipment | J95: 12 | K95: MO
A96: MCSF-BI | B96: MCSF-BI | C96: Facility Investment - MCSF-BI | D96: Preventive Maintenance (PM) Program | E96: D003 | F96: D003AH | G96: 1502000(MCSF-BI) | H96: 3.3.5 | I96: Fire Protection Systems | J96: 12 | K96: MO
A97: MCSF-BI | B97: MCSF-BI | C97: Facility Investment - MCSF-BI | D97: Preventive Maintenance (PM) Program | E97: D003 | F97: D003AJ | G97: 1502000(MCSF-BI) | H97: 3.3.6 | I97: Irrigation Equipment and Systems | J97: 12 | K97: MO
A98: MCSF-BI | B98: MCSF-BI | C98: Facility Investment - MCSF-BI | D98: Preventive Maintenance (PM) Program | E98: D003 | F98: D003AK | G98: 1502000(MCSF-BI) | H98: 3.3.7 | I98: Unfired Pressure Vessels (UPVs) | J98: 12 | K98: MO
A99: MCSF-BI | B99: MCSF-BI | C99: Facility Investment - MCSF-BI | D99: Preventive Maintenance (PM) Program | E99: D003 | F99: D003AL | G99: 1502000(MCSF-BI) | H99: 3.3.8 | I99: Vertical Transportation Equipment (VTE) | J99: 12 | K99: MO
A100: MCSF-BI | B100: MCSF-BI | C100: Facility Investment - MCSF-BI | D100: Integrated Maintenance Program (IMP) | E100: D003 | F100: D003AM | G100: 1502000(MCSF-BI) | H100: 3.4.1 | I100: Blast, Paint, and Drying Systems | J100: 12 | K100: MO
A101: MCSF-BI | B101: MCSF-BI | C101: Facility Investment - MCSF-BI | D101: Integrated Maintenance Program (IMP) | E101: D003 | F101: D003AN | G101: 1502000(MCSF-BI) | H101: 3.4.2 | I101: Boiler Systems | J101: 12 | K101: MO
A102: MCSF-BI | B102: MCSF-BI | C102: Facility Investment - MCSF-BI | D102: Integrated Maintenance Program (IMP) | E102: D003 | F102: D003AP | G102: 1502000(MCSF-BI) | H102: 3.4.3 | I102: HVAC and Refrigeration Systems | J102: 12 | K102: MO
A103: MCSF-BI | B103: MCSF-BI | C103: Facility Investment - MCSF-BI | D103: Integrated Maintenance Program (IMP) | E103: D003 | F103: D003AQ | G103: 1502000(MCSF-BI) | H103: 3.4.4 | I103: Railroad Signal and Battery House Systems and Equipment | J103: 12 | K103: MO
... A119: MCSF-BI | B119: MCSF-BI | C119: Facility Investment - MCSF-BI | D119: Other Recurring Services Program | E119: D003 | F119: D003BG | G119: 1502000(MCSF-BI) | H119: 3.6.10 | I119: Fuel Storage Tanks and Berms | J119: 12 | K119: MO
A120: MCSF-BI | B120: MCSF-BI | C120: Custodial - MCSF-BI | D120: Recurring Work | E120: D003 | F120: D003BH | G120: 1503010(MCSF-BI) | H120: 3.1 | I120: Scheduled Services | J120: 12 | K120: MO
A121: MCSF-BI | B121: MCSF-BI | C121: Custodial - MCSF-BI | D121: Recurring Work | E121: D003 | F121: D003BJ | G121: 1503010(MCSF-BI) | H121: 3.2 | I121: Custodial Service Orders | J121: 12 | K121: EA
A122: MCSF-BI | B122: MCSF-BI | C122: Pest Control - MCSF-BI | D122: Recurring Work | E122: D003 | F122: D003BK | G122: 1503020(MCSF-BI) | H122: 3.1 | I122: Scheduled Pest Control Services | J122: 12 | K122: MO
A123: MCSF-BI | B123: MCSF-BI | C123: Pest Control - MCSF-BI | D123: Recurring Work | E123: D003 | F123: D003BL | G123: 1503020(MCSF-BI) | H123: 3.2 | I123: Pest Control Service Orders | J123: 100 | K123: EA
A124: MCSF-BI | B124: MCSF-BI | C124: Pest Control - MCSF-BI | D124: Recurring Work | E124: D003 | F124: D003BM | G124: 1503020(MCSF-BI) | H124: 3.3 | I124: Pest Management Reporting | J124: 12 | K124: MO
A125: MCSF-BI | B125: MCSF-BI | C125: Integrated Solid Waste Management - MCSF-BI | D125: Recurring Work | E125: D003 | F125: D003BN | G125: 1503030(MCSF-BI) | H125: 3 | I125: Recurring Work ISWM | J125: 12 | K125: MO
A126: MCSF-BI | B126: MCSF-BI | C126: Grounds Maintenance and Landscaping - MCSF-BI | D126: Recurring Work | E126: D003 | F126: D003BP | G126: 1503050(MCSF-BI) | H126: 3.1 | I126: Improved Grounds | J126: 12 | K126: MO
A127: MCSF-BI | B127: MCSF-BI | C127: Grounds Maintenance and Landscaping - MCSF-BI | D127: Recurring Work | E127: D003 | F127: D003BQ | G127: 1503050(MCSF-BI) | H127: 3.2 | I127: Operational Areas | J127: 12 | K127: MO
A128: MCSF-BI | B128: MCSF-BI | C128: Grounds Maintenance and Landscaping - MCSF-BI | D128: Recurring Work | E128: D003 | F128: D003BR | G128: 1503050(MCSF-BI) | H128: 3.3 | I128: Storm Drainage Systems | J128: 12 | K128: MO
A129: MCSF-BI | B129: MCSF-BI | C129: Grounds Maintenance and Landscaping - MCSF-BI | D129: Recurring Work | E129: D003 | F129: D003BS | G129: 1503050(MCSF-BI) | H129: 3.4 | I129: Street Sweeping | J129: 12 | K129: MO
A130: MCSF-BI | B130: MCSF-BI | C130: Grounds Maintenance and Landscaping - MCSF-BI | D130: Recurring Work | E130: D003 | F130: D003BT | G130: 1503050(MCSF-BI) | H130: 3.5 | I130: Grounds Maintenance Service Orders | J130: 12 | K130: EA
A131: MCSF-BI | B131: MCSF-BI | C131: Environmental - MCSF-BI | D131: Recurring Work | E131: D003 | F131: D003BU | G131: 1800000(MCSF-BI) | H131: 3.1 | I131: Sampling, Field Testing and Laboratory Services | J131: 12 | K131: MO
... A136: MCSF-BI | B136: MCSF-BI | C136: Environmental - MCSF-BI | D136: Recurring Work | E136: D003 | F136: D003BZ | G136: 1800000(MCSF-BI) | H136: 3.6 | I136: Inspection of POL Tanks and Systems | J136: 12 | K136: MO
A137: NCIS | B137: NCIS | C137: Facility Investment | D137: Preventive Maintenance (PM) Program | E137: D004 | F137: D004AA | G137: 1502000 | H137: 3.3.10 | I137: Security Systems and Equipment | J137: 12 | K137: MO
A138: FLCJ | B138: FLCJ | C138: Facility Investment | D138: E/U/R Work Orders | E138: D005 | F138: D005AA | G138: 1502000 | H138: 3.1 | I138: Emergency, Urgent and Routine (E/U/R) Work | J138: 50 | K138: MO
A139: FLCJ | B139: FLCJ | C139: Facility Investment | D139: Recurring Work | E139: D005 | F139: D005AB | G139: 1502000 | H139: 3.2 | I139: Project Work Orders | J139: 10 | K139: MO
A140: FLCJ | B140: FLCJ | C140: Transportation | D140: Maintenance (Government Owned) | E140: D005 | F140: D005AC | G140: 1700000 | H140: 3.3.1.2 | I140: Preventive Maintenance, Inspection, Load Test and Certification of WHE, MHE and AWP | J140: 12 | K140: MO
...

Sheet CLIN 0011 3rd Period Opt N-RW
B1: Attachment J-0200000-17
B2: Exhibit Line Item Numbers - NAVSTA Mayport
B3: Contract No.: N6945025R0003
B5: CLIN 0011 - Non-Recurring Work - Option Period 3
B6: Provide Prices for Recurring Work in accordance with Section C, Spec Item 4
B7: ELINs D700 through D718
A8: ELIN | B8: Product Name (120 Characters) | C8: Description Extended | D8: Estimated Quantity | E8: Unit of Measure | F8: Unit Price | G8: Extended Price
A9: D700 | B9: Unit Priced Labor Hour Work - MUST BE NEGOTIATED BY KO. | C9: The Contractor shall perform all UPL work in accordance with the scope and delivery schedule negotiated per each task order. Refer to: Section C, Annex 0200000 Managmenent and Administration, Specification Item 2.15.2 Unit Priced Labor (UPL)Work (Negotiated) for description of UPL Work. Refer to: Section J, Annex 0200000 Managmenent and Administration, Attachment J-0200000-01 Definitions and Acronyms for description of Unit Priced Labor (UPL) Hour and Universal Equipment. Task order completion times will be specified on each task order. For self-performed work: the unit price proposed for Sub-ELIN D700AA will be used to determine the labor cost to the Governent. For subcontracted labor: the FBR proposed for Sub-ELIN D700AB will be used to determine the labor cost to the Governmnet. The estimated quantity of each Sub-ELIN is used to establish the ELIN Extended Price. During administration the labor Sub-ELINs may be used in any combination and quantity provided the ELIN extended price is not exceeded. The contract will not be modified to re-allocate capacity among labor SLINs. | D9: =G10+G11 -> 0 | E9: DO | F9: 1
A10: D700AA | B10: Self-Performed Unit Priced Labor Hour Work - MUST BE NEGOTIATED BY KO. | C10: The Contractor shall self-perform all UPL work in accordance with the scope and delivery schedule negotiated per each task order. Refer to: Section C, Annex 0200000 Managmenent and Administration, Specification Item 2.15.2 Unit Priced Labor (UPL)Work (Negotiated) for description of UPL Work. Refer to: Section J, Annex 0200000 Managmenent and Administration, Attachment J-0200000-01 Definitions and Acronyms for description of Unit Priced Labor (UPL) Hour and Universal Equipment. | D10: ='CLIN 0002 Base Period N-RW'!D10 -> 16000 | E10: LH
A11: D700AB | B11: Subcontractor Labor (Fixed Burden Rate) - MUST BE NEGOTIATED BY KO. | C11: The Contractor shall perform management and oversight of subcontracted non-recurring work in accordance with the scope and delivery schedule negotiated per each task order. Refer to: Section C, Annex 0200000 Management and Administration, Specification Item 2.15.2.1.2 Subcontractor Requirements description of Sub. Refer to: Section J, Annex 0200000 Management and Administration, Attachment J-0200000-01 Definitions and Acronyms for definition of Sub-Contractor Fixed Burden Rate. The estimated quantity (in dollars) is provided. A Fixed Burdened Rate (FBR) shall be entered in the Unit Price column. The FBR shall include all direct and indirect factors for management and oversight of subcontracted non-recurring work. Similar to FBR example in J-0200000-01, if a 15% markup is the Contractor's proposed FBR, the Unit Price should be $1.15. During performance, if the lowest subcontractor labor proposal is $1,000.00 and the FBR is $1.15, the labor cost to the Government will be $1,150.00. (DO - Dollars). | D11: ='CLIN 0002 Base Period N-RW'!D11 -> 1600000 | E11: DO
A12: D701 | B12: Material and Equipment - MUST BE NEGOTIATED BY KO. | C12: Provide all materials and construction equipment to perform Unit Priced Labor work per the scope and delivery schedule specified in the order. Pre-expended bin supplies and materials will not be included in the list of materials since the cost for these items were included in the labor hour unit price bid. Material prices provided by the Contractor shall be the lowest price available considering the availability of materials and the time constraints of the job. The direct material price shall be adjusted by all discounts and rebates for core value or salvage value that accrue to the Contractor. Contractor owned equipment rental rates shall be based on calculations set forth in US Army Corp of Engineers “Construction Equipment Ownership and Operating Expense Schedule (EP 1110-1-8 (Vol. 11) July 03 or latest revision) Chapter 2. The estitmate quantity (in dollars) is provided. A Fixed burdened rate (FBR) shall be entered in the Unit Price column. The FBR shall include factors for ordering, handling, and stockpiling materials and repair parts. Similar to FBR example in J-0200000-01, if a 10% markup is the Contractor's proposed FBR, the Unit Price should be $1.10. When multiplying the proposed Unit Price by the Estimated Quantity, the Extended Price should be During administration, if the vendor's invoice on material is $1,000.00 and the unit price is $1.10, the cost of the material to the government will be $1,050.00. (DO - Dollars) | D12: 2000000 | E12: DO
A13: D702 | B13: Category I Calls - MUST BE NEGOTIATED BY KO. | C13: The Contractor shall perform Category I Calls to accomplish any work identified within the entire boundary of the installation and will include a wide variety of work. Category I Calls shall be completed within two weeks of receipt of call order, unless otherwise agreed to by the customer and contractor and annotated on the CAT call request. As part of the Category I Call, the Contractor has full responsibility for any work identified up to the Category I Call Threshold of $5,000 in direct labor and direct material, per Category I Call. A Blanket Task Order (BTO) may be issued on a DD Form 1155 with a Not To Exceed (NTE) quantity and value for Non-recurring Work Category Calls. | D13: 115 | E13: EA
A14: D703 | B14: Category II Calls - MUST BE NEGOTIATED BY KO. | C14: The Contractor shall perform Category II Calls to accomplish any work identified within the entire boundary of the installation and will include a wide variety of work. Category II Calls shall be completed within three weeks of receipt of call order, unless otherwise agreed to by the customer and contractor and annotated on the CAT call request. As part of the Category II Call, the Contractor has full responsibility for any work identified up to the Category II Call Threshold of $7,500 in direct labor and direct material, per Category II Call. A Blanket Task Order (BTO) may be issued on a DD Form 1155 with a Not To Exceed (NTE) quantity and value for Non-recurring Work Category Calls. | D14: 130 | E14: EA
A15: D704 | B15: Category III Calls - MUST BE NEGOTIATED BY KO. | C15: The Contractor shall perform Category III Calls to accomplish any work identified within the entire boundary of the installation and will include a wide variety of work. Category III Calls shall be completed within 30 days of receipt of call order, unless otherwise agreed to by the customer and contractor and annotated on the CAT call request. As part of the Category III Call, the Contractor has full responsibility for any work identified up to the Category III Call Threshold of $10,000 in direct labor and direct material, per Category III Call. A Blanket Task Order (BTO) may be issued on a DD Form 1155 with a Not To Exceed (NTE) quantity and value for Non-recurring Work Category Calls. | D15: 95 | E15: EA
A16: D705 | B16: Category IV Calls - MUST BE NEGOTIATED BY KO. | C16: The Contractor shall perform Category IV Calls to accomplish any work identified within the entire boundary of the installation and will include a wide variety of work. Category IV Calls shall be completed within 30 days of receipt of call order, unless otherwise agreed to by the customer and contractor and annotated on the CAT call request. As part of the Category IV Call, the Contractor has full responsibility for any work identified up to the Category IV Call Threshold of $12,500 in direct labor and direct material, per Category IV Call. A Blanket Task Order (BTO) may be issued on a DD Form 1155 with a Not To Exceed (NTE) quantity and value for Non-recurring Work Category Calls. | D16: 50 | E16: EA
A17: D706 | B17: Category V Calls - MUST BE NEGOTIATED BY KO. | C17: The Contractor shall perform Category V Calls to accomplish any work identified within the entire boundary of the installation and will include a wide variety of work. Category V Calls shall be completed within 30 days of receipt of call order, unless otherwise agreed to by the customer and contractor and annotated on the CAT call request. As part of the Category V Call, the Contractor has full responsibility for any work identified up to the Category V Call Threshold of $15,000 in direct labor and direct material, per Category V Call. A Blanket Task Order (BTO) may be issued on a DD Form 1155 with a Not To Exceed (NTE) quantity and value for Non-recurring Work Category Calls. | D17: 40 | E17: EA
A18: D707 | B18: Category VI Calls - MUST BE NEGOTIATED BY KO. | C18: The Contractor shall perform Category VI Calls to accomplish any work identified within the entire boundary of the installation and will include a wide variety of work. Category VI Calls shall be completed within 30 days of receipt of call order, unless otherwise agreed to by the customer and contractor and annotated on the CAT call request. As part of the Category VI Call, the Contractor has full responsibility for any work identified up to the Category VI Call Threshold of $17,500 in direct labor and direct material, per Category VI Call. A Blanket Task Order (BTO) may be issued on a DD Form 1155 with a Not To Exceed (NTE) quantity and value for Non-recurring Work Category Calls. | D18: 30 | E18: EA
A19: D708 | B19: Category VII Calls - MUST BE NEGOTIATED BY KO. | C19: The Contractor shall perform Category VII Calls to accomplish any work identified within the entire boundary of the installation and will include a wide variety of work. Category VII Calls shall be completed within 30 days of receipt of call order, unless otherwise agreed to by the customer and contractor and annotated on the CAT call request. As part of the Category VII Call, the Contractor has full responsibility for any work identified up to the Category VII Call Threshold of $20,000 in direct labor and direct material, per Category VII Call. A Blanket Task Order (BTO) may be issued on a DD Form 1155 with a Not To Exceed (NTE) quantity and value for Non-recurring Work Category Calls. | D19: 20 | E19: EA
A20: D709 | B20: Water Damage Removal available on FEDMALL | C20: The Contractor shall carefully remove and dispose of damaged interior finishes to include drywall, carpeting, etc. to prevent further damage or mold/mildew development in the event of water intrusion into a facility. In addition to the removal of the interior finishes, the Contractor shall dry the effected areas by providing dehumidifaction and airflow to remove any moisture from the space. Work shall begin within 12 hours of notification. Task order completion times will be specified on each task order. | D20: 20000 | E20: SF
A21: D710 | B21: Temporary Roof Repairs available on FEDMALL | C21: The Contractor shall provide all labor, material, and equipment to perform temporary roof repairs (i.e. tarping, roof patches, polyethylene film, etc.) to minimize water intrusion into a facility. Roof repairs shall be sufficient to last for a period no less than six months before requiring replacement or further repair.Within six months from the date of the original installation, the Contractor shall provide repairs and maintenance of the temporary repair at no additional cost to the Government. Work shall begin within 12 hours of notification. Task order completion times will be specified on each task order. | D21: 30000 | E21: SF
A22: D711 | B22: Temporary HVAC 100 ton Chiller available on FEDMALL | C22: Includes monthly rental rate, delivery, set-up, periodic monitoring, and demobilization, as well as ancillary components necessary to operate (such as but not limited to: hoses, flanges, fittings, transformers, power cables, temporary ducting, etc.). Work shall be delivered within 12 hours of receipt of order. Work shall be delivered within 12 hours of receipt of order. | D22: 18 | E22: MO
A23: D712 | B23: Temporary HVAC 40 ton package unit available on FEDMALL | C23: Includes monthly rental rate, delivery, set-up, periodic monitoring, and demobilization, as well as ancillary components necessary to operate (such as but not limited to: hoses, flanges, fittings, transformers, power cables, temporary ducting, etc.). Work shall be delivered within 12 hours of receipt of order. Work shall be delivered within 12 hours of receipt of order. | D23: 18 | E23: MO
... A29: D718 | B29: Blount Island Shoreline Cleanup available on FEDMALL | C29: The Contractor shall perfrome shore cleanup, following the MCSF-BI Integrated Natural Resources Management Plan (INRMP). The shoreline clean up covers approximately 5 acres, and includes removal of debris, separation of recycling and not recycling materials, and proper disposal of the removed materials. The Contractor shall submit a report to the contracting Officer within 2 days after each service. Work shall begin within 12 hours of notification. | D29: 2 | E29: EA
A30: Total Non-recurring Work - Base Period:

Sheet CLIN 0012 -3rd Period Water RW
B1: Attachment J-0200000-17
B2: Exhibit Line Item Numbers - NAVSTA Mayport
B3: Contract No.: N6945025R0003
B6: CLIN 0012 - UT Recurring Work - Third Option Period
B7: Provide Prices for Recurring Work in accordance with Section C, Spec Item 3
B8: ELIN D015
A9: Customer/ Program | B9: Category | C9: Sub-Category | D9: ELIN | E9: Sub-ELIN | F9: Annex/Sub-annex | G9: Spec Item | H9: Description | I9: Quantity | J9: Unit of Measure | K9: Unit Price | L9: Extended Price
A10: CNRSE UT | B10: Water | C10: Recurring Services | D10: D015 | E10: D015AA | F10: 1606000 | G10: 3.1 | H10: Operation | I10: 12 | J10: MO
A11: CNRSE ST | B11: Water | C11: E/U/R Work Orders | D11: D015 | E11: D015AC | F11: 1606000 | G11: 3.2.2 | H11: E/U/R Work Orders | I11: 80 | J11: EA
A12: CNRSE ST | B12: Water | C12: Recurring Services | D12: D015 | E12: D015AE | F12: 1606000 | G12: 3.3 | H12: Preventive Maintenance (PM) | I12: 12 | J12: MO
A13: CNRSE UT | B13: Water | C13: Recurring Services | D13: D015 | E13: D015AF | F13: 1606000 | G13: 3.4 | H13: Inspection, Testing, and Certification of Fire Hydrants | I13: 12 | J13: MO

Sheet CLIN 0013 4th Period Opt RW
C1: Attachment J-0200000-17
C2: Exhibit Line Item Numbers - NAVSTA Mayport
C3: Contract No.: N6945025R0003
C4: CLIN 0013 - Recurring Work - Fourth Option Period
C5: Provide Prices for Recurring Work in accordance with Section C, Spec Item 3
C6: ELINs E001 through E014
A7: Customer | B7: Funding Source | C7: Category | D7: Sub-Category | E7: ELIN | F7: Sub-ELIN | G7: Annex/Sub-annex | H7: Spec Item | I7: Description | J7: Quantity | K7: Unit of Measure | L7: Unit Price | M7: Extended Price
A8: CNRSE | B8: Port Ops | C8: Port Operations | D8: Port Ops Equipment Work Order | E8: E001 | F8: E001AA | G8: 0600000 | H8: 3.1 | I8: Port Ops Equipment Work Order | J8: 20 | K8: EA
A9: CNRSE | B9: Port Ops | C9: Port Operations | D9: Recurring Work | E9: E001 | F9: E001AB | G9: 0600000 | H9: 3.2 | I9: Ship Movements - Berthing and Hotel Services | J9: 12 | K9: MO
A10: CNRSE | B10: CNRSE FP | C10: Facility Management | D10: Recurring Work | E10: E001 | F10: E001AC | G10: 1501000 | H10: 3.1 | I10: NAVFAC Maximo Data Entry | J10: 12 | K10: MO
A11: CNRSE | B11: CNRSE FP | C11: Facility Management | D11: Recurring Work | E11: E001 | F11: E001AD | G11: 1501000 | H11: 3.2 | I11: Infrastructure Condition Assessment Program (ICAP) Services | J11: 12 | K11: MO
A12: CNRSE | B12: CNRSE FP | C12: Facility Management | D12: Recurring Work | E12: E001 | F12: E001AE | G12: 1501000 | H12: 3.3 | I12: Technical Library Operations | J12: 12 | K12: MO
A13: CNRSE | B13: CNRSE ST-FAC | C13: Facility Investment | D13: E/U/R Work Orders | E13: E001 | F13: E001AF | G13: 1502000 | H13: 3.1 | I13: Emergency, Urgent and Routine (E/U/R) Work | J13: 3658 | K13: EA
A14: CNRSE | B14: CNRSE ST-FAC | C14: Facility Investment | D14: Recurring Work | E14: E001 | F14: E001AG | G14: 1502000 | H14: 3.2 | I14: Project Work Orders | J14: 50 | K14: EA
A15: CNRSE | B15: CNRSE ST-FAC | C15: Facility Investment | D15: Preventive Maintenance (PM) Program | E15: E001 | F15: E001AH | G15: 1502000 | H15: 3.3.1 | I15: Airfield Lighting Systems | J15: 12 | K15: MO
A16: CNRSE | B16: CNRSE ST-FAC | C16: Facility Investment | D16: Preventive Maintenance (PM) Program | E16: E001 | F16: E001AJ | G16: 1502000 | H16: 3.3.2 | I16: Auxiliary Generator Systems | J16: 12 | K16: MO
A17: CNRSE | B17: CNRSE ST-FAC | C17: Facility Investment | D17: Preventive Maintenance (PM) Program | E17: E001 | F17: E001AK | G17: 1502000 | H17: 3.3.3 | I17: Boiler and Unfired Pressure Vessel (UPV) Systems | J17: 12 | K17: MO
A18: CNRSE | B18: CNRSE ST-FAC | C18: Facility Investment | D18: Preventive Maintenance (PM) Program | E18: E001 | F18: E001AL | G18: 1502000 | H18: 3.3.4 | I18: Compressed Air Systems | J18: 12 | K18: MO
A19: CNRSE | B19: CNRSE ST-FAC | C19: Facility Investment | D19: Preventive Maintenance (PM) Program | E19: E001 | F19: E001AM | G19: 1502000 | H19: 3.3.5 | I19: Door and Gate Systems | J19: 12 | K19: MO
A20: CNRSE | B20: CNRSE ST-FAC | C20: Facility Investment | D20: Preventive Maintenance (PM) Program | E20: E001 | F20: E001AN | G20: 1502000 | H20: 3.3.6 | I20: Fire Protection Systems | J20: 12 | K20: MO
A21: CNRSE | B21: CNRSE ST-FAC | C21: Facility Investment | D21: Preventive Maintenance (PM) Program | E21: E001 | F21: E001AP | G21: 1502000 | H21: 3.3.7 | I21: Frequency Converter (400 HZ) Systems | J21: 12 | K21: MO
A22: CNRSE | B22: CNRSE ST-FAC | C22: Facility Investment | D22: Preventive Maintenance (PM) Program | E22: E001 | F22: E001AQ | G22: 1502000 | H22: 3.3.8 | I22: Galley Equipment and Systems | J22: 12 | K22: MO
A23: CNRSE | B23: CNRSE ST-FAC | C23: Facility Investment | D23: Preventive Maintenance (PM) Program | E23: E001 | F23: E001AR | G23: 1502000 | H23: 3.3.9 | I23: HVAC and Refrigeration Systems | J23: 12 | K23: MO
A24: CNRSE | B24: CNRSE ST-FAC | C24: Facility Investment | D24: Preventive Maintenance (PM) Program | E24: E001 | F24: E001AS | G24: 1502000 | H24: 3.3.10 | I24: Security Systems and Equipment | J24: 12 | K24: MO
A25: CNRSE | B25: CNRSE ST-FAC | C25: Facility Investment | D25: Preventive Maintenance (PM) Program | E25: E001 | F25: E001AT | G25: 1502000 | H25: 3.3.11 | I25: Uninterruptible Power Supplies (UPS) | J25: 12 | K25: MO
A26: CNRSE | B26: CNRSE ST-FAC | C26: Facility Investment | D26: Preventive Maintenance (PM) Program | E26: E001 | F26: E001AU | G26: 1502000 | H26: 3.3.12 | I26: Vertical Transportation Equipment (VTE) | J26: 12 | K26: MO
... A42: CNRSE | B42: CNRSE ST-FAC | C42: Facility Investment | D42: Other Recurring Services Program | E42: E001 | F42: E001BL | G42: 1502000 | H42: 3.5.11 | I42: Spot Coolers | J42: 12 | K42: MO
A43: CNRSE | B43: CNRSE ST-FAC | C43: Facility Investment | D43: Other (Swimming Pools) | E43: E001 | F43: E001BM | G43: 1503040 | H43: 3.1 | I43: Pool Operator Maintenance | J43: 12 | K43: MO
A44: CNRSE | B44: CNRSE ST-FAC | C44: Facility Investment | D44: Other (Swimming Pools) | E44: E001 | F44: E001BN | G44: 1503040 | H44: 3.2 | I44: Preventive Maintenance (PM) Program | J44: 12 | K44: MO
A45: CNRSE | B45: CNRSE FX | C45: Facility Investment | D45: Other (Swimming Pools) | E45: E001 | F45: E001BP | G45: 1503040 | H45: 3.3 | I45: Water Treatment | J45: 12 | K45: MO
A46: CNRSE | B46: CNRSE UT | C46: Utilities Management | D46: Utility Operations Support | E46: E001 | F46: E001BQ | G46: 1601000 | H46: 3.1 | I46: Utility Operations Support | J46: 12 | K46: MO
A47: CNRSE | B47: CNRSE UT | C47: Utilities Management | D47: Recurring Work | E47: E001 | F47: E001BR | G47: 1601000 | H47: 3.2 | I47: Utility Infrastructure Condition Assessment Program (UICAP) Support | J47: 12 | K47: MO
A48: CNRSE | B48: CNRSE UT | C48: Utilities Management | D48: Recurring Work | E48: E001 | F48: E001BS | G48: 1601000 | H48: 3.3 | I48: Operation and Management of Facility Related Control Systems (FRCS) | J48: 12 | K48: MO
A49: CNRSE | B49: CNRSE UT | C49: Utilities Management | D49: Recurring Work | E49: E001 | F49: E001BT | G49: 1601000 | H49: 3.4 | I49: NAVFAC Maximo Data Entry | J49: 12 | K49: MO
A50: CNRSE | B50: CNRSE UT | C50: Electrical | D50: Recurring Work | E50: E001 | F50: E001BU | G50: 1602000 | H50: 3.1 | I50: Operate Electrical Power Transmission and Distribution Systems | J50: 12 | K50: MO
A51: CNRSE | B51: CNRSE ST | C51: Electrical | D51: E/U/R Work Orders | E51: E001 | F51: E001BV | G51: 1602000 | H51: 3.2 | I51: Emergency, Urgent and Routine (E/U/R) Work | J51: 220 | K51: EA
A52: CNRSE | B52: CNRSE ST | C52: Electrical | D52: Recurring Work | E52: E001 | F52: E001BW | G52: 1602000 | H52: 3.3 | I52: Preventive Maintenance (PM) Program | J52: 12 | K52: MO
A53: CNRSE | B53: CNRSE UT | C53: Electrical | D53: Other Recurring Services Program | E53: E001 | F53: E001BX | G53: 1602000 | H53: 3.4 | I53: Other Recurring Services | J53: 12 | K53: MO
A54: CNRSE | B54: CNRSE UT | C54: Electrical | D54: Other Recurring Services Program | E54: E001 | F54: E001BY | G54: 1602000 | H54: 3.5 | I54: Utility Right of Way Clearance | J54: 12 | K54: MO
A55: CNRSE | B55: CNRSE TR | C55: Transportation | D55: Operations | E55: E001 | F55: E001BZ | G55: 1700000 | H55: 3.1.1 | I55: WHE/MHE/NTVE Services | J55: 12 | K55: MO
A56: CNRSE | B56: CNRSE TR | C56: Transportation | D56: Operations | E56: E001 | F56: E001CA | G56: 1700000 | H56: 3.1.2 | I56: Fuel Delivery Services | J56: 12 | K56: MO
A57: CNRSE | B57: CNRSE TR | C57: Transportation | D57: Support Services | E57: E001 | F57: E001CB | G57: 1700000 | H57: 3.2.1 | I57: Dispatching Services | J57: 12 | K57: MO
A58: CNRSE | B58: CNRSE TR | C58: Transportation | D58: Support Services | E58: E001 | F58: E001CC | G58: 1700000 | H58: 3.2.2 | I58: Non-Government Owned Leased Vehicles | J58: 12 | K58: MO
A59: CNRSE | B59: CNRSE TR | C59: Transportation | D59: Maintenance of NTVE | E59: E001 | F59: E001CD | G59: 1700000 | H59: 3.3.1.1 | I59: New and Reassigned Vehicles and Equipment Services | J59: 12 | K59: MO
A60: CNRSE | B60: CNRSE TR | C60: Transportation | D60: Maintenance of CESE | E60: E001 | F60: E001CE | G60: 1700000 | H60: 3.3.1.2 | I60: Preventive Maintenance, Inspection, Load Test and Certification of WHE, MHE and AWP | J60: 12 | K60: MO
A61: CNRSE | B61: CNRSE TR | C61: Transportation | D61: Maintenance of CESE | E61: E001 | F61: E001CF | G61: 1700000 | H61: 3.3.1.3 | I61: Preventive Maintenance Inspection of NTVE | J61: 12 | K61: MO
A62: CNRSE | B62: CNRSE TR | C62: Transportation | D62: Maintenance of CESE | E62: E001 | F62: E001CG | G62: 1700000 | H62: 3.3.1.4 | I62: Repair (NTVE, WHE, MHE and AWP) | J62: 12 | K62: MO
A63: CNRSE | B63: CNRSE TR | C63: Transportation | D63: Maintenance of CESE | E63: E001 | F63: E001CH | G63: 1700000 | H63: 3.3.1.5 | I63: NTVE Trouble Calls | J63: 150 | K63: EA
A64: CNRSE | B64: CNRSE TR | C64: Transportation | D64: Maintenance of CESE | E64: E001 | F64: E001CJ | G64: 1700000 | H64: 3.3.2 | I64: BSVE Accessories Installation and Removal | J64: 12 | K64: MO
A65: CNRSE | B65: CNRSE EC | C65: Environmental | D65: Recurring Work | E65: E001 | F65: E001CK | G65: 1800000 | H65: 3.1 | I65: Oil and Regulated Substance Spill Response and Cleanup Ashore | J65: 12 | K65: MO
A66: CNRSE | B66: CNRSE EC | C66: Environmental | D66: Recurring Work | E66: E001 | F66: E001CL | G66: 1800000 | H66: 3.2 | I66: Used Oil Management Services | J66: 12 | K66: MO
A67: CNRSE | B67: CNRSE EC | C67: Environmental | D67: Recurring Work | E67: E001 | F67: E001CM | G67: 1800000 | H67: 3.3 | I67: Storm Water Monitoring | J67: 12 | K67: MO
A68: CNRSE | B68: CNRSE ST-UH | C68: Facility Investment | D68: E/U/R Work Orders | E68: E001 | F68: E001CN | G68: 1502000 | H68: 3.1 | I68: Emergency, Urgent and Routine (E/U/R) Work | J68: 1350 | K68: EA
A69: CNRSE | B69: CNRSE ST-UH | C69: Facility Investment | D69: Preventive Maintenance (PM) Program | E69: E001 | F69: E001CP | G69: 1502000 | H69: 3.3.3 | I69: Boiler and Unfired Pressure Vessel (UPV) Systems | J69: 12 | K69: MO
A70: CNRSE | B70: CNRSE ST-UH | C70: Facility Investment | D70: Preventive Maintenance (PM) Program | E70: E001 | F70: E001CQ | G70: 1502000 | H70: 3.3.6 | I70: Fire Protection Systems | J70: 12 | K70: MO
A71: CNRSE | B71: CNRSE ST-UH | C71: Facility Investment | D71: Preventive Maintenance (PM) Program | E71: E001 | F71: E001CR | G71: 1502000 | H71: 3.3.9 | I71: HVAC and Refrigeration Systems | J71: 12 | K71: MO
A72: CNRSE | B72: CNRSE ST-UH | C72: Facility Investment | D72: Inspection, Testing, and Certification | E72: E001 | F72: E001CS | G72: 1502000 | H72: 3.4.1 | I72: Backflow Prevention Devices | J72: 12 | K72: MO
A73: CNRSE | B73: CNRSE ST-UH | C73: Facility Investment | D73: Inspection, Testing, and Certification | E73: E001 | F73: E001CT | G73: 1502000 | H73: 3.4.2 | I73: Boilers and UPVs | J73: 12 | K73: MO
A74: CNRSE | B74: CNRSE ST-UH | C74: Facility Investment | D74: Other Recurring Services Program | E74: E001 | F74: E001CU | G74: 1502000 | H74: 3.5.1 & 3.5.7 | I74: Boiler & HVAC Seasonal Startup and Shutdown | J74: 12 | K74: MO
A75: CNRSE | B75: CNRSE ST-UH | C75: Facility Investment | D75: Other Recurring Services Program | E75: E001 | F75: E001CV | G75: 1502000 | H75: 3.5.2 | I75: Boiler Systems Water Testing and Treatment Services | J75: 12 | K75: MO
A76: CNRSE | B76: CNRSE ST-UH | C76: Facility Investment | D76: Other Recurring Services Program | E76: E001 | F76: E001CW | G76: 1502000 | H76: 3.5.8 | I76: HVAC Water Testing and Treatment Services | J76: 12 | K76: MO
A77: CNRSE | B77: CNRSE ST-UH | C77: Facility Investment | D77: Other Recurring Services Program | E77: E001 | F77: E001CX | G77: 1502000 | H77: 3.5.9 | I77: HVAC Condenser Tube Inspections | J77: 12 | K77: MO
A78: CNRSE | B78: CNRSE ST-UH | C78: Facility Investment | D78: Other Recurring Services Program | E78: E001 | F78: E001CY | G78: 1502000 | H78: 3.5.3 | I78: Change of Occupancy Maintenance (COM) | J78: 50 | K78: EA
A79: CNRSE | B79: CNRSE ST-UH | C79: Facility Investment | D79: Other Recurring Services Program | E79: E001 | F79: E001CZ | G79: 1502000 | H79: 3.5.10 | I79: Lint Traps | J79: 12 | K79: MO
A80: CNRSE | B80: Family Housing | C80: Facility Invetment | D80: Preventive Maintenance (PM) Program | E80: E001 | F80: E001DA | G80: 1502000 | H80: 3.3.9 | I80: HVAC and Refrigeration Systems | J80: 12 | K80: MO
... A87: FRC VRT | B87: FRC VRT | C87: Transportation | D87: Maintenance (Government Owned) | E87: E002 | F87: E002AB | G87: 1700000 | H87: 3.3.1.4 | I87: Repair (NTVE, WHE, MHE and AWP) | J87: 12 | K87: MO
A88: FRC VRT | B88: FRC VRT | C88: Environmental | D88: Recurring Work | E88: E002 | F88: E002AC | G88: 1800000 | H88: 3.2 | I88: Used Oil Management Services | J88: 12 | K88: MO
A89: MCSF-BI | B89: MCSF-BI | C89: Facility Management | D89: Recurring Work | E89: E003 | F89: E003AA | G89: 1501000(MCSF-BI) | H89: 3.1,3.2,3.3 | I89: USMC Maximo, ICAP and Tech Library | J89: 12 | K89: MO
A90: MCSF-BI | B90: MCSF-BI | C90: Facility Investment - MCSF-BI | D90: E/U/R Work Orders | E90: E003 | F90: E003AB | G90: 1502000(MCSF-BI) | H90: 3.1 | I90: Emergency, Urgent and Routine (E/U/R) Work | J90: 750 | K90: EA
A91: MCSF-BI | B91: MCSF-BI | C91: Facility Investment - MCSF-BI | D91: Recurring Work | E91: E003 | F91: E003AC | G91: 1502000(MCSF-BI) | H91: 3.2 | I91: Urgent and Routine Project Work Orders | J91: 48 | K91: EA
A92: MCSF-BI | B92: MCSF-BI | C92: Facility Investment - MCSF-BI | D92: Preventive Maintenance (PM) Program | E92: E003 | F92: E003AD | G92: 1502000(MCSF-BI) | H92: 3.3.1 | I92: Auxiliary Generator Systems | J92: 12 | K92: MO
A93: MCSF-BI | B93: MCSF-BI | C93: Facility Investment - MCSF-BI | D93: Preventive Maintenance (PM) Program | E93: E003 | F93: E003AE | G93: 1502000(MCSF-BI) | H93: 3.3.2 | I93: Cathodic Protection | J93: 12 | K93: MO
A94: MCSF-BI | B94: MCSF-BI | C94: Facility Investment - MCSF-BI | D94: Preventive Maintenance (PM) Program | E94: E003 | F94: E003AF | G94: 1502000(MCSF-BI) | H94: 3.3.3 | I94: Compressed Air Systems | J94: 12 | K94: MO
A95: MCSF-BI | B95: MCSF-BI | C95: Facility Investment - MCSF-BI | D95: Preventive Maintenance (PM) Program | E95: E003 | F95: E003AG | G95: 1502000(MCSF-BI) | H95: 3.3.4 | I95: Facilities, Systems, and Equipment | J95: 12 | K95: MO
A96: MCSF-BI | B96: MCSF-BI | C96: Facility Investment - MCSF-BI | D96: Preventive Maintenance (PM) Program | E96: E003 | F96: E003AH | G96: 1502000(MCSF-BI) | H96: 3.3.5 | I96: Fire Protection Systems | J96: 12 | K96: MO
A97: MCSF-BI | B97: MCSF-BI | C97: Facility Investment - MCSF-BI | D97: Preventive Maintenance (PM) Program | E97: E003 | F97: E003AJ | G97: 1502000(MCSF-BI) | H97: 3.3.6 | I97: Irrigation Equipment and Systems | J97: 12 | K97: MO
A98: MCSF-BI | B98: MCSF-BI | C98: Facility Investment - MCSF-BI | D98: Preventive Maintenance (PM) Program | E98: E003 | F98: E003AK | G98: 1502000(MCSF-BI) | H98: 3.3.7 | I98: Unfired Pressure Vessels (UPVs) | J98: 12 | K98: MO
A99: MCSF-BI | B99: MCSF-BI | C99: Facility Investment - MCSF-BI | D99: Preventive Maintenance (PM) Program | E99: E003 | F99: E003AL | G99: 1502000(MCSF-BI) | H99: 3.3.8 | I99: Vertical Transportation Equipment (VTE) | J99: 12 | K99: MO
A100: MCSF-BI | B100: MCSF-BI | C100: Facility Investment - MCSF-BI | D100: Integrated Maintenance Program (IMP) | E100: E003 | F100: E003AM | G100: 1502000(MCSF-BI) | H100: 3.4.1 | I100: Blast, Paint, and Drying Systems | J100: 12 | K100: MO
A101: MCSF-BI | B101: MCSF-BI | C101: Facility Investment - MCSF-BI | D101: Integrated Maintenance Program (IMP) | E101: E003 | F101: E003AN | G101: 1502000(MCSF-BI) | H101: 3.4.2 | I101: Boiler Systems | J101: 12 | K101: MO
A102: MCSF-BI | B102: MCSF-BI | C102: Facility Investment - MCSF-BI | D102: Integrated Maintenance Program (IMP) | E102: E003 | F102: E003AP | G102: 1502000(MCSF-BI) | H102: 3.4.3 | I102: HVAC and Refrigeration Systems | J102: 12 | K102: MO
A103: MCSF-BI | B103: MCSF-BI | C103: Facility Investment - MCSF-BI | D103: Integrated Maintenance Program (IMP) | E103: E003 | F103: E003AQ | G103: 1502000(MCSF-BI) | H103: 3.4.4 | I103: Railroad Signal and Battery House Systems and Equipment | J103: 12 | K103: MO
... A119: MCSF-BI | B119: MCSF-BI | C119: Facility Investment - MCSF-BI | D119: Other Recurring Services Program | E119: E003 | F119: E003BG | G119: 1502000(MCSF-BI) | H119: 3.6.10 | I119: Fuel Storage Tanks and Berms | J119: 12 | K119: MO
A120: MCSF-BI | B120: MCSF-BI | C120: Custodial - MCSF-BI | D120: Recurring Work | E120: E003 | F120: E003BH | G120: 1503010(MCSF-BI) | H120: 3.1 | I120: Scheduled Services | J120: 12 | K120: MO
A121: MCSF-BI | B121: MCSF-BI | C121: Custodial - MCSF-BI | D121: Recurring Work | E121: E003 | F121: E003BJ | G121: 1503010(MCSF-BI) | H121: 3.2 | I121: Custodial Service Orders | J121: 12 | K121: EA
A122: MCSF-BI | B122: MCSF-BI | C122: Pest Control - MCSF-BI | D122: Recurring Work | E122: E003 | F122: E003BK | G122: 1503020(MCSF-BI) | H122: 3.1 | I122: Scheduled Pest Control Services | J122: 12 | K122: MO
A123: MCSF-BI | B123: MCSF-BI | C123: Pest Control - MCSF-BI | D123: Recurring Work | E123: E003 | F123: E003BL | G123: 1503020(MCSF-BI) | H123: 3.2 | I123: Pest Control Service Orders | J123: 100 | K123: EA
A124: MCSF-BI | B124: MCSF-BI | C124: Pest Control - MCSF-BI | D124: Recurring Work | E124: E003 | F124: E003BM | G124: 1503020(MCSF-BI) | H124: 3.3 | I124: Pest Management Reporting | J124: 12 | K124: MO
A125: MCSF-BI | B125: MCSF-BI | C125: Integrated Solid Waste Management - MCSF-BI | D125: Recurring Work | E125: E003 | F125: E003BN | G125: 1503030(MCSF-BI) | H125: 3 | I125: Recurring Work ISWM | J125: 12 | K125: MO
A126: MCSF-BI | B126: MCSF-BI | C126: Grounds Maintenance and Landscaping - MCSF-BI | D126: Recurring Work | E126: E003 | F126: E003BP | G126: 1503050(MCSF-BI) | H126: 3.1 | I126: Improved Grounds | J126: 12 | K126: MO
A127: MCSF-BI | B127: MCSF-BI | C127: Grounds Maintenance and Landscaping - MCSF-BI | D127: Recurring Work | E127: E003 | F127: E003BQ | G127: 1503050(MCSF-BI) | H127: 3.2 | I127: Operational Areas | J127: 12 | K127: MO
A128: MCSF-BI | B128: MCSF-BI | C128: Grounds Maintenance and Landscaping - MCSF-BI | D128: Recurring Work | E128: E003 | F128: E003BR | G128: 1503050(MCSF-BI) | H128: 3.3 | I128: Storm Drainage Systems | J128: 12 | K128: MO
A129: MCSF-BI | B129: MCSF-BI | C129: Grounds Maintenance and Landscaping - MCSF-BI | D129: Recurring Work | E129: E003 | F129: E003BS | G129: 1503050(MCSF-BI) | H129: 3.4 | I129: Street Sweeping | J129: 12 | K129: MO
A130: MCSF-BI | B130: MCSF-BI | C130: Grounds Maintenance and Landscaping - MCSF-BI | D130: Recurring Work | E130: E003 | F130: E003BT | G130: 1503050(MCSF-BI) | H130: 3.5 | I130: Grounds Maintenance Service Orders | J130: 12 | K130: EA
A131: MCSF-BI | B131: MCSF-BI | C131: Environmental - MCSF-BI | D131: Recurring Work | E131: E003 | F131: E003BU | G131: 1800000(MCSF-BI) | H131: 3.1 | I131: Sampling, Field Testing and Laboratory Services | J131: 12 | K131: MO
... A136: MCSF-BI | B136: MCSF-BI | C136: Environmental - MCSF-BI | D136: Recurring Work | E136: E003 | F136: E003BZ | G136: 1800000(MCSF-BI) | H136: 3.6 | I136: Inspection of POL Tanks and Systems | J136: 12 | K136: MO
A137: NCIS | B137: NCIS | C137: Facility Investment | D137: Preventive Maintenance (PM) Program | E137: E004 | F137: E004AA | G137: 1502000 | H137: 3.3.10 | I137: Security Systems and Equipment | J137: 12 | K137: MO
A138: FLCJ | B138: FLCJ | C138: Facility Investment | D138: E/U/R Work Orders | E138: E005 | F138: E005AA | G138: 1502000 | H138: 3.1 | I138: Emergency, Urgent and Routine (E/U/R) Work | J138: 50 | K138: MO
A139: FLCJ | B139: FLCJ | C139: Facility Investment | D139: Recurring Work | E139: E005 | F139: E005AB | G139: 1502000 | H139: 3.2 | I139: Project Work Orders | J139: 10 | K139: MO
A140: FLCJ | B140: FLCJ | C140: Transportation | D140: Maintenance (Government Owned) | E140: E005 | F140: E005AC | G140: 1700000 | H140: 3.3.1.2 | I140: Preventive Maintenance, Inspection, Load Test and Certification of WHE, MHE and AWP | J140: 12 | K140: MO
...

Sheet CLIN 0014 4th Period Opt N-RW
B1: Attachment J-0200000-17
B2: Exhibit Line Item Numbers - NAVSTA Mayport
B3: Contract No.: N6945025R0003
B5: CLIN 0014 - Non-Recurring Work - Option Period 4
B6: Provide Prices for Recurring Work in accordance with Section C, Spec Item 4
B7: ELINs E700 through E718
A8: ELIN | B8: Product Name (120 Characters) | C8: Description Extended | D8: Estimated Quantity | E8: Unit of Measure | F8: Unit Price | G8: Extended Price
A9: E700 | B9: Unit Priced Labor Hour Work - MUST BE NEGOTIATED BY KO. | C9: The Contractor shall perform all UPL work in accordance with the scope and delivery schedule negotiated per each task order. Refer to: Section C, Annex 0200000 Managmenent and Administration, Specification Item 2.15.2 Unit Priced Labor (UPL)Work (Negotiated) for description of UPL Work. Refer to: Section J, Annex 0200000 Managmenent and Administration, Attachment J-0200000-01 Definitions and Acronyms for description of Unit Priced Labor (UPL) Hour and Universal Equipment. Task order completion times will be specified on each task order. For self-performed work: the unit price proposed for Sub-ELIN E700AA will be used to determine the labor cost to the Governent. For subcontracted labor: the FBR proposed for Sub-ELIN E700AB will be used to determine the labor cost to the Governmnet. The estimated quantity of each Sub-ELIN is used to establish the ELIN Extended Price. During administration the labor Sub-ELINs may be used in any combination and quantity provided the ELIN extended price is not exceeded. The contract will not be modified to re-allocate capacity among labor SLINs. | D9: =G10+G11 -> 0 | E9: DO | F9: 1
A10: E700AA | B10: Self-Performed Unit Priced Labor Hour Work - MUST BE NEGOTIATED BY KO. | C10: The Contractor shall self-perform all UPL work in accordance with the scope and delivery schedule negotiated per each task order. Refer to: Section C, Annex 0200000 Managmenent and Administration, Specification Item 2.15.2 Unit Priced Labor (UPL)Work (Negotiated) for description of UPL Work. Refer to: Section J, Annex 0200000 Managmenent and Administration, Attachment J-0200000-01 Definitions and Acronyms for description of Unit Priced Labor (UPL) Hour and Universal Equipment. | D10: ='CLIN 0002 Base Period N-RW'!D10 -> 16000 | E10: LH
A11: E700AB | B11: Subcontractor Labor (Fixed Burden Rate) - MUST BE NEGOTIATED BY KO. | C11: The Contractor shall perform management and oversight of subcontracted non-recurring work in accordance with the scope and delivery schedule negotiated per each task order. Refer to: Section C, Annex 0200000 Management and Administration, Specification Item 2.15.2.1.2 Subcontractor Requirements description of Sub. Refer to: Section J, Annex 0200000 Management and Administration, Attachment J-0200000-01 Definitions and Acronyms for definition of Sub-Contractor Fixed Burden Rate. The estimated quantity (in dollars) is provided. A Fixed Burdened Rate (FBR) shall be entered in the Unit Price column. The FBR shall include all direct and indirect factors for management and oversight of subcontracted non-recurring work. Similar to FBR example in J-0200000-01, if a 15% markup is the Contractor's proposed FBR, the Unit Price should be $1.15. During performance, if the lowest subcontractor labor proposal is $1,000.00 and the FBR is $1.15, the labor cost to the Government will be $1,150.00. (DO - Dollars). | D11: ='CLIN 0002 Base Period N-RW'!D11 -> 1600000 | E11: DO
A12: E701 | B12: Material and Equipment - MUST BE NEGOTIATED BY KO. | C12: Provide all materials and construction equipment to perform Unit Priced Labor work per the scope and delivery schedule specified in the order. Pre-expended bin supplies and materials will not be included in the list of materials since the cost for these items were included in the labor hour unit price bid. Material prices provided by the Contractor shall be the lowest price available considering the availability of materials and the time constraints of the job. The direct material price shall be adjusted by all discounts and rebates for core value or salvage value that accrue to the Contractor. Contractor owned equipment rental rates shall be based on calculations set forth in US Army Corp of Engineers “Construction Equipment Ownership and Operating Expense Schedule (EP 1110-1-8 (Vol. 11) July 03 or latest revision) Chapter 2. The estitmate quantity (in dollars) is provided. A Fixed burdened rate (FBR) shall be entered in the Unit Price column. The FBR shall include factors for ordering, handling, and stockpiling materials and repair parts. Similar to FBR example in J-0200000-01, if a 10% markup is the Contractor's proposed FBR, the Unit Price should be $1.10. When multiplying the proposed Unit Price by the Estimated Quantity, the Extended Price should be During administration, if the vendor's invoice on material is $1,000.00 and the unit price is $1.10, the cost of the material to the government will be $1,050.00. (DO - Dollars) | D12: 2000000 | E12: DO
A13: E702 | B13: Category I Calls - MUST BE NEGOTIATED BY KO. | C13: The Contractor shall perform Category I Calls to accomplish any work identified within the entire boundary of the installation and will include a wide variety of work. Category I Calls shall be completed within two weeks of receipt of call order, unless otherwise agreed to by the customer and contractor and annotated on the CAT call request. As part of the Category I Call, the Contractor has full responsibility for any work identified up to the Category I Call Threshold of $5,000 in direct labor and direct material, per Category I Call. A Blanket Task Order (BTO) may be issued on a DD Form 1155 with a Not To Exceed (NTE) quantity and value for Non-recurring Work Category Calls. | D13: 115 | E13: EA
A14: E703 | B14: Category II Calls - MUST BE NEGOTIATED BY KO. | C14: The Contractor shall perform Category II Calls to accomplish any work identified within the entire boundary of the installation and will include a wide variety of work. Category II Calls shall be completed within three weeks of receipt of call order, unless otherwise agreed to by the customer and contractor and annotated on the CAT call request. As part of the Category II Call, the Contractor has full responsibility for any work identified up to the Category II Call Threshold of $7,500 in direct labor and direct material, per Category II Call. A Blanket Task Order (BTO) may be issued on a DD Form 1155 with a Not To Exceed (NTE) quantity and value for Non-recurring Work Category Calls. | D14: 130 | E14: EA
A15: E704 | B15: Category III Calls - MUST BE NEGOTIATED BY KO. | C15: The Contractor shall perform Category III Calls to accomplish any work identified within the entire boundary of the installation and will include a wide variety of work. Category III Calls shall be completed within 30 days of receipt of call order, unless otherwise agreed to by the customer and contractor and annotated on the CAT call request. As part of the Category III Call, the Contractor has full responsibility for any work identified up to the Category III Call Threshold of $10,000 in direct labor and direct material, per Category III Call. A Blanket Task Order (BTO) may be issued on a DD Form 1155 with a Not To Exceed (NTE) quantity and value for Non-recurring Work Category Calls. | D15: 95 | E15: EA
A16: E705 | B16: Category IV Calls - MUST BE NEGOTIATED BY KO. | C16: The Contractor shall perform Category IV Calls to accomplish any work identified within the entire boundary of the installation and will include a wide variety of work. Category IV Calls shall be completed within 30 days of receipt of call order, unless otherwise agreed to by the customer and contractor and annotated on the CAT call request. As part of the Category IV Call, the Contractor has full responsibility for any work identified up to the Category IV Call Threshold of $12,500 in direct labor and direct material, per Category IV Call. A Blanket Task Order (BTO) may be issued on a DD Form 1155 with a Not To Exceed (NTE) quantity and value for Non-recurring Work Category Calls. | D16: 50 | E16: EA
A17: E706 | B17: Category V Calls - MUST BE NEGOTIATED BY KO. | C17: The Contractor shall perform Category V Calls to accomplish any work identified within the entire boundary of the installation and will include a wide variety of work. Category V Calls shall be completed within 30 days of receipt of call order, unless otherwise agreed to by the customer and contractor and annotated on the CAT call request. As part of the Category V Call, the Contractor has full responsibility for any work identified up to the Category V Call Threshold of $15,000 in direct labor and direct material, per Category V Call. A Blanket Task Order (BTO) may be issued on a DD Form 1155 with a Not To Exceed (NTE) quantity and value for Non-recurring Work Category Calls. | D17: 40 | E17: EA
A18: E707 | B18: Category VI Calls - MUST BE NEGOTIATED BY KO. | C18: The Contractor shall perform Category VI Calls to accomplish any work identified within the entire boundary of the installation and will include a wide variety of work. Category VI Calls shall be completed within 30 days of receipt of call order, unless otherwise agreed to by the customer and contractor and annotated on the CAT call request. As part of the Category VI Call, the Contractor has full responsibility for any work identified up to the Category VI Call Threshold of $17,500 in direct labor and direct material, per Category VI Call. A Blanket Task Order (BTO) may be issued on a DD Form 1155 with a Not To Exceed (NTE) quantity and value for Non-recurring Work Category Calls. | D18: 30 | E18: EA
A19: E708 | B19: Category VII Calls - MUST BE NEGOTIATED BY KO. | C19: The Contractor shall perform Category VII Calls to accomplish any work identified within the entire boundary of the installation and will include a wide variety of work. Category VII Calls shall be completed within 30 days of receipt of call order, unless otherwise agreed to by the customer and contractor and annotated on the CAT call request. As part of the Category VII Call, the Contractor has full responsibility for any work identified up to the Category VII Call Threshold of $20,000 in direct labor and direct material, per Category VII Call. A Blanket Task Order (BTO) may be issued on a DD Form 1155 with a Not To Exceed (NTE) quantity and value for Non-recurring Work Category Calls. | D19: 20 | E19: EA
A20: E709 | B20: Water Damage Removal available on FEDMALL | C20: The Contractor shall carefully remove and dispose of damaged interior finishes to include drywall, carpeting, etc. to prevent further damage or mold/mildew development in the event of water intrusion into a facility. In addition to the removal of the interior finishes, the Contractor shall dry the effected areas by providing dehumidifaction and airflow to remove any moisture from the space. Work shall begin within 12 hours of notification. Task order completion times will be specified on each task order. | D20: 20000 | E20: SF
A21: E710 | B21: Temporary Roof Repairs available on FEDMALL | C21: The Contractor shall provide all labor, material, and equipment to perform temporary roof repairs (i.e. tarping, roof patches, polyethylene film, etc.) to minimize water intrusion into a facility. Roof repairs shall be sufficient to last for a period no less than six months before requiring replacement or further repair.Within six months from the date of the original installation, the Contractor shall provide repairs and maintenance of the temporary repair at no additional cost to the Government. Work shall begin within 12 hours of notification. Task order completion times will be specified on each task order. | D21: 30000 | E21: SF
A22: E711 | B22: Temporary HVAC 100 ton Chiller available on FEDMALL | C22: Includes monthly rental rate, delivery, set-up, periodic monitoring, and demobilization, as well as ancillary components necessary to operate (such as but not limited to: hoses, flanges, fittings, transformers, power cables, temporary ducting, etc.). Work shall be delivered within 12 hours of receipt of order. Work shall be delivered within 12 hours of receipt of order. | D22: 18 | E22: MO
A23: E712 | B23: Temporary HVAC 40 ton package unit available on FEDMALL | C23: Includes monthly rental rate, delivery, set-up, periodic monitoring, and demobilization, as well as ancillary components necessary to operate (such as but not limited to: hoses, flanges, fittings, transformers, power cables, temporary ducting, etc.). Work shall be delivered within 12 hours of receipt of order. Work shall be delivered within 12 hours of receipt of order. | D23: 18 | E23: MO
... A29: E718 | B29: Blount Island Shoreline Cleanup available on FEDMALL | C29: The Contractor shall perfrome shore cleanup, following the MCSF-BI Integrated Natural Resources Management Plan (INRMP). The shoreline clean up covers approximately 5 acres, and includes removal of debris, separation of recycling and not recycling materials, and proper disposal of the removed materials. The Contractor shall submit a report to the contracting Officer within 2 days after each service. Work shall begin within 12 hours of notification. | D29: 2 | E29: EA
A30: Total Non-recurring Work - Base Period:

Sheet CLIN 0015 -4th Period Water RW
B1: Attachment J-0200000-17
B2: Exhibit Line Item Numbers - NAVSTA Mayport
B3: Contract No.: N6945025R0003
B6: CLIN 0015 - UT Recurring Work - Fourth Option Period
B7: Provide Prices for Recurring Work in accordance with Section C, Spec Item 3
B8: ELIN E017
A9: Customer/ Program | B9: Category | C9: Sub-Category | D9: ELIN | E9: Sub-ELIN | F9: Annex/Sub-annex | G9: Spec Item | H9: Description | I9: Quantity | J9: Unit of Measure | K9: Unit Price | L9: Extended Price
A10: CNRSE UT | B10: Water | C10: Recurring Services | D10: E017 | E10: E017AA | F10: 1606000 | G10: 3.1 | H10: Operation | I10: 12 | J10: MO
A11: CNRSE ST | B11: Water | C11: E/U/R Work Orders | D11: E017 | E11: E017AC | F11: 1606000 | G11: 3.2.2 | H11: E/U/R Work Orders | I11: 80 | J11: EA
A12: CNRSE ST | B12: Water | C12: Recurring Services | D12: E017 | E12: E017AE | F12: 1606000 | G12: 3.3 | H12: Preventive Maintenance (PM) | I12: 12 | J12: MO
A13: CNRSE UT | B13: Water | C13: Recurring Services | D13: E017 | E13: E017AF | F13: 1606000 | G13: 3.4 | H13: Inspection, Testing, and Certification of Fire Hydrants | I13: 12 | J13: MO

Sheet CLIN 0016 5th Period Opt RW
C1: Attachment J-0200000-17
C2: Exhibit Line Item Numbers - NAVSTA Mayport
C3: Contract No.: N6945025R0003
C4: CLIN 0016 - Recurring Work - Fifth Option Period
C5: Provide Prices for Recurring Work in accordance with Section C, Spec Item 3
C6: ELINs F001 through F014
A7: Customer | B7: Funding Source | C7: Category | D7: Sub-Category | E7: ELIN | F7: Sub-ELIN | G7: Annex/Sub-annex | H7: Spec Item | I7: Description | J7: Quantity | K7: Unit of Measure | L7: Unit Price | M7: Extended Price
A8: CNRSE | B8: Port Ops | C8: Port Operations | D8: Port Ops Equipment Work Order | E8: F001 | F8: F001AA | G8: 0600000 | H8: 3.1 | I8: Port Ops Equipment Work Order | J8: 20 | K8: EA
A9: CNRSE | B9: Port Ops | C9: Port Operations | D9: Recurring Work | E9: F001 | F9: F001AB | G9: 0600000 | H9: 3.2 | I9: Ship Movements - Berthing and Hotel Services | J9: 12 | K9: MO
A10: CNRSE | B10: CNRSE FP | C10: Facility Management | D10: Recurring Work | E10: F001 | F10: F001AC | G10: 1501000 | H10: 3.1 | I10: NAVFAC Maximo Data Entry | J10: 12 | K10: MO
A11: CNRSE | B11: CNRSE FP | C11: Facility Management | D11: Recurring Work | E11: F001 | F11: F001AD | G11: 1501000 | H11: 3.2 | I11: Infrastructure Condition Assessment Program (ICAP) Services | J11: 12 | K11: MO
A12: CNRSE | B12: CNRSE FP | C12: Facility Management | D12: Recurring Work | E12: F001 | F12: F001AE | G12: 1501000 | H12: 3.3 | I12: Technical Library Operations | J12: 12 | K12: MO
A13: CNRSE | B13: CNRSE ST-FAC | C13: Facility Investment | D13: E/U/R Work Orders | E13: F001 | F13: F001AF | G13: 1502000 | H13: 3.1 | I13: Emergency, Urgent and Routine (E/U/R) Work | J13: 3658 | K13: EA
A14: CNRSE | B14: CNRSE ST-FAC | C14: Facility Investment | D14: Recurring Work | E14: F001 | F14: F001AG | G14: 1502000 | H14: 3.2 | I14: Project Work Orders | J14: 50 | K14: EA
A15: CNRSE | B15: CNRSE ST-FAC | C15: Facility Investment | D15: Preventive Maintenance (PM) Program | E15: F001 | F15: F001AH | G15: 1502000 | H15: 3.3.1 | I15: Airfield Lighting Systems | J15: 12 | K15: MO
A16: CNRSE | B16: CNRSE ST-FAC | C16: Facility Investment | D16: Preventive Maintenance (PM) Program | E16: F001 | F16: F001AJ | G16: 1502000 | H16: 3.3.2 | I16: Auxiliary Generator Systems | J16: 12 | K16: MO
A17: CNRSE | B17: CNRSE ST-FAC | C17: Facility Investment | D17: Preventive Maintenance (PM) Program | E17: F001 | F17: F001AK | G17: 1502000 | H17: 3.3.3 | I17: Boiler and Unfired Pressure Vessel (UPV) Systems | J17: 12 | K17: MO
A18: CNRSE | B18: CNRSE ST-FAC | C18: Facility Investment | D18: Preventive Maintenance (PM) Program | E18: F001 | F18: F001AL | G18: 1502000 | H18: 3.3.4 | I18: Compressed Air Systems | J18: 12 | K18: MO
A19: CNRSE | B19: CNRSE ST-FAC | C19: Facility Investment | D19: Preventive Maintenance (PM) Program | E19: F001 | F19: F001AM | G19: 1502000 | H19: 3.3.5 | I19: Door and Gate Systems | J19: 12 | K19: MO
A20: CNRSE | B20: CNRSE ST-FAC | C20: Facility Investment | D20: Preventive Maintenance (PM) Program | E20: F001 | F20: F001AN | G20: 1502000 | H20: 3.3.6 | I20: Fire Protection Systems | J20: 12 | K20: MO
A21: CNRSE | B21: CNRSE ST-FAC | C21: Facility Investment | D21: Preventive Maintenance (PM) Program | E21: F001 | F21: F001AP | G21: 1502000 | H21: 3.3.7 | I21: Frequency Converter (400 HZ) Systems | J21: 12 | K21: MO
A22: CNRSE | B22: CNRSE ST-FAC | C22: Facility Investment | D22: Preventive Maintenance (PM) Program | E22: F001 | F22: F001AQ | G22: 1502000 | H22: 3.3.8 | I22: Galley Equipment and Systems | J22: 12 | K22: MO
A23: CNRSE | B23: CNRSE ST-FAC | C23: Facility Investment | D23: Preventive Maintenance (PM) Program | E23: F001 | F23: F001AR | G23: 1502000 | H23: 3.3.9 | I23: HVAC and Refrigeration Systems | J23: 12 | K23: MO
A24: CNRSE | B24: CNRSE ST-FAC | C24: Facility Investment | D24: Preventive Maintenance (PM) Program | E24: F001 | F24: F001AS | G24: 1502000 | H24: 3.3.10 | I24: Security Systems and Equipment | J24: 12 | K24: MO
A25: CNRSE | B25: CNRSE ST-FAC | C25: Facility Investment | D25: Preventive Maintenance (PM) Program | E25: F001 | F25: F001AT | G25: 1502000 | H25: 3.3.11 | I25: Uninterruptible Power Supplies (UPS) | J25: 12 | K25: MO
A26: CNRSE | B26: CNRSE ST-FAC | C26: Facility Investment | D26: Preventive Maintenance (PM) Program | E26: F001 | F26: F001AU | G26: 1502000 | H26: 3.3.12 | I26: Vertical Transportation Equipment (VTE) | J26: 12 | K26: MO
... A42: CNRSE | B42: CNRSE ST-FAC | C42: Facility Investment | D42: Other Recurring Services Program | E42: F001 | F42: F001BL | G42: 1502000 | H42: 3.5.11 | I42: Spot Coolers | J42: 12 | K42: MO
A43: CNRSE | B43: CNRSE ST-FAC | C43: Facility Investment | D43: Other (Swimming Pools) | E43: F001 | F43: F001BM | G43: 1503040 | H43: 3.1 | I43: Pool Operator Maintenance | J43: 12 | K43: MO
A44: CNRSE | B44: CNRSE ST-FAC | C44: Facility Investment | D44: Other (Swimming Pools) | E44: F001 | F44: F001BN | G44: 1503040 | H44: 3.2 | I44: Preventive Maintenance (PM) Program | J44: 12 | K44: MO
A45: CNRSE | B45: CNRSE FX | C45: Facility Investment | D45: Other (Swimming Pools) | E45: F001 | F45: F001BP | G45: 1503040 | H45: 3.3 | I45: Water Treatment | J45: 12 | K45: MO
A46: CNRSE | B46: CNRSE UT | C46: Utilities Management | D46: Utility Operations Support | E46: F001 | F46: F001BQ | G46: 1601000 | H46: 3.1 | I46: Utility Operations Support | J46: 12 | K46: MO
A47: CNRSE | B47: CNRSE UT | C47: Utilities Management | D47: Recurring Work | E47: F001 | F47: F001BR | G47: 1601000 | H47: 3.2 | I47: Utility Infrastructure Condition Assessment Program (UICAP) Support | J47: 12 | K47: MO
A48: CNRSE | B48: CNRSE UT | C48: Utilities Management | D48: Recurring Work | E48: F001 | F48: F001BS | G48: 1601000 | H48: 3.3 | I48: Operation and Management of Facility Related Control Systems (FRCS) | J48: 12 | K48: MO
A49: CNRSE | B49: CNRSE UT | C49: Utilities Management | D49: Recurring Work | E49: F001 | F49: F001BT | G49: 1601000 | H49: 3.4 | I49: NAVFAC Maximo Data Entry | J49: 12 | K49: MO
A50: CNRSE | B50: CNRSE UT | C50: Electrical | D50: Recurring Work | E50: F001 | F50: F001BU | G50: 1602000 | H50: 3.1 | I50: Operate Electrical Power Transmission and Distribution Systems | J50: 12 | K50: MO
A51: CNRSE | B51: CNRSE ST | C51: Electrical | D51: E/U/R Work Orders | E51: F001 | F51: F001BV | G51: 1602000 | H51: 3.2 | I51: Emergency, Urgent and Routine (E/U/R) Work | J51: 220 | K51: EA
A52: CNRSE | B52: CNRSE ST | C52: Electrical | D52: Recurring Work | E52: F001 | F52: F001BW | G52: 1602000 | H52: 3.3 | I52: Preventive Maintenance (PM) Program | J52: 12 | K52: MO
A53: CNRSE | B53: CNRSE UT | C53: Electrical | D53: Other Recurring Services Program | E53: F001 | F53: F001BX | G53: 1602000 | H53: 3.4 | I53: Other Recurring Services | J53: 12 | K53: MO
A54: CNRSE | B54: CNRSE UT | C54: Electrical | D54: Other Recurring Services Program | E54: F001 | F54: F001BY | G54: 1602000 | H54: 3.5 | I54: Utility Right of Way Clearance | J54: 12 | K54: MO
A55: CNRSE | B55: CNRSE TR | C55: Transportation | D55: Operations | E55: F001 | F55: F001BZ | G55: 1700000 | H55: 3.1.1 | I55: WHE/MHE/NTVE Services | J55: 12 | K55: MO
A56: CNRSE | B56: CNRSE TR | C56: Transportation | D56: Operations | E56: F001 | F56: F001CA | G56: 1700000 | H56: 3.1.2 | I56: Fuel Delivery Services | J56: 12 | K56: MO
A57: CNRSE | B57: CNRSE TR | C57: Transportation | D57: Support Services | E57: F001 | F57: F001CB | G57: 1700000 | H57: 3.2.1 | I57: Dispatching Services | J57: 12 | K57: MO
A58: CNRSE | B58: CNRSE TR | C58: Transportation | D58: Support Services | E58: F001 | F58: F001CC | G58: 1700000 | H58: 3.2.2 | I58: Non-Government Owned Leased Vehicles | J58: 12 | K58: MO
A59: CNRSE | B59: CNRSE TR | C59: Transportation | D59: Maintenance of NTVE | E59: F001 | F59: F001CD | G59: 1700000 | H59: 3.3.1.1 | I59: New and Reassigned Vehicles and Equipment Services | J59: 12 | K59: MO
A60: CNRSE | B60: CNRSE TR | C60: Transportation | D60: Maintenance of CESE | E60: F001 | F60: F001CE | G60: 1700000 | H60: 3.3.1.2 | I60: Preventive Maintenance, Inspection, Load Test and Certification of WHE, MHE and AWP | J60: 12 | K60: MO
A61: CNRSE | B61: CNRSE TR | C61: Transportation | D61: Maintenance of CESE | E61: F001 | F61: F001CF | G61: 1700000 | H61: 3.3.1.3 | I61: Preventive Maintenance Inspection of NTVE | J61: 12 | K61: MO
A62: CNRSE | B62: CNRSE TR | C62: Transportation | D62: Maintenance of CESE | E62: F001 | F62: F001CG | G62: 1700000 | H62: 3.3.1.4 | I62: Repair (NTVE, WHE, MHE and AWP) | J62: 12 | K62: MO
A63: CNRSE | B63: CNRSE TR | C63: Transportation | D63: Maintenance of CESE | E63: F001 | F63: F001CH | G63: 1700000 | H63: 3.3.1.5 | I63: NTVE Trouble Calls | J63: 150 | K63: EA
A64: CNRSE | B64: CNRSE TR | C64: Transportation | D64: Maintenance of CESE | E64: F001 | F64: F001CJ | G64: 1700000 | H64: 3.3.2 | I64: BSVE Accessories Installation and Removal | J64: 12 | K64: MO
A65: CNRSE | B65: CNRSE EC | C65: Environmental | D65: Recurring Work | E65: F001 | F65: F001CK | G65: 1800000 | H65: 3.1 | I65: Oil and Regulated Substance Spill Response and Cleanup Ashore | J65: 12 | K65: MO
A66: CNRSE | B66: CNRSE EC | C66: Environmental | D66: Recurring Work | E66: F001 | F66: F001CL | G66: 1800000 | H66: 3.2 | I66: Used Oil Management Services | J66: 12 | K66: MO
A67: CNRSE | B67: CNRSE EC | C67: Environmental | D67: Recurring Work | E67: F001 | F67: F001CM | G67: 1800000 | H67: 3.3 | I67: Storm Water Monitoring | J67: 12 | K67: MO
A68: CNRSE | B68: CNRSE ST-UH | C68: Facility Investment | D68: E/U/R Work Orders | E68: F001 | F68: F001CN | G68: 1502000 | H68: 3.1 | I68: Emergency, Urgent and Routine (E/U/R) Work | J68: 1350 | K68: EA
A69: CNRSE | B69: CNRSE ST-UH | C69: Facility Investment | D69: Preventive Maintenance (PM) Program | E69: F001 | F69: F001CP | G69: 1502000 | H69: 3.3.3 | I69: Boiler and Unfired Pressure Vessel (UPV) Systems | J69: 12 | K69: MO
A70: CNRSE | B70: CNRSE ST-UH | C70: Facility Investment | D70: Preventive Maintenance (PM) Program | E70: F001 | F70: F001CQ | G70: 1502000 | H70: 3.3.6 | I70: Fire Protection Systems | J70: 12 | K70: MO
A71: CNRSE | B71: CNRSE ST-UH | C71: Facility Investment | D71: Preventive Maintenance (PM) Program | E71: F001 | F71: F001CR | G71: 1502000 | H71: 3.3.9 | I71: HVAC and Refrigeration Systems | J71: 12 | K71: MO
A72: CNRSE | B72: CNRSE ST-UH | C72: Facility Investment | D72: Inspection, Testing, and Certification | E72: F001 | F72: F001CS | G72: 1502000 | H72: 3.4.1 | I72: Backflow Prevention Devices | J72: 12 | K72: MO
A73: CNRSE | B73: CNRSE ST-UH | C73: Facility Investment | D73: Inspection, Testing, and Certification | E73: F001 | F73: F001CT | G73: 1502000 | H73: 3.4.2 | I73: Boilers and UPVs | J73: 12 | K73: MO
A74: CNRSE | B74: CNRSE ST-UH | C74: Facility Investment | D74: Other Recurring Services Program | E74: F001 | F74: F001CU | G74: 1502000 | H74: 3.5.1 & 3.5.7 | I74: Boiler & HVAC Seasonal Startup and Shutdown | J74: 12 | K74: MO
A75: CNRSE | B75: CNRSE ST-UH | C75: Facility Investment | D75: Other Recurring Services Program | E75: F001 | F75: F001CV | G75: 1502000 | H75: 3.5.2 | I75: Boiler Systems Water Testing and Treatment Services | J75: 12 | K75: MO
A76: CNRSE | B76: CNRSE ST-UH | C76: Facility Investment | D76: Other Recurring Services Program | E76: F001 | F76: F001CW | G76: 1502000 | H76: 3.5.8 | I76: HVAC Water Testing and Treatment Services | J76: 12 | K76: MO
A77: CNRSE | B77: CNRSE ST-UH | C77: Facility Investment | D77: Other Recurring Services Program | E77: F001 | F77: F001CX | G77: 1502000 | H77: 3.5.9 | I77: HVAC Condenser Tube Inspections | J77: 12 | K77: MO
A78: CNRSE | B78: CNRSE ST-UH | C78: Facility Investment | D78: Other Recurring Services Program | E78: F001 | F78: F001CY | G78: 1502000 | H78: 3.5.3 | I78: Change of Occupancy Maintenance (COM) | J78: 50 | K78: EA
A79: CNRSE | B79: CNRSE ST-UH | C79: Facility Investment | D79: Other Recurring Services Program | E79: F001 | F79: F001CZ | G79: 1502000 | H79: 3.5.10 | I79: Lint Traps | J79: 12 | K79: MO
A80: CNRSE | B80: Family Housing | C80: Facility Invetment | D80: Preventive Maintenance (PM) Program | E80: F001 | F80: F001DA | G80: 1502000 | H80: 3.3.9 | I80: HVAC and Refrigeration Systems | J80: 12 | K80: MO
... A87: FRC VRT | B87: FRC VRT | C87: Transportation | D87: Maintenance (Government Owned) | E87: F002 | F87: F002AB | G87: 1700000 | H87: 3.3.1.4 | I87: Repair (NTVE, WHE, MHE and AWP) | J87: 12 | K87: MO
A88: FRC VRT | B88: FRC VRT | C88: Environmental | D88: Recurring Work | E88: F002 | F88: F002AC | G88: 1800000 | H88: 3.2 | I88: Used Oil Management Services | J88: 12 | K88: MO
A89: MCSF-BI | B89: MCSF-BI | C89: Facility Management | D89: Recurring Work | E89: F003 | F89: F003AA | G89: 1501000(MCSF-BI) | H89: 3.1,3.2,3.3 | I89: USMC Maximo, ICAP and Tech Library | J89: 12 | K89: MO
A90: MCSF-BI | B90: MCSF-BI | C90: Facility Investment - MCSF-BI | D90: E/U/R Work Orders | E90: F003 | F90: F003AB | G90: 1502000(MCSF-BI) | H90: 3.1 | I90: Emergency, Urgent and Routine (E/U/R) Work | J90: 750 | K90: EA
A91: MCSF-BI | B91: MCSF-BI | C91: Facility Investment - MCSF-BI | D91: Recurring Work | E91: F003 | F91: F003AC | G91: 1502000(MCSF-BI) | H91: 3.2 | I91: Urgent and Routine Project Work Orders | J91: 48 | K91: EA
A92: MCSF-BI | B92: MCSF-BI | C92: Facility Investment - MCSF-BI | D92: Preventive Maintenance (PM) Program | E92: F003 | F92: F003AD | G92: 1502000(MCSF-BI) | H92: 3.3.1 | I92: Auxiliary Generator Systems | J92: 12 | K92: MO
A93: MCSF-BI | B93: MCSF-BI | C93: Facility Investment - MCSF-BI | D93: Preventive Maintenance (PM) Program | E93: F003 | F93: F003AE | G93: 1502000(MCSF-BI) | H93: 3.3.2 | I93: Cathodic Protection | J93: 12 | K93: MO
A94: MCSF-BI | B94: MCSF-BI | C94: Facility Investment - MCSF-BI | D94: Preventive Maintenance (PM) Program | E94: F003 | F94: F003AF | G94: 1502000(MCSF-BI) | H94: 3.3.3 | I94: Compressed Air Systems | J94: 12 | K94: MO
A95: MCSF-BI | B95: MCSF-BI | C95: Facility Investment - MCSF-BI | D95: Preventive Maintenance (PM) Program | E95: F003 | F95: F003AG | G95: 1502000(MCSF-BI) | H95: 3.3.4 | I95: Facilities, Systems, and Equipment | J95: 12 | K95: MO
A96: MCSF-BI | B96: MCSF-BI | C96: Facility Investment - MCSF-BI | D96: Preventive Maintenance (PM) Program | E96: F003 | F96: F003AH | G96: 1502000(MCSF-BI) | H96: 3.3.5 | I96: Fire Protection Systems | J96: 12 | K96: MO
A97: MCSF-BI | B97: MCSF-BI | C97: Facility Investment - MCSF-BI | D97: Preventive Maintenance (PM) Program | E97: F003 | F97: F003AJ | G97: 1502000(MCSF-BI) | H97: 3.3.6 | I97: Irrigation Equipment and Systems | J97: 12 | K97: MO
A98: MCSF-BI | B98: MCSF-BI | C98: Facility Investment - MCSF-BI | D98: Preventive Maintenance (PM) Program | E98: F003 | F98: F003AK | G98: 1502000(MCSF-BI) | H98: 3.3.7 | I98: Unfired Pressure Vessels (UPVs) | J98: 12 | K98: MO
A99: MCSF-BI | B99: MCSF-BI | C99: Facility Investment - MCSF-BI | D99: Preventive Maintenance (PM) Program | E99: F003 | F99: F003AL | G99: 1502000(MCSF-BI) | H99: 3.3.8 | I99: Vertical Transportation Equipment (VTE) | J99: 12 | K99: MO
A100: MCSF-BI | B100: MCSF-BI | C100: Facility Investment - MCSF-BI | D100: Integrated Maintenance Program (IMP) | E100: F003 | F100: F003AM | G100: 1502000(MCSF-BI) | H100: 3.4.1 | I100: Blast, Paint, and Drying Systems | J100: 12 | K100: MO
A101: MCSF-BI | B101: MCSF-BI | C101: Facility Investment - MCSF-BI | D101: Integrated Maintenance Program (IMP) | E101: F003 | F101: F003AN | G101: 1502000(MCSF-BI) | H101: 3.4.2 | I101: Boiler Systems | J101: 12 | K101: MO
A102: MCSF-BI | B102: MCSF-BI | C102: Facility Investment - MCSF-BI | D102: Integrated Maintenance Program (IMP) | E102: F003 | F102: F003AP | G102: 1502000(MCSF-BI) | H102: 3.4.3 | I102: HVAC and Refrigeration Systems | J102: 12 | K102: MO
A103: MCSF-BI | B103: MCSF-BI | C103: Facility Investment - MCSF-BI | D103: Integrated Maintenance Program (IMP) | E103: F003 | F103: F003AQ | G103: 1502000(MCSF-BI) | H103: 3.4.4 | I103: Railroad Signal and Battery House Systems and Equipment | J103: 12 | K103: MO
... A119: MCSF-BI | B119: MCSF-BI | C119: Facility Investment - MCSF-BI | D119: Other Recurring Services Program | E119: F003 | F119: F003BG | G119: 1502000(MCSF-BI) | H119: 3.6.10 | I119: Fuel Storage Tanks and Berms | J119: 12 | K119: MO
A120: MCSF-BI | B120: MCSF-BI | C120: Custodial - MCSF-BI | D120: Recurring Work | E120: F003 | F120: F003BH | G120: 1503010(MCSF-BI) | H120: 3.1 | I120: Scheduled Services | J120: 12 | K120: MO
A121: MCSF-BI | B121: MCSF-BI | C121: Custodial - MCSF-BI | D121: Recurring Work | E121: F003 | F121: F003BJ | G121: 1503010(MCSF-BI) | H121: 3.2 | I121: Custodial Service Orders | J121: 12 | K121: EA
A122: MCSF-BI | B122: MCSF-BI | C122: Pest Control - MCSF-BI | D122: Recurring Work | E122: F003 | F122: F003BK | G122: 1503020(MCSF-BI) | H122: 3.1 | I122: Scheduled Pest Control Services | J122: 12 | K122: MO
A123: MCSF-BI | B123: MCSF-BI | C123: Pest Control - MCSF-BI | D123: Recurring Work | E123: F003 | F123: F003BL | G123: 1503020(MCSF-BI) | H123: 3.2 | I123: Pest Control Service Orders | J123: 100 | K123: EA
A124: MCSF-BI | B124: MCSF-BI | C124: Pest Control - MCSF-BI | D124: Recurring Work | E124: F003 | F124: F003BM | G124: 1503020(MCSF-BI) | H124: 3.3 | I124: Pest Management Reporting | J124: 12 | K124: MO
A125: MCSF-BI | B125: MCSF-BI | C125: Integrated Solid Waste Management - MCSF-BI | D125: Recurring Work | E125: F003 | F125: F003BN | G125: 1503030(MCSF-BI) | H125: 3 | I125: Recurring Work ISWM | J125: 12 | K125: MO
A126: MCSF-BI | B126: MCSF-BI | C126: Grounds Maintenance and Landscaping - MCSF-BI | D126: Recurring Work | E126: F003 | F126: F003BP | G126: 1503050(MCSF-BI) | H126: 3.1 | I126: Improved Grounds | J126: 12 | K126: MO
A127: MCSF-BI | B127: MCSF-BI | C127: Grounds Maintenance and Landscaping - MCSF-BI | D127: Recurring Work | E127: F003 | F127: F003BQ | G127: 1503050(MCSF-BI) | H127: 3.2 | I127: Operational Areas | J127: 12 | K127: MO
A128: MCSF-BI | B128: MCSF-BI | C128: Grounds Maintenance and Landscaping - MCSF-BI | D128: Recurring Work | E128: F003 | F128: F003BR | G128: 1503050(MCSF-BI) | H128: 3.3 | I128: Storm Drainage Systems | J128: 12 | K128: MO
A129: MCSF-BI | B129: MCSF-BI | C129: Grounds Maintenance and Landscaping - MCSF-BI | D129: Recurring Work | E129: F003 | F129: F003BS | G129: 1503050(MCSF-BI) | H129: 3.4 | I129: Street Sweeping | J129: 12 | K129: MO
A130: MCSF-BI | B130: MCSF-BI | C130: Grounds Maintenance and Landscaping - MCSF-BI | D130: Recurring Work | E130: F003 | F130: F003BT | G130: 1503050(MCSF-BI) | H130: 3.5 | I130: Grounds Maintenance Service Orders | J130: 12 | K130: EA
A131: MCSF-BI | B131: MCSF-BI | C131: Environmental - MCSF-BI | D131: Recurring Work | E131: F003 | F131: F003BU | G131: 1800000(MCSF-BI) | H131: 3.1 | I131: Sampling, Field Testing and Laboratory Services | J131: 12 | K131: MO
... A136: MCSF-BI | B136: MCSF-BI | C136: Environmental - MCSF-BI | D136: Recurring Work | E136: F003 | F136: F003BZ | G136: 1800000(MCSF-BI) | H136: 3.6 | I136: Inspection of POL Tanks and Systems | J136: 12 | K136: MO
A137: NCIS | B137: NCIS | C137: Facility Investment | D137: Preventive Maintenance (PM) Program | E137: F004 | F137: F004AA | G137: 1502000 | H137: 3.3.10 | I137: Security Systems and Equipment | J137: 12 | K137: MO
A138: FLCJ | B138: FLCJ | C138: Facility Investment | D138: E/U/R Work Orders | E138: F005 | F138: F005AA | G138: 1502000 | H138: 3.1 | I138: Emergency, Urgent and Routine (E/U/R) Work | J138: 50 | K138: MO
A139: FLCJ | B139: FLCJ | C139: Facility Investment | D139: Recurring Work | E139: F005 | F139: F005AB | G139: 1502000 | H139: 3.2 | I139: Project Work Orders | J139: 10 | K139: MO
A140: FLCJ | B140: FLCJ | C140: Transportation | D140: Maintenance (Government Owned) | E140: F005 | F140: F005AC | G140: 1700000 | H140: 3.3.1.2 | I140: Preventive Maintenance, Inspection, Load Test and Certification of WHE, MHE and AWP | J140: 12 | K140: MO
...

Sheet CLIN 0017 5th Period Opt N-RW
B1: Attachment J-0200000-17
B2: Exhibit Line Item Numbers - NAVSTA Mayport
B3: Contract No.: N6945025R0003
B5: CLIN 0017 - Non-Recurring Work - Option Period 5
B6: Provide Prices for Recurring Work in accordance with Section C, Spec Item 4
B7: ELINs F700 through F718
A8: ELIN | B8: Product Name (120 Characters) | C8: Description Extended | D8: Estimated Quantity | E8: Unit of Measure | F8: Unit Price | G8: Extended Price
A9: F700 | B9: Unit Priced Labor Hour Work - MUST BE NEGOTIATED BY KO. | C9: The Contractor shall perform all UPL work in accordance with the scope and delivery schedule negotiated per each task order. Refer to: Section C, Annex 0200000 Managmenent and Administration, Specification Item 2.15.2 Unit Priced Labor (UPL)Work (Negotiated) for description of UPL Work. Refer to: Section J, Annex 0200000 Managmenent and Administration, Attachment J-0200000-01 Definitions and Acronyms for description of Unit Priced Labor (UPL) Hour and Universal Equipment. Task order completion times will be specified on each task order. For self-performed work: the unit price proposed for Sub-ELIN F700AA will be used to determine the labor cost to the Governent. For subcontracted labor: the FBR proposed for Sub-ELIN F700AB will be used to determine the labor cost to the Governmnet. The estimated quantity of each Sub-ELIN is used to establish the ELIN Extended Price. During administration the labor Sub-ELINs may be used in any combination and quantity provided the ELIN extended price is not exceeded. The contract will not be modified to re-allocate capacity among labor SLINs. | D9: =G10+G11 -> 0 | E9: DO | F9: 1
A10: F700AA | B10: Self-Performed Unit Priced Labor Hour Work - MUST BE NEGOTIATED BY KO. | C10: The Contractor shall self-perform all UPL work in accordance with the scope and delivery schedule negotiated per each task order. Refer to: Section C, Annex 0200000 Managmenent and Administration, Specification Item 2.15.2 Unit Priced Labor (UPL)Work (Negotiated) for description of UPL Work. Refer to: Section J, Annex 0200000 Managmenent and Administration, Attachment J-0200000-01 Definitions and Acronyms for description of Unit Priced Labor (UPL) Hour and Universal Equipment. | D10: ='CLIN 0002 Base Period N-RW'!D10 -> 16000 | E10: LH
A11: F700AB | B11: Subcontractor Labor (Fixed Burden Rate) - MUST BE NEGOTIATED BY KO. | C11: The Contractor shall perform management and oversight of subcontracted non-recurring work in accordance with the scope and delivery schedule negotiated per each task order. Refer to: Section C, Annex 0200000 Management and Administration, Specification Item 2.15.2.1.2 Subcontractor Requirements description of Sub. Refer to: Section J, Annex 0200000 Management and Administration, Attachment J-0200000-01 Definitions and Acronyms for definition of Sub-Contractor Fixed Burden Rate. The estimated quantity (in dollars) is provided. A Fixed Burdened Rate (FBR) shall be entered in the Unit Price column. The FBR shall include all direct and indirect factors for management and oversight of subcontracted non-recurring work. Similar to FBR example in J-0200000-01, if a 15% markup is the Contractor's proposed FBR, the Unit Price should be $1.15. During performance, if the lowest subcontractor labor proposal is $1,000.00 and the FBR is $1.15, the labor cost to the Government will be $1,150.00. (DO - Dollars). | D11: ='CLIN 0002 Base Period N-RW'!D11 -> 1600000 | E11: DO
A12: F701 | B12: Material and Equipment - MUST BE NEGOTIATED BY KO. | C12: Provide all materials and construction equipment to perform Unit Priced Labor work per the scope and delivery schedule specified in the order. Pre-expended bin supplies and materials will not be included in the list of materials since the cost for these items were included in the labor hour unit price bid. Material prices provided by the Contractor shall be the lowest price available considering the availability of materials and the time constraints of the job. The direct material price shall be adjusted by all discounts and rebates for core value or salvage value that accrue to the Contractor. Contractor owned equipment rental rates shall be based on calculations set forth in US Army Corp of Engineers “Construction Equipment Ownership and Operating Expense Schedule (EP 1110-1-8 (Vol. 11) July 03 or latest revision) Chapter 2. The estitmate quantity (in dollars) is provided. A Fixed burdened rate (FBR) shall be entered in the Unit Price column. The FBR shall include factors for ordering, handling, and stockpiling materials and repair parts. Similar to FBR example in J-0200000-01, if a 10% markup is the Contractor's proposed FBR, the Unit Price should be $1.10. When multiplying the proposed Unit Price by the Estimated Quantity, the Extended Price should be During administration, if the vendor's invoice on material is $1,000.00 and the unit price is $1.10, the cost of the material to the government will be $1,050.00. (DO - Dollars) | D12: 2000000 | E12: DO
A13: F702 | B13: Category I Calls - MUST BE NEGOTIATED BY KO. | C13: The Contractor shall perform Category I Calls to accomplish any work identified within the entire boundary of the installation and will include a wide variety of work. Category I Calls shall be completed within two weeks of receipt of call order, unless otherwise agreed to by the customer and contractor and annotated on the CAT call request. As part of the Category I Call, the Contractor has full responsibility for any work identified up to the Category I Call Threshold of $5,000 in direct labor and direct material, per Category I Call. A Blanket Task Order (BTO) may be issued on a DD Form 1155 with a Not To Exceed (NTE) quantity and value for Non-recurring Work Category Calls. | D13: 115 | E13: EA
A14: F703 | B14: Category II Calls - MUST BE NEGOTIATED BY KO. | C14: The Contractor shall perform Category II Calls to accomplish any work identified within the entire boundary of the installation and will include a wide variety of work. Category II Calls shall be completed within three weeks of receipt of call order, unless otherwise agreed to by the customer and contractor and annotated on the CAT call request. As part of the Category II Call, the Contractor has full responsibility for any work identified up to the Category II Call Threshold of $7,500 in direct labor and direct material, per Category II Call. A Blanket Task Order (BTO) may be issued on a DD Form 1155 with a Not To Exceed (NTE) quantity and value for Non-recurring Work Category Calls. | D14: 130 | E14: EA
