Workbook
Name A10_List: _xlfn.TEXTJOIN(",",TRUE,IF(LEFT(#REF!,3)=LEFT('Asset Data'!$N$2,3),#REF!,""))
Name condition_code: 'Value Lists'!$G$3:$G$7
Name dd_component: #REF!
Name dd_mastersys: 'Value Lists'!$X$2:$X$46
Name dd_subsystem: #REF!
Name dd_system: #REF!
Name itemset: 'Value Lists'!$O$1:$O$21
Name Meter: 'Value Lists'!$AA$2:$AA$15
Name Meter_Group: 'Value Lists'!$AE$2:$AE$5
Name site: 'Value Lists'!$M$1:$M$21
Name Status: 'Value Lists'!$D$10:$D$12
Name YorN: 'Value Lists'!$D$3:$D$4

Sheet Instructions
A1: General Instructions
A2: This template can be used to insert new records or update existing records in USMCmax. Carefully review the information on this tab and the field descriptions before entering information on the data tab. Separate templates should be used to add new assets or update existing assets
A3: Asset Data Tab
A4: Enter a row for each asset to be added to USMCmax. The color code of the field indicates the information requirements. If the fields are not properly populated with data, that record will not be loaded / updated in USMCmax, and the spreadsheet will be returned for correction
A5: Indicates the field is required by the program business logic or current business practices - When an asset description is entered, the data fields will highlight in red until a value is entered. If a value can not be determined an explanation must be entered in the comments column.
A6: Indicates the field is optional and the data entered will depend on prescribed business processes. If a default value is shown for the field the field can be left blank and the default value will be used
A7: Indicates the field is populated by logic and is not editable
A8: Specification Tab
A9: Enter the asset attribute details on the specification Data tab. When a classification is entered for the asset on the asset data tab, the classification and attributes will populate on the corresponding row on the specification data tab. Enter the attribute details for each asset. If there is no classification enter the pertinent attribute data as available. Additional classifications may be requested.
A11: Some fields are associated with a value lists, others are free text. If the attribute values are free text the field will be highlighted. If a value list is associated with the field, you must select from the provided list.
A13: The comments column is used to provide additional information about the asset, or to identify data issues. As an example, if the serial number (a required field) was illegible, it would be noted in the comment field. If a specification attribute value is not on the associated it should be identified here.

Sheet Field description
A1: Database field name | B1: Field Label | C1: Comments on data field | D1: Default | E1: Value list | G1: Mapping eOMSI to USMCmax
B2: Template ID | G2: eOMSI | J2: USMCmax
A3: SITEID | B3: Site | C3: Site id for the installation | E3: Site | G3: 1 | H3: AssetNum | J3: Asset Tag
A4: ASSETNUM | B4: Asset Number (Enter value or enter Auto to auto number) | C4: Asset numbers can be auto generated by the system (recommend) or manually entered by the user | G4: 2 | H4: Description | J4: Description
A5: DESCRIPTION | B5: Asset Description | C5: Description of the asset. Utilize the standard naming convention when possible | G5: 3 | H5: Long Description | J5: Long Description
A6: DESCRIPTION_LONGDESCRIPTION | B6: Long Description | C6: Additional information about the asset. Do not cut and paste, avoid using special characters | G6: 4 | H6: MASTERSYSTEM | J6: Master System
A7: HASLD | B7: Has Long Description (0= No, 1 = Yes - Default = 0) | C7: If the Long description field is populated the Value will default to 1, if the field is blank it will defaultto= 0) (Read Only) | D7: 0 | G7: 5 | H7: SYSTEM | J7: System
A8: LOCATION | B8: Location (Must Exist In USMCmax Location application) | C8: The location the asset is assigned to. The location must exist in the USMCmax Locations application | G8: 6 | H8: SUBSYSTEM | J8: Sub System
A9: EQ1 | B9: Asset Specific Location | C9: Additional information to help locate the asset. Ex. North side of roof | G9: 7 | H9: Building Number | J9: Location
A10: ASSETTYPE | B10: Asset Type | C10: The type of asset | E10: Asset Type | G10: 8 | H10: Asset Quantity | J10: Quantity / Unit of Measure
A11: MANUFACTURER | B11: Manufacturer (Must Exist in USMCMax Company application) | C11: The company that manufactured the asset. The value must come from the USMCmax Companies application | G11: 9 | H11: Replacement Cost | J11: Purchase Price
A12: EQ13 | B12: Model # (From name plate data) | C12: From name plate data | G12: 10 | H12: Contract Number | J12: Contract #
A13: SERIALNUM | B13: Serial Number (From name plate data) | C13: Serial number from the name plate data | G13: 11 | H13: Task/Delivery Order Number | J13: Task Order #
A14: FAILURECODE | B14: Failure Code (Select From Value List) | C14: Failure code associated with this asset | E14: Failure Code | G14: 12 | H14: Warranty Expiration Date | J14: Warranty Expiration Date
A15: MASTERSYS | B15: Master System | C15: Master System from Uniformat tables. Select from value list | E15: Master System | G15: 13 | H15: Installation Date | J15: Date Installaled
A16: SYSTEM | B16: System | C16: System from Uniformat tables. Select from value list | E16: System | G16: 14 | H16: Room Number | J16: Asset Specific Location
A17: SUBSYS | B17: Sub System | C17: Sub System from Uniformat tables. Select from value list | E17: Sub-System | G17: 15 | H17: Manufacturer | J17: Manufacturer
A18: COMP_TYPE | B18: Component | C18: Component from Uniformat tables. Select from value list | E18: Component | G18: 16 | H18: Model | J18: Model #
A19: XX_VALIDATEDATE | B19: Date Validated | C19: Date the asset was validated | G19: 17 | H19: Serial # | J19: Serial Number
A20: MASTERSYS | B20: Contract number | C20: Contract number the asset was purchased under
A21: SYSTEM | B21: Task order | C21: Task order the asset was purchased under
A22: SUBSYS | B22: Quantity | C22: Quantity of assets the record represents. If the record is for flourecent lights the quantity would be the number of light fixtures. | D22: 1
A23: COMP_TYPE | B23: Unit of Measure (Default Value = EA) | C23: Unit of measure. | D23: EA
A24: HIERARCHYPATH | B24: Classification Hierarchy | C24: The classification path for the asset. The path can contain one or more levels | E24: Hierarchy
A25: CLASSSTRUCTUREID | B25: Classstructureid | C25: The numeric value for the classificaiton (read only)
A26: XX_OWNERGROUP | B26: Owner Group (Must exist in the USMCmax Person Group application) | C26: Person group responsible for the asset. Must be a valid Person Group in USMCmax
A27: METER | B27: Meter | C27: A single meter associated with the asset | E27: Meter
A28: METER | B28: Meter Group | C28: The meter group associated with the asset | E28: Meter Group
A29: VENDOR | B29: Vendor (Must Exist in USMCmax Company application) | C29: The vendor the asset was purchased from
A30: EQ23 | B30: Date Received | C30: Date Asset was received at the installation. It may be different than the Date installed if they asset is held in inventory as a spare
A31: INSTALLDATE | B31: Date Installed | C31: Date the asset was installed. May be the same as the Date Asset Received Value
A32: WARRANTYEXPDATE | B32: Warranty Expiration date | C32: Date the warranty expires on the asset. Warranty information should be entered in the Warranty Contracts application
A33: EQ11 | B33: Asset Condition Code | C33: The condition of the asset base on visual inspection | E33: Asset Condition Code
A34: PRIORITY | B34: Priority | C34: Mission related priority of the asset | E34: Priority
A35: PARENT | B35: Parent Asset (Must exist in USMCmax Asset application on in this list) | C35: If the asset has a parent asset enter the parent asset number
A36: HASPARENT | B36: Has Parent (0= No, 1 = Yes - Default = 0) | C36: If the Parent field is populated the field will default to 1. if the parent field is blank the field will default to 0 (Read only) | D36: 0 | E36: Yes or No
A37: HASCHILDREN | B37: Has Children (0= No, 1 = Yes - Default = 0) | C37: If the asset has child assets enter 1 if not enter 0 or leave blank | D37: 0 | E37: Yes or No
A38: PURCHASEPRICE | B38: Purchase Price | C38: Price paid for the asset at time of purchase | D38: 0
A39: REPLACECOST | B39: Replacement Cost | C39: Cost to replace the asset | D39: 0
A40: STATUS | B40: Status Default = NOT READY | C40: The current status of the asset | D40: NOT READY | E40: Status
A41: XX_STATUSDATE | B41: Status Date | C41: Date asset is validated
A42: ASSETTAG | B42: Asset Tag # | C42: Number or code to identify the asset other than the asset number. Ex asset number from the construction drawings or equipment list
A43: UEMLOCATION | B43: UEM Location ( Utility Assets Only) | C43: Used to identify a linear location for utility assets
B44: Comments | C44: Enter comments relative to missing data or additional information about the asset record

Sheet Asset Data
A1: Template ID | B1: Site | C1: Asset Number (Enter value or enter Auto to auto number) | D1: Asset Description | E1: Long Description | F1: Has Long Description (0= No, 1 = Yes - Default = 0) | G1: Location (Must Exist In USMCmax Location application) | H1: Asset Specific Location | I1: Asset Type | J1: Manufacturer (Must Exist in USMCMax Company application) | K1: Model # (From name plate data) | L1: Serial Number (From name plate data) | M1: Failure Code (Select From Value List) | N1: Master System | O1: System | P1: Sub System | Q1: Component | R1: Date Validated | S1: Contract number | T1: Task order | U1: Quantity | V1: Unit of Measure (Default Value = EA) | W1: Classification Hierarchy | X1: Classstructureid | Y1: Owner Group (Must exist in the USMCmax Person Group application) | Z1: Meter | AA1: Meter Group | AB1: Vendor (Must Exist in USMCmax Company application) | AC1: Date Received | AD1: Date Installed | AE1: Warranty Expiration date | AF1: Asset Condition Code | AG1: Priority | AH1: Parent Asset (Must exist in USMCmax Asset application on in this list) | AI1: Has Parent (0= No, 1 = Yes - Default = 0) | AJ1: Has Children (0= No, 1 = Yes - Default = 0) | AK1: Purchase Price | AL1: Replacement Cost | AM1: Status Default = NOT READY | AN1: Status Date | AO1: Asset Tag # | AP1: UEM Location ( Utility Assets Only) | AQ1: Comments
A2: Sample Data | B2: YU | C2: PW-025187 | D2: Air Cooled Condenser | E2: Enter additional information for the long descrition field. Do not copy text with formatting | F2: 1 | G2: 622 | H2: SERVER 156 | I2: FACILITIES | J2: CARRIER | K2: PX023UA1AD | L2: 1625KLT58648 | M2: Air Cooled Conderser | N2: D30-HVAC | O2: D3030-COOLING GENERATING SYSTEMS | P2: D303002-DIRECT EXPANSION SYSTEMS | Q2: D303002-Condenser, DX, Air Cooled | R2: 44535 | U2: 1 | V2: EA | W2: Air Conditioner Condenser Unit | X2: 1002 | AB2: ACME AC | AC2: 43871 | AD2: 43871 | AE2: 44237 | AF2: 2 | AG2: 2 | AI2: 0 | AK2: 2500 | AL2: 2750 | AM2: OPERATING | AN2: 43871 | AO2: ACCOND3
A3: 1 | F3: =IF(ISBLANK(B3),"",IF(ISBLANK(E3),0,1)) | X3: =IFERROR(VLOOKUP(W3,Specifications!A:B,2,FALSE),"") | AI3: =IF(ISBLANK(B3),"",IF(ISBLANK(AH3),0,1))
A4: 2 | F4: =IF(ISBLANK(B4),"",IF(ISBLANK(E4),0,1)) | X4: =IFERROR(VLOOKUP(W4,Specifications!A:B,2,FALSE),"") | AI4: =IF(ISBLANK(B4),"",IF(ISBLANK(AH4),0,1))
A5: 3 | F5: =IF(ISBLANK(B5),"",IF(ISBLANK(E5),0,1)) | X5: =IFERROR(VLOOKUP(W5,Specifications!A:B,2,FALSE),"") | AI5: =IF(ISBLANK(B5),"",IF(ISBLANK(AH5),0,1))
A6: 4 | F6: =IF(ISBLANK(B6),"",IF(ISBLANK(E6),0,1)) | X6: =IFERROR(VLOOKUP(W6,Specifications!A:B,2,FALSE),"") | AI6: =IF(ISBLANK(B6),"",IF(ISBLANK(AH6),0,1))
A7: 5 | F7: =IF(ISBLANK(B7),"",IF(ISBLANK(E7),0,1)) | X7: =IFERROR(VLOOKUP(W7,Specifications!A:B,2,FALSE),"") | AI7: =IF(ISBLANK(B7),"",IF(ISBLANK(AH7),0,1))
A8: 6 | F8: =IF(ISBLANK(B8),"",IF(ISBLANK(E8),0,1)) | X8: =IFERROR(VLOOKUP(W8,Specifications!A:B,2,FALSE),"") | AI8: =IF(ISBLANK(B8),"",IF(ISBLANK(AH8),0,1))
A9: 7 | F9: =IF(ISBLANK(B9),"",IF(ISBLANK(E9),0,1)) | X9: =IFERROR(VLOOKUP(W9,Specifications!A:B,2,FALSE),"") | AI9: =IF(ISBLANK(B9),"",IF(ISBLANK(AH9),0,1))
A10: 8 | F10: =IF(ISBLANK(B10),"",IF(ISBLANK(E10),0,1)) | X10: =IFERROR(VLOOKUP(W10,Specifications!A:B,2,FALSE),"") | AI10: =IF(ISBLANK(B10),"",IF(ISBLANK(AH10),0,1))
A11: 9 | F11: =IF(ISBLANK(B11),"",IF(ISBLANK(E11),0,1)) | X11: =IFERROR(VLOOKUP(W11,Specifications!A:B,2,FALSE),"") | AI11: =IF(ISBLANK(B11),"",IF(ISBLANK(AH11),0,1))
A12: 10 | F12: =IF(ISBLANK(B12),"",IF(ISBLANK(E12),0,1)) | X12: =IFERROR(VLOOKUP(W12,Specifications!A:B,2,FALSE),"") | AI12: =IF(ISBLANK(B12),"",IF(ISBLANK(AH12),0,1))
A13: 11 | F13: =IF(ISBLANK(B13),"",IF(ISBLANK(E13),0,1)) | X13: =IFERROR(VLOOKUP(W13,Specifications!A:B,2,FALSE),"") | AI13: =IF(ISBLANK(B13),"",IF(ISBLANK(AH13),0,1))
A14: 12 | F14: =IF(ISBLANK(B14),"",IF(ISBLANK(E14),0,1)) | X14: =IFERROR(VLOOKUP(W14,Specifications!A:B,2,FALSE),"") | AI14: =IF(ISBLANK(B14),"",IF(ISBLANK(AH14),0,1))
... A502: 500 | F502: =IF(ISBLANK(B502),"",IF(ISBLANK(E502),0,1)) | X502: =IFERROR(VLOOKUP(W502,Specifications!A:B,2,FALSE),"") | AI502: =IF(ISBLANK(B502),"",IF(ISBLANK(AH502),0,1))

Sheet Specification Data
A1: template ID # | B1: assetnum | C1: Classtructureid | D1: Hierarchy | E1: Attribute 1 | F1: Value | G1: attribute 2 | H1: Value | I1: Attribute 3 | J1: Value | K1: Attribute 4 | L1: Value | M1: Attribute 5 | N1: Value | O1: Attribute 6 | P1: Value | Q1: Attribute 7 | R1: Value | S1: Attribute 8 | T1: Value | U1: Attribute 9 | V1: Value | W1: Attribute 10 | X1: Value | Y1: Attribute 11 | Z1: Value | AA1: Attribute 12 | AB1: Value | AC1: Attribute 13 | AD1: Value | AE1: Attribute 14 | AF1: Value | AG1: Attribute 15 | AH1: Value | AI1: Attribute 16 | AJ1: Value | AK1: Attribute 17 | AL1: Value | AM1: Attribute 18 | AN1: Value | AO1: Attribute 19 | AP1: Value | AQ1: Attribute 20 | AR1: Value | AS1: Attribute 21 | AT1: Value | AU1: Attribute 22 | AV1: Value | AW1: Attribute 23 | AX1: Value | AY1: Attribute 24 | AZ1: Value | BA1: Attribute 25 | BB1: Value | BC1: Attribute 26 | BD1: Value | BE1: Attribute 27 | BF1: Value | BG1: Attribute 28 | BH1: Value | BI1: Attribute 29 | BJ1: Value | BK1: Attribute 30 | BL1: Value | BM1: Attribute 31 | BN1: Value | BO1: Attribute 32 | BP1: Value | BQ1: Attribute 33 | BR1: Value | BS1: Attribute 34 | BT1: Value | BU1: Attribute 35 | BV1: Value | BW1: Attribute 36 | BX1: Value | BY1: Attribute 37 | BZ1: Value | CA1: Attribute 38 | CB1: Value | CC1: Attribute 39 | CD1: Value | CE1: Attribute 40 | CF1: Value | CG1: Attribute 41 | CH1: Value | CI1: Attribute 42 | CJ1: Value | CK1: Attribute 43 | CL1: Value | CM1: Attribute 44 | CN1: Value | CO1: Attribute 45 | CP1: Value | CQ1: Attribute 46 | CR1: Value | CS1: Attribute 47 | CT1: Value
A2: =IF(ISBLANK('Asset Data'!C3),0,'Asset Data'!A3) -> 0 | B2: =IF($A2<1,"",VLOOKUP($A2,'Asset Data'!$A:$C,3,FALSE)) | C2: =IF(A2<1,"",VLOOKUP(D2,Specifications!A:B,2,FALSE)) | D2: =IF(A2<1,"",VLOOKUP(A2,'Asset Data'!A:W,23,FALSE)) | E2: =IF($A2<1,"",VLOOKUP($D2,Specifications!$A:$AX,4,FALSE)) | G2: =IF($A2<1,"",VLOOKUP($D2,Specifications!$A:$AX,5,FALSE)) | I2: =IF($A2<1,"",VLOOKUP($D2,Specifications!$A:$AX,6,FALSE)) | K2: =IF($A2<1,"",VLOOKUP($D2,Specifications!$A:$AX,7,FALSE)) | M2: =IF($A2<1,"",VLOOKUP($D2,Specifications!$A:$AX,8,FALSE)) | O2: =IF($A2<1,"",VLOOKUP($D2,Specifications!$A:$AX,9,FALSE)) | Q2: =IF($A2<1,"",VLOOKUP($D2,Specifications!$A:$AX,10,FALSE)) | S2: =IF($A2<1,"",VLOOKUP($D2,Specifications!$A:$AX,11,FALSE)) | U2: =IF($A2<1,"",VLOOKUP($D2,Specifications!$A:$AX,12,FALSE)) | W2: =IF($A2<1,"",VLOOKUP($D2,Specifications!$A:$AX,13,FALSE)) | Y2: =IF($A2<1,"",VLOOKUP($D2,Specifications!$A:$AX,14,FALSE)) | AA2: =IF($A2<1,"",VLOOKUP($D2,Specifications!$A:$AX,15,FALSE)) | AC2: =IF($A2<1,"",VLOOKUP($D2,Specifications!$A:$AX,16,FALSE)) | AE2: =IF($A2<1,"",VLOOKUP($D2,Specifications!$A:$AX,17,FALSE)) | AG2: =IF($A2<1,"",VLOOKUP($D2,Specifications!$A:$AX,18,FALSE)) | AI2: =IF($A2<1,"",VLOOKUP($D2,Specifications!$A:$AX,19,FALSE)) | AK2: =IF($A2<1,"",VLOOKUP($D2,Specifications!$A:$AX,20,FALSE)) | AM2: =IF($A2<1,"",VLOOKUP($D2,Specifications!$A:$AX,21,FALSE)) | AO2: =IF($A2<1,"",VLOOKUP($D2,Specifications!$A:$AX,22,FALSE)) | AQ2: =IF($A2<1,"",VLOOKUP($D2,Specifications!$A:$AX,23,FALSE)) | AS2: =IF($A2<1,"",VLOOKUP($D2,Specifications!$A:$AX,24,FALSE)) | AU2: =IF($A2<1,"",VLOOKUP($D2,Specifications!$A:$AX,25,FALSE)) | AW2: =IF($A2<1,"",VLOOKUP($D2,Specifications!$A:$AX,26,FALSE)) | AY2: =IF($A2<1,"",VLOOKUP($D2,Specifications!$A:$AX,27,FALSE)) | BA2: =IF($A2<1,"",VLOOKUP($D2,Specifications!$A:$AX,28,FALSE)) | BC2: =IF($A2<1,"",VLOOKUP($D2,Specifications!$A:$AX,29,FALSE)) | BE2: =IF($A2<1,"",VLOOKUP($D2,Specifications!$A:$AX,30,FALSE)) | BG2: =IF($A2<1,"",VLOOKUP($D2,Specifications!$A:$AX,31,FALSE)) | BI2: =IF($A2<1,"",VLOOKUP($D2,Specifications!$A:$AX,32,FALSE)) | BK2: =IF($A2<1,"",VLOOKUP($D2,Specifications!$A:$AX,33,FALSE)) | BM2: =IF($A2<1,"",VLOOKUP($D2,Specifications!$A:$AX,34,FALSE)) | BO2: =IF($A2<1,"",VLOOKUP($D2,Specifications!$A:$AX,35,FALSE)) | BQ2: =IF($A2<1,"",VLOOKUP($D2,Specifications!$A:$AX,36,FALSE)) | BS2: =IF($A2<1,"",VLOOKUP($D2,Specifications!$A:$AX,37,FALSE)) | BU2: =IF($A2<1,"",VLOOKUP($D2,Specifications!$A:$AX,38,FALSE)) | BW2: =IF($A2<1,"",VLOOKUP($D2,Specifications!$A:$AX,39,FALSE)) | BY2: =IF($A2<1,"",VLOOKUP($D2,Specifications!$A:$AX,40,FALSE)) | CA2: =IF($A2<1,"",VLOOKUP($D2,Specifications!$A:$AX,41,FALSE)) | CC2: =IF($A2<1,"",VLOOKUP($D2,Specifications!$A:$AX,42,FALSE)) | CE2: =IF($A2<1,"",VLOOKUP($D2,Specifications!$A:$AX,43,FALSE)) | CG2: =IF($A2<1,"",VLOOKUP($D2,Specifications!$A:$AX,44,FALSE)) | CI2: =IF($A2<1,"",VLOOKUP($D2,Specifications!$A:$AX,45,FALSE)) | CK2: =IF($A2<1,"",VLOOKUP($D2,Specifications!$A:$AX,46,FALSE)) | CM2: =IF($A2<1,"",VLOOKUP($D2,Specifications!$A:$AX,47,FALSE)) | CO2: =IF($A2<1,"",VLOOKUP($D2,Specifications!$A:$AX,48,FALSE)) | CQ2: =IF($A2<1,"",VLOOKUP($D2,Specifications!$A:$AX,49,FALSE)) | CS2: =IF($A2<1,"",VLOOKUP($D2,Specifications!$A:$AX,50,FALSE))
A3: =IF(ISBLANK('Asset Data'!C4),0,'Asset Data'!A4) -> 0 | B3: =IF($A3<1,"",VLOOKUP($A3,'Asset Data'!$A:$C,3,FALSE)) | C3: =IF(A3<1,"",VLOOKUP(D3,Specifications!A:B,2,FALSE)) | D3: =IF(A3<1,"",VLOOKUP(A3,'Asset Data'!A:W,23,FALSE)) | E3: =IF($A3<1,"",VLOOKUP($D3,Specifications!$A:$AX,4,FALSE)) | G3: =IF($A3<1,"",VLOOKUP($D3,Specifications!$A:$AX,5,FALSE)) | I3: =IF($A3<1,"",VLOOKUP($D3,Specifications!$A:$AX,6,FALSE)) | K3: =IF($A3<1,"",VLOOKUP($D3,Specifications!$A:$AX,7,FALSE)) | M3: =IF($A3<1,"",VLOOKUP($D3,Specifications!$A:$AX,8,FALSE)) | O3: =IF($A3<1,"",VLOOKUP($D3,Specifications!$A:$AX,9,FALSE)) | Q3: =IF($A3<1,"",VLOOKUP($D3,Specifications!$A:$AX,10,FALSE)) | S3: =IF($A3<1,"",VLOOKUP($D3,Specifications!$A:$AX,11,FALSE)) | U3: =IF($A3<1,"",VLOOKUP($D3,Specifications!$A:$AX,12,FALSE)) | W3: =IF($A3<1,"",VLOOKUP($D3,Specifications!$A:$AX,13,FALSE)) | Y3: =IF($A3<1,"",VLOOKUP($D3,Specifications!$A:$AX,14,FALSE)) | AA3: =IF($A3<1,"",VLOOKUP($D3,Specifications!$A:$AX,15,FALSE)) | AC3: =IF($A3<1,"",VLOOKUP($D3,Specifications!$A:$AX,16,FALSE)) | AE3: =IF($A3<1,"",VLOOKUP($D3,Specifications!$A:$AX,17,FALSE)) | AG3: =IF($A3<1,"",VLOOKUP($D3,Specifications!$A:$AX,18,FALSE)) | AI3: =IF($A3<1,"",VLOOKUP($D3,Specifications!$A:$AX,19,FALSE)) | AK3: =IF($A3<1,"",VLOOKUP($D3,Specifications!$A:$AX,20,FALSE)) | AM3: =IF($A3<1,"",VLOOKUP($D3,Specifications!$A:$AX,21,FALSE)) | AO3: =IF($A3<1,"",VLOOKUP($D3,Specifications!$A:$AX,22,FALSE)) | AQ3: =IF($A3<1,"",VLOOKUP($D3,Specifications!$A:$AX,23,FALSE)) | AS3: =IF($A3<1,"",VLOOKUP($D3,Specifications!$A:$AX,24,FALSE)) | AU3: =IF($A3<1,"",VLOOKUP($D3,Specifications!$A:$AX,25,FALSE)) | AW3: =IF($A3<1,"",VLOOKUP($D3,Specifications!$A:$AX,26,FALSE)) | AY3: =IF($A3<1,"",VLOOKUP($D3,Specifications!$A:$AX,27,FALSE)) | BA3: =IF($A3<1,"",VLOOKUP($D3,Specifications!$A:$AX,28,FALSE)) | BC3: =IF($A3<1,"",VLOOKUP($D3,Specifications!$A:$AX,29,FALSE)) | BE3: =IF($A3<1,"",VLOOKUP($D3,Specifications!$A:$AX,30,FALSE)) | BG3: =IF($A3<1,"",VLOOKUP($D3,Specifications!$A:$AX,31,FALSE)) | BI3: =IF($A3<1,"",VLOOKUP($D3,Specifications!$A:$AX,32,FALSE)) | BK3: =IF($A3<1,"",VLOOKUP($D3,Specifications!$A:$AX,33,FALSE)) | BM3: =IF($A3<1,"",VLOOKUP($D3,Specifications!$A:$AX,34,FALSE)) | BO3: =IF($A3<1,"",VLOOKUP($D3,Specifications!$A:$AX,35,FALSE)) | BQ3: =IF($A3<1,"",VLOOKUP($D3,Specifications!$A:$AX,36,FALSE)) | BS3: =IF($A3<1,"",VLOOKUP($D3,Specifications!$A:$AX,37,FALSE)) | BU3: =IF($A3<1,"",VLOOKUP($D3,Specifications!$A:$AX,38,FALSE)) | BW3: =IF($A3<1,"",VLOOKUP($D3,Specifications!$A:$AX,39,FALSE)) | BY3: =IF($A3<1,"",VLOOKUP($D3,Specifications!$A:$AX,40,FALSE)) | CA3: =IF($A3<1,"",VLOOKUP($D3,Specifications!$A:$AX,41,FALSE)) | CC3: =IF($A3<1,"",VLOOKUP($D3,Specifications!$A:$AX,42,FALSE)) | CE3: =IF($A3<1,"",VLOOKUP($D3,Specifications!$A:$AX,43,FALSE)) | CG3: =IF($A3<1,"",VLOOKUP($D3,Specifications!$A:$AX,44,FALSE)) | CI3: =IF($A3<1,"",VLOOKUP($D3,Specifications!$A:$AX,45,FALSE)) | CK3: =IF($A3<1,"",VLOOKUP($D3,Specifications!$A:$AX,46,FALSE)) | CM3: =IF($A3<1,"",VLOOKUP($D3,Specifications!$A:$AX,47,FALSE)) | CO3: =IF($A3<1,"",VLOOKUP($D3,Specifications!$A:$AX,48,FALSE)) | CQ3: =IF($A3<1,"",VLOOKUP($D3,Specifications!$A:$AX,49,FALSE)) | CS3: =IF($A3<1,"",VLOOKUP($D3,Specifications!$A:$AX,50,FALSE))
A4: =IF(ISBLANK('Asset Data'!C5),0,'Asset Data'!A5) -> 0 | B4: =IF($A4<1,"",VLOOKUP($A4,'Asset Data'!$A:$C,3,FALSE)) | C4: =IF(A4<1,"",VLOOKUP(D4,Specifications!A:B,2,FALSE)) | D4: =IF(A4<1,"",VLOOKUP(A4,'Asset Data'!A:W,23,FALSE)) | E4: =IF($A4<1,"",VLOOKUP($D4,Specifications!$A:$AX,4,FALSE)) | G4: =IF($A4<1,"",VLOOKUP($D4,Specifications!$A:$AX,5,FALSE)) | I4: =IF($A4<1,"",VLOOKUP($D4,Specifications!$A:$AX,6,FALSE)) | K4: =IF($A4<1,"",VLOOKUP($D4,Specifications!$A:$AX,7,FALSE)) | M4: =IF($A4<1,"",VLOOKUP($D4,Specifications!$A:$AX,8,FALSE)) | O4: =IF($A4<1,"",VLOOKUP($D4,Specifications!$A:$AX,9,FALSE)) | Q4: =IF($A4<1,"",VLOOKUP($D4,Specifications!$A:$AX,10,FALSE)) | S4: =IF($A4<1,"",VLOOKUP($D4,Specifications!$A:$AX,11,FALSE)) | U4: =IF($A4<1,"",VLOOKUP($D4,Specifications!$A:$AX,12,FALSE)) | W4: =IF($A4<1,"",VLOOKUP($D4,Specifications!$A:$AX,13,FALSE)) | Y4: =IF($A4<1,"",VLOOKUP($D4,Specifications!$A:$AX,14,FALSE)) | AA4: =IF($A4<1,"",VLOOKUP($D4,Specifications!$A:$AX,15,FALSE)) | AC4: =IF($A4<1,"",VLOOKUP($D4,Specifications!$A:$AX,16,FALSE)) | AE4: =IF($A4<1,"",VLOOKUP($D4,Specifications!$A:$AX,17,FALSE)) | AG4: =IF($A4<1,"",VLOOKUP($D4,Specifications!$A:$AX,18,FALSE)) | AI4: =IF($A4<1,"",VLOOKUP($D4,Specifications!$A:$AX,19,FALSE)) | AK4: =IF($A4<1,"",VLOOKUP($D4,Specifications!$A:$AX,20,FALSE)) | AM4: =IF($A4<1,"",VLOOKUP($D4,Specifications!$A:$AX,21,FALSE)) | AO4: =IF($A4<1,"",VLOOKUP($D4,Specifications!$A:$AX,22,FALSE)) | AQ4: =IF($A4<1,"",VLOOKUP($D4,Specifications!$A:$AX,23,FALSE)) | AS4: =IF($A4<1,"",VLOOKUP($D4,Specifications!$A:$AX,24,FALSE)) | AU4: =IF($A4<1,"",VLOOKUP($D4,Specifications!$A:$AX,25,FALSE)) | AW4: =IF($A4<1,"",VLOOKUP($D4,Specifications!$A:$AX,26,FALSE)) | AY4: =IF($A4<1,"",VLOOKUP($D4,Specifications!$A:$AX,27,FALSE)) | BA4: =IF($A4<1,"",VLOOKUP($D4,Specifications!$A:$AX,28,FALSE)) | BC4: =IF($A4<1,"",VLOOKUP($D4,Specifications!$A:$AX,29,FALSE)) | BE4: =IF($A4<1,"",VLOOKUP($D4,Specifications!$A:$AX,30,FALSE)) | BG4: =IF($A4<1,"",VLOOKUP($D4,Specifications!$A:$AX,31,FALSE)) | BI4: =IF($A4<1,"",VLOOKUP($D4,Specifications!$A:$AX,32,FALSE)) | BK4: =IF($A4<1,"",VLOOKUP($D4,Specifications!$A:$AX,33,FALSE)) | BM4: =IF($A4<1,"",VLOOKUP($D4,Specifications!$A:$AX,34,FALSE)) | BO4: =IF($A4<1,"",VLOOKUP($D4,Specifications!$A:$AX,35,FALSE)) | BQ4: =IF($A4<1,"",VLOOKUP($D4,Specifications!$A:$AX,36,FALSE)) | BS4: =IF($A4<1,"",VLOOKUP($D4,Specifications!$A:$AX,37,FALSE)) | BU4: =IF($A4<1,"",VLOOKUP($D4,Specifications!$A:$AX,38,FALSE)) | BW4: =IF($A4<1,"",VLOOKUP($D4,Specifications!$A:$AX,39,FALSE)) | BY4: =IF($A4<1,"",VLOOKUP($D4,Specifications!$A:$AX,40,FALSE)) | CA4: =IF($A4<1,"",VLOOKUP($D4,Specifications!$A:$AX,41,FALSE)) | CC4: =IF($A4<1,"",VLOOKUP($D4,Specifications!$A:$AX,42,FALSE)) | CE4: =IF($A4<1,"",VLOOKUP($D4,Specifications!$A:$AX,43,FALSE)) | CG4: =IF($A4<1,"",VLOOKUP($D4,Specifications!$A:$AX,44,FALSE)) | CI4: =IF($A4<1,"",VLOOKUP($D4,Specifications!$A:$AX,45,FALSE)) | CK4: =IF($A4<1,"",VLOOKUP($D4,Specifications!$A:$AX,46,FALSE)) | CM4: =IF($A4<1,"",VLOOKUP($D4,Specifications!$A:$AX,47,FALSE)) | CO4: =IF($A4<1,"",VLOOKUP($D4,Specifications!$A:$AX,48,FALSE)) | CQ4: =IF($A4<1,"",VLOOKUP($D4,Specifications!$A:$AX,49,FALSE)) | CS4: =IF($A4<1,"",VLOOKUP($D4,Specifications!$A:$AX,50,FALSE))
A5: =IF(ISBLANK('Asset Data'!C6),0,'Asset Data'!A6) -> 0 | B5: =IF($A5<1,"",VLOOKUP($A5,'Asset Data'!$A:$C,3,FALSE)) | C5: =IF(A5<1,"",VLOOKUP(D5,Specifications!A:B,2,FALSE)) | D5: =IF(A5<1,"",VLOOKUP(A5,'Asset Data'!A:W,23,FALSE)) | E5: =IF($A5<1,"",VLOOKUP($D5,Specifications!$A:$AX,4,FALSE)) | G5: =IF($A5<1,"",VLOOKUP($D5,Specifications!$A:$AX,5,FALSE)) | I5: =IF($A5<1,"",VLOOKUP($D5,Specifications!$A:$AX,6,FALSE)) | K5: =IF($A5<1,"",VLOOKUP($D5,Specifications!$A:$AX,7,FALSE)) | M5: =IF($A5<1,"",VLOOKUP($D5,Specifications!$A:$AX,8,FALSE)) | O5: =IF($A5<1,"",VLOOKUP($D5,Specifications!$A:$AX,9,FALSE)) | Q5: =IF($A5<1,"",VLOOKUP($D5,Specifications!$A:$AX,10,FALSE)) | S5: =IF($A5<1,"",VLOOKUP($D5,Specifications!$A:$AX,11,FALSE)) | U5: =IF($A5<1,"",VLOOKUP($D5,Specifications!$A:$AX,12,FALSE)) | W5: =IF($A5<1,"",VLOOKUP($D5,Specifications!$A:$AX,13,FALSE)) | Y5: =IF($A5<1,"",VLOOKUP($D5,Specifications!$A:$AX,14,FALSE)) | AA5: =IF($A5<1,"",VLOOKUP($D5,Specifications!$A:$AX,15,FALSE)) | AC5: =IF($A5<1,"",VLOOKUP($D5,Specifications!$A:$AX,16,FALSE)) | AE5: =IF($A5<1,"",VLOOKUP($D5,Specifications!$A:$AX,17,FALSE)) | AG5: =IF($A5<1,"",VLOOKUP($D5,Specifications!$A:$AX,18,FALSE)) | AI5: =IF($A5<1,"",VLOOKUP($D5,Specifications!$A:$AX,19,FALSE)) | AK5: =IF($A5<1,"",VLOOKUP($D5,Specifications!$A:$AX,20,FALSE)) | AM5: =IF($A5<1,"",VLOOKUP($D5,Specifications!$A:$AX,21,FALSE)) | AO5: =IF($A5<1,"",VLOOKUP($D5,Specifications!$A:$AX,22,FALSE)) | AQ5: =IF($A5<1,"",VLOOKUP($D5,Specifications!$A:$AX,23,FALSE)) | AS5: =IF($A5<1,"",VLOOKUP($D5,Specifications!$A:$AX,24,FALSE)) | AU5: =IF($A5<1,"",VLOOKUP($D5,Specifications!$A:$AX,25,FALSE)) | AW5: =IF($A5<1,"",VLOOKUP($D5,Specifications!$A:$AX,26,FALSE)) | AY5: =IF($A5<1,"",VLOOKUP($D5,Specifications!$A:$AX,27,FALSE)) | BA5: =IF($A5<1,"",VLOOKUP($D5,Specifications!$A:$AX,28,FALSE)) | BC5: =IF($A5<1,"",VLOOKUP($D5,Specifications!$A:$AX,29,FALSE)) | BE5: =IF($A5<1,"",VLOOKUP($D5,Specifications!$A:$AX,30,FALSE)) | BG5: =IF($A5<1,"",VLOOKUP($D5,Specifications!$A:$AX,31,FALSE)) | BI5: =IF($A5<1,"",VLOOKUP($D5,Specifications!$A:$AX,32,FALSE)) | BK5: =IF($A5<1,"",VLOOKUP($D5,Specifications!$A:$AX,33,FALSE)) | BM5: =IF($A5<1,"",VLOOKUP($D5,Specifications!$A:$AX,34,FALSE)) | BO5: =IF($A5<1,"",VLOOKUP($D5,Specifications!$A:$AX,35,FALSE)) | BQ5: =IF($A5<1,"",VLOOKUP($D5,Specifications!$A:$AX,36,FALSE)) | BS5: =IF($A5<1,"",VLOOKUP($D5,Specifications!$A:$AX,37,FALSE)) | BU5: =IF($A5<1,"",VLOOKUP($D5,Specifications!$A:$AX,38,FALSE)) | BW5: =IF($A5<1,"",VLOOKUP($D5,Specifications!$A:$AX,39,FALSE)) | BY5: =IF($A5<1,"",VLOOKUP($D5,Specifications!$A:$AX,40,FALSE)) | CA5: =IF($A5<1,"",VLOOKUP($D5,Specifications!$A:$AX,41,FALSE)) | CC5: =IF($A5<1,"",VLOOKUP($D5,Specifications!$A:$AX,42,FALSE)) | CE5: =IF($A5<1,"",VLOOKUP($D5,Specifications!$A:$AX,43,FALSE)) | CG5: =IF($A5<1,"",VLOOKUP($D5,Specifications!$A:$AX,44,FALSE)) | CI5: =IF($A5<1,"",VLOOKUP($D5,Specifications!$A:$AX,45,FALSE)) | CK5: =IF($A5<1,"",VLOOKUP($D5,Specifications!$A:$AX,46,FALSE)) | CM5: =IF($A5<1,"",VLOOKUP($D5,Specifications!$A:$AX,47,FALSE)) | CO5: =IF($A5<1,"",VLOOKUP($D5,Specifications!$A:$AX,48,FALSE)) | CQ5: =IF($A5<1,"",VLOOKUP($D5,Specifications!$A:$AX,49,FALSE)) | CS5: =IF($A5<1,"",VLOOKUP($D5,Specifications!$A:$AX,50,FALSE))
A6: =IF(ISBLANK('Asset Data'!C7),0,'Asset Data'!A7) -> 0 | B6: =IF($A6<1,"",VLOOKUP($A6,'Asset Data'!$A:$C,3,FALSE)) | C6: =IF(A6<1,"",VLOOKUP(D6,Specifications!A:B,2,FALSE)) | D6: =IF(A6<1,"",VLOOKUP(A6,'Asset Data'!A:W,23,FALSE)) | E6: =IF($A6<1,"",VLOOKUP($D6,Specifications!$A:$AX,4,FALSE)) | G6: =IF($A6<1,"",VLOOKUP($D6,Specifications!$A:$AX,5,FALSE)) | I6: =IF($A6<1,"",VLOOKUP($D6,Specifications!$A:$AX,6,FALSE)) | K6: =IF($A6<1,"",VLOOKUP($D6,Specifications!$A:$AX,7,FALSE)) | M6: =IF($A6<1,"",VLOOKUP($D6,Specifications!$A:$AX,8,FALSE)) | O6: =IF($A6<1,"",VLOOKUP($D6,Specifications!$A:$AX,9,FALSE)) | Q6: =IF($A6<1,"",VLOOKUP($D6,Specifications!$A:$AX,10,FALSE)) | S6: =IF($A6<1,"",VLOOKUP($D6,Specifications!$A:$AX,11,FALSE)) | U6: =IF($A6<1,"",VLOOKUP($D6,Specifications!$A:$AX,12,FALSE)) | W6: =IF($A6<1,"",VLOOKUP($D6,Specifications!$A:$AX,13,FALSE)) | Y6: =IF($A6<1,"",VLOOKUP($D6,Specifications!$A:$AX,14,FALSE)) | AA6: =IF($A6<1,"",VLOOKUP($D6,Specifications!$A:$AX,15,FALSE)) | AC6: =IF($A6<1,"",VLOOKUP($D6,Specifications!$A:$AX,16,FALSE)) | AE6: =IF($A6<1,"",VLOOKUP($D6,Specifications!$A:$AX,17,FALSE)) | AG6: =IF($A6<1,"",VLOOKUP($D6,Specifications!$A:$AX,18,FALSE)) | AI6: =IF($A6<1,"",VLOOKUP($D6,Specifications!$A:$AX,19,FALSE)) | AK6: =IF($A6<1,"",VLOOKUP($D6,Specifications!$A:$AX,20,FALSE)) | AM6: =IF($A6<1,"",VLOOKUP($D6,Specifications!$A:$AX,21,FALSE)) | AO6: =IF($A6<1,"",VLOOKUP($D6,Specifications!$A:$AX,22,FALSE)) | AQ6: =IF($A6<1,"",VLOOKUP($D6,Specifications!$A:$AX,23,FALSE)) | AS6: =IF($A6<1,"",VLOOKUP($D6,Specifications!$A:$AX,24,FALSE)) | AU6: =IF($A6<1,"",VLOOKUP($D6,Specifications!$A:$AX,25,FALSE)) | AW6: =IF($A6<1,"",VLOOKUP($D6,Specifications!$A:$AX,26,FALSE)) | AY6: =IF($A6<1,"",VLOOKUP($D6,Specifications!$A:$AX,27,FALSE)) | BA6: =IF($A6<1,"",VLOOKUP($D6,Specifications!$A:$AX,28,FALSE)) | BC6: =IF($A6<1,"",VLOOKUP($D6,Specifications!$A:$AX,29,FALSE)) | BE6: =IF($A6<1,"",VLOOKUP($D6,Specifications!$A:$AX,30,FALSE)) | BG6: =IF($A6<1,"",VLOOKUP($D6,Specifications!$A:$AX,31,FALSE)) | BI6: =IF($A6<1,"",VLOOKUP($D6,Specifications!$A:$AX,32,FALSE)) | BK6: =IF($A6<1,"",VLOOKUP($D6,Specifications!$A:$AX,33,FALSE)) | BM6: =IF($A6<1,"",VLOOKUP($D6,Specifications!$A:$AX,34,FALSE)) | BO6: =IF($A6<1,"",VLOOKUP($D6,Specifications!$A:$AX,35,FALSE)) | BQ6: =IF($A6<1,"",VLOOKUP($D6,Specifications!$A:$AX,36,FALSE)) | BS6: =IF($A6<1,"",VLOOKUP($D6,Specifications!$A:$AX,37,FALSE)) | BU6: =IF($A6<1,"",VLOOKUP($D6,Specifications!$A:$AX,38,FALSE)) | BW6: =IF($A6<1,"",VLOOKUP($D6,Specifications!$A:$AX,39,FALSE)) | BY6: =IF($A6<1,"",VLOOKUP($D6,Specifications!$A:$AX,40,FALSE)) | CA6: =IF($A6<1,"",VLOOKUP($D6,Specifications!$A:$AX,41,FALSE)) | CC6: =IF($A6<1,"",VLOOKUP($D6,Specifications!$A:$AX,42,FALSE)) | CE6: =IF($A6<1,"",VLOOKUP($D6,Specifications!$A:$AX,43,FALSE)) | CG6: =IF($A6<1,"",VLOOKUP($D6,Specifications!$A:$AX,44,FALSE)) | CI6: =IF($A6<1,"",VLOOKUP($D6,Specifications!$A:$AX,45,FALSE)) | CK6: =IF($A6<1,"",VLOOKUP($D6,Specifications!$A:$AX,46,FALSE)) | CM6: =IF($A6<1,"",VLOOKUP($D6,Specifications!$A:$AX,47,FALSE)) | CO6: =IF($A6<1,"",VLOOKUP($D6,Specifications!$A:$AX,48,FALSE)) | CQ6: =IF($A6<1,"",VLOOKUP($D6,Specifications!$A:$AX,49,FALSE)) | CS6: =IF($A6<1,"",VLOOKUP($D6,Specifications!$A:$AX,50,FALSE))
A7: =IF(ISBLANK('Asset Data'!C8),0,'Asset Data'!A8) -> 0 | B7: =IF($A7<1,"",VLOOKUP($A7,'Asset Data'!$A:$C,3,FALSE)) | C7: =IF(A7<1,"",VLOOKUP(D7,Specifications!A:B,2,FALSE)) | D7: =IF(A7<1,"",VLOOKUP(A7,'Asset Data'!A:W,23,FALSE)) | E7: =IF($A7<1,"",VLOOKUP($D7,Specifications!$A:$AX,4,FALSE)) | G7: =IF($A7<1,"",VLOOKUP($D7,Specifications!$A:$AX,5,FALSE)) | I7: =IF($A7<1,"",VLOOKUP($D7,Specifications!$A:$AX,6,FALSE)) | K7: =IF($A7<1,"",VLOOKUP($D7,Specifications!$A:$AX,7,FALSE)) | M7: =IF($A7<1,"",VLOOKUP($D7,Specifications!$A:$AX,8,FALSE)) | O7: =IF($A7<1,"",VLOOKUP($D7,Specifications!$A:$AX,9,FALSE)) | Q7: =IF($A7<1,"",VLOOKUP($D7,Specifications!$A:$AX,10,FALSE)) | S7: =IF($A7<1,"",VLOOKUP($D7,Specifications!$A:$AX,11,FALSE)) | U7: =IF($A7<1,"",VLOOKUP($D7,Specifications!$A:$AX,12,FALSE)) | W7: =IF($A7<1,"",VLOOKUP($D7,Specifications!$A:$AX,13,FALSE)) | Y7: =IF($A7<1,"",VLOOKUP($D7,Specifications!$A:$AX,14,FALSE)) | AA7: =IF($A7<1,"",VLOOKUP($D7,Specifications!$A:$AX,15,FALSE)) | AC7: =IF($A7<1,"",VLOOKUP($D7,Specifications!$A:$AX,16,FALSE)) | AE7: =IF($A7<1,"",VLOOKUP($D7,Specifications!$A:$AX,17,FALSE)) | AG7: =IF($A7<1,"",VLOOKUP($D7,Specifications!$A:$AX,18,FALSE)) | AI7: =IF($A7<1,"",VLOOKUP($D7,Specifications!$A:$AX,19,FALSE)) | AK7: =IF($A7<1,"",VLOOKUP($D7,Specifications!$A:$AX,20,FALSE)) | AM7: =IF($A7<1,"",VLOOKUP($D7,Specifications!$A:$AX,21,FALSE)) | AO7: =IF($A7<1,"",VLOOKUP($D7,Specifications!$A:$AX,22,FALSE)) | AQ7: =IF($A7<1,"",VLOOKUP($D7,Specifications!$A:$AX,23,FALSE)) | AS7: =IF($A7<1,"",VLOOKUP($D7,Specifications!$A:$AX,24,FALSE)) | AU7: =IF($A7<1,"",VLOOKUP($D7,Specifications!$A:$AX,25,FALSE)) | AW7: =IF($A7<1,"",VLOOKUP($D7,Specifications!$A:$AX,26,FALSE)) | AY7: =IF($A7<1,"",VLOOKUP($D7,Specifications!$A:$AX,27,FALSE)) | BA7: =IF($A7<1,"",VLOOKUP($D7,Specifications!$A:$AX,28,FALSE)) | BC7: =IF($A7<1,"",VLOOKUP($D7,Specifications!$A:$AX,29,FALSE)) | BE7: =IF($A7<1,"",VLOOKUP($D7,Specifications!$A:$AX,30,FALSE)) | BG7: =IF($A7<1,"",VLOOKUP($D7,Specifications!$A:$AX,31,FALSE)) | BI7: =IF($A7<1,"",VLOOKUP($D7,Specifications!$A:$AX,32,FALSE)) | BK7: =IF($A7<1,"",VLOOKUP($D7,Specifications!$A:$AX,33,FALSE)) | BM7: =IF($A7<1,"",VLOOKUP($D7,Specifications!$A:$AX,34,FALSE)) | BO7: =IF($A7<1,"",VLOOKUP($D7,Specifications!$A:$AX,35,FALSE)) | BQ7: =IF($A7<1,"",VLOOKUP($D7,Specifications!$A:$AX,36,FALSE)) | BS7: =IF($A7<1,"",VLOOKUP($D7,Specifications!$A:$AX,37,FALSE)) | BU7: =IF($A7<1,"",VLOOKUP($D7,Specifications!$A:$AX,38,FALSE)) | BW7: =IF($A7<1,"",VLOOKUP($D7,Specifications!$A:$AX,39,FALSE)) | BY7: =IF($A7<1,"",VLOOKUP($D7,Specifications!$A:$AX,40,FALSE)) | CA7: =IF($A7<1,"",VLOOKUP($D7,Specifications!$A:$AX,41,FALSE)) | CC7: =IF($A7<1,"",VLOOKUP($D7,Specifications!$A:$AX,42,FALSE)) | CE7: =IF($A7<1,"",VLOOKUP($D7,Specifications!$A:$AX,43,FALSE)) | CG7: =IF($A7<1,"",VLOOKUP($D7,Specifications!$A:$AX,44,FALSE)) | CI7: =IF($A7<1,"",VLOOKUP($D7,Specifications!$A:$AX,45,FALSE)) | CK7: =IF($A7<1,"",VLOOKUP($D7,Specifications!$A:$AX,46,FALSE)) | CM7: =IF($A7<1,"",VLOOKUP($D7,Specifications!$A:$AX,47,FALSE)) | CO7: =IF($A7<1,"",VLOOKUP($D7,Specifications!$A:$AX,48,FALSE)) | CQ7: =IF($A7<1,"",VLOOKUP($D7,Specifications!$A:$AX,49,FALSE)) | CS7: =IF($A7<1,"",VLOOKUP($D7,Specifications!$A:$AX,50,FALSE))
A8: =IF(ISBLANK('Asset Data'!C9),0,'Asset Data'!A9) -> 0 | B8: =IF($A8<1,"",VLOOKUP($A8,'Asset Data'!$A:$C,3,FALSE)) | C8: =IF(A8<1,"",VLOOKUP(D8,Specifications!A:B,2,FALSE)) | D8: =IF(A8<1,"",VLOOKUP(A8,'Asset Data'!A:W,23,FALSE)) | E8: =IF($A8<1,"",VLOOKUP($D8,Specifications!$A:$AX,4,FALSE)) | G8: =IF($A8<1,"",VLOOKUP($D8,Specifications!$A:$AX,5,FALSE)) | I8: =IF($A8<1,"",VLOOKUP($D8,Specifications!$A:$AX,6,FALSE)) | K8: =IF($A8<1,"",VLOOKUP($D8,Specifications!$A:$AX,7,FALSE)) | M8: =IF($A8<1,"",VLOOKUP($D8,Specifications!$A:$AX,8,FALSE)) | O8: =IF($A8<1,"",VLOOKUP($D8,Specifications!$A:$AX,9,FALSE)) | Q8: =IF($A8<1,"",VLOOKUP($D8,Specifications!$A:$AX,10,FALSE)) | S8: =IF($A8<1,"",VLOOKUP($D8,Specifications!$A:$AX,11,FALSE)) | U8: =IF($A8<1,"",VLOOKUP($D8,Specifications!$A:$AX,12,FALSE)) | W8: =IF($A8<1,"",VLOOKUP($D8,Specifications!$A:$AX,13,FALSE)) | Y8: =IF($A8<1,"",VLOOKUP($D8,Specifications!$A:$AX,14,FALSE)) | AA8: =IF($A8<1,"",VLOOKUP($D8,Specifications!$A:$AX,15,FALSE)) | AC8: =IF($A8<1,"",VLOOKUP($D8,Specifications!$A:$AX,16,FALSE)) | AE8: =IF($A8<1,"",VLOOKUP($D8,Specifications!$A:$AX,17,FALSE)) | AG8: =IF($A8<1,"",VLOOKUP($D8,Specifications!$A:$AX,18,FALSE)) | AI8: =IF($A8<1,"",VLOOKUP($D8,Specifications!$A:$AX,19,FALSE)) | AK8: =IF($A8<1,"",VLOOKUP($D8,Specifications!$A:$AX,20,FALSE)) | AM8: =IF($A8<1,"",VLOOKUP($D8,Specifications!$A:$AX,21,FALSE)) | AO8: =IF($A8<1,"",VLOOKUP($D8,Specifications!$A:$AX,22,FALSE)) | AQ8: =IF($A8<1,"",VLOOKUP($D8,Specifications!$A:$AX,23,FALSE)) | AS8: =IF($A8<1,"",VLOOKUP($D8,Specifications!$A:$AX,24,FALSE)) | AU8: =IF($A8<1,"",VLOOKUP($D8,Specifications!$A:$AX,25,FALSE)) | AW8: =IF($A8<1,"",VLOOKUP($D8,Specifications!$A:$AX,26,FALSE)) | AY8: =IF($A8<1,"",VLOOKUP($D8,Specifications!$A:$AX,27,FALSE)) | BA8: =IF($A8<1,"",VLOOKUP($D8,Specifications!$A:$AX,28,FALSE)) | BC8: =IF($A8<1,"",VLOOKUP($D8,Specifications!$A:$AX,29,FALSE)) | BE8: =IF($A8<1,"",VLOOKUP($D8,Specifications!$A:$AX,30,FALSE)) | BG8: =IF($A8<1,"",VLOOKUP($D8,Specifications!$A:$AX,31,FALSE)) | BI8: =IF($A8<1,"",VLOOKUP($D8,Specifications!$A:$AX,32,FALSE)) | BK8: =IF($A8<1,"",VLOOKUP($D8,Specifications!$A:$AX,33,FALSE)) | BM8: =IF($A8<1,"",VLOOKUP($D8,Specifications!$A:$AX,34,FALSE)) | BO8: =IF($A8<1,"",VLOOKUP($D8,Specifications!$A:$AX,35,FALSE)) | BQ8: =IF($A8<1,"",VLOOKUP($D8,Specifications!$A:$AX,36,FALSE)) | BS8: =IF($A8<1,"",VLOOKUP($D8,Specifications!$A:$AX,37,FALSE)) | BU8: =IF($A8<1,"",VLOOKUP($D8,Specifications!$A:$AX,38,FALSE)) | BW8: =IF($A8<1,"",VLOOKUP($D8,Specifications!$A:$AX,39,FALSE)) | BY8: =IF($A8<1,"",VLOOKUP($D8,Specifications!$A:$AX,40,FALSE)) | CA8: =IF($A8<1,"",VLOOKUP($D8,Specifications!$A:$AX,41,FALSE)) | CC8: =IF($A8<1,"",VLOOKUP($D8,Specifications!$A:$AX,42,FALSE)) | CE8: =IF($A8<1,"",VLOOKUP($D8,Specifications!$A:$AX,43,FALSE)) | CG8: =IF($A8<1,"",VLOOKUP($D8,Specifications!$A:$AX,44,FALSE)) | CI8: =IF($A8<1,"",VLOOKUP($D8,Specifications!$A:$AX,45,FALSE)) | CK8: =IF($A8<1,"",VLOOKUP($D8,Specifications!$A:$AX,46,FALSE)) | CM8: =IF($A8<1,"",VLOOKUP($D8,Specifications!$A:$AX,47,FALSE)) | CO8: =IF($A8<1,"",VLOOKUP($D8,Specifications!$A:$AX,48,FALSE)) | CQ8: =IF($A8<1,"",VLOOKUP($D8,Specifications!$A:$AX,49,FALSE)) | CS8: =IF($A8<1,"",VLOOKUP($D8,Specifications!$A:$AX,50,FALSE))
A9: =IF(ISBLANK('Asset Data'!C10),0,'Asset Data'!A10) -> 0 | B9: =IF($A9<1,"",VLOOKUP($A9,'Asset Data'!$A:$C,3,FALSE)) | C9: =IF(A9<1,"",VLOOKUP(D9,Specifications!A:B,2,FALSE)) | D9: =IF(A9<1,"",VLOOKUP(A9,'Asset Data'!A:W,23,FALSE)) | E9: =IF($A9<1,"",VLOOKUP($D9,Specifications!$A:$AX,4,FALSE)) | G9: =IF($A9<1,"",VLOOKUP($D9,Specifications!$A:$AX,5,FALSE)) | I9: =IF($A9<1,"",VLOOKUP($D9,Specifications!$A:$AX,6,FALSE)) | K9: =IF($A9<1,"",VLOOKUP($D9,Specifications!$A:$AX,7,FALSE)) | M9: =IF($A9<1,"",VLOOKUP($D9,Specifications!$A:$AX,8,FALSE)) | O9: =IF($A9<1,"",VLOOKUP($D9,Specifications!$A:$AX,9,FALSE)) | Q9: =IF($A9<1,"",VLOOKUP($D9,Specifications!$A:$AX,10,FALSE)) | S9: =IF($A9<1,"",VLOOKUP($D9,Specifications!$A:$AX,11,FALSE)) | U9: =IF($A9<1,"",VLOOKUP($D9,Specifications!$A:$AX,12,FALSE)) | W9: =IF($A9<1,"",VLOOKUP($D9,Specifications!$A:$AX,13,FALSE)) | Y9: =IF($A9<1,"",VLOOKUP($D9,Specifications!$A:$AX,14,FALSE)) | AA9: =IF($A9<1,"",VLOOKUP($D9,Specifications!$A:$AX,15,FALSE)) | AC9: =IF($A9<1,"",VLOOKUP($D9,Specifications!$A:$AX,16,FALSE)) | AE9: =IF($A9<1,"",VLOOKUP($D9,Specifications!$A:$AX,17,FALSE)) | AG9: =IF($A9<1,"",VLOOKUP($D9,Specifications!$A:$AX,18,FALSE)) | AI9: =IF($A9<1,"",VLOOKUP($D9,Specifications!$A:$AX,19,FALSE)) | AK9: =IF($A9<1,"",VLOOKUP($D9,Specifications!$A:$AX,20,FALSE)) | AM9: =IF($A9<1,"",VLOOKUP($D9,Specifications!$A:$AX,21,FALSE)) | AO9: =IF($A9<1,"",VLOOKUP($D9,Specifications!$A:$AX,22,FALSE)) | AQ9: =IF($A9<1,"",VLOOKUP($D9,Specifications!$A:$AX,23,FALSE)) | AS9: =IF($A9<1,"",VLOOKUP($D9,Specifications!$A:$AX,24,FALSE)) | AU9: =IF($A9<1,"",VLOOKUP($D9,Specifications!$A:$AX,25,FALSE)) | AW9: =IF($A9<1,"",VLOOKUP($D9,Specifications!$A:$AX,26,FALSE)) | AY9: =IF($A9<1,"",VLOOKUP($D9,Specifications!$A:$AX,27,FALSE)) | BA9: =IF($A9<1,"",VLOOKUP($D9,Specifications!$A:$AX,28,FALSE)) | BC9: =IF($A9<1,"",VLOOKUP($D9,Specifications!$A:$AX,29,FALSE)) | BE9: =IF($A9<1,"",VLOOKUP($D9,Specifications!$A:$AX,30,FALSE)) | BG9: =IF($A9<1,"",VLOOKUP($D9,Specifications!$A:$AX,31,FALSE)) | BI9: =IF($A9<1,"",VLOOKUP($D9,Specifications!$A:$AX,32,FALSE)) | BK9: =IF($A9<1,"",VLOOKUP($D9,Specifications!$A:$AX,33,FALSE)) | BM9: =IF($A9<1,"",VLOOKUP($D9,Specifications!$A:$AX,34,FALSE)) | BO9: =IF($A9<1,"",VLOOKUP($D9,Specifications!$A:$AX,35,FALSE)) | BQ9: =IF($A9<1,"",VLOOKUP($D9,Specifications!$A:$AX,36,FALSE)) | BS9: =IF($A9<1,"",VLOOKUP($D9,Specifications!$A:$AX,37,FALSE)) | BU9: =IF($A9<1,"",VLOOKUP($D9,Specifications!$A:$AX,38,FALSE)) | BW9: =IF($A9<1,"",VLOOKUP($D9,Specifications!$A:$AX,39,FALSE)) | BY9: =IF($A9<1,"",VLOOKUP($D9,Specifications!$A:$AX,40,FALSE)) | CA9: =IF($A9<1,"",VLOOKUP($D9,Specifications!$A:$AX,41,FALSE)) | CC9: =IF($A9<1,"",VLOOKUP($D9,Specifications!$A:$AX,42,FALSE)) | CE9: =IF($A9<1,"",VLOOKUP($D9,Specifications!$A:$AX,43,FALSE)) | CG9: =IF($A9<1,"",VLOOKUP($D9,Specifications!$A:$AX,44,FALSE)) | CI9: =IF($A9<1,"",VLOOKUP($D9,Specifications!$A:$AX,45,FALSE)) | CK9: =IF($A9<1,"",VLOOKUP($D9,Specifications!$A:$AX,46,FALSE)) | CM9: =IF($A9<1,"",VLOOKUP($D9,Specifications!$A:$AX,47,FALSE)) | CO9: =IF($A9<1,"",VLOOKUP($D9,Specifications!$A:$AX,48,FALSE)) | CQ9: =IF($A9<1,"",VLOOKUP($D9,Specifications!$A:$AX,49,FALSE)) | CS9: =IF($A9<1,"",VLOOKUP($D9,Specifications!$A:$AX,50,FALSE))
A10: =IF(ISBLANK('Asset Data'!C11),0,'Asset Data'!A11) -> 0 | B10: =IF($A10<1,"",VLOOKUP($A10,'Asset Data'!$A:$C,3,FALSE)) | C10: =IF(A10<1,"",VLOOKUP(D10,Specifications!A:B,2,FALSE)) | D10: =IF(A10<1,"",VLOOKUP(A10,'Asset Data'!A:W,23,FALSE)) | E10: =IF($A10<1,"",VLOOKUP($D10,Specifications!$A:$AX,4,FALSE)) | G10: =IF($A10<1,"",VLOOKUP($D10,Specifications!$A:$AX,5,FALSE)) | I10: =IF($A10<1,"",VLOOKUP($D10,Specifications!$A:$AX,6,FALSE)) | K10: =IF($A10<1,"",VLOOKUP($D10,Specifications!$A:$AX,7,FALSE)) | M10: =IF($A10<1,"",VLOOKUP($D10,Specifications!$A:$AX,8,FALSE)) | O10: =IF($A10<1,"",VLOOKUP($D10,Specifications!$A:$AX,9,FALSE)) | Q10: =IF($A10<1,"",VLOOKUP($D10,Specifications!$A:$AX,10,FALSE)) | S10: =IF($A10<1,"",VLOOKUP($D10,Specifications!$A:$AX,11,FALSE)) | U10: =IF($A10<1,"",VLOOKUP($D10,Specifications!$A:$AX,12,FALSE)) | W10: =IF($A10<1,"",VLOOKUP($D10,Specifications!$A:$AX,13,FALSE)) | Y10: =IF($A10<1,"",VLOOKUP($D10,Specifications!$A:$AX,14,FALSE)) | AA10: =IF($A10<1,"",VLOOKUP($D10,Specifications!$A:$AX,15,FALSE)) | AC10: =IF($A10<1,"",VLOOKUP($D10,Specifications!$A:$AX,16,FALSE)) | AE10: =IF($A10<1,"",VLOOKUP($D10,Specifications!$A:$AX,17,FALSE)) | AG10: =IF($A10<1,"",VLOOKUP($D10,Specifications!$A:$AX,18,FALSE)) | AI10: =IF($A10<1,"",VLOOKUP($D10,Specifications!$A:$AX,19,FALSE)) | AK10: =IF($A10<1,"",VLOOKUP($D10,Specifications!$A:$AX,20,FALSE)) | AM10: =IF($A10<1,"",VLOOKUP($D10,Specifications!$A:$AX,21,FALSE)) | AO10: =IF($A10<1,"",VLOOKUP($D10,Specifications!$A:$AX,22,FALSE)) | AQ10: =IF($A10<1,"",VLOOKUP($D10,Specifications!$A:$AX,23,FALSE)) | AS10: =IF($A10<1,"",VLOOKUP($D10,Specifications!$A:$AX,24,FALSE)) | AU10: =IF($A10<1,"",VLOOKUP($D10,Specifications!$A:$AX,25,FALSE)) | AW10: =IF($A10<1,"",VLOOKUP($D10,Specifications!$A:$AX,26,FALSE)) | AY10: =IF($A10<1,"",VLOOKUP($D10,Specifications!$A:$AX,27,FALSE)) | BA10: =IF($A10<1,"",VLOOKUP($D10,Specifications!$A:$AX,28,FALSE)) | BC10: =IF($A10<1,"",VLOOKUP($D10,Specifications!$A:$AX,29,FALSE)) | BE10: =IF($A10<1,"",VLOOKUP($D10,Specifications!$A:$AX,30,FALSE)) | BG10: =IF($A10<1,"",VLOOKUP($D10,Specifications!$A:$AX,31,FALSE)) | BI10: =IF($A10<1,"",VLOOKUP($D10,Specifications!$A:$AX,32,FALSE)) | BK10: =IF($A10<1,"",VLOOKUP($D10,Specifications!$A:$AX,33,FALSE)) | BM10: =IF($A10<1,"",VLOOKUP($D10,Specifications!$A:$AX,34,FALSE)) | BO10: =IF($A10<1,"",VLOOKUP($D10,Specifications!$A:$AX,35,FALSE)) | BQ10: =IF($A10<1,"",VLOOKUP($D10,Specifications!$A:$AX,36,FALSE)) | BS10: =IF($A10<1,"",VLOOKUP($D10,Specifications!$A:$AX,37,FALSE)) | BU10: =IF($A10<1,"",VLOOKUP($D10,Specifications!$A:$AX,38,FALSE)) | BW10: =IF($A10<1,"",VLOOKUP($D10,Specifications!$A:$AX,39,FALSE)) | BY10: =IF($A10<1,"",VLOOKUP($D10,Specifications!$A:$AX,40,FALSE)) | CA10: =IF($A10<1,"",VLOOKUP($D10,Specifications!$A:$AX,41,FALSE)) | CC10: =IF($A10<1,"",VLOOKUP($D10,Specifications!$A:$AX,42,FALSE)) | CE10: =IF($A10<1,"",VLOOKUP($D10,Specifications!$A:$AX,43,FALSE)) | CG10: =IF($A10<1,"",VLOOKUP($D10,Specifications!$A:$AX,44,FALSE)) | CI10: =IF($A10<1,"",VLOOKUP($D10,Specifications!$A:$AX,45,FALSE)) | CK10: =IF($A10<1,"",VLOOKUP($D10,Specifications!$A:$AX,46,FALSE)) | CM10: =IF($A10<1,"",VLOOKUP($D10,Specifications!$A:$AX,47,FALSE)) | CO10: =IF($A10<1,"",VLOOKUP($D10,Specifications!$A:$AX,48,FALSE)) | CQ10: =IF($A10<1,"",VLOOKUP($D10,Specifications!$A:$AX,49,FALSE)) | CS10: =IF($A10<1,"",VLOOKUP($D10,Specifications!$A:$AX,50,FALSE))
A11: =IF(ISBLANK('Asset Data'!C12),0,'Asset Data'!A12) -> 0 | B11: =IF($A11<1,"",VLOOKUP($A11,'Asset Data'!$A:$C,3,FALSE)) | C11: =IF(A11<1,"",VLOOKUP(D11,Specifications!A:B,2,FALSE)) | D11: =IF(A11<1,"",VLOOKUP(A11,'Asset Data'!A:W,23,FALSE)) | E11: =IF($A11<1,"",VLOOKUP($D11,Specifications!$A:$AX,4,FALSE)) | G11: =IF($A11<1,"",VLOOKUP($D11,Specifications!$A:$AX,5,FALSE)) | I11: =IF($A11<1,"",VLOOKUP($D11,Specifications!$A:$AX,6,FALSE)) | K11: =IF($A11<1,"",VLOOKUP($D11,Specifications!$A:$AX,7,FALSE)) | M11: =IF($A11<1,"",VLOOKUP($D11,Specifications!$A:$AX,8,FALSE)) | O11: =IF($A11<1,"",VLOOKUP($D11,Specifications!$A:$AX,9,FALSE)) | Q11: =IF($A11<1,"",VLOOKUP($D11,Specifications!$A:$AX,10,FALSE)) | S11: =IF($A11<1,"",VLOOKUP($D11,Specifications!$A:$AX,11,FALSE)) | U11: =IF($A11<1,"",VLOOKUP($D11,Specifications!$A:$AX,12,FALSE)) | W11: =IF($A11<1,"",VLOOKUP($D11,Specifications!$A:$AX,13,FALSE)) | Y11: =IF($A11<1,"",VLOOKUP($D11,Specifications!$A:$AX,14,FALSE)) | AA11: =IF($A11<1,"",VLOOKUP($D11,Specifications!$A:$AX,15,FALSE)) | AC11: =IF($A11<1,"",VLOOKUP($D11,Specifications!$A:$AX,16,FALSE)) | AE11: =IF($A11<1,"",VLOOKUP($D11,Specifications!$A:$AX,17,FALSE)) | AG11: =IF($A11<1,"",VLOOKUP($D11,Specifications!$A:$AX,18,FALSE)) | AI11: =IF($A11<1,"",VLOOKUP($D11,Specifications!$A:$AX,19,FALSE)) | AK11: =IF($A11<1,"",VLOOKUP($D11,Specifications!$A:$AX,20,FALSE)) | AM11: =IF($A11<1,"",VLOOKUP($D11,Specifications!$A:$AX,21,FALSE)) | AO11: =IF($A11<1,"",VLOOKUP($D11,Specifications!$A:$AX,22,FALSE)) | AQ11: =IF($A11<1,"",VLOOKUP($D11,Specifications!$A:$AX,23,FALSE)) | AS11: =IF($A11<1,"",VLOOKUP($D11,Specifications!$A:$AX,24,FALSE)) | AU11: =IF($A11<1,"",VLOOKUP($D11,Specifications!$A:$AX,25,FALSE)) | AW11: =IF($A11<1,"",VLOOKUP($D11,Specifications!$A:$AX,26,FALSE)) | AY11: =IF($A11<1,"",VLOOKUP($D11,Specifications!$A:$AX,27,FALSE)) | BA11: =IF($A11<1,"",VLOOKUP($D11,Specifications!$A:$AX,28,FALSE)) | BC11: =IF($A11<1,"",VLOOKUP($D11,Specifications!$A:$AX,29,FALSE)) | BE11: =IF($A11<1,"",VLOOKUP($D11,Specifications!$A:$AX,30,FALSE)) | BG11: =IF($A11<1,"",VLOOKUP($D11,Specifications!$A:$AX,31,FALSE)) | BI11: =IF($A11<1,"",VLOOKUP($D11,Specifications!$A:$AX,32,FALSE)) | BK11: =IF($A11<1,"",VLOOKUP($D11,Specifications!$A:$AX,33,FALSE)) | BM11: =IF($A11<1,"",VLOOKUP($D11,Specifications!$A:$AX,34,FALSE)) | BO11: =IF($A11<1,"",VLOOKUP($D11,Specifications!$A:$AX,35,FALSE)) | BQ11: =IF($A11<1,"",VLOOKUP($D11,Specifications!$A:$AX,36,FALSE)) | BS11: =IF($A11<1,"",VLOOKUP($D11,Specifications!$A:$AX,37,FALSE)) | BU11: =IF($A11<1,"",VLOOKUP($D11,Specifications!$A:$AX,38,FALSE)) | BW11: =IF($A11<1,"",VLOOKUP($D11,Specifications!$A:$AX,39,FALSE)) | BY11: =IF($A11<1,"",VLOOKUP($D11,Specifications!$A:$AX,40,FALSE)) | CA11: =IF($A11<1,"",VLOOKUP($D11,Specifications!$A:$AX,41,FALSE)) | CC11: =IF($A11<1,"",VLOOKUP($D11,Specifications!$A:$AX,42,FALSE)) | CE11: =IF($A11<1,"",VLOOKUP($D11,Specifications!$A:$AX,43,FALSE)) | CG11: =IF($A11<1,"",VLOOKUP($D11,Specifications!$A:$AX,44,FALSE)) | CI11: =IF($A11<1,"",VLOOKUP($D11,Specifications!$A:$AX,45,FALSE)) | CK11: =IF($A11<1,"",VLOOKUP($D11,Specifications!$A:$AX,46,FALSE)) | CM11: =IF($A11<1,"",VLOOKUP($D11,Specifications!$A:$AX,47,FALSE)) | CO11: =IF($A11<1,"",VLOOKUP($D11,Specifications!$A:$AX,48,FALSE)) | CQ11: =IF($A11<1,"",VLOOKUP($D11,Specifications!$A:$AX,49,FALSE)) | CS11: =IF($A11<1,"",VLOOKUP($D11,Specifications!$A:$AX,50,FALSE))
A12: =IF(ISBLANK('Asset Data'!C13),0,'Asset Data'!A13) -> 0 | B12: =IF($A12<1,"",VLOOKUP($A12,'Asset Data'!$A:$C,3,FALSE)) | C12: =IF(A12<1,"",VLOOKUP(D12,Specifications!A:B,2,FALSE)) | D12: =IF(A12<1,"",VLOOKUP(A12,'Asset Data'!A:W,23,FALSE)) | E12: =IF($A12<1,"",VLOOKUP($D12,Specifications!$A:$AX,4,FALSE)) | G12: =IF($A12<1,"",VLOOKUP($D12,Specifications!$A:$AX,5,FALSE)) | I12: =IF($A12<1,"",VLOOKUP($D12,Specifications!$A:$AX,6,FALSE)) | K12: =IF($A12<1,"",VLOOKUP($D12,Specifications!$A:$AX,7,FALSE)) | M12: =IF($A12<1,"",VLOOKUP($D12,Specifications!$A:$AX,8,FALSE)) | O12: =IF($A12<1,"",VLOOKUP($D12,Specifications!$A:$AX,9,FALSE)) | Q12: =IF($A12<1,"",VLOOKUP($D12,Specifications!$A:$AX,10,FALSE)) | S12: =IF($A12<1,"",VLOOKUP($D12,Specifications!$A:$AX,11,FALSE)) | U12: =IF($A12<1,"",VLOOKUP($D12,Specifications!$A:$AX,12,FALSE)) | W12: =IF($A12<1,"",VLOOKUP($D12,Specifications!$A:$AX,13,FALSE)) | Y12: =IF($A12<1,"",VLOOKUP($D12,Specifications!$A:$AX,14,FALSE)) | AA12: =IF($A12<1,"",VLOOKUP($D12,Specifications!$A:$AX,15,FALSE)) | AC12: =IF($A12<1,"",VLOOKUP($D12,Specifications!$A:$AX,16,FALSE)) | AE12: =IF($A12<1,"",VLOOKUP($D12,Specifications!$A:$AX,17,FALSE)) | AG12: =IF($A12<1,"",VLOOKUP($D12,Specifications!$A:$AX,18,FALSE)) | AI12: =IF($A12<1,"",VLOOKUP($D12,Specifications!$A:$AX,19,FALSE)) | AK12: =IF($A12<1,"",VLOOKUP($D12,Specifications!$A:$AX,20,FALSE)) | AM12: =IF($A12<1,"",VLOOKUP($D12,Specifications!$A:$AX,21,FALSE)) | AO12: =IF($A12<1,"",VLOOKUP($D12,Specifications!$A:$AX,22,FALSE)) | AQ12: =IF($A12<1,"",VLOOKUP($D12,Specifications!$A:$AX,23,FALSE)) | AS12: =IF($A12<1,"",VLOOKUP($D12,Specifications!$A:$AX,24,FALSE)) | AU12: =IF($A12<1,"",VLOOKUP($D12,Specifications!$A:$AX,25,FALSE)) | AW12: =IF($A12<1,"",VLOOKUP($D12,Specifications!$A:$AX,26,FALSE)) | AY12: =IF($A12<1,"",VLOOKUP($D12,Specifications!$A:$AX,27,FALSE)) | BA12: =IF($A12<1,"",VLOOKUP($D12,Specifications!$A:$AX,28,FALSE)) | BC12: =IF($A12<1,"",VLOOKUP($D12,Specifications!$A:$AX,29,FALSE)) | BE12: =IF($A12<1,"",VLOOKUP($D12,Specifications!$A:$AX,30,FALSE)) | BG12: =IF($A12<1,"",VLOOKUP($D12,Specifications!$A:$AX,31,FALSE)) | BI12: =IF($A12<1,"",VLOOKUP($D12,Specifications!$A:$AX,32,FALSE)) | BK12: =IF($A12<1,"",VLOOKUP($D12,Specifications!$A:$AX,33,FALSE)) | BM12: =IF($A12<1,"",VLOOKUP($D12,Specifications!$A:$AX,34,FALSE)) | BO12: =IF($A12<1,"",VLOOKUP($D12,Specifications!$A:$AX,35,FALSE)) | BQ12: =IF($A12<1,"",VLOOKUP($D12,Specifications!$A:$AX,36,FALSE)) | BS12: =IF($A12<1,"",VLOOKUP($D12,Specifications!$A:$AX,37,FALSE)) | BU12: =IF($A12<1,"",VLOOKUP($D12,Specifications!$A:$AX,38,FALSE)) | BW12: =IF($A12<1,"",VLOOKUP($D12,Specifications!$A:$AX,39,FALSE)) | BY12: =IF($A12<1,"",VLOOKUP($D12,Specifications!$A:$AX,40,FALSE)) | CA12: =IF($A12<1,"",VLOOKUP($D12,Specifications!$A:$AX,41,FALSE)) | CC12: =IF($A12<1,"",VLOOKUP($D12,Specifications!$A:$AX,42,FALSE)) | CE12: =IF($A12<1,"",VLOOKUP($D12,Specifications!$A:$AX,43,FALSE)) | CG12: =IF($A12<1,"",VLOOKUP($D12,Specifications!$A:$AX,44,FALSE)) | CI12: =IF($A12<1,"",VLOOKUP($D12,Specifications!$A:$AX,45,FALSE)) | CK12: =IF($A12<1,"",VLOOKUP($D12,Specifications!$A:$AX,46,FALSE)) | CM12: =IF($A12<1,"",VLOOKUP($D12,Specifications!$A:$AX,47,FALSE)) | CO12: =IF($A12<1,"",VLOOKUP($D12,Specifications!$A:$AX,48,FALSE)) | CQ12: =IF($A12<1,"",VLOOKUP($D12,Specifications!$A:$AX,49,FALSE)) | CS12: =IF($A12<1,"",VLOOKUP($D12,Specifications!$A:$AX,50,FALSE))
A13: =IF(ISBLANK('Asset Data'!C14),0,'Asset Data'!A14) -> 0 | B13: =IF($A13<1,"",VLOOKUP($A13,'Asset Data'!$A:$C,3,FALSE)) | C13: =IF(A13<1,"",VLOOKUP(D13,Specifications!A:B,2,FALSE)) | D13: =IF(A13<1,"",VLOOKUP(A13,'Asset Data'!A:W,23,FALSE)) | E13: =IF($A13<1,"",VLOOKUP($D13,Specifications!$A:$AX,4,FALSE)) | G13: =IF($A13<1,"",VLOOKUP($D13,Specifications!$A:$AX,5,FALSE)) | I13: =IF($A13<1,"",VLOOKUP($D13,Specifications!$A:$AX,6,FALSE)) | K13: =IF($A13<1,"",VLOOKUP($D13,Specifications!$A:$AX,7,FALSE)) | M13: =IF($A13<1,"",VLOOKUP($D13,Specifications!$A:$AX,8,FALSE)) | O13: =IF($A13<1,"",VLOOKUP($D13,Specifications!$A:$AX,9,FALSE)) | Q13: =IF($A13<1,"",VLOOKUP($D13,Specifications!$A:$AX,10,FALSE)) | S13: =IF($A13<1,"",VLOOKUP($D13,Specifications!$A:$AX,11,FALSE)) | U13: =IF($A13<1,"",VLOOKUP($D13,Specifications!$A:$AX,12,FALSE)) | W13: =IF($A13<1,"",VLOOKUP($D13,Specifications!$A:$AX,13,FALSE)) | Y13: =IF($A13<1,"",VLOOKUP($D13,Specifications!$A:$AX,14,FALSE)) | AA13: =IF($A13<1,"",VLOOKUP($D13,Specifications!$A:$AX,15,FALSE)) | AC13: =IF($A13<1,"",VLOOKUP($D13,Specifications!$A:$AX,16,FALSE)) | AE13: =IF($A13<1,"",VLOOKUP($D13,Specifications!$A:$AX,17,FALSE)) | AG13: =IF($A13<1,"",VLOOKUP($D13,Specifications!$A:$AX,18,FALSE)) | AI13: =IF($A13<1,"",VLOOKUP($D13,Specifications!$A:$AX,19,FALSE)) | AK13: =IF($A13<1,"",VLOOKUP($D13,Specifications!$A:$AX,20,FALSE)) | AM13: =IF($A13<1,"",VLOOKUP($D13,Specifications!$A:$AX,21,FALSE)) | AO13: =IF($A13<1,"",VLOOKUP($D13,Specifications!$A:$AX,22,FALSE)) | AQ13: =IF($A13<1,"",VLOOKUP($D13,Specifications!$A:$AX,23,FALSE)) | AS13: =IF($A13<1,"",VLOOKUP($D13,Specifications!$A:$AX,24,FALSE)) | AU13: =IF($A13<1,"",VLOOKUP($D13,Specifications!$A:$AX,25,FALSE)) | AW13: =IF($A13<1,"",VLOOKUP($D13,Specifications!$A:$AX,26,FALSE)) | AY13: =IF($A13<1,"",VLOOKUP($D13,Specifications!$A:$AX,27,FALSE)) | BA13: =IF($A13<1,"",VLOOKUP($D13,Specifications!$A:$AX,28,FALSE)) | BC13: =IF($A13<1,"",VLOOKUP($D13,Specifications!$A:$AX,29,FALSE)) | BE13: =IF($A13<1,"",VLOOKUP($D13,Specifications!$A:$AX,30,FALSE)) | BG13: =IF($A13<1,"",VLOOKUP($D13,Specifications!$A:$AX,31,FALSE)) | BI13: =IF($A13<1,"",VLOOKUP($D13,Specifications!$A:$AX,32,FALSE)) | BK13: =IF($A13<1,"",VLOOKUP($D13,Specifications!$A:$AX,33,FALSE)) | BM13: =IF($A13<1,"",VLOOKUP($D13,Specifications!$A:$AX,34,FALSE)) | BO13: =IF($A13<1,"",VLOOKUP($D13,Specifications!$A:$AX,35,FALSE)) | BQ13: =IF($A13<1,"",VLOOKUP($D13,Specifications!$A:$AX,36,FALSE)) | BS13: =IF($A13<1,"",VLOOKUP($D13,Specifications!$A:$AX,37,FALSE)) | BU13: =IF($A13<1,"",VLOOKUP($D13,Specifications!$A:$AX,38,FALSE)) | BW13: =IF($A13<1,"",VLOOKUP($D13,Specifications!$A:$AX,39,FALSE)) | BY13: =IF($A13<1,"",VLOOKUP($D13,Specifications!$A:$AX,40,FALSE)) | CA13: =IF($A13<1,"",VLOOKUP($D13,Specifications!$A:$AX,41,FALSE)) | CC13: =IF($A13<1,"",VLOOKUP($D13,Specifications!$A:$AX,42,FALSE)) | CE13: =IF($A13<1,"",VLOOKUP($D13,Specifications!$A:$AX,43,FALSE)) | CG13: =IF($A13<1,"",VLOOKUP($D13,Specifications!$A:$AX,44,FALSE)) | CI13: =IF($A13<1,"",VLOOKUP($D13,Specifications!$A:$AX,45,FALSE)) | CK13: =IF($A13<1,"",VLOOKUP($D13,Specifications!$A:$AX,46,FALSE)) | CM13: =IF($A13<1,"",VLOOKUP($D13,Specifications!$A:$AX,47,FALSE)) | CO13: =IF($A13<1,"",VLOOKUP($D13,Specifications!$A:$AX,48,FALSE)) | CQ13: =IF($A13<1,"",VLOOKUP($D13,Specifications!$A:$AX,49,FALSE)) | CS13: =IF($A13<1,"",VLOOKUP($D13,Specifications!$A:$AX,50,FALSE))
... A500: =IF(ISBLANK('Asset Data'!C501),0,'Asset Data'!A501) -> 0 | B500: =IF($A500<1,"",VLOOKUP($A500,'Asset Data'!$A:$C,3,FALSE)) | C500: =IF(A500<1,"",VLOOKUP(D500,Specifications!A:B,2,FALSE)) | D500: =IF(A500<1,"",VLOOKUP(A500,'Asset Data'!A:W,23,FALSE)) | E500: =IF($A500<1,"",VLOOKUP($D500,Specifications!$A:$AX,4,FALSE)) | G500: =IF($A500<1,"",VLOOKUP($D500,Specifications!$A:$AX,5,FALSE)) | I500: =IF($A500<1,"",VLOOKUP($D500,Specifications!$A:$AX,6,FALSE)) | K500: =IF($A500<1,"",VLOOKUP($D500,Specifications!$A:$AX,7,FALSE)) | M500: =IF($A500<1,"",VLOOKUP($D500,Specifications!$A:$AX,8,FALSE)) | O500: =IF($A500<1,"",VLOOKUP($D500,Specifications!$A:$AX,9,FALSE)) | Q500: =IF($A500<1,"",VLOOKUP($D500,Specifications!$A:$AX,10,FALSE)) | S500: =IF($A500<1,"",VLOOKUP($D500,Specifications!$A:$AX,11,FALSE)) | U500: =IF($A500<1,"",VLOOKUP($D500,Specifications!$A:$AX,12,FALSE)) | W500: =IF($A500<1,"",VLOOKUP($D500,Specifications!$A:$AX,13,FALSE)) | Y500: =IF($A500<1,"",VLOOKUP($D500,Specifications!$A:$AX,14,FALSE)) | AA500: =IF($A500<1,"",VLOOKUP($D500,Specifications!$A:$AX,15,FALSE)) | AC500: =IF($A500<1,"",VLOOKUP($D500,Specifications!$A:$AX,16,FALSE)) | AE500: =IF($A500<1,"",VLOOKUP($D500,Specifications!$A:$AX,17,FALSE)) | AG500: =IF($A500<1,"",VLOOKUP($D500,Specifications!$A:$AX,18,FALSE)) | AI500: =IF($A500<1,"",VLOOKUP($D500,Specifications!$A:$AX,19,FALSE)) | AK500: =IF($A500<1,"",VLOOKUP($D500,Specifications!$A:$AX,20,FALSE)) | AM500: =IF($A500<1,"",VLOOKUP($D500,Specifications!$A:$AX,21,FALSE)) | AO500: =IF($A500<1,"",VLOOKUP($D500,Specifications!$A:$AX,22,FALSE)) | AQ500: =IF($A500<1,"",VLOOKUP($D500,Specifications!$A:$AX,23,FALSE)) | AS500: =IF($A500<1,"",VLOOKUP($D500,Specifications!$A:$AX,24,FALSE)) | AU500: =IF($A500<1,"",VLOOKUP($D500,Specifications!$A:$AX,25,FALSE)) | AW500: =IF($A500<1,"",VLOOKUP($D500,Specifications!$A:$AX,26,FALSE)) | AY500: =IF($A500<1,"",VLOOKUP($D500,Specifications!$A:$AX,27,FALSE)) | BA500: =IF($A500<1,"",VLOOKUP($D500,Specifications!$A:$AX,28,FALSE)) | BC500: =IF($A500<1,"",VLOOKUP($D500,Specifications!$A:$AX,29,FALSE)) | BE500: =IF($A500<1,"",VLOOKUP($D500,Specifications!$A:$AX,30,FALSE)) | BG500: =IF($A500<1,"",VLOOKUP($D500,Specifications!$A:$AX,31,FALSE)) | BI500: =IF($A500<1,"",VLOOKUP($D500,Specifications!$A:$AX,32,FALSE)) | BK500: =IF($A500<1,"",VLOOKUP($D500,Specifications!$A:$AX,33,FALSE)) | BM500: =IF($A500<1,"",VLOOKUP($D500,Specifications!$A:$AX,34,FALSE)) | BO500: =IF($A500<1,"",VLOOKUP($D500,Specifications!$A:$AX,35,FALSE)) | BQ500: =IF($A500<1,"",VLOOKUP($D500,Specifications!$A:$AX,36,FALSE)) | BS500: =IF($A500<1,"",VLOOKUP($D500,Specifications!$A:$AX,37,FALSE)) | BU500: =IF($A500<1,"",VLOOKUP($D500,Specifications!$A:$AX,38,FALSE)) | BW500: =IF($A500<1,"",VLOOKUP($D500,Specifications!$A:$AX,39,FALSE)) | BY500: =IF($A500<1,"",VLOOKUP($D500,Specifications!$A:$AX,40,FALSE)) | CA500: =IF($A500<1,"",VLOOKUP($D500,Specifications!$A:$AX,41,FALSE)) | CC500: =IF($A500<1,"",VLOOKUP($D500,Specifications!$A:$AX,42,FALSE)) | CE500: =IF($A500<1,"",VLOOKUP($D500,Specifications!$A:$AX,43,FALSE)) | CG500: =IF($A500<1,"",VLOOKUP($D500,Specifications!$A:$AX,44,FALSE)) | CI500: =IF($A500<1,"",VLOOKUP($D500,Specifications!$A:$AX,45,FALSE)) | CK500: =IF($A500<1,"",VLOOKUP($D500,Specifications!$A:$AX,46,FALSE)) | CM500: =IF($A500<1,"",VLOOKUP($D500,Specifications!$A:$AX,47,FALSE)) | CO500: =IF($A500<1,"",VLOOKUP($D500,Specifications!$A:$AX,48,FALSE)) | CQ500: =IF($A500<1,"",VLOOKUP($D500,Specifications!$A:$AX,49,FALSE)) | CS500: =IF($A500<1,"",VLOOKUP($D500,Specifications!$A:$AX,50,FALSE))
A501: =IF(ISBLANK('Asset Data'!C501),0,'Asset Data'!A501) -> 0 | B501: =IF($A501<1,"",VLOOKUP($A501,'Asset Data'!$A:$C,3,FALSE)) | C501: =IF(A501<1,"",VLOOKUP(D501,Specifications!A:B,2,FALSE)) | D501: =IF(A501<1,"",VLOOKUP(A501,'Asset Data'!A:W,23,FALSE)) | E501: =IF($A501<1,"",VLOOKUP($D501,Specifications!$A:$AX,4,FALSE)) | G501: =IF($A501<1,"",VLOOKUP($D501,Specifications!$A:$AX,5,FALSE)) | I501: =IF($A501<1,"",VLOOKUP($D501,Specifications!$A:$AX,6,FALSE)) | K501: =IF($A501<1,"",VLOOKUP($D501,Specifications!$A:$AX,7,FALSE)) | M501: =IF($A501<1,"",VLOOKUP($D501,Specifications!$A:$AX,8,FALSE)) | O501: =IF($A501<1,"",VLOOKUP($D501,Specifications!$A:$AX,9,FALSE)) | Q501: =IF($A501<1,"",VLOOKUP($D501,Specifications!$A:$AX,10,FALSE)) | S501: =IF($A501<1,"",VLOOKUP($D501,Specifications!$A:$AX,11,FALSE)) | U501: =IF($A501<1,"",VLOOKUP($D501,Specifications!$A:$AX,12,FALSE)) | W501: =IF($A501<1,"",VLOOKUP($D501,Specifications!$A:$AX,13,FALSE)) | Y501: =IF($A501<1,"",VLOOKUP($D501,Specifications!$A:$AX,14,FALSE)) | AA501: =IF($A501<1,"",VLOOKUP($D501,Specifications!$A:$AX,15,FALSE)) | AC501: =IF($A501<1,"",VLOOKUP($D501,Specifications!$A:$AX,16,FALSE)) | AE501: =IF($A501<1,"",VLOOKUP($D501,Specifications!$A:$AX,17,FALSE)) | AG501: =IF($A501<1,"",VLOOKUP($D501,Specifications!$A:$AX,18,FALSE)) | AI501: =IF($A501<1,"",VLOOKUP($D501,Specifications!$A:$AX,19,FALSE)) | AK501: =IF($A501<1,"",VLOOKUP($D501,Specifications!$A:$AX,20,FALSE)) | AM501: =IF($A501<1,"",VLOOKUP($D501,Specifications!$A:$AX,21,FALSE)) | AO501: =IF($A501<1,"",VLOOKUP($D501,Specifications!$A:$AX,22,FALSE)) | AQ501: =IF($A501<1,"",VLOOKUP($D501,Specifications!$A:$AX,23,FALSE)) | AS501: =IF($A501<1,"",VLOOKUP($D501,Specifications!$A:$AX,24,FALSE)) | AU501: =IF($A501<1,"",VLOOKUP($D501,Specifications!$A:$AX,25,FALSE)) | AW501: =IF($A501<1,"",VLOOKUP($D501,Specifications!$A:$AX,26,FALSE)) | AY501: =IF($A501<1,"",VLOOKUP($D501,Specifications!$A:$AX,27,FALSE)) | BA501: =IF($A501<1,"",VLOOKUP($D501,Specifications!$A:$AX,28,FALSE)) | BC501: =IF($A501<1,"",VLOOKUP($D501,Specifications!$A:$AX,29,FALSE)) | BE501: =IF($A501<1,"",VLOOKUP($D501,Specifications!$A:$AX,30,FALSE)) | BG501: =IF($A501<1,"",VLOOKUP($D501,Specifications!$A:$AX,31,FALSE)) | BI501: =IF($A501<1,"",VLOOKUP($D501,Specifications!$A:$AX,32,FALSE)) | BK501: =IF($A501<1,"",VLOOKUP($D501,Specifications!$A:$AX,33,FALSE)) | BM501: =IF($A501<1,"",VLOOKUP($D501,Specifications!$A:$AX,34,FALSE)) | BO501: =IF($A501<1,"",VLOOKUP($D501,Specifications!$A:$AX,35,FALSE)) | BQ501: =IF($A501<1,"",VLOOKUP($D501,Specifications!$A:$AX,36,FALSE)) | BS501: =IF($A501<1,"",VLOOKUP($D501,Specifications!$A:$AX,37,FALSE)) | BU501: =IF($A501<1,"",VLOOKUP($D501,Specifications!$A:$AX,38,FALSE)) | BW501: =IF($A501<1,"",VLOOKUP($D501,Specifications!$A:$AX,39,FALSE)) | BY501: =IF($A501<1,"",VLOOKUP($D501,Specifications!$A:$AX,40,FALSE)) | CA501: =IF($A501<1,"",VLOOKUP($D501,Specifications!$A:$AX,41,FALSE)) | CC501: =IF($A501<1,"",VLOOKUP($D501,Specifications!$A:$AX,42,FALSE)) | CE501: =IF($A501<1,"",VLOOKUP($D501,Specifications!$A:$AX,43,FALSE)) | CG501: =IF($A501<1,"",VLOOKUP($D501,Specifications!$A:$AX,44,FALSE)) | CI501: =IF($A501<1,"",VLOOKUP($D501,Specifications!$A:$AX,45,FALSE)) | CK501: =IF($A501<1,"",VLOOKUP($D501,Specifications!$A:$AX,46,FALSE)) | CM501: =IF($A501<1,"",VLOOKUP($D501,Specifications!$A:$AX,47,FALSE)) | CO501: =IF($A501<1,"",VLOOKUP($D501,Specifications!$A:$AX,48,FALSE)) | CQ501: =IF($A501<1,"",VLOOKUP($D501,Specifications!$A:$AX,49,FALSE)) | CS501: =IF($A501<1,"",VLOOKUP($D501,Specifications!$A:$AX,50,FALSE))

Sheet Value Lists
A1: Asset Type | D1: Yes or No | G1: Asset Condition Code | J1: UOM | K1: Description | M1: Site | N1: org | O1: itemset | P1: Description | R1: FailureCode | U1: Attributes and Domain | X1: mastersys | Z1: Meter | AA1: Description | AB1: Meter Type | AD1: Meter Group | AE1: Description
A2: Value | B2: Description | D2: Value | E2: Description | G2: Value | H2: Description | J2: AC | K2: Alternating Curretn | M2: AL | N2: ALBANY | O2: IALBANY | P2: MCLB Albany, GA | R2: Value | S2: Description | U2: assetattrid | V2: domainid | X2: A10-FOUNDATIONS | Z2: ASSETCOND | AA2: Asset Condition | AB2: CHARACTERISTIC | AD2: ADVANCED | AE2: Advanced Metering
A3: FACILITIES | B3: Facilities Assets | D3: 0 | E3: No | G3: 1 | H3: New equipment | J3: AH | K3: Amp Hour | M3: BA | N3: BARSTOW | O3: IBARSTOW | P3: MCLB Barstow, CA | R3: ACC | S3: Air Cooled Conderser | U3: ABSORBTYPE | V3: UABSORBTYPE | X3: A20-BASEMENT CONSTRUCTION | Z3: ELECTRICALUSAGE | AA3: Electrical Usage Meter | AB3: CONTINUOUS | AD3: BACKFLOW | AE3: Backflow Certification
A4: FLEET | B4: Fleet Assets | D4: 1 | E4: Yes | G4: 2 | H4: Operational w/ no major flaws | J4: AMP | K4: Amp | M4: BE | N4: BEAUFORT | O4: IBEAUFORT | P4: MCAS Beaufort, SC | R4: AERAFLOAT | S4: Aerator Floats | U4: ACCOOLTYPE | V4: UCOOLTYPE | X4: B10-SUPERSTRUCTURE | Z4: GRNDCOND | AA4: Ground Condition | AB4: CHARACTERISTIC | AD4: BOILER | AE4: Boiler Certification
A5: IT | B5: IT Assets | G5: 3 | H5: Showing signs of wear | J5: AT | K5: Assortment | M5: BP | N5: BRIDGE | O5: IBRIDGE | P5: MCMWTC Bridgeport | R5: AFFF | S5: AFFF System | U5: ACFUNCTION | V5: ACFUNCTION | X5: B20-EXTERIOR ENCLOSURE | Z5: TEMPERATUREIN | AA5: Incoming Tempreture Meter | AB5: GAUGE | AD5: TANK | AE5: Storage tank
A6: PRODUCTION | B6: Production Assets | G6: 4 | H6: Marginal condition | J6: AWG | K6: American Wire Gauge | M6: CP | N6: CHERRY | O6: ICHERRY | P6: Cherry Point | R6: AFFFT | S6: AFFF Tank | U6: ACTIONTYPE | V6: UACTIONTYPE | X6: B30-ROOFING | Z6: NATURALGASUSAGE | AA6: Natural Gas Usage Meter | AB6: CONTINUOUS
A7: UTILITIES | B7: Utility Assets | G7: 5 | H7: High deterioration or failure | J7: AY | K7: Assembly | M7: EI | N7: WASHDC | O7: IWASHDC | P7: Eighth and I | R7: AHU | S7: Air Handling Unit | U7: ACTUATORTYPE | V7: UVLVCNTRLTYPE | X7: C10-INTERIOR CONSTRUCTION | Z7: O2 | AA7: O2 meter | AB7: GAUGE
J8: BF | K8: Board Foot | M8: HI | N8: KANEOHE | O8: IKANEOHE | P8: MCBH KANEOHE BAY | R8: AIRCOMP | S8: Air Compressor | U8: AIRPREHEATER | V8: UYESNOINDICATOR | X8: C20-STAIRS | Z8: TEMPRETUREOUT | AA8: Outgoing Temperature meter | AB8: GAUGE
A9: Language Code | D9: Status | J9: BG | K9: Bag | M9: IW | N9: IWAKUNI | O9: IIWAKUNI | P9: MCAS Iwakuni, Japan | R9: AIRCURT | S9: Air Curtain | U9: AMRINDICATOR | V9: UYESNOINDICATOR | X9: C30-INTERIOR FINISHES | Z9: POWER | AA9: Power Meter | AB9: GAUGE
A10: Value | B10: Description | D10: NOT READY | J10: BK | K10: Book | M10: LE | N10: LEJEUNE | O10: ILEJEUNE | P10: MCB Camp Lejeune/MCAS New Ri | R10: ALARMPAN | S10: Alarm Panel | U10: ANODEMATERIAL | V10: UANODEMATLTYPE | X10: D10-CONVEYING | Z10: STEAMFLOW | AA10: Steam Flow Meter | AB10: GAUGE
A11: EN | B11: English | D11: OPERATING | J11: BTU | K11: British Thermal Unit | M11: MI | N11: MIRAMAR | O11: IMIRAMAR | P11: MCAS Miramar, CA | R11: ATS | S11: Automatic Transfer Switch | U11: BARSCREENTYPE | V11: UBARSCREENTYPE | X11: D20-PLUMBING | Z11: STEAMPRESSURE | AA11: Steam Pressure Meter | AB11: GAUGE
A12: ES | B12: Español | D12: DISPOSED | J12: BX | K12: Box | M12: MR | N12: MARRES | O12: IMARRES | P12: Marine Corp Forces Reserves | R12: BARMIN | S12: Barminutor | U12: BATTERYROLE | V12: UBATTERYROLE | X12: D30-HVAC | Z12: STEAMUSAGE | AA12: Steam Usage Meter | AB12: CONTINUOUS
A13: JA | B13: Japanese | J13: C | K13: Degree Centigrade | M13: MU | N13: MUJUK | O13: IMUJUK | P13: Camp Mujuk Korea | R13: BASE | S13: Base | U13: BATTERYTYPE | V13: UBATTERYTYPE | X13: D40-FIRE PROTECTION | Z13: RUNHOURMETER | AA13: Total Run Hours Meter | AB13: CONTINUOUS
A14: KO | B14: Korean | J14: CD | K14: Cubic Yard | M14: OK | N14: OKINAWA | O14: IOKINAWA | P14: Okinawa, Japan (All bases) | R14: BATHPART | S14: Bathroom Partition | U14: BILRATING | V14: UBILRATING | X14: D50-ELECTRICAL | Z14: DI | AA14: Utility Degradation Index | AB14: CHARACTERISTIC
J15: CF | K15: Cubic Foot | M15: PA | N15: MCASPA | O15: IMCASPA | P15: MCAS Camp Pendleton | R15: BATY | S15: Battery | U15: BOILERTYPE | V15: UBOILERTYPE | X15: E10-EQUIPMENT | Z15: WATERUSAGE | AA15: Water Usage Meeter | AB15: CONTINUOUS
A16: Priority | J16: CFM | K16: Cubic Feet Per Minute | M16: PE | N16: CPEN | O16: ICPEN | P16: MCB Camp Pendleton | R16: BATYC | S16: Battery Charger | U16: BONNETCOLOR | V16: UCOLOR | X16: E20-FURNISHINGS
A17: Value | B17: Description | J17: CI | K17: Cubic Inch | M17: PI | N17: PARRIS | O17: IPARRIS | P17: MCRD Parris Island | R17: BKFLOW | S17: Backflow Device | U17: BOOSTPERCENT | V17: UVOLTREGPERCENT | X17: F10-SPECIAL CONSTRUCTION
A18: 0 | B18: None | J18: CM | K18: Centimeter | M18: QU | N18: QUANTICO | O18: IQUANTICO | P18: MCB/MCAF Quantico, VA | R18: BKP | S18: Breaker Panel | U18: BUCKETTRUCKREQUIRED | V18: UYESNOINDICATOR | X18: F20-SELECTIVE BUILDING DEMOLITION
A19: 1 | B19: Low | J19: CM2 | K19: Square Centimeter | M19: SD | N19: SANDIEGO | O19: ISANDIEGO | P19: MCRD San Diego, CA | R19: BKRLV | S19: Breaker Low Voltage | U19: BUCKPERCENT | V19: UVOLTREGPERCENT | X19: G10-SITE PREPARATIONS
A20: 2 | B20: Medium | J20: CZ | K20: Cubic Meter | M20: TP | N20: 29PALMS | O20: I29PALMS | P20: MCAGTC Twentynine Palms, CA | R20: BLDG | S20: Building Repairs | U20: BUSBARSHAPE | V20: UBUSSHAPE | X20: G20-SITE IMPROVEMENTS
A21: 3 | B21: High | J21: DC | K21: Direct Current | M21: YU | N21: YUMA | O21: IYUMA | P21: MCAS Yuma, AZ | R21: BLDSIGN | S21: Building Sign | U21: BUSMATERIAL | V21: UMATERIAL | X21: G30-SITE CIVIL/MECHANICAL UTILITIES
J22: DEG | K22: Degree | R22: BLOWER | S22: Blower | U22: BYPASSINDICATOR | V22: UYESNOINDICATOR | X22: G40-SITE ELECTRICAL UTILITIES
A23: Item Type | J23: EA | K23: Each | R23: BLR | S23: Boiler | U23: BYPASSSWITCH | V23: UYESNOINDICATOR | X23: G90-OTHER SITE CONSTRUCTION
A24: Item | J24: F | K24: Degree Fahrenheit | R24: BRIDGE | S24: Bridge | U24: BYPASSSWITCHINDICATOR | V24: UYESNOINDICATOR | X24: H10-WATERFRONT STRUCTURES
A25: Tool | J25: FLOZ | K25: Fluid Ounce | R25: CABINET | S25: Cabinet | U25: CAPACITYUOM | V25: UCAPACITYUOM | X25: H30-COASTAL PROTECTION
J26: FT | K26: Foot | R26: CAP | S26: Carousel Pastry | U26: CAPACITYUOM | V26: UVOLUMEUOM | X26: H40-NAV DREDGING / RECLAMATION
J27: GL | K27: Gallon | R27: CARPET | S27: Carpet | U27: CAPBANKTYPE | V27: UCAPBANKTYPE | X27: H50-WATERFRONT UTILITIES
J28: GM | K28: Gram | R28: CAULIG | S28: Caution Light | U28: CHARGERINPUTVOLTAGE | V28: UCONTROLSYSVOLTAGE | X28: J10-Electric Utilities
J29: GP | K29: Group | R29: CHKVLV | S29: Check Valve | U29: CHARGEROUTPUTVOLTAGE | V29: UCONTROLSYSVOLTAGE | X29: K10-Potable Water Utilities
J30: GPD | K30: Gallons Per Day | R30: CHOLDER | S30: Cup Holder | U30: CHEMICALSTATE | V30: UCHEMSTATE | X30: K20-Non-Potable Water Utilities
J31: GPH | K31: Gallons Per Hour | R31: CHR | S31: Chiller | U31: CLARIFIERTYPE | V31: UCLARIFIFIERTYPE | X31: K30-Fire Protection Water Utili
J32: GPM | K32: Gallons Per Minute | R32: CLAR | S32: Clarifier | U32: COMPRESSORTYPE | V32: UCOMPTYPE | X32: K40-Salt Water Utilities
J33: GR | K33: Gross | R33: COF | S33: Coffee Maker | U33: CONDUCTORMATERIAL | V33: UCONDUCTORMAT | X33: L10-Steam Utilities
J34: HD | K34: Hundred | R34: COLDBAR | S34: Cold Bar | U34: CONDUCTORSIZE | V34: UMAXCONDSIZE | X34: L20-High Temp Hot Water Utiliti
J35: HP | K35: Horse Power | R35: COMMIN | S35: Comminutor | U35: CONDUCTORTYPE | V35: UCONDUCTORTYPE | X35: L30-Domestic Hot Water Utilitie
J36: HR | K36: Hour | R36: COMPATOR | S36: Compactor | U36: CONDUITINDICATOR | V36: UYESNOINDICATOR | X36: L40-Chilled Water Utilities
J37: HZ | K37: Hertz | R37: COMPRMAC | S37: Computer Room A/C | U37: CONDUITMATERIAL | V37: UMATERIAL | X37: M10-Sanitary Sewer Utilities
... J46: LF | K46: Liner Foot | R46: CURB | S46: Curb | U46: CONTSPEC | V46: CONTSPEC | X46: Q10-Multiple Commodity Utilitie
J47: LI | K47: Liter | R47: DAMPER | S47: Damper | U47: CONTTYPE | V47: CONTTYPE
J48: LPM | K48: Liters Per Minute | R48: DEF | S48: Deep Fryer | U48: CONVEYORTYPE | V48: UCONVEYORTYPE
J49: M | K49: Meter | R49: DEHUMIDIFIER | S49: Dehumidifier | U49: COOLINGTYPE | V49: UCOOLINGTYPE
J50: M2 | K50: Square Meters | R50: DETEC | S50: Detector | U50: COOLTYPE | V50: UCOOLTYPE
J51: MBH | K51: Thousand BTU per Hour | R51: DIMMER | S51: Dimmer | U51: COVERRATING | V51: UCOVERRATING
J52: MC | K52: Thousand Cubic Foot | R52: DIS | S52: Dispenser | U52: CRITICALCUSTOMERINDICATOR | V52: UYESNOINDICATOR
J53: MFD | K53: Micro Ferad | R53: DISCONN | S53: Disconnect | U53: CYCLETYPE | V53: UCYCLETYPE
J54: MILE | K54: Mile | R54: DISTSYS | S54: Disinfectant System | U54: DEAERATORCAPACITYUOM | V54: UFLOWUOM
J55: MM | K55: Milimeter | R55: DIW | S55: Dishwasher | U55: DEAERATORTYPE | V55: UDATYPE
J56: MMHG | K56: MM Mercury Vacuum | R56: DOOR | S56: Door | U56: DEPTHUOM | V56: ULENGTHUOM
J57: MO | K57: Month | R57: DOORFRA | S57: Door Frame | U57: DESIGNPRESSUREUOM | V57: UPRESSUREUOM
J58: MR | K58: Meter | R58: DRAIN | S58: Drain | U58: DIAMETERUOM | V58: ULENGTHUOM
... J77: YR | K77: Year | R77: FLOOR | S77: Floor | U77: ERATEDFUSEINDICATOR | V77: UYESNOINDICATOR
P78: FOOTER | Q78: Footing | S78: EXTERIORLIGHTTYPE | T78: UEXTLIGHTROLE
P79: FOUND | Q79: Foundation | S79: FANROLE | T79: UFANROLE
P80: FRECVT | Q80: Frequency Converter | S80: FEEDTHROUGH | T80: UYESNOINDICATOR
P81: FUR | Q81: Furance | S81: FILTERTYPE | T81: UFILTERTYPE
P82: FUSE | Q82: Fuse | S82: FLOWRANGEUOM | T82: UFLOWUOM
P83: GASDIST | Q83: Gas Distribution | S83: FLOWUOM | T83: UFLOWUOM
P84: GASMETER | Q84: Gas Meter | S84: FLUIDTYPE | T84: UFLUIDTYPE
P85: GATE | Q85: Gate | S85: FLUIDVOLUMEUOM | T85: UVOLUMEUOM
P86: GEARBOX | Q86: Gear Box | S86: FRAMINGTYPE | T86: UFRAMETYPE
P87: GEN | Q87: Generator | S87: FUELTYPE | T87: UFUELTYPE
P88: GLASS | Q88: Glass | S88: FUNDSOURCE | T88: FUNDSOURCE
P89: GRD | Q89: Grounding | S89: FUNDTYPE | T89: FUNDTYPE
... P184: YARDH | Q184: Yard Hydrant | S184: REGULATIONTYPE | T184: UCNTRLVLVREGTYPE
S185: REHEATER | T185: UYESNOINDICATOR
S186: RELIEFVALVETYPE | T186: URELIEFVLVTYPE
S187: REMOTEREADINDICATOR | T187: UYESNOINDICATOR
S188: RESPPARTY | T188: RESPPARTY
S189: SECONDARYFUELTYPE | T189: UFUELTYPE
S190: SENSORINDICATOR | T190: UYESNOINDICATOR
S191: SERVICEPROT | T191: USERVPROT
S192: SERVICETYPE | T192: USERVICETYPE
S193: SHAFTALIGNMENT | T193: UALIGN
S194: SIZEUOM | T194: ULENGTHUOM
S195: SPCC | T195: SPCC
S196: SPECIALTYDOOR | T196: SPECIALTYDOOR
... S243: XFMRSWITCHTYPE | T243: UXFMRSWITCH

Sheet System
A1: A10-FOUNDATIONS | B1: A20-BASEMENT CONSTRUCTION | C1: B10-SUPERSTRUCTURE | D1: B20-EXTERIOR ENCLOSURE | E1: B30-ROOFING | F1: C10-INTERIOR CONSTRUCTION | G1: C20-STAIRS | H1: C30-INTERIOR FINISHES | I1: D10-CONVEYING | J1: D20-PLUMBING | K1: D30-HVAC | L1: D40-FIRE PROTECTION | M1: D50-ELECTRICAL | N1: E10-EQUIPMENT | O1: E20-FURNISHINGS | P1: F10-SPECIAL CONSTRUCTION | Q1: F20-SELECTIVE BUILDING DEMOLITION | R1: G10-SITE PREPARATIONS | S1: G20-SITE IMPROVEMENTS | T1: G30-SITE CIVIL/MECHANICAL UTILITIES | U1: G40-SITE ELECTRICAL UTILITIES | V1: G90-OTHER SITE CONSTRUCTION | W1: H10-WATERFRONT STRUCTURES | X1: H30-COASTAL PROTECTION | Y1: H40-NAV DREDGING / RECLAMATION | Z1: H50-WATERFRONT UTILITIES | AA1: J10-Electric Utilities | AB1: K10-Potable Water Utilities | AC1: K20-Non-Potable Water Utilities | AD1: K30-Fire Protection Water Utili | AE1: K40-Salt Water Utilities | AF1: L10-Steam Utilities | AG1: L20-High Temp Hot Water Utiliti | AH1: L30-Domestic Hot Water Utilitie | AI1: L40-Chilled Water Utilities | AJ1: M10-Sanitary Sewer Utilities | AK1: M20-Industrial Wastewater Utili | AL1: M30-Oily Wastewater Utilities | AM1: M40-Storm Water Utilities | AN1: N10-Natural Gas Utilities | AO1: N20-Propane Utilities | AP1: P10-Compressed Air Utilities | AQ1: P20-HP Compressed Air Utilities | AR1: P30-Compressed Inert Gas Utilit | AS1: Q10-Multiple Commodity Utilitie
A2: A1010-STANDARD FOUNDATIONS | B2: A2010-BASEMENT EXCAVATION | C2: B1010-FLOOR CONSTRUCTION | D2: B2010-EXTERIOR WALLS | E2: B3010-ROOF COVERINGS | F2: C1010-PARTITIONS | G2: C2010-STAIR CONSTRUCTION | H2: C3010-WALL FINISHES | I2: D1010-ELEVATORS AND LIFTS | J2: D2010-PLUMBING FIXTURES | K2: D3010-ENERGY SUPPLY | L2: D4010-FIRE ALARM AND DETECTION SYSTEMS | M2: D5010-ELECTRICAL SERVICE / DISTRIBUTION | N2: E1010-COMMERCIAL EQUIPMENT | O2: E2010-FIXED FURNISHINGS | P2: F1010-SPECIAL STRUCTURES | Q2: F2010-BUILDING ELEMENTS DEMOLITION | R2: G1010-SITE CLEARING | S2: G2010-ROADWAYS | T2: G3010-WATER SUPPLY | U2: G4010-ELECTRICAL DISTRIBUTION | V2: G9010-SERVICE AND PEDESTRIAN TUNNELS | W2: H1010-SUBSTRUCTURE | X2: H3010-WAVE PROTECTION | Y2: H4020-DREDGING DISPOSAL | Z2: H5010-CIVIL/MECHANICAL UTILITIES | AA2: J1010-Production | AB2: K1010-Production | AC2: K2010-Production | AD2: K3010-Production | AE2: K4010-Production | AF2: L1010-Production | AG2: L2010-Production | AH2: L3010-Production | AI2: L4010-Production | AJ2: M1010-Production | AK2: M2010-Production | AL2: M3010-Production | AM2: M4010-Production | AN2: N1010-Production | AO2: N2010-Production | AP2: P1010-Production | AQ2: P2010-Production | AR2: P3010-Production | AS2: Q1020-Distribution
A3: A1020-SPECIAL FOUNDATIONS | B3: A2020-BASEMENT WALLS | C3: B1020-ROOF CONSTRUCTION | D3: B2020-EXTERIOR WINDOWS | F3: C1020-INTERIOR DOORS | H3: C3020-FLOOR FINISHES | I3: D1020-WEIGHT HANDLING EQUIPMENT | J3: D2020-DOMESTIC WATER DISTRIBUTION | K3: D3020-HEAT GENERATING SYSTEMS | L3: D4020-FIRE SUPP WATER SUPPLY / EQUIP | M3: D5020-LIGHTING / BRANCH WIRING | N3: E1020-INSTITUTIONAL EQUIPMENT | O3: E2020-MOVEABLE FURNISHINGS | P3: F1020-INTEGRATED CONSTRUCTION | Q3: F2020-HAZARDOUS COMPONENTS ABATEMENT | R3: G1020-SITE DEMOLITION / RELOCATIONS | S3: G2020-PARKING LOTS | T3: G3020-SANITARY SEWER | U3: G4020-SITE LIGHTING | V3: G9090-OTHER SITE CONSTRUCTION | W3: H1020-SUPERSTRUCTURE | X3: H3020-SLOPE PROTECTION | Z3: H5020-ELECTRICAL UTILITIES | AA3: J1020-Transmission | AB3: K1020-Distribution | AC3: K2020-Distribution | AD3: K3020-Distribution | AE3: K4020-Distribution | AF3: L1020-Distribution | AG3: L2020-Distribution | AH3: L3020-Distribution | AI3: L4020-Distribution | AJ3: M1020-Distribution | AK3: M2020-Distribution | AL3: M3020-Distribution | AM3: M4020-Distribution | AN3: N1020-Distribution | AO3: N2020-Distribution | AP3: P1020-Distribution | AQ3: P2020-Distribution | AR3: P3020-Distribution
A4: A1030-SLAB ON GRADE | D4: B2030-EXTERIOR DOORS | F4: C1030-SPECIALTIES | H4: C3030-CEILING FINISHES | I4: D1030-ESCALATORS AND MOVING WALKS | J4: D2030-SANITARY WASTE | K4: D3030-COOLING GENERATING SYSTEMS | L4: D4030-STANDPIPE SYSTEMS | M4: D5030-COMMUNICATIONS / SECURITY | N4: E1030-VEHICULAR EQUIPMENT | P4: F1030-SPECIAL CONSTRUCTION SYSTEMS | R4: G1030-SITE EARTHWORK | S4: G2030-PEDESTRIAN PAVING | T4: G3030-STORM SEWER | U4: G4030-SITE COMMUNICATION AND SECURITY | W4: H1030-DECK | Z4: H5030-FIRE PROTECTION AND SUPPRESSION | AA4: J1030-Distribution | AF4: L1030-Return | AG4: L2030-Return | AH4: L3030-Return | AI4: L4030-Return
H5: C3040-INT COATINGS / SPECIAL FINISHES | I5: D1090-OTHER CONVEYING SYSTEMS | J5: D2040-RAIN WATER DRAINAGE | K5: D3040-DISTRIBUTION SYSTEMS | L5: D4040-SPRINKLERS | M5: D5090-OTHER ELECTRICAL SERVICES | N5: E1090-OTHER EQUIPMENT | P5: F1040-SPECIAL FACILITIES | R5: G1040-HAZARDOUS WASTE REMEDIATION | S5: G2040-SITE DEVELOPMENT | T5: G3040-HEATING DISTRIBUTION | U5: G4090-OTHER SITE ELECTRICAL UTILITIES | W5: H1040-MOORING AND BERTHING SYSTEM
J6: D2090-OTHER PLUMBING SYSTEMS | K6: D3050-TERMINAL / PACKAGE UNITS | L6: D4050-FIRE PROTECTION SPECIALTIES | P6: F1050-SPECIAL CTRLS / INSTRUMENTATION | S6: G2050-LANDSCAPING | T6: G3050-COOLING DISTRIBUTION
K7: D3060-CONTROLS / INSTRUMENTATION | L7: D4090-OTHER FIRE PROTECTION SYSTEMS | S7: G2060-AIRFIELD PAVING | T7: G3060-FUEL DISTRIBUTION
K8: D3070-SYSTEMS TESTING / BALANCING | T8: G3090-OTHER SITE MECHANICAL UTILITIES
K9: D3090-OTHER HVAC SYSTEMS AND EQUIPMENT

Sheet Subsystem
A1: A1010-STANDARD FOUNDATIONS | B1: A1020-SPECIAL FOUNDATIONS | C1: A1030-SLAB ON GRADE | D1: A2010-BASEMENT EXCAVATION | E1: A2020-BASEMENT WALLS | F1: B1010-FLOOR CONSTRUCTION | G1: B1020-ROOF CONSTRUCTION | H1: B2010-EXTERIOR WALLS | I1: B2020-EXTERIOR WINDOWS | J1: B2030-EXTERIOR DOORS | K1: B3010-ROOF COVERINGS | L1: C1010-PARTITIONS | M1: C1020-INTERIOR DOORS | N1: C1030-SPECIALTIES | O1: C2010-STAIR CONSTRUCTION | P1: C3010-WALL FINISHES | Q1: C3020-FLOOR FINISHES | R1: C3030-CEILING FINISHES | S1: C3040-INT COATINGS / SPECIAL FINISHES | T1: D1010-ELEVATORS AND LIFTS | U1: D1020-WEIGHT HANDLING EQUIPMENT | V1: D1030-ESCALATORS AND MOVING WALKS | W1: D1090-OTHER CONVEYING SYSTEMS | X1: D2010-PLUMBING FIXTURES | Y1: D2020-DOMESTIC WATER DISTRIBUTION | Z1: D2030-SANITARY WASTE | AA1: D2040-RAIN WATER DRAINAGE | AB1: D2090-OTHER PLUMBING SYSTEMS | AC1: D3010-ENERGY SUPPLY | AD1: D3020-HEAT GENERATING SYSTEMS | AE1: D3030-COOLING GENERATING SYSTEMS | AF1: D3040-DISTRIBUTION SYSTEMS | AG1: D3050-TERMINAL / PACKAGE UNITS | AH1: D3060-CONTROLS / INSTRUMENTATION | AI1: D3070-SYSTEMS TESTING / BALANCING | AJ1: D3090-OTHER HVAC SYSTEMS AND EQUIPMENT | AK1: D4010-FIRE ALARM AND DETECTION SYSTEMS | AL1: D4020-FIRE SUPP WATER SUPPLY / EQUIP | AM1: D4030-STANDPIPE SYSTEMS | AN1: D4040-SPRINKLERS | AO1: D4050-FIRE PROTECTION SPECIALTIES | AP1: D4090-OTHER FIRE PROTECTION SYSTEMS | AQ1: D5010-ELECTRICAL SERVICE / DISTRIBUTION | AR1: D5020-LIGHTING / BRANCH WIRING | AS1: D5030-COMMUNICATIONS / SECURITY | AT1: D5090-OTHER ELECTRICAL SERVICES | AU1: E1010-COMMERCIAL EQUIPMENT | AV1: E1020-INSTITUTIONAL EQUIPMENT | AW1: E1030-VEHICULAR EQUIPMENT | AX1: E1090-OTHER EQUIPMENT | AY1: E2010-FIXED FURNISHINGS | AZ1: E2020-MOVEABLE FURNISHINGS | BA1: F1010-SPECIAL STRUCTURES | BB1: F1020-INTEGRATED CONSTRUCTION | BC1: F1030-SPECIAL CONSTRUCTION SYSTEMS | BD1: F1040-SPECIAL FACILITIES | BE1: F1050-SPECIAL CTRLS / INSTRUMENTATION | BF1: F2010-BUILDING ELEMENTS DEMOLITION | BG1: F2020-HAZARDOUS COMPONENTS ABATEMENT | BH1: G1010-SITE CLEARING | BI1: G1020-SITE DEMOLITION / RELOCATIONS | BJ1: G1030-SITE EARTHWORK | BK1: G1040-HAZARDOUS WASTE REMEDIATION | BL1: G2010-ROADWAYS | BM1: G2020-PARKING LOTS | BN1: G2030-PEDESTRIAN PAVING | BO1: G2040-SITE DEVELOPMENT | BP1: G2050-LANDSCAPING | BQ1: G2060-AIRFIELD PAVING | BR1: G3010-WATER SUPPLY | BS1: G3020-SANITARY SEWER | BT1: G3030-STORM SEWER | BU1: G3040-HEATING DISTRIBUTION | BV1: G3050-COOLING DISTRIBUTION | BW1: G3060-FUEL DISTRIBUTION | BX1: G3090-OTHER SITE MECHANICAL UTILITIES | BY1: G4010-ELECTRICAL DISTRIBUTION | BZ1: G4020-SITE LIGHTING | CA1: G4030-SITE COMMUNICATION AND SECURITY | CB1: G4090-OTHER SITE ELECTRICAL UTILITIES | CC1: G9010-SERVICE AND PEDESTRIAN TUNNELS | CD1: G9090-OTHER SITE CONSTRUCTION | CE1: H1010-SUBSTRUCTURE | CF1: H1020-SUPERSTRUCTURE | CG1: H1030-DECK | CH1: H1040-MOORING AND BERTHING SYSTEM | CI1: H3010-WAVE PROTECTION | CJ1: H3020-SLOPE PROTECTION | CK1: H4020-DREDGING DISPOSAL | CL1: H5010-CIVIL/MECHANICAL UTILITIES | CM1: H5020-ELECTRICAL UTILITIES | CN1: H5030-FIRE PROTECTION AND SUPPRESSION | CO1: J1010-Production | CP1: J1020-Transmission | CQ1: J1030-Distribution | CR1: K1010-Production | CS1: K1020-Distribution | CT1: K2010-Production | CU1: K2020-Distribution | CV1: K3010-Production | CW1: K3020-Distribution | CX1: K4010-Production | CY1: K4020-Distribution | CZ1: L1010-Production | DA1: L1020-Distribution | DB1: L1030-Return | DC1: L2010-Production | DD1: L2020-Distribution | DE1: L2030-Return | DF1: L3010-Production | DG1: L3020-Distribution | DH1: L3030-Return | DI1: L4010-Production | DJ1: L4020-Distribution | DK1: L4030-Return | DL1: M1010-Production | DM1: M1020-Distribution | DN1: M2010-Production | DO1: M2020-Distribution | DP1: M3010-Production | DQ1: M3020-Distribution | DR1: M4010-Production | DS1: M4020-Distribution | DT1: N1010-Production | DU1: N1020-Distribution | DV1: N2010-Production | DW1: N2020-Distribution | DX1: P1010-Production | DY1: P1020-Distribution | DZ1: P2010-Production | EA1: P2020-Distribution | EB1: P3010-Production | EC1: P3020-Distribution | ED1: Q1020-Distribution
A2: A101001-WALL FOUNDATIONS | B2: A102001-PILE FOUNDATIONS | C2: A103001-STANDARD SLAB ON GRADE | D2: A201001-EXCAVATION FOR BASEMENTS | E2: A202001-BASEMENT WALL CONSTRUCTION | F2: B101001-STRUCTURAL FRAME | G2: B102001-STRUCTURAL FRAME | H2: B201001-EXTERIOR CLOSURE | I2: B202001-WINDOWS | J2: B203001-SOLID DOORS | K2: B301001-STEEP SLOPE ROOF SYSTEMS | L2: C101001-FIXED PARTITIONS | M2: C102001-STANDARD INTERIOR DOORS | N2: C103001-COMPARTMENTS, CUBICLES / TOILET PARTITIONS | O2: C201001-INTERIOR AND EXTERIOR STAIRS | P2: C301001-CONCRETE WALL FINISHES | Q2: C302001-TILE FLOOR FINISHES | R2: C303001-ACOUSTICAL CEILING TILES / PANELS | S2: C304001-GENERAL REQUIREMENTS | T2: D101001-GENERAL CONSTRUCTION ITEMS | U2: D102001-BASIC REQUIREMENTS OF CRANES AND MONORAILS | V2: D103001-ESCALATORS | X2: D201001-WATERCLOSETS | Y2: D202001-PIPES / FITTINGS | Z2: D203001-WASTE PIPE / FITTINGS | AA2: D204001-PIPE / FITTINGS | AB2: D209001-SPECIAL PIPING SYSTEMS | AC2: D301001-OIL SUPPLY SYSTEM | AD2: D302001-BOILERS | AE2: D303001-CHILLED WATER SYSTEMS | AF2: D304001-AIR DISTRIBUTION, HEATING / COOLING | AG2: D305001-UNIT VENTILATORS | AH2: D306001-HVAC CONTROLS | AI2: D307001-WATER SIDE TESTING / BALANCING - HEATING / COOLING | AJ2: D309001-GENERAL CONSTRUCTION ITEMS | AK2: D401001-FIRE ALARM DISTRIBUTION | AL2: D402001-FIRE PROTECTION WATER PIPING AND EQUIPMENT | AM2: D403001-STANDPIPE EQUIPMENT / PIPING | AN2: D404001-SPRINKLERS AND RELEASING DEVICES | AO2: D405001-PORTABLE EXTINGUISHERS | AP2: D409001-CARBON DIOXIDE SYSTEMS | AQ2: D501001-MAIN TRANSFORMERS | AR2: D502001-BRANCH WIRING | AS2: D503001-TELECOMMUNICATIONS SYSTEMS | AT2: D509001-GENERAL CONSTRUCTION ITEMS (ELECTRICAL) | AU2: E101001-CHECKROOM EQUIPMENT | AV2: E102001-MISCELLANEOUS COMMON FIXED / MOVEABLE EQUIPMENT | AW2: E103001-PARKING CONTROL EQUIPMENT | AX2: E109001-BUILT-IN MAINTENANCE EQUIPMENT | AY2: E201001-FIXED ARTWORK | AZ2: E202001-MOVEABLE ART WORK | BA2: F101001-METAL BUILDING SYSTEMS | BB2: F102001-SPECIAL PURPOSE ROOMS | BC2: F103001-VAULTS | BD2: F104001-INTERIOR SWIMMING POOLS | BE2: F105001-RECORDING INSTRUMENTATION | BF2: F201001-SUBSTRUCTURE / SUPERSTRUCTURE | BG2: F202001-SUBSTRUCTURE / SUPERSTRUCTURE | BH2: G101001-CLEARING | BI2: G102001-BUILDING MASS DEMOLITION | BJ2: G103001-GRADING | BK2: G104001-REMOVAL OF CONTAMINATED SOIL | BL2: G201001-BASES / SUBBASES | BM2: G202001-BASES / SUBBASES | BN2: G203001-BASES / SUBBASES | BO2: G204001-FENCING / GATES | BP2: G205001-FINE GRADING / SOIL PREPARATION | BQ2: G206001-AIRFIELD PAVING CONSTRUCTION | BR2: G301001-WELL SYSTEMS | BS2: G302001-SANITARY SEWER PIPING | BT2: G303001-STORM SEWER PIPING | BU2: G304001-OVERHEAD HOT WATER SYSTEMS | BV2: G305001-OVERHEAD COOLING SYSTEMS | BW2: G306001-LIQUID FUEL DISTRIBUTION PIPING SYSTEM | BX2: G309001-INDUSTRIAL WASTE PIPE | BY2: G401001-SUBSTATIONS | BZ2: G402001-EXTERIOR LIGHTING FIXTURES / CONTROLS | CA2: G403001-TELECOMMUNICATIONS SYSTEMS | CB2: G409001-SACRIFICIAL ANODE CATHODIC PROTECTION SYSTEM | CC2: G901001-SERVICE AND PEDESTRIAN TUNNELS | CD2: G909001-BRIDGES | CE2: H101001-PILE FOUNDATIONS | CF2: H102001-BEAMS AND GIRDERS | CG2: H103001-DECK | CH2: H104001-PRIMARY FENDER SYSTEM | CI2: H301001-WAVE PROTECTION ARMORS | CJ2: H302001-ROCK REVETMENTS | CK2: H402001-OCEAN DISPOSAL | CL2: H501001-POTABLE WATER | CM2: H502001-POWER DISTRIBUTION SYSTEM | CN2: H503001-FIRE PROTECTION WATER DISTRIBUTION SYSTEM | CO2: J1010110-UG Structures | CP2: J1020110-UG Structures | CQ2: J1030110-UG Structures | CR2: K1010110-Wells | CS2: K1020100-Service Areas | CT2: K2010110-Wells | CU2: K2020100-Service Areas | CV2: K3010110-Wells | CW2: K3020100-Service Areas | CX2: K4010110-Wells | CY2: K4020100-Service Areas | CZ2: L1010100-Plant Electrical | DA2: L1020100-Service Area | DB2: L1030100-Service Area | DC2: L2010100-Plant Electrical | DD2: L2020100-Service Area | DE2: L2030100-Service Area | DF2: L3010100-Plant Electrical | DG2: L3020100-Service Area | DH2: L3030100-Service Area | DI2: L4010100-Plant Electrical | DJ2: L4020100-Service Area | DK2: L4030100-Service Area | DL2: M1010100-Pump Stations | DM2: M1020100-Service Area | DN2: M2010100-Pump Stations | DO2: M2020100-Service Area | DP2: M3010100-Pump Stations | DQ2: M3020100-Service Area | DR2: M4010100-Pump Stations | DS2: M4020100-Service Area | DT2: N1010100-Plant Electric | DU2: N1020100-Service Area | DV2: N2010100-Plant Electric | DW2: N2020100-Service Area | DX2: P1010100-Plant Electric | DY2: P1020100-Service Area | DZ2: P2010100-Plant Electric | EA2: P2020100-Service Area | EB2: P3010100-Plant Electric | EC2: P3020100-Service Area | ED2: Q1020100-Surface Structures
A3: A101002-COLUMN FOUNDATIONS / PILE CAPS | B3: A102002-CAISSONS | C3: A103002-STRUCTURAL SLAB ON GRADE | D3: A201002-STRUCTURE BACKFILL / COMPACTION | E3: A202002-MOISTURE PROTECTION | F3: B101002-STRUCTURAL INTERIOR WALLS | G3: B102002-STRUCTURAL INTERIOR WALLS | H3: B201002-EXTERIOR WALL BACKUP CONSTRUCTION | I3: B202002-STOREFRONTS | J3: B203002-GLAZED DOORS | K3: B301002-LOW SLOPE ROOF SYSTEMS | L3: C101002-DEMOUNTABLE PARTITIONS | M3: C102002-GLAZED INTERIOR DOORS | N3: C103002-TOILET / BATH ACCESSORIES | O3: C201002-FIRE ESCAPE STAIRS | P3: C301002-PLASTER WALL FINISHES | Q3: C302002-TERRAZZO FLOOR FINISHES | R3: C303002-GYPSUM WALLBOARD CEILING FINISHES | S3: C304002-CONCRETE FINISHES | T3: D101002-PASSENGER ELEVATORS | U3: D102002-OVERHEAD CRANES | V3: D103002-MOVING WALKS | X3: D201002-URINALS | Y3: D202002-VALVES / HYDRANTS | Z3: D203002-VENT PIPE / FITTINGS | AA3: D204002-ROOF DRAINS | AB3: D209002-ACID WASTE SYSTEMS | AC3: D301002-GAS SUPPLY SYSTEM | AD3: D302002-FURNACES | AE3: D303002-DIRECT EXPANSION SYSTEMS | AF3: D304002-STEAM DISTRIBUTION SYSTEMS | AG3: D305002-UNIT HEATERS | AH3: D306002-ELECTRONIC CONTROLS | AI3: D307002-AIR SIDE TESTING / BALANCING - HEATING, COOLING / | AJ3: D309002-REFRIGERATION SYSTEMS | AK3: D401002-FIRE ALARM DEVICES | AL3: D402002-FIRE PUMP | AN3: D404002-SPRINKLER WATER SUPPLY EQUIPMENT AND PIPING | AP3: D409002-FOAM GENERATING EQUIPMENT | AQ3: D501002-SERVICE ENTRANCE EQUIPMENT | AR3: D502002-LIGHTING EQUIPMENT | AS3: D503002-PUBLIC ADDRESS SYSTEMS | AT3: D509002-EMERGENCY LIGHTING / POWER | AU3: E101002-REGISTRATION EQUIPMENT | AV3: E102002-MEDICAL EQUIPMENT | AW3: E103002-LOADING DOCK EQUIPMENT | AX3: E109002-FOOD SERVICE EQUIPMENT | AY3: E201002-WINDOW TREATMENTS | AZ3: E202002-MODULAR PREFABRICATED FURNITURE | BA3: F101002-EXTERIOR UTILITY BUILDINGS | BB3: F102002-INTEGRATED ASSEMBLIES | BC3: F103002-SOUND, VIBRATION, AND SEISMIC CONSTRUCTION | BD3: F104002-LIQUID AND GAS STORAGE TANKS | BE3: F105002-BUILDING AUTOMATION SYSTEMS | BF3: F201002-EXTERIOR CLOSURE | BG3: F202002-EXTERIOR CLOSURE | BH3: G101002-TREE REMOVAL | BI3: G102002-ABOVE GROUND SITE DEMOLITION | BJ3: G103002-COMMON EXCAVATION | BK3: G104002-SOIL RESTORATION AND TREATMENT | BL3: G201002-CURBS / GUTTERS | BM3: G202002-CURBS / GUTTERS | BN3: G203002-CURBS / GUTTERS | BO3: G204002-RETAINING WALLS AND FREESTANDING WALLS | BP3: G205002-EROSION CONTROL MEASURES | BQ3: G206002-OTHER PAVING | BR3: G301002-POTABLE WATER DISTRIBUTION | BS3: G302002-SANITARY SEWER MANHOLES / CLEANOUTS | BT3: G303002-STORM SEWER STRUCTURES | BU3: G304002-OVERHEAD STEAM SYSTEMS | BV3: G305002-UNDERGROUND COOLING SYSTEMS | BW3: G306002-AVIATION FUEL DISTRIBUTION PIPING SYSTEM | BX3: G309002-INDUSTRIAL WASTE MANHOLES / CLEANOUTS | BY3: G401002-TRANSFORMERS | BZ3: G402002-SPECIAL SECURITY LIGHTING SYSTEMS | CA3: G403002-CABLE TV SYSTEMS (CATV) | CB3: G409002-INDUCED CURRENT CATHODIC PROTECTION SYSTEM | CC3: G901002-PREFABRICATED SERVICE AND PEDESTRIAN TUNNELS | CD3: G909002-RAILROAD SPURS | CE3: H101002-PILE CAPS | CF3: H102002-COLUMNS | CG3: H103002-ON-GRADE SLAB | CH3: H104002-SECONDARY FENDER SYSTEM | CI3: H301002-BREAKWATERS | CJ3: H302002-GRANULAR FILL REVETMENTS | CK3: H402002-NEW CONFINED DISPOSAL FACILITIES | CL3: H501002-SALTWATER | CM3: H502002-TELECOMMUNICATION SYSTEM | CN3: H503002-FIRE ALARM | CO3: J1010120-Support Structures | CP3: J1020120-Support Structures | CQ3: J1030120-Support Structures | CR3: K1010120-Raw Water Service Area | CS3: K1020110-Pump Stations | CT3: K2010120-Water Supply Service Area | CU3: K2020110-Pump Stations | CV3: K3010120-Water Supply Service Area | CW3: K3020110-Pump Stations | CX3: K4010120-Water Supply Service Area | CY3: K4020110-Pump Stations | CZ3: L1010110-Plant Water | DA3: L1020140-UG Structures | DB3: L1030110-Pump Station | DC3: L2010110-Plant Water | DD3: L2020110-Pump Station | DE3: L2030110-Pump Station | DF3: L3010110-Plant Water | DG3: L3020110-Pump Station | DH3: L3030110-Pump Station | DI3: L4010110-Plant Water | DJ3: L4020110-Pump Station | DK3: L4030110-Pump Station | DL3: M1010110-Equalization | DM3: M1020110-Storage | DN3: M2010110-Equalization | DO3: M2020120-Pump Stations | DP3: M3010110-Equalization | DQ3: M3020110-Storage | DR3: M4010110-Storage | DS3: M4020110-Storage | DT3: N1010110-Plant Water | DU3: N1020110-Storage | DV3: N2010110-Plant Water | DW3: N2020110-Storage | DX3: P1010110-Plant Water | DY3: P1020110-Storage | DZ3: P2010110-Plant Water | EA3: P2020110-Storage | EB3: P3010110-Plant Water | EC3: P3020110-Storage | ED3: Q1020110-UG Structures
A4: A101003-DEWATERING | B4: A102003-UNDERPINNING | C4: A103003-TRENCHES | D4: A201003-SHORING | E4: A202003-BASEMENT WALL INSULATION | F4: B101003-FLOOR DECKS AND SLABS | G4: B102003-ROOF DECKS AND SLABS | H4: B201003-INSULATION / VAPOR RETARDER | I4: B202003-CURTAIN WALLS | J4: B203003-REVOLVING DOORS | K4: B301003-ROOF INSULATION / FILL | L4: C101003-RETRACTABLE PARTITIONS | M4: C102003-FIRE DOORS | N4: C103003-MARKER BOARDS / TACK BOARDS | O4: C201090-STAIR HANDRAILS, GUARDRAILS AND ACCESSORIES | P4: C301003-GYPSUM WALLBOARD FINISHES | Q4: C302003-WOOD FLOORING | R4: C303003-PLASTER CEILING FINISHES | S4: C304003-CONCRETE MASONRY FINISHES | T4: D101003-FREIGHT ELEVATORS | U4: D102003-MONORAILS | V4: D103090-OTHER MOVING STAIRS / WALKS | X4: D201003-LAVATORIES | Y4: D202003-DOMESTIC WATER EQUIPMENT | Z4: D203003-FLOOR DRAINS | AA4: D204003-RAINWATER DRAINAGE EQUIPMENT | AB4: D209003-INTERCEPTORS | AC4: D301003-STEAM SUPPLY SYSTEM (FROM CENTRAL PLANT) | AD4: D302003-FUEL-FIRED UNIT HEATERS | AE4: D303090-OTHER COOLING GENERATING SYSTEMS | AF4: D304003-HOT WATER DISTRIBUTION SYSTEMS | AG4: D305003-FAN COIL UNITS | AH4: D306003-PNEUMATIC CONTROLS | AI4: D307003-HVAC COMMISSIONING | AJ4: D309090-OTHER SPECIAL MECHANICAL SYSTEMS | AP4: D409003-CLEAN AGENT SYSTEMS | AQ4: D501003-INTERIOR DISTRIBUTION TRANSFORMERS | AR4: D502090-OTHER LIGHTING AND BRANCH WIRING | AS4: D503003-INTERCOMMUNICATIONS SYSTEMS | AT4: D509003-GROUNDING SYSTEMS | AU4: E101003-VENDING EQUIPMENT | AV4: E102003-LABORATORY EQUIPMENT | AW4: E103003-WAREHOUSE EQUIPMENT | AX4: E109003-WASTE HANDLING EQUIPMENT | AY4: E201003-SEATING (FIXED) | AZ4: E202003-FREESTANDING FURNITURE | BA4: F101003-AIR-SUPPORTED STRUCTURES | BB4: F102090-OTHER INTEGRATED CONSTRUCTION | BC4: F103003-RADIATION PROTECTION | BD4: F104003-KENNELS AND ANIMAL SHELTERS | BE4: F105090-OTHER SPECIAL CONTROLS AND INSTRUMENTATION | BF4: F201003-ROOFING | BG4: F202003-ROOFING | BH4: G101003-STUMP REMOVAL | BI4: G102003-UNDERGROUND SITE DEMOLITION | BJ4: G103003-ROCK EXCAVATION | BK4: G104090-OTHER HAZARDOUS WASTE REMEDIATION | BL4: G201003-PAVED SURFACES | BM4: G202003-PAVED SURFACES | BN4: G203003-PAVED SURFACES | BO4: G204003-EXTERIOR FURNISHINGS | BP4: G205003-TOPSOIL / PLANTING BEDS | BQ4: G206003-JOINTS AND ANCHORAGE | BR4: G301003-POTABLE WATER STORAGE | BS4: G302003-LIFT STATIONS AND PUMPING STATIONS | BT4: G303003-LIFT STATIONS | BU4: G304003-UNDERGROUND HOT WATER SYSTEMS | BV4: G305003-TRENCHBOXES | BW4: G306003-LIQUID FUEL STORAGE TANKS | BX4: G309003-INDUSTRIAL WASTE LIFT STATIONS | BY4: G401003-SWITCHES, CONTROLS / DEVICES | BZ4: G402003-OTHER AREA LIGHTING | CA4: G403003-CABLES / WIRING | CB4: G409003-EMERGENCY POWER GENERATION | CD4: G909003-SNOW MELTING SYSTEMS | CE4: H101003-QUAYS | CF4: H102003-UTILITY ENCLOSURES | CG4: H103003-DECK OVERLAY | CH4: H104003-CORNER FENDER SYSTEM | CJ4: H302003-COMBINED ROCK AND GRANULAR FILL REVETMENTS | CK4: H402003-EXISTING CONFINED DISPOSAL FACILITIES | CL4: H501003-SANITARY SEWER | CM4: H502003-LIGHTING SYSTEMS | CO4: J1010130-Switch Stations | CP4: J1020130-Switch Stations | CQ4: J1030130-Switch Stations | CR4: K1010130-Raw Water Pumping | CS4: K1020120-Storage | CT4: K2010130-Pump Stations | CU4: K2020120-Storage | CV4: K3010130-Pump Stations | CW4: K3020120-Storage | CX4: K4010130-Pump Stations | CY4: K4020120-Storage | CZ4: L1010120-Plant Steam | DA4: L1020150-Support Structures | DB4: L1030120-UG Structures | DC4: L2010120-Plant High Temp Hot Water | DD4: L2020140-UG Structures | DE4: L2030120-UG Structures | DF4: L3010120-Plant Domestic Hot Water | DG4: L3020140-UG Structures | DH4: L3030120-UG Structures | DI4: L4010120-Plant Chilled Water | DJ4: L4020140-UG Structures | DK4: L4030120-UG Structures | DL4: M1010120-Preliminary Treatment | DM4: M1020120-Pump Stations | DN4: M2010120-Preliminary Treatment | DP4: M3010120-Preliminary Treatment | DQ4: M3020120-Pump Stations | DR4: M4010120-Plant Controls | DS4: M4020120-Pump Stations | DT4: N1010130-Compressed Air | DU4: N1020120-Pump Stations | DV4: N2010130-Compressed Air | DW4: N2020120-Pump Stations | DX4: P1010130-Compressed Air | DY4: P1020120-Pump Stations | DZ4: P2010130-Compressed Air | EA4: P2020120-Pump Stations | EB4: P3010130-Compressed Air | EC4: P3020120-Pump Stations | ED4: Q1020120-Support Structures
A5: A101090-OTHER STANDARD FOUNDATIONS | B5: A102004-DEWATERING | C5: A103004-PITS AND BASES | D5: A201090-OTHER BASEMENT EXCAVATION | E5: A202090-OTHER BASEMENT WALLS | F5: B101004-INCLINED AND STEPPED FLOORS | G5: B102004-CANOPIES | H5: B201004-PARAPETS | I5: B202090-OTHER EXTERIOR WINDOWS | J5: B203004-OVERHEAD AND ROLL-UP DOORS | K5: B301004-FLASHINGS / TRIM | L5: C101004-INTERIOR GUARDRAILS / SCREENS | M5: C102004-SLIDING / FOLDING DOORS | N5: C103004-IDENTIFYING DEVICES | P5: C301004-TILE / TERRAZZO WALL FINISHES | Q5: C302004-RESILIENT FLOOR FINISHES | R5: C303004-WOOD CEILINGS | S5: C304004-METAL FINISHES | T5: D101004-WHEELCHAIR LIFT | W5: D109001-PNEUMATIC TUBE SYSTEMS | X5: D201004-SINKS | Y5: D202004-INSULATION / IDENTIFICATION | Z5: D203004-SANITARY AND VENT EQUIPMENT | AA5: D204004-INSULATION / IDENTIFICATION | AB5: D209004-POOL PIPING AND EQUIPMENT | AC5: D301004-HOT WATER SUPPLY SYSTEM (FROM CENTRAL PLANT) | AD5: D302004-AUXILIARY EQUIPMENT | AF5: D304004-CHANGE OVER DISTRIBUTION SYSTEMS | AG5: D305004-FIN TUBE RADIATION | AH5: D306004-INSTRUMENT AIR COMPRESSORS | AI5: D307090-OTHER SYSTEMS TESTING / BALANCING | AP5: D409004-HOOD / DUCT FIRE PROTECTION | AQ5: D501004-PANELBOARDS | AS5: D503004-TELEVISION SYSTEMS | AT5: D509004-LIGHTNING PROTECTION | AU5: E101004-LAUNDRY EQUIPMENT | AV5: E102004-MORTUARY EQUIPMENT | AW5: E103004-AUTOMOTIVE SHOP EQUIPMENT | AX5: E109004-RESIDENTIAL EQUIPMENT | AY5: E201004-FIXED INTERIOR LANDSCAPING | AZ5: E202004-RUGS / ACCESSORIES | BA5: F101090-OTHER SPECIAL CONSTRUCTION | BC5: F103090-OTHER SPECIAL CONSTRUCTION SYSTEMS | BD5: F104004-SITE CONSTRUCTED INCINERATORS | BF5: F201004-INTERIOR CONSTRUCTION / FINISHES | BG5: F202004-INTERIOR CONSTRUCTION / FINISHES | BH5: G101004-GRUBBING | BI5: G102004-BUILDING RELOCATION | BJ5: G103004-FILL / BORROW | BL5: G201004-MARKING / SIGNAGE | BM5: G202004-MARKING / SIGNAGE | BN5: G203004-GUARDRAILS / BARRIERS | BO5: G204004-SECURITY STRUCTURES | BP5: G205004-SEEDING, SPRIGGING AND SODDING | BQ5: G206004-NAVIGATION AIDS | BR5: G301004-FIRE PROTECTION WATER DISTRIBUTION | BS5: G302004-PACKAGED SANITARY SEWER TREATMENT PLANTS | BT5: G303004-CULVERTS | BU5: G304004-UNDERGROUND STEAM DISTRIBUTION SYSTEMS | BV5: G305004-WELLS FOR COOLING | BW5: G306004-LIQUID FUEL DISPENSING EQUIPMENT | BX5: G309004-INDUSTRIAL WASTE HOLDING TANKS / SEPARATORS | BY5: G401004-OVERHEAD ELECTRIC CONDUCTORS | BZ5: G402004-LIGHTING POLES | CA5: G403004-DUCTBANKS, MANHOLES / HANDHOLES | CB5: G409090-OTHER CATHODIC PROTECTION | CD5: G909090-OTHER SPECIAL CONSTRUCTION | CE5: H101004-RELIEVING PLATFORMS | CF5: H102004-OTHER SUPERSTRUCTURE ELEMENTS | CG5: H103004-CURBS AND BULLRAILS | CH5: H104004-DOLPHINS | CL5: H501004-BILGE AND OILY WASTE | CM5: H502004-LIGHTNING PROTECTION SYSTEM | CO5: J1010140-Sub Stations | CP5: J1020140-Sub Stations | CQ5: J1030140-Sub Stations | CR5: K1010140-Finished Water Storage | CT5: K2010140-Storage | CV5: K3010140-Storage | CX5: K4010140-Storage | CZ5: L1010135-Plant Controls | DB5: L1030130-Support Structures | DC5: L2010135-Plant Controls | DD5: L2020150-Support Structures | DE5: L2030130-Support Structures | DF5: L3010135-Plant Controls | DG5: L3020150-Support Structures | DH5: L3030130-Support Structures | DI5: L4010135-Plant Controls | DJ5: L4020150-Support Structures | DK5: L4030130-Support Structures | DL5: M1010130-Primary Clarification | DN5: M2010130-Primary Clarification | DP5: M3010130-Primary Clarification | DT5: N1010140-Compressed Gas | DV5: N2010140-Compressed Gas | DX5: P1010140-Compressed Gas | DZ5: P2010140-Compressed Gas | EB5: P3010140-Compressed Gas
B6: A102005-RAFT FOUNDATIONS | C6: A103005-FOUNDATION DRAINAGE | F6: B101005-BALCONY CONSTRUCTION | G6: B102090-OTHER ROOF CONSTRUCTION | H6: B201005-EXTERIOR LOUVERS / SCREENS | J6: B203005-HANGAR DOORS | K6: B301005-GUTTERS / DOWNSPOUTS | L6: C101005-INTERIOR WINDOWS | M6: C102005-INTERIOR OVERHEAD DOORS | N6: C103005-LOCKERS | P6: C301005-WALL COVERINGS | Q6: C302005-CARPETING | R6: C303005-SUSPENSION SYSTEMS | S6: C304005-INTERIOR WOOD FINISHES | T6: D101005-DUMBWAITERS | W6: D109002-CONVEYORS | X6: D201005-SHOWERS/TUBS | Y6: D202005-SPECIALTIES | Z6: D203005-INSULATION / IDENTIFICATION | AA6: D204090-OTHER RAIN WATER DRAINAGE SYSTEM | AB6: D209005-COMPRESSED AIR SYSTEM (NON-BREATHING) | AC6: D301005-SOLAR ENERGY SYSTEMS | AD6: D302005-EQUIPMENT THERMAL INSULATION | AF6: D304005-GLYCOL DISTRIBUTION SYSTEMS | AG6: D305005-ELECTRIC HEATING | AH6: D306005-GAS PURGING SYSTEMS | AP6: D409090-OTHER SPECIAL FIRE PROTECTION SYSTEMS | AQ6: D501005-ENCLOSED CIRCUIT BREAKERS | AS6: D503005-SECURITY SYSTEMS | AT6: D509005-ELECTRIC HEATING | AU6: E101005-SECURITY / VAULT EQUIPMENT | AV6: E102005-AUDITORIUM / STAGE EQUIPMENT | AX6: E109005-UNIT KITCHENS | AY6: E201090-OTHER FIXED INTERIOR FURNISHINGS | AZ6: E202005-MOVEABLE MULTIPLE SEATING | BD6: F104005-ICE RINKS | BF6: F201005-CONVEYING SYSTEMS | BG6: F202005-CONVEYING SYSTEMS | BH6: G101005-SELECTIVE THINNING | BI6: G102005-UTILITY RELOCATION | BJ6: G103005-COMPACTION | BL6: G201005-GUARDRAILS / BARRIERS | BM6: G202005-GUARDRAILS / BARRIERS | BN6: G203005-RESURFACING | BO6: G204005-SIGNAGE | BP6: G205005-PLANTINGS | BQ6: G206005-AIRFIELD MARKINGS | BR6: G301005-FIRE PROTECTION WATER STORAGE | BS6: G302005-SEPTIC TANKS | BT6: G303005-HEADWALLS | BU6: G304005-REINFORCED CONCRETE MANHOLES / VALVE BOXES | BV6: G305005-PUMPING STATIONS | BW6: G306005-LIQUID FUEL SYSTEM TRENCHBOXES | BX6: G309005-INDUSTRIAL WASTE TRENCHBOXES | BY6: G401005-TOWERS, POLES, CROSSARMS / INSULATORS | BZ6: G402005-UNDERGROUND ELECTRIC CONDUCTORS | CA6: G403005-TOWERS, POLES / STANDS | CE6: H101005-REVETMENTS | CG6: H103005-MOORING FOUNDATIONS | CH6: H104005-MOORING HARDWARE | CL6: H501005-COMPRESSED AIR | CM6: H502005-POWER BOOMS | CO6: J1010150-Circuits | CP6: J1020150-Circuits | CQ6: J1030150-Circuits | CR6: K1010150-Preliminary Treatment | CT6: K2010150-Plant Compressed Air | CV6: K3010150-Plant Compressed Air | CX6: K4010150-Plant Compressed Air | CZ6: L1010140-Make-up Water | DC6: L2010140-Make-up Water | DF6: L3010140-Make-up Water | DI6: L4010140-Make-up Water | DL6: M1010140-Holding Tanks | DN6: M2010140-Holding Tanks | DP6: M3010140-Holding Tanks | DT6: N1010150-Plant Controls | DV6: N2010150-Plant Controls | DX6: P1010150-Plant Controls | DZ6: P2010150-Plant Controls | EB6: P3010150-Plant Controls
B7: A102006-PRESSURE INJECTED GROUTING | C7: A103090-OTHER SLAB ON GRADE | F7: B101006-RAMPS | H7: B201006-BALCONY WALLS / HANDRAILS | J7: B203006-BLAST RESISTANT DOORS | K7: B301006-ROOF OPENINGS AND SUPPORTS | L7: C101006-GLAZED PARTITIONS / STOREFRONTS | M7: C102006-INTERIOR GATES | N7: C103006-SHELVING | P7: C301006-ACOUSTICAL PANELS ADHERED TO WALLS | Q7: C302006-MASONRY / STONE FLOORING | R7: C303006-METAL STRIP CEILINGS | S7: C304006-GYPSUM WALLBOARD FINISHES | T7: D101090-OTHER VERTICAL TRANSPORTATION EQUIPMENT | W7: D109003-LINEN, TRASH, AND MAIL CHUTES | X7: D201006-DRINKING FOUNTAINS AND COOLERS | Y7: D202090-OTHER DOMESTIC WATER SUPPLY | Z7: D203090-OTHER SANITARY WASTE | AB7: D209090-OTHER SPECIAL PLUMBING SYSTEMS | AC7: D301006-WIND ENERGY SUPPLY SYSTEM | AD7: D302090-OTHER HEAT GENERATING SYSTEMS | AF7: D304006-CHILLED WATER DISTRIBUTION SYSTEMS | AG7: D305006-PACKAGE UNITS | AH7: D306090-OTHER CONTROLS INSTRUMENTATION | AQ7: D501006-MOTOR CONTROL CENTERS | AS7: D503006-NURSE CALL SYSTEMS | AT7: D509006-ENERGY MANAGEMENT CONTROL SYSTEM | AU7: E101006-TELLER AND SERVICE EQUIPMENT | AV7: E102006-LIBRARY EQUIPMENT | AX7: E109006-DARKROOM EQUIPMENT | AZ7: E202006-MOVEABLE INTERIOR LANDSCAPING | BD7: F104090-OTHER SPECIAL FACILITIES | BF7: F201006-MECHANICAL SYSTEMS | BG7: F202006-MECHANICAL SYSTEMS | BH7: G101006-DEBRIS DISPOSAL | BI7: G102006-FENCING RELOCATION | BJ7: G103006-SOIL STABILIZATION | BL7: G201006-RESURFACING | BM7: G202006-RESURFACING | BN7: G203090-OTHER WALKS, STEPS / TERRACES | BO7: G204006-FOUNTAINS / POOLS | BP7: G205006-PLANTERS | BR7: G301006-NON-POTABLE WATER DISTRIBUTION | BS7: G302006-DRAIN FIELDS | BT7: G303006-EROSION / SEDIMENT CONTROL MEASURES | BU7: G304006-PUMPING STATIONS | BV7: G305006-ON-SITE COOLING TOWERS | BW7: G306006-GAS DISTRIBUTION PIPING (NATURAL AND PROPANE) | BX7: G309090-OTHER INDUSTRIAL WASTE | BY7: G401006-UNDERGROUND ELECTRIC CONDUCTORS | BZ7: G402006-DUCTBANKS, MANHOLES / HANDHOLES | CA7: G403006-TV CAMERAS / MONITORS | CE7: H101006-SEAWALLS | CG7: H103006-HIGH MAST LIGHTING FOUNDATIONS | CH7: H104006-OTHER MOORING AND BERTHING COMPONENTS | CL7: H501006-STEAM | CM7: H502006-OTHER ELECTRICAL UTILITIES | CO7: J1010155-Plant Electrical | CR7: K1010160-Coagulation Flocculation | CT7: K2010160-Plant Controls | CV7: K3010160-Plant Controls | CX7: K4010160-Plant Controls | CZ7: L1010150-Boiler Feedwater | DC7: L2010150-Boiler Feedwater | DF7: L3010150-Boiler Feedwater | DI7: L4010150-Chiller Feedwater | DL7: M1010150-Biological Treatment | DN7: M2010150-Biological Treatment | DP7: M3010150-Biological Treatment | DX7: P1010160-Cooling System
B8: A102090-OTHER SPECIAL FOUNDATIONS | F8: B101007-FLOOR RACEWAY SYSTEMS | H8: B201007-EXTERIOR SOFFITS | J8: B203007-GATES | K8: B301090-OTHER ROOFING | L8: C101007-INTERIOR GLAZING | M8: C102007-INTERIOR DOOR HARDWARE | N8: C103007-FIRE EXTINGUISHER CABINETS | P8: C301090-OTHER WALL FINISHES | Q8: C302007-WALL BASE FINISHES | R8: C303090-OTHER CEILING / CEILING FINISHES | S8: C304007-SPECIAL COATINGS ON WALLS | W8: D109004-TURNTABLES | X8: D201007-BIDETS | AC8: D301007-COAL SUPPLY SYSTEM | AF8: D304007-EXHAUST SYSTEMS | AG8: D305090-OTHER TERMINAL / PACKAGE UNITS | AQ8: D501090-OTHER SERVICE AND DISTRIBUTION | AS8: D503007-CLOCK / PROGRAM SYSTEMS | AT8: D509090-OTHER SPECIAL SYSTEMS AND DEVICES | AU8: E101007-MERCANTILE EQUIPMENT | AV8: E102007-ECCLESIASTICAL EQUIPMENT | AX8: E109007-ATHLETIC, RECREATIONAL, / THERAPEUTIC EQUIPMENT | AZ8: E202090-OTHER MOVEABLE FURNISHINGS | BF8: F201007-ELECTRICAL SYSTEMS | BG8: F202007-ELECTRICAL SYSTEMS | BH8: G101090-OTHER SITE CLEARING | BI8: G102007-SITE CLEANUP | BJ8: G103007-SLOPE STABILIZATION | BL8: G201090-OTHER ROADWAYS | BM8: G202007-MISCELLANEOUS STRUCTURES AND EQUIPMENT | BO8: G204007-PLAYING FIELDS | BP8: G205007-IRRIGATION SYSTEMS | BR8: G301007-PUMPING STATIONS | BS8: G302090-OTHER SANITARY SEWER | BT8: G303007-STORMWATER MANAGEMENT | BU8: G304090-OTHER HEATING DISTRIBUTION | BV8: G305090-OTHER COOLING DISTRIBUTION | BW8: G306007-GAS STORAGE TANKS | BY8: G401007-DUCTBANKS, MANHOLES, HANDHOLES / RACEWAYS | BZ8: G402007-GROUNDING SYSTEMS | CA8: G403007-ELECTRONIC SECURITY SYSTEMS (ESS) | CE8: H101007-BOAT RAMPS | CG8: H103007-UTILITY MOUNDS | CL8: H501007-OTHER CIVIL/MECHANICAL UTILITIES | CO8: J1010160-Power Generation | CR8: K1010170-Sedimentation | CT8: K2010180-Plant Electrical | CV8: K3010180-Plant Electrical | CX8: K4010180-Plant Electrical | CZ8: L1010160-Boilers | DC8: L2010160-Boilers | DF8: L3010160-Boilers | DI8: L4010160-Chiller | DL8: M1010160-Chemical Treatment | DN8: M2010160-Chemical Treatment | DP8: M3010160-Chemical Treatment
F9: B101090-OTHER FLOOR CONSTRUCTION | H9: B201008-FLASHING | J9: B203008-EXTERIOR DOOR HARDWARE | L9: C101008-INTERIOR JOINT SEALANT | M9: C102090-OTHER INTERIOR SPECIALTY DOORS | N9: C103008-COUNTERS | Q9: C302008-STAIR FINISHES | W9: D109005-OPERABLE SCAFFOLDING | X9: D201090-OTHER PLUMBING FIXTURES | AC9: D301090-OTHER ENERGY SUPPLY | AF9: D304008-AIR HANDLING UNITS | AS9: D503090-OTHER COMMUNICATIONS / ALARM SYSTEMS | AU9: E101008-OFFICE EQUIPMENT | AV9: E102008-INSTRUMENTAL EQUIPMENT | AX9: E109008-PLANETARIUM EQUIPMENT | BF9: F201008-EQUIPMENT / FURNISHINGS | BG9: F202008-EQUIPMENT / FURNISHINGS | BI9: G102090-OTHER SITE DEMOLITION / RELOCATIONS | BJ9: G103008-SOIL TREATMENT | BM9: G202090-OTHER PARKING LOTS | BO9: G204008-TERRACE AND PERIMETER WALLS | BP9: G205090-OTHER LANDSCAPING | BR9: G301008-PACKAGED WATER TREATMENT PLANTS | BT9: G303090-OTHER STORM SEWER | BW9: G306008-GAS SYSTEM TRENCHBOXES | BY9: G401008-GROUNDING SYSTEMS | CA9: G403008-OTHER COMMUNICATION / ALARM | CE9: H101008-CUT-OFF WALLS | CG9: H103008-EXPANSION JOINTS | CL9: H501008-PIPE GUARDRAILS | CO9: J1010170-Plant Controls | CR9: K1010180-Adsorption | CZ9: L1010170-Chemical Feed | DC9: L2010170-Chemical Feed | DF9: L3010170-Chemical Feed | DI9: L4010170-Chemical Feed | DL9: M1010170-Secondary Clarification | DN9: M2010170-Secondary Clarification | DP9: M3010170-Secondary Clarification
H10: B201009-EXTERIOR PAINTING AND SPECIAL COATINGS | J10: B203090-OTHER EXTERIOR SPECIALTY DOORS | L10: C101090-OTHER PARTITIONS | M10: C102091-OTHER INTERIOR PERSONNEL DOORS | N10: C103009-CABINETS | Q10: C302009-FLOOR TOPPINGS AND TRAFFIC MEMBRANES | W10: D109006-TRANSPORTATION SYSTEMS | AF10: D304090-OTHER DISTRIBUTION SYSTEMS | AV10: E102009-AUDIO-VISUAL EQUIPMENT | AX10: E109009-OBSERVATORY EQUIPMENT | BF10: F201090-OTHER NON-HAZARDOUS SELECTIVE BUILDING DEMOLITION | BG10: F202090-OTHER HAZARDOUS SELECTIVE BUILDING DEMOLITION | BJ10: G103009-SHORING | BO10: G204009-FLAGPOLES | BR10: G301090-OTHER WATER SUPPLY | BW10: G306009-OTHER GAS DISTRIBUTION | BY10: G401009-METERING | CA10: G403009-GROUNDING SYSTEMS | CE10: H101009-GUARD POSTS AND RAILING | CG10: H103009-GUARD POSTS AND RAILING | CO10: J1010175-Cooling System | CR10: K1010190-Filtration | CZ10: L1010180-Compressed Air | DC10: L2010180-Compressed Air | DF10: L3010180-Compressed Air | DI10: L4010180-Compressed Air | DL10: M1010180-Filtration | DN10: M2010180-Filtration | DP10: M3010180-Filtration
H11: B201010-EXTERIOR JOINT SEALANT | J11: B203091-OTHER EXTERIOR PERSONNEL DOORS | N11: C103010-CASEWORK | Q11: C302010-HARDENERS AND SEALERS | W11: D109090-OTHER MATERIAL HANDLING SYSTEMS | AV11: E102010-DETENTION EQUIPMENT | AX11: E109010-AGRICULTURAL EQUIPMENT | BJ11: G103010-TEMPORARY DEWATERING | BO11: G204090-OTHER SITE IMPROVEMENTS | BW11: G306090-OTHER FUEL DISTRIBUTION | BY11: G401010-CATHODIC PROTECTION | CA11: G403090-OTHER SECURITY SYSTEMS | CE11: H101010-OTHER SUBSTRUCTURE COMPONENTS | CG11: H103010-PAINT STRIPING | CO11: J1010180-Fuel System | CR11: K1010200-Chemical Treatment | CZ11: L1010190-Condensate and Blowdown | DC11: L2010190-Condensate and Blowdown | DF11: L3010190-Condensate and Blowdown | DI11: L4010190-Condenser | DL11: M1010190-Disinfection | DN11: M2010190-Disinfection | DP11: M3010190-Disinfection
H12: B201011-SUN CONTROL DEVICES | N12: C103011-CLOSETS | Q12: C302011-RAISED ACCESS FLOORING | AX12: E109090-OTHER SPECIALIZED FIXED AND MOVEABLE EQUIPMENT | BJ12: G103011-TEMPORARY EROSION / SEDIMENT CONTROL | BY12: G401011-EQUIPMENT REQUIREMENTS FOR COASTAL AND HIGH HUMID | CG12: H103011-OTHER DECK COMPONENTS | CO12: J1010185-Compressed Air | CR12: K1010210-Finished Water Pumping | CZ12: L1010200-Fuel System | DC12: L2010200-Fuel System | DF12: L3010200-Fuel System | DI12: L4010200-Fuel System | DL12: M1010200-Sludge Dewatering | DN12: M2010200-Sludge Dewatering | DP12: M3010200-Sludge Dewatering
H13: B201012-SCREEN WALLS | N13: C103012-FIRESTOPPING PENETRATIONS | Q13: C302090-OTHER FLOORING / FLOOR FINISHES | BJ13: G103090-OTHER SITE EARTHWORK | BY13: G401090-OTHER ELECTRIC TRANSMISSION / DISTRIBUTION | CO13: J1010190-Power Conversion | CR13: K1010220-Disinfection | CZ13: L1010220-UG Structures | DL13: M1010210-Sludge Disposal | DN13: M2010210-Sludge Disposal | DP13: M3010210-Sludge Disposal
H14: B201090-OTHER EXTERIOR WALLS | N14: C103013-SPRAYED FIRE-RESISTIVE MATERIALS | CR14: K1010230-Solids Handling | CZ14: L1010230-Support Structures | DL14: M1010220-Sludge Digestion | DN14: M2010220-Sludge Digestion | DP14: M3010220-Sludge Digestion
N15: C103014-ENTRANCE FLOOR GRILLES AND MATS | CR15: K1010250-Plant Electrical | DL15: M1010240-Plant Electrical | DN15: M2010240-Plant Electrical | DP15: M3010240-Plant Electrical
N16: C103015-ORNAMENTAL METALWORK | CR16: K1010260-Plant Water | DL16: M1010250-Plant Water | DN16: M2010250-Plant Water | DP16: M3010250-Plant Water
N17: C103090-OTHER INTERIOR SPECIALTIES | CR17: K1010280-Plant Controls | DL17: M1010270-Plant Controls | DN17: M2010270-Plant Controls | DP17: M3010270-Plant Controls
CR18: K1010290-Plant Compressed Air | DL18: M1010280-Plant Compressed Air | DN18: M2010280-Plant Compressed Air | DP18: M3010280-Plant Compressed Air
CR19: K1010300-Raw Water Storage | DL19: M1010290-Plan Effluent

Sheet Component
A1: A101001-WALL FOUNDATIONS | B1: A101002-COLUMN FOUNDATIONS / PILE CAPS | C1: A101003-DEWATERING | D1: A101090-OTHER STANDARD FOUNDATIONS | E1: A102001-PILE FOUNDATIONS | F1: A102002-CAISSONS | G1: A102003-UNDERPINNING | H1: A102004-DEWATERING | I1: A102005-RAFT FOUNDATIONS | J1: A102006-PRESSURE INJECTED GROUTING | K1: A102090-OTHER SPECIAL FOUNDATIONS | L1: A103001-STANDARD SLAB ON GRADE | M1: A103002-STRUCTURAL SLAB ON GRADE | N1: A103003-TRENCHES | O1: A103004-PITS AND BASES | P1: A103005-FOUNDATION DRAINAGE | Q1: A103090-OTHER SLAB ON GRADE | R1: A201001-EXCAVATION FOR BASEMENTS | S1: A201002-STRUCTURE BACKFILL / COMPACTION | T1: A201003-SHORING | U1: A201090-OTHER BASEMENT EXCAVATION | V1: A202001-BASEMENT WALL CONSTRUCTION | W1: A202002-MOISTURE PROTECTION | X1: A202003-BASEMENT WALL INSULATION | Y1: A202090-OTHER BASEMENT WALLS | Z1: B101001-STRUCTURAL FRAME | AA1: B101002-STRUCTURAL INTERIOR WALLS | AB1: B101003-FLOOR DECKS AND SLABS | AC1: B101004-INCLINED AND STEPPED FLOORS | AD1: B101005-BALCONY CONSTRUCTION | AE1: B101006-RAMPS | AF1: B101007-FLOOR RACEWAY SYSTEMS | AG1: B101090-OTHER FLOOR CONSTRUCTION | AH1: B102001-STRUCTURAL FRAME | AI1: B102002-STRUCTURAL INTERIOR WALLS | AJ1: B102003-ROOF DECKS AND SLABS | AK1: B102004-CANOPIES | AL1: B102090-OTHER ROOF CONSTRUCTION | AM1: B201001-EXTERIOR CLOSURE | AN1: B201002-EXTERIOR WALL BACKUP CONSTRUCTION | AO1: B201003-INSULATION / VAPOR RETARDER | AP1: B201004-PARAPETS | AQ1: B201005-EXTERIOR LOUVERS / SCREENS | AR1: B201006-BALCONY WALLS / HANDRAILS | AS1: B201007-EXTERIOR SOFFITS | AT1: B201008-FLASHING | AU1: B201009-EXTERIOR PAINTING AND SPECIAL COATINGS | AV1: B201010-EXTERIOR JOINT SEALANT | AW1: B201011-SUN CONTROL DEVICES | AX1: B201012-SCREEN WALLS | AY1: B201090-OTHER EXTERIOR WALLS | AZ1: B202001-WINDOWS | BA1: B202002-STOREFRONTS | BB1: B202003-CURTAIN WALLS | BC1: B202090-OTHER EXTERIOR WINDOWS | BD1: B203001-SOLID DOORS | BE1: B203002-GLAZED DOORS | BF1: B203003-REVOLVING DOORS | BG1: B203004-OVERHEAD AND ROLL-UP DOORS | BH1: B203005-HANGAR DOORS | BI1: B203006-BLAST RESISTANT DOORS | BJ1: B203007-GATES | BK1: B203008-EXTERIOR DOOR HARDWARE | BL1: B203090-OTHER EXTERIOR SPECIALTY DOORS | BM1: B203091-OTHER EXTERIOR PERSONNEL DOORS | BN1: B301001-STEEP SLOPE ROOF SYSTEMS | BO1: B301002-LOW SLOPE ROOF SYSTEMS | BP1: B301003-ROOF INSULATION / FILL | BQ1: B301004-FLASHINGS / TRIM | BR1: B301005-GUTTERS / DOWNSPOUTS | BS1: B301006-ROOF OPENINGS AND SUPPORTS | BT1: B301090-OTHER ROOFING | BU1: C101001-FIXED PARTITIONS | BV1: C101002-DEMOUNTABLE PARTITIONS | BW1: C101003-RETRACTABLE PARTITIONS | BX1: C101004-INTERIOR GUARDRAILS / SCREENS | BY1: C101005-INTERIOR WINDOWS | BZ1: C101006-GLAZED PARTITIONS / STOREFRONTS | CA1: C101007-INTERIOR GLAZING | CB1: C101008-INTERIOR JOINT SEALANT | CC1: C101090-OTHER PARTITIONS | CD1: C102001-STANDARD INTERIOR DOORS | CE1: C102002-GLAZED INTERIOR DOORS | CF1: C102003-FIRE DOORS | CG1: C102004-SLIDING / FOLDING DOORS | CH1: C102005-INTERIOR OVERHEAD DOORS | CI1: C102006-INTERIOR GATES | CJ1: C102007-INTERIOR DOOR HARDWARE | CK1: C102090-OTHER INTERIOR SPECIALTY DOORS | CL1: C102091-OTHER INTERIOR PERSONNEL DOORS | CM1: C103001-COMPARTMENTS, CUBICLES / TOILET PARTITIONS | CN1: C103002-TOILET / BATH ACCESSORIES | CO1: C103003-MARKER BOARDS / TACK BOARDS | CP1: C103004-IDENTIFYING DEVICES | CQ1: C103005-LOCKERS | CR1: C103006-SHELVING | CS1: C103007-FIRE EXTINGUISHER CABINETS | CT1: C103008-COUNTERS | CU1: C103009-CABINETS | CV1: C103010-CASEWORK | CW1: C103011-CLOSETS | CX1: C103012-FIRESTOPPING PENETRATIONS | CY1: C103013-SPRAYED FIRE-RESISTIVE MATERIALS | CZ1: C103014-ENTRANCE FLOOR GRILLES AND MATS | DA1: C103015-ORNAMENTAL METALWORK | DB1: C103090-OTHER INTERIOR SPECIALTIES | DC1: C201001-INTERIOR AND EXTERIOR STAIRS | DD1: C201002-FIRE ESCAPE STAIRS | DE1: C201090-STAIR HANDRAILS, GUARDRAILS AND ACCESSORIES | DF1: C301001-CONCRETE WALL FINISHES | DG1: C301002-PLASTER WALL FINISHES | DH1: C301003-GYPSUM WALLBOARD FINISHES | DI1: C301004-TILE / TERRAZZO WALL FINISHES | DJ1: C301005-WALL COVERINGS | DK1: C301006-ACOUSTICAL PANELS ADHERED TO WALLS | DL1: C301090-OTHER WALL FINISHES | DM1: C302001-TILE FLOOR FINISHES | DN1: C302002-TERRAZZO FLOOR FINISHES | DO1: C302003-WOOD FLOORING | DP1: C302004-RESILIENT FLOOR FINISHES | DQ1: C302005-CARPETING | DR1: C302006-MASONRY / STONE FLOORING | DS1: C302007-WALL BASE FINISHES | DT1: C302008-STAIR FINISHES | DU1: C302009-FLOOR TOPPINGS AND TRAFFIC MEMBRANES | DV1: C302010-HARDENERS AND SEALERS | DW1: C302011-RAISED ACCESS FLOORING | DX1: C302090-OTHER FLOORING / FLOOR FINISHES | DY1: C303001-ACOUSTICAL CEILING TILES / PANELS | DZ1: C303002-GYPSUM WALLBOARD CEILING FINISHES | EA1: C303003-PLASTER CEILING FINISHES | EB1: C303004-WOOD CEILINGS | EC1: C303005-SUSPENSION SYSTEMS | ED1: C303006-METAL STRIP CEILINGS | EE1: C303090-OTHER CEILING / CEILING FINISHES | EF1: C304001-GENERAL REQUIREMENTS | EG1: C304002-CONCRETE FINISHES | EH1: C304003-CONCRETE MASONRY FINISHES | EI1: C304004-METAL FINISHES | EJ1: C304005-INTERIOR WOOD FINISHES | EK1: C304006-GYPSUM WALLBOARD FINISHES | EL1: C304007-SPECIAL COATINGS ON WALLS | EM1: D101001-GENERAL CONSTRUCTION ITEMS | EN1: D101002-PASSENGER ELEVATORS | EO1: D101003-FREIGHT ELEVATORS | EP1: D101004-WHEELCHAIR LIFT | EQ1: D101005-DUMBWAITERS | ER1: D101090-OTHER VERTICAL TRANSPORTATION EQUIPMENT | ES1: D102001-BASIC REQUIREMENTS OF CRANES AND MONORAILS | ET1: D102002-OVERHEAD CRANES | EU1: D102003-MONORAILS | EV1: D103001-ESCALATORS | EW1: D103002-MOVING WALKS | EX1: D103090-OTHER MOVING STAIRS / WALKS | EY1: D109001-PNEUMATIC TUBE SYSTEMS | EZ1: D109002-CONVEYORS | FA1: D109003-LINEN, TRASH, AND MAIL CHUTES | FB1: D109004-TURNTABLES | FC1: D109005-OPERABLE SCAFFOLDING | FD1: D109006-TRANSPORTATION SYSTEMS | FE1: D109090-OTHER MATERIAL HANDLING SYSTEMS | FF1: D201001-WATERCLOSETS | FG1: D201002-URINALS | FH1: D201003-LAVATORIES | FI1: D201004-SINKS | FJ1: D201005-SHOWERS/TUBS | FK1: D201006-DRINKING FOUNTAINS AND COOLERS | FL1: D201007-BIDETS | FM1: D201090-OTHER PLUMBING FIXTURES | FN1: D202001-PIPES / FITTINGS | FO1: D202002-VALVES / HYDRANTS | FP1: D202003-DOMESTIC WATER EQUIPMENT | FQ1: D202004-INSULATION / IDENTIFICATION | FR1: D202005-SPECIALTIES | FS1: D202090-OTHER DOMESTIC WATER SUPPLY | FT1: D203001-WASTE PIPE / FITTINGS | FU1: D203002-VENT PIPE / FITTINGS | FV1: D203003-FLOOR DRAINS | FW1: D203004-SANITARY AND VENT EQUIPMENT | FX1: D203005-INSULATION / IDENTIFICATION | FY1: D203090-OTHER SANITARY WASTE | FZ1: D204001-PIPE / FITTINGS | GA1: D204002-ROOF DRAINS | GB1: D204003-RAINWATER DRAINAGE EQUIPMENT | GC1: D204004-INSULATION / IDENTIFICATION | GD1: D204090-OTHER RAIN WATER DRAINAGE SYSTEM | GE1: D209001-SPECIAL PIPING SYSTEMS | GF1: D209002-ACID WASTE SYSTEMS | GG1: D209003-INTERCEPTORS | GH1: D209004-POOL PIPING AND EQUIPMENT | GI1: D209005-COMPRESSED AIR SYSTEM (NON-BREATHING) | GJ1: D209090-OTHER SPECIAL PLUMBING SYSTEMS | GK1: D301001-OIL SUPPLY SYSTEM | GL1: D301002-GAS SUPPLY SYSTEM | GM1: D301003-STEAM SUPPLY SYSTEM (FROM CENTRAL PLANT) | GN1: D301004-HOT WATER SUPPLY SYSTEM (FROM CENTRAL PLANT) | GO1: D301005-SOLAR ENERGY SYSTEMS | GP1: D301006-WIND ENERGY SUPPLY SYSTEM | GQ1: D301007-COAL SUPPLY SYSTEM | GR1: D301090-OTHER ENERGY SUPPLY | GS1: D302001-BOILERS | GT1: D302002-FURNACES | GU1: D302003-FUEL-FIRED UNIT HEATERS | GV1: D302004-AUXILIARY EQUIPMENT | GW1: D302005-EQUIPMENT THERMAL INSULATION | GX1: D302090-OTHER HEAT GENERATING SYSTEMS | GY1: D303001-CHILLED WATER SYSTEMS | GZ1: D303002-DIRECT EXPANSION SYSTEMS | HA1: D303090-OTHER COOLING GENERATING SYSTEMS | HB1: D304001-AIR DISTRIBUTION, HEATING / COOLING | HC1: D304002-STEAM DISTRIBUTION SYSTEMS | HD1: D304003-HOT WATER DISTRIBUTION SYSTEMS | HE1: D304004-CHANGE OVER DISTRIBUTION SYSTEMS | HF1: D304005-GLYCOL DISTRIBUTION SYSTEMS | HG1: D304006-CHILLED WATER DISTRIBUTION SYSTEMS | HH1: D304007-EXHAUST SYSTEMS | HI1: D304008-AIR HANDLING UNITS | HJ1: D304090-OTHER DISTRIBUTION SYSTEMS | HK1: D305001-UNIT VENTILATORS | HL1: D305002-UNIT HEATERS | HM1: D305003-FAN COIL UNITS | HN1: D305004-FIN TUBE RADIATION | HO1: D305005-ELECTRIC HEATING | HP1: D305006-PACKAGE UNITS | HQ1: D305090-OTHER TERMINAL / PACKAGE UNITS | HR1: D306001-HVAC CONTROLS | HS1: D306002-ELECTRONIC CONTROLS | HT1: D306003-PNEUMATIC CONTROLS | HU1: D306004-INSTRUMENT AIR COMPRESSORS | HV1: D306005-GAS PURGING SYSTEMS | HW1: D306090-OTHER CONTROLS INSTRUMENTATION | HX1: D307001-WATER SIDE TESTING / BALANCING - HEATING / COOLING | HY1: D307002-AIR SIDE TESTING / BALANCING - HEATING, COOLING / | HZ1: D307003-HVAC COMMISSIONING | IA1: D307090-OTHER SYSTEMS TESTING / BALANCING | IB1: D309001-GENERAL CONSTRUCTION ITEMS | IC1: D309002-REFRIGERATION SYSTEMS | ID1: D309090-OTHER SPECIAL MECHANICAL SYSTEMS | IE1: D401001-FIRE ALARM DISTRIBUTION | IF1: D401002-FIRE ALARM DEVICES | IG1: D402001-FIRE PROTECTION WATER PIPING AND EQUIPMENT | IH1: D402002-FIRE PUMP | II1: D403001-STANDPIPE EQUIPMENT / PIPING | IJ1: D404001-SPRINKLERS AND RELEASING DEVICES | IK1: D404002-SPRINKLER WATER SUPPLY EQUIPMENT AND PIPING | IL1: D405001-PORTABLE EXTINGUISHERS | IM1: D409001-CARBON DIOXIDE SYSTEMS | IN1: D409002-FOAM GENERATING EQUIPMENT | IO1: D409003-CLEAN AGENT SYSTEMS | IP1: D409004-HOOD / DUCT FIRE PROTECTION | IQ1: D409090-OTHER SPECIAL FIRE PROTECTION SYSTEMS | IR1: D501001-MAIN TRANSFORMERS | IS1: D501002-SERVICE ENTRANCE EQUIPMENT | IT1: D501003-INTERIOR DISTRIBUTION TRANSFORMERS | IU1: D501004-PANELBOARDS | IV1: D501005-ENCLOSED CIRCUIT BREAKERS | IW1: D501006-MOTOR CONTROL CENTERS | IX1: D501090-OTHER SERVICE AND DISTRIBUTION | IY1: D502001-BRANCH WIRING | IZ1: D502002-LIGHTING EQUIPMENT | JA1: D502090-OTHER LIGHTING AND BRANCH WIRING | JB1: D503001-TELECOMMUNICATIONS SYSTEMS | JC1: D503002-PUBLIC ADDRESS SYSTEMS | JD1: D503003-INTERCOMMUNICATIONS SYSTEMS | JE1: D503004-TELEVISION SYSTEMS | JF1: D503005-SECURITY SYSTEMS | JG1: D503006-NURSE CALL SYSTEMS | JH1: D503007-CLOCK / PROGRAM SYSTEMS | JI1: D503090-OTHER COMMUNICATIONS / ALARM SYSTEMS | JJ1: D509001-GENERAL CONSTRUCTION ITEMS (ELECTRICAL) | JK1: D509002-EMERGENCY LIGHTING / POWER | JL1: D509003-GROUNDING SYSTEMS | JM1: D509004-LIGHTNING PROTECTION | JN1: D509005-ELECTRIC HEATING | JO1: D509006-ENERGY MANAGEMENT CONTROL SYSTEM | JP1: D509090-OTHER SPECIAL SYSTEMS AND DEVICES | JQ1: E101001-CHECKROOM EQUIPMENT | JR1: E101002-REGISTRATION EQUIPMENT | JS1: E101003-VENDING EQUIPMENT | JT1: E101004-LAUNDRY EQUIPMENT | JU1: E101005-SECURITY / VAULT EQUIPMENT | JV1: E101006-TELLER AND SERVICE EQUIPMENT | JW1: E101007-MERCANTILE EQUIPMENT | JX1: E101008-OFFICE EQUIPMENT | JY1: E102001-MISCELLANEOUS COMMON FIXED / MOVEABLE EQUIPMENT | JZ1: E102002-MEDICAL EQUIPMENT | KA1: E102003-LABORATORY EQUIPMENT | KB1: E102004-MORTUARY EQUIPMENT | KC1: E102005-AUDITORIUM / STAGE EQUIPMENT | KD1: E102006-LIBRARY EQUIPMENT | KE1: E102007-ECCLESIASTICAL EQUIPMENT | KF1: E102008-INSTRUMENTAL EQUIPMENT | KG1: E102009-AUDIO-VISUAL EQUIPMENT | KH1: E102010-DETENTION EQUIPMENT | KI1: E103001-PARKING CONTROL EQUIPMENT | KJ1: E103002-LOADING DOCK EQUIPMENT | KK1: E103003-WAREHOUSE EQUIPMENT | KL1: E103004-AUTOMOTIVE SHOP EQUIPMENT | KM1: E109001-BUILT-IN MAINTENANCE EQUIPMENT | KN1: E109002-FOOD SERVICE EQUIPMENT | KO1: E109003-WASTE HANDLING EQUIPMENT | KP1: E109004-RESIDENTIAL EQUIPMENT | KQ1: E109005-UNIT KITCHENS | KR1: E109006-DARKROOM EQUIPMENT | KS1: E109007-ATHLETIC, RECREATIONAL, / THERAPEUTIC EQUIPMENT | KT1: E109008-PLANETARIUM EQUIPMENT | KU1: E109009-OBSERVATORY EQUIPMENT | KV1: E109010-AGRICULTURAL EQUIPMENT | KW1: E109090-OTHER SPECIALIZED FIXED AND MOVEABLE EQUIPMENT | KX1: E201001-FIXED ARTWORK | KY1: E201002-WINDOW TREATMENTS | KZ1: E201003-SEATING (FIXED) | LA1: E201004-FIXED INTERIOR LANDSCAPING | LB1: E201090-OTHER FIXED INTERIOR FURNISHINGS | LC1: E202001-MOVEABLE ART WORK | LD1: E202002-MODULAR PREFABRICATED FURNITURE | LE1: E202003-FREESTANDING FURNITURE | LF1: E202004-RUGS / ACCESSORIES | LG1: E202005-MOVEABLE MULTIPLE SEATING | LH1: E202006-MOVEABLE INTERIOR LANDSCAPING | LI1: E202090-OTHER MOVEABLE FURNISHINGS | LJ1: F101001-METAL BUILDING SYSTEMS | LK1: F101002-EXTERIOR UTILITY BUILDINGS | LL1: F101003-AIR-SUPPORTED STRUCTURES | LM1: F101090-OTHER SPECIAL CONSTRUCTION | LN1: F102001-SPECIAL PURPOSE ROOMS | LO1: F102002-INTEGRATED ASSEMBLIES | LP1: F102090-OTHER INTEGRATED CONSTRUCTION | LQ1: F103001-VAULTS | LR1: F103002-SOUND, VIBRATION, AND SEISMIC CONSTRUCTION | LS1: F103003-RADIATION PROTECTION | LT1: F103090-OTHER SPECIAL CONSTRUCTION SYSTEMS | LU1: F104001-INTERIOR SWIMMING POOLS | LV1: F104002-LIQUID AND GAS STORAGE TANKS | LW1: F104003-KENNELS AND ANIMAL SHELTERS | LX1: F104004-SITE CONSTRUCTED INCINERATORS | LY1: F104005-ICE RINKS | LZ1: F104090-OTHER SPECIAL FACILITIES | MA1: F105001-RECORDING INSTRUMENTATION | MB1: F105002-BUILDING AUTOMATION SYSTEMS | MC1: F105090-OTHER SPECIAL CONTROLS AND INSTRUMENTATION | MD1: F201001-SUBSTRUCTURE / SUPERSTRUCTURE | ME1: F201002-EXTERIOR CLOSURE | MF1: F201003-ROOFING | MG1: F201004-INTERIOR CONSTRUCTION / FINISHES | MH1: F201005-CONVEYING SYSTEMS | MI1: F201006-MECHANICAL SYSTEMS | MJ1: F201007-ELECTRICAL SYSTEMS | MK1: F201008-EQUIPMENT / FURNISHINGS | ML1: F201090-OTHER NON-HAZARDOUS SELECTIVE BUILDING DEMOLITION | MM1: F202001-SUBSTRUCTURE / SUPERSTRUCTURE | MN1: F202002-EXTERIOR CLOSURE | MO1: F202003-ROOFING | MP1: F202004-INTERIOR CONSTRUCTION / FINISHES | MQ1: F202005-CONVEYING SYSTEMS | MR1: F202006-MECHANICAL SYSTEMS | MS1: F202007-ELECTRICAL SYSTEMS | MT1: F202008-EQUIPMENT / FURNISHINGS | MU1: F202090-OTHER HAZARDOUS SELECTIVE BUILDING DEMOLITION | MV1: G101001-CLEARING | MW1: G101002-TREE REMOVAL | MX1: G101003-STUMP REMOVAL | MY1: G101004-GRUBBING | MZ1: G101005-SELECTIVE THINNING | NA1: G101006-DEBRIS DISPOSAL | NB1: G101090-OTHER SITE CLEARING | NC1: G102001-BUILDING MASS DEMOLITION | ND1: G102002-ABOVE GROUND SITE DEMOLITION | NE1: G102003-UNDERGROUND SITE DEMOLITION | NF1: G102004-BUILDING RELOCATION | NG1: G102005-UTILITY RELOCATION | NH1: G102006-FENCING RELOCATION | NI1: G102007-SITE CLEANUP | NJ1: G102090-OTHER SITE DEMOLITION / RELOCATIONS | NK1: G103001-GRADING | NL1: G103002-COMMON EXCAVATION | NM1: G103003-ROCK EXCAVATION | NN1: G103004-FILL / BORROW | NO1: G103005-COMPACTION | NP1: G103006-SOIL STABILIZATION | NQ1: G103007-SLOPE STABILIZATION | NR1: G103008-SOIL TREATMENT | NS1: G103009-SHORING | NT1: G103010-TEMPORARY DEWATERING | NU1: G103011-TEMPORARY EROSION / SEDIMENT CONTROL | NV1: G103090-OTHER SITE EARTHWORK | NW1: G104001-REMOVAL OF CONTAMINATED SOIL | NX1: G104002-SOIL RESTORATION AND TREATMENT | NY1: G104090-OTHER HAZARDOUS WASTE REMEDIATION | NZ1: G201001-BASES / SUBBASES | OA1: G201002-CURBS / GUTTERS | OB1: G201003-PAVED SURFACES | OC1: G201004-MARKING / SIGNAGE | OD1: G201005-GUARDRAILS / BARRIERS | OE1: G201006-RESURFACING | OF1: G201090-OTHER ROADWAYS | OG1: G202001-BASES / SUBBASES | OH1: G202002-CURBS / GUTTERS | OI1: G202003-PAVED SURFACES | OJ1: G202004-MARKING / SIGNAGE | OK1: G202005-GUARDRAILS / BARRIERS | OL1: G202006-RESURFACING | OM1: G202007-MISCELLANEOUS STRUCTURES AND EQUIPMENT | ON1: G202090-OTHER PARKING LOTS | OO1: G203001-BASES / SUBBASES | OP1: G203002-CURBS / GUTTERS | OQ1: G203003-PAVED SURFACES | OR1: G203004-GUARDRAILS / BARRIERS | OS1: G203005-RESURFACING | OT1: G203090-OTHER WALKS, STEPS / TERRACES | OU1: G204001-FENCING / GATES | OV1: G204002-RETAINING WALLS AND FREESTANDING WALLS | OW1: G204003-EXTERIOR FURNISHINGS | OX1: G204004-SECURITY STRUCTURES | OY1: G204005-SIGNAGE | OZ1: G204006-FOUNTAINS / POOLS | PA1: G204007-PLAYING FIELDS | PB1: G204008-TERRACE AND PERIMETER WALLS | PC1: G204009-FLAGPOLES | PD1: G204090-OTHER SITE IMPROVEMENTS | PE1: G205001-FINE GRADING / SOIL PREPARATION | PF1: G205002-EROSION CONTROL MEASURES | PG1: G205003-TOPSOIL / PLANTING BEDS | PH1: G205004-SEEDING, SPRIGGING AND SODDING | PI1: G205005-PLANTINGS | PJ1: G205006-PLANTERS | PK1: G205007-IRRIGATION SYSTEMS | PL1: G205090-OTHER LANDSCAPING | PM1: G206001-AIRFIELD PAVING CONSTRUCTION | PN1: G206002-OTHER PAVING | PO1: G206003-JOINTS AND ANCHORAGE | PP1: G206004-NAVIGATION AIDS | PQ1: G206005-AIRFIELD MARKINGS | PR1: G301001-WELL SYSTEMS | PS1: G301002-POTABLE WATER DISTRIBUTION | PT1: G301003-POTABLE WATER STORAGE | PU1: G301004-FIRE PROTECTION WATER DISTRIBUTION | PV1: G301005-FIRE PROTECTION WATER STORAGE | PW1: G301006-NON-POTABLE WATER DISTRIBUTION | PX1: G301007-PUMPING STATIONS | PY1: G301008-PACKAGED WATER TREATMENT PLANTS | PZ1: G301090-OTHER WATER SUPPLY | QA1: G302001-SANITARY SEWER PIPING | QB1: G302002-SANITARY SEWER MANHOLES / CLEANOUTS | QC1: G302003-LIFT STATIONS AND PUMPING STATIONS | QD1: G302004-PACKAGED SANITARY SEWER TREATMENT PLANTS | QE1: G302005-SEPTIC TANKS | QF1: G302006-DRAIN FIELDS | QG1: G302090-OTHER SANITARY SEWER | QH1: G303001-STORM SEWER PIPING | QI1: G303002-STORM SEWER STRUCTURES | QJ1: G303003-LIFT STATIONS | QK1: G303004-CULVERTS | QL1: G303005-HEADWALLS | QM1: G303006-EROSION / SEDIMENT CONTROL MEASURES | QN1: G303007-STORMWATER MANAGEMENT | QO1: G303090-OTHER STORM SEWER | QP1: G304001-OVERHEAD HOT WATER SYSTEMS | QQ1: G304002-OVERHEAD STEAM SYSTEMS | QR1: G304003-UNDERGROUND HOT WATER SYSTEMS | QS1: G304004-UNDERGROUND STEAM DISTRIBUTION SYSTEMS | QT1: G304005-REINFORCED CONCRETE MANHOLES / VALVE BOXES | QU1: G304006-PUMPING STATIONS | QV1: G304090-OTHER HEATING DISTRIBUTION | QW1: G305001-OVERHEAD COOLING SYSTEMS | QX1: G305002-UNDERGROUND COOLING SYSTEMS | QY1: G305003-TRENCHBOXES | QZ1: G305004-WELLS FOR COOLING | RA1: G305005-PUMPING STATIONS | RB1: G305006-ON-SITE COOLING TOWERS | RC1: G305090-OTHER COOLING DISTRIBUTION | RD1: G306001-LIQUID FUEL DISTRIBUTION PIPING SYSTEM | RE1: G306002-AVIATION FUEL DISTRIBUTION PIPING SYSTEM | RF1: G306003-LIQUID FUEL STORAGE TANKS | RG1: G306004-LIQUID FUEL DISPENSING EQUIPMENT | RH1: G306005-LIQUID FUEL SYSTEM TRENCHBOXES | RI1: G306006-GAS DISTRIBUTION PIPING (NATURAL AND PROPANE) | RJ1: G306007-GAS STORAGE TANKS | RK1: G306008-GAS SYSTEM TRENCHBOXES | RL1: G306009-OTHER GAS DISTRIBUTION | RM1: G306090-OTHER FUEL DISTRIBUTION | RN1: G309001-INDUSTRIAL WASTE PIPE | RO1: G309002-INDUSTRIAL WASTE MANHOLES / CLEANOUTS | RP1: G309003-INDUSTRIAL WASTE LIFT STATIONS | RQ1: G309004-INDUSTRIAL WASTE HOLDING TANKS / SEPARATORS | RR1: G309005-INDUSTRIAL WASTE TRENCHBOXES | RS1: G309090-OTHER INDUSTRIAL WASTE | RT1: G401001-SUBSTATIONS | RU1: G401002-TRANSFORMERS | RV1: G401003-SWITCHES, CONTROLS / DEVICES | RW1: G401004-OVERHEAD ELECTRIC CONDUCTORS | RX1: G401005-TOWERS, POLES, CROSSARMS / INSULATORS | RY1: G401006-UNDERGROUND ELECTRIC CONDUCTORS | RZ1: G401007-DUCTBANKS, MANHOLES, HANDHOLES / RACEWAYS | SA1: G401008-GROUNDING SYSTEMS | SB1: G401009-METERING | SC1: G401010-CATHODIC PROTECTION | SD1: G401011-EQUIPMENT REQUIREMENTS FOR COASTAL AND HIGH HUMID | SE1: G401090-OTHER ELECTRIC TRANSMISSION / DISTRIBUTION | SF1: G402001-EXTERIOR LIGHTING FIXTURES / CONTROLS | SG1: G402002-SPECIAL SECURITY LIGHTING SYSTEMS | SH1: G402003-OTHER AREA LIGHTING | SI1: G402004-LIGHTING POLES | SJ1: G402005-UNDERGROUND ELECTRIC CONDUCTORS | SK1: G402006-DUCTBANKS, MANHOLES / HANDHOLES | SL1: G402007-GROUNDING SYSTEMS | SM1: G403001-TELECOMMUNICATIONS SYSTEMS | SN1: G403002-CABLE TV SYSTEMS (CATV) | SO1: G403003-CABLES / WIRING | SP1: G403004-DUCTBANKS, MANHOLES / HANDHOLES | SQ1: G403005-TOWERS, POLES / STANDS | SR1: G403006-TV CAMERAS / MONITORS | SS1: G403007-ELECTRONIC SECURITY SYSTEMS (ESS) | ST1: G403008-OTHER COMMUNICATION / ALARM | SU1: G403009-GROUNDING SYSTEMS | SV1: G403090-OTHER SECURITY SYSTEMS | SW1: G409001-SACRIFICIAL ANODE CATHODIC PROTECTION SYSTEM | SX1: G409002-INDUCED CURRENT CATHODIC PROTECTION SYSTEM | SY1: G409003-EMERGENCY POWER GENERATION | SZ1: G409090-OTHER CATHODIC PROTECTION | TA1: G901001-SERVICE AND PEDESTRIAN TUNNELS | TB1: G901002-PREFABRICATED SERVICE AND PEDESTRIAN TUNNELS | TC1: G909001-BRIDGES | TD1: G909002-RAILROAD SPURS | TE1: G909003-SNOW MELTING SYSTEMS | TF1: G909090-OTHER SPECIAL CONSTRUCTION | TG1: H101001-PILE FOUNDATIONS | TH1: H101002-PILE CAPS | TI1: H101003-QUAYS | TJ1: H101004-RELIEVING PLATFORMS | TK1: H101005-REVETMENTS | TL1: H101006-SEAWALLS | TM1: H101007-BOAT RAMPS | TN1: H101008-CUT-OFF WALLS | TO1: H101009-GUARD POSTS AND RAILING | TP1: H101010-OTHER SUBSTRUCTURE COMPONENTS | TQ1: H102001-BEAMS AND GIRDERS | TR1: H102002-COLUMNS | TS1: H102003-UTILITY ENCLOSURES | TT1: H102004-OTHER SUPERSTRUCTURE ELEMENTS | TU1: H103001-DECK | TV1: H103002-ON-GRADE SLAB | TW1: H103003-DECK OVERLAY | TX1: H103004-CURBS AND BULLRAILS | TY1: H103005-MOORING FOUNDATIONS | TZ1: H103006-HIGH MAST LIGHTING FOUNDATIONS | UA1: H103007-UTILITY MOUNDS | UB1: H103008-EXPANSION JOINTS | UC1: H103009-GUARD POSTS AND RAILING | UD1: H103010-PAINT STRIPING | UE1: H103011-OTHER DECK COMPONENTS | UF1: H104001-PRIMARY FENDER SYSTEM | UG1: H104002-SECONDARY FENDER SYSTEM | UH1: H104003-CORNER FENDER SYSTEM | UI1: H104004-DOLPHINS | UJ1: H104005-MOORING HARDWARE | UK1: H104006-OTHER MOORING AND BERTHING COMPONENTS | UL1: H301001-WAVE PROTECTION ARMORS | UM1: H301002-BREAKWATERS | UN1: H302001-ROCK REVETMENTS | UO1: H302002-GRANULAR FILL REVETMENTS | UP1: H302003-COMBINED ROCK AND GRANULAR FILL REVETMENTS | UQ1: H402001-OCEAN DISPOSAL | UR1: H402002-NEW CONFINED DISPOSAL FACILITIES | US1: H402003-EXISTING CONFINED DISPOSAL FACILITIES | UT1: H501001-POTABLE WATER | UU1: H501002-SALTWATER | UV1: H501003-SANITARY SEWER | UW1: H501004-BILGE AND OILY WASTE | UX1: H501005-COMPRESSED AIR | UY1: H501006-STEAM | UZ1: H501007-OTHER CIVIL/MECHANICAL UTILITIES | VA1: H501008-PIPE GUARDRAILS | VB1: H502001-POWER DISTRIBUTION SYSTEM | VC1: H502002-TELECOMMUNICATION SYSTEM | VD1: H502003-LIGHTING SYSTEMS | VE1: H502004-LIGHTNING PROTECTION SYSTEM | VF1: H502005-POWER BOOMS | VG1: H502006-OTHER ELECTRICAL UTILITIES | VH1: H503001-FIRE PROTECTION WATER DISTRIBUTION SYSTEM | VI1: H503002-FIRE ALARM
A2: A101001-Foundation Wall | B2: A101002-Column Pier | C2: A101003-General | D2: A101090-General | E2: A102001-CIP Concrete | F2: A102002-General | G2: A102003-General | H2: A102004-General | I2: A102005-General | J2: A102006-General | K2: A102090-General | L2: A103001-General | M2: A103002-General | N2: A103003-General | O2: A103004-General | P2: A103005-General | Q2: A103090-General | R2: A201001-General | S2: A201002-General | T2: A201003-General | U2: A201090-General | V2: A202001-CIP Concrete | W2: A202002-General | X2: A202003-General | Y2: A202090-General | Z2: B101001-Beam/Girder | AA2: B101002-CMU | AB2: B101003-Deck - Composite w/Bar Joists | AC2: B101004-General | AD2: B101005-General | AE2: B101006-General | AF2: B101007-General | AG2: B101090-General | AH2: B102001-Beam/Girder | AI2: B102002-CMU | AJ2: B102003-CIP Concrete Beam and Slab | AK2: B102004-General | AL2: B102090-General | AM2: B201001-Adobe | AN2: B201002-General | AO2: B201003-Fiberglass Batts | AP2: B201004-General | AQ2: B201005-General | AR2: B201006-General | AS2: B201007-General | AT2: B201008-General | AU2: B201009-General | AV2: B201010-General | AW2: B201011-General | AX2: B201012-General | AY2: B201090-General | AZ2: B202001-Aluminum Windows | BA2: B202002-General | BB2: B202003-General | BC2: B202090-General | BD2: B203001-Aluminum | BE2: B203002-General | BF2: B203003-Electric | BG2: B203004-Aluminum/Fiberglass, Electric, 12 FT x 12 Ft | BH2: B203005-General | BI2: B203006-General | BJ2: B203007-General | BK2: B203008-General | BL2: B203090-Emergency Egress Door | BM2: B203091-General | BN2: B301001-Asbestos Cement Shingles | BO2: B301002-Built-Up | BP2: B301003-Cellular Fill | BQ2: B301004-Flashings - Apron | BR2: B301005-Downspouts | BS2: B301006-General | BT2: B301090-General | BU2: C101001-General | BV2: C101002-General | BW2: C101003-General | BX2: C101004-General | BY2: C101005-General | BZ2: C101006-General | CA2: C101007-General | CB2: C101008-General | CC2: C101090-General | CD2: C102001-General | CE2: C102002-General | CF2: C102003-Fire Door - Rollup | CG2: C102004-General | CH2: C102005-General | CI2: C102006-General | CJ2: C102007-General | CK2: C102090-Cold Storage | CL2: C102091-Cipher Lock | CM2: C103001-General | CN2: C103002-General | CO2: C103003-General | CP2: C103004-General | CQ2: C103005-General | CR2: C103006-General | CS2: C103007-General | CT2: C103008-Concrete | CU2: C103009-General | CV2: C103010-General | CW2: C103011-General | CX2: C103012-General | CY2: C103013-General | CZ2: C103014-Fiberglass Grate System | DA2: C103015-General | DB2: C103090-General | DC2: C201001-Exterior Stairs | DD2: C201002-General | DE2: C201090-General | DF2: C301001-General | DG2: C301002-General | DH2: C301003-General | DI2: C301004-General | DJ2: C301005-General | DK2: C301006-General | DL2: C301090-General | DM2: C302001-Ceramic Tile | DN2: C302002-General | DO2: C302003-General | DP2: C302004-Composition Sheet | DQ2: C302005-Carpet Tile | DR2: C302006-General | DS2: C302007-General | DT2: C302008-General | DU2: C302009-General | DV2: C302010-Concrete Topping | DW2: C302011-General | DX2: C302090-General | DY2: C303001-General | DZ2: C303002-General | EA2: C303003-General | EB2: C303004-General | EC2: C303005-General | ED2: C303006-General | EE2: C303090-Exposed Concrete Finish | EF2: C304001-General | EG2: C304002-General | EH2: C304003-General | EI2: C304004-General | EJ2: C304005-General | EK2: C304006-General | EL2: C304007-General | EM2: D101001-General | EN2: D101002-General | EO2: D101003-General | EP2: D101004-General | EQ2: D101005-Automatic | ER2: D101090-Correspondence lifts, elec | ES2: D102001-General | ET2: D102002-Cranes, Bridge girder, 10 ton, 20 Ft span | EU2: D102003-General | EV2: D103001-10 Ft hieght, 32 In width | EW2: D103002-Flat, 2 Ft-0 In width | EX2: D103090-General | EY2: D109001-General | EZ2: D109002-General | FA2: D109003-Chute - Linen / Refuse | FB2: D109004-General | FC2: D109005-General | FD2: D109006-General | FE2: D109090-General | FF2: D201001-General | FG2: D201002-General | FH2: D201003-General | FI2: D201004-General | FJ2: D201005-Bathtub | FK2: D201006-Drinking Fountain | FL2: D201007-General | FM2: D201090-Emergency Eye Wash | FN2: D202001-Black / Galvanized Steel < 1 In Pipe | FO2: D202002-Backflow Preventer | FP2: D202003-Booster Pump | FQ2: D202004-General | FR2: D202005-General | FS2: D202090-General | FT2: D203001-General | FU2: D203002-General | FV2: D203003-General | FW2: D203004-Backflow Preventer | FX2: D203005-General | FY2: D203090-General | FZ2: D204001-General | GA2: D204002-General | GB2: D204003-General | GC2: D204004-General | GD2: D204090-General | GE2: D209001-General | GF2: D209002-General | GG2: D209003-General | GH2: D209004-General | GI2: D209005-General | GJ2: D209090-General | GK2: D301001-General | GL2: D301002-Fuel Storage Tank | GM2: D301003-General | GN2: D301004-General | GO2: D301005-Charge Controller | GP2: D301006-General | GQ2: D301007-General | GR2: D301090-General | GS2: D302001-Electric, Hot Water | GT2: D302002-Electric, 10.2 MBH | GU2: D302003-Gas | GV2: D302004-Air Separator | GW2: D302005-General | GX2: D302090-General | GY2: D303001-Chiller, Absorption, Gas, Water Cooled | GZ2: D303002-Condenser, DX, Air Cooled | HA2: D303090-General | HB2: D304001-Dehumidifier | HC2: D304002-General | HD2: D304003-Circulating Pump, Double Suction | HE2: D304004-General | HF2: D304005-General | HG2: D304006-Circulating Pump, Double Suction | HH2: D304007-Ceiling Vents, Passive | HI2: D304008-Central Station | HJ2: D304090-General | HK2: D305001-Air Curtain | HL2: D305002-General | HM2: D305003-Cab Mount, Four Pipe | HN2: D305004-Baseboard Heating | HO2: D305005-208-240 volt, 10 kW | HP2: D305006-A/C Unit, Computer Room | HQ2: D305090-General | HR2: D306001-General | HS2: D306002-analog inputs, sensors (avg. 50 Ft run in 1/2 In EMT), CFM/transducer | HT2: D306003-air supply for pneumatic, tank mounted duplex compressor, sterter, alternat | HU2: D306004-General | HV2: D306005-General | HW2: D306090-General | HX2: D307001-General | HY2: D307002-General | HZ2: D307003-General | IA2: D307090-General | IB2: D309001-General | IC2: D309002-General | ID2: D309090-General | IE2: D401001-Fire Alarm Control Panel | IF2: D401002-Annunciator | IG2: D402001-Air Compressor | IH2: D402002-4 In pump, 30 HP, 500 GPM | II2: D403001-Fire Hose Equipment | IJ2: D404001-Deluge Systems | IK2: D404002-General | IL2: D405001-Dispersion nozzle | IM2: D409001-General | IN2: D409002-General | IO2: D409003-General | IP2: D409004-General | IQ2: D409090-General | IR2: D501001-General | IS2: D501002-Electrical Service - 3 Phase, 120/208 V, 100 A | IT2: D501003-Buck-boost, 120/240 V primary 12/24 V secondary, 0.10 kVA | IU2: D501004-General | IV2: D501005-General | IW2: D501006-General | IX2: D501090-Capacitor Bank | IY2: D502001-General | IZ2: D502002-Exit Lighting | JA2: D502090-General | JB2: D503001-General | JC2: D503002-100 outlets | JD2: D503003-100 stations | JE2: D503004-General | JF2: D503005-General | JG2: D503006-General | JH2: D503007-General | JI2: D503090-General | JJ2: D509001-General | JK2: D509002-Emergency Lighting | JL2: D509003-General | JM2: D509004-General | JN2: D509005-General | JO2: D509006-General | JP2: D509090-General | JQ2: E101001-General | JR2: E101002-General | JS2: E101003-General | JT2: E101004-General | JU2: E101005-General | JV2: E101006-General | JW2: E101007-General | JX2: E101008-General | JY2: E102001-General | JZ2: E102002-General | KA2: E102003-General | KB2: E102004-General | KC2: E102005-General | KD2: E102006-General | KE2: E102007-General | KF2: E102008-General | KG2: E102009-General | KH2: E102010-General | KI2: E103001-General | KJ2: E103002-General | KK2: E103003-General | KL2: E103004-Automotive lifts (Hydraulic), clear floor, 2 post, 30,000 lb | KM2: E109001-General | KN2: E109002-General | KO2: E109003-General | KP2: E109004-General | KQ2: E109005-General | KR2: E109006-General | KS2: E109007-General | KT2: E109008-General | KU2: E109009-General | KV2: E109010-General | KW2: E109090-General | KX2: E201001-General | KY2: E201002-General | KZ2: E201003-General | LA2: E201004-General | LB2: E201090-General | LC2: E202001-General | LD2: E202002-General | LE2: E202003-General | LF2: E202004-General | LG2: E202005-General | LH2: E202006-General | LI2: E202090-General | LJ2: F101001-General | LK2: F101002-General | LL2: F101003-General | LM2: F101090-General | LN2: F102001-Cold Storage Room | LO2: F102002-General | LP2: F102090-General | LQ2: F103001-General | LR2: F103002-General | LS2: F103003-General | LT2: F103090-General | LU2: F104001-General | LV2: F104002-General | LW2: F104003-General | LX2: F104004-General | LY2: F104005-General | LZ2: F104090-General | MA2: F105001-General | MB2: F105002-General | MC2: F105090-General | MD2: F201001-General | ME2: F201002-General | MF2: F201003-General | MG2: F201004-General | MH2: F201005-General | MI2: F201006-General | MJ2: F201007-General | MK2: F201008-General | ML2: F201090-General | MM2: F202001-General | MN2: F202002-General | MO2: F202003-General | MP2: F202004-General | MQ2: F202005-General | MR2: F202006-General | MS2: F202007-General | MT2: F202008-General | MU2: F202090-General | MV2: G101001-General | MW2: G101002-General | MX2: G101003-General | MY2: G101004-General | MZ2: G101005-General | NA2: G101006-General | NB2: G101090-General | NC2: G102001-General | ND2: G102002-General | NE2: G102003-General | NF2: G102004-General | NG2: G102005-General | NH2: G102006-General | NI2: G102007-General | NJ2: G102090-General | NK2: G103001-General | NL2: G103002-General | NM2: G103003-General | NN2: G103004-General | NO2: G103005-General | NP2: G103006-General | NQ2: G103007-General | NR2: G103008-General | NS2: G103009-General | NT2: G103010-General | NU2: G103011-General | NV2: G103090-General | NW2: G104001-General | NX2: G104002-General | NY2: G104090-General | NZ2: G201001-General | OA2: G201002-General | OB2: G201003-General | OC2: G201004-General | OD2: G201005-General | OE2: G201006-General | OF2: G201090-General | OG2: G202001-General | OH2: G202002-General | OI2: G202003-General | OJ2: G202004-General | OK2: G202005-General | OL2: G202006-General | OM2: G202007-General | ON2: G202090-General | OO2: G203001-General | OP2: G203002-General | OQ2: G203003-General | OR2: G203004-General | OS2: G203005-General | OT2: G203090-General | OU2: G204001-Fence/Privacy Wall | OV2: G204002-Concrete | OW2: G204003-General | OX2: G204004-General | OY2: G204005-General | OZ2: G204006-General | PA2: G204007-General | PB2: G204008-General | PC2: G204009-General | PD2: G204090-General | PE2: G205001-General | PF2: G205002-General | PG2: G205003-General | PH2: G205004-General | PI2: G205005-General | PJ2: G205006-General | PK2: G205007-General | PL2: G205090-General | PM2: G206001-General | PN2: G206002-General | PO2: G206003-General | PP2: G206004-General | PQ2: G206005-General | PR2: G301001-General | PS2: G301002-General | PT2: G301003-General | PU2: G301004-General | PV2: G301005-General | PW2: G301006-General | PX2: G301007-General | PY2: G301008-General | PZ2: G301090-General | QA2: G302001-General | QB2: G302002-General | QC2: G302003-General | QD2: G302004-General | QE2: G302005-General | QF2: G302006-General | QG2: G302090-General | QH2: G303001-General | QI2: G303002-General | QJ2: G303003-General | QK2: G303004-General | QL2: G303005-General | QM2: G303006-General | QN2: G303007-General | QO2: G303090-General | QP2: G304001-General | QQ2: G304002-General | QR2: G304003-General | QS2: G304004-General | QT2: G304005-General | QU2: G304006-General | QV2: G304090-General | QW2: G305001-General | QX2: G305002-General | QY2: G305003-General | QZ2: G305004-General | RA2: G305005-General | RB2: G305006-General | RC2: G305090-General | RD2: G306001-General | RE2: G306002-General | RF2: G306003-General | RG2: G306004-General | RH2: G306005-General | RI2: G306006-General | RJ2: G306007-General | RK2: G306008-General | RL2: G306009-General | RM2: G306090-General | RN2: G309001-General | RO2: G309002-General | RP2: G309003-General | RQ2: G309004-General | RR2: G309005-General | RS2: G309090-General | RT2: G401001-General | RU2: G401002-General | RV2: G401003-General | RW2: G401004-General | RX2: G401005-General | RY2: G401006-General | RZ2: G401007-General | SA2: G401008-General | SB2: G401009-General | SC2: G401010-General | SD2: G401011-General | SE2: G401090-General | SF2: G402001-General | SG2: G402002-General | SH2: G402003-General | SI2: G402004-General | SJ2: G402005-General | SK2: G402006-General | SL2: G402007-General | SM2: G403001-General | SN2: G403002-General | SO2: G403003-General | SP2: G403004-General | SQ2: G403005-General | SR2: G403006-General | SS2: G403007-General | ST2: G403008-General | SU2: G403009-General | SV2: G403090-General | SW2: G409001-General | SX2: G409002-General | SY2: G409003-General | SZ2: G409090-General | TA2: G901001-General | TB2: G901002-General | TC2: G909001-General | TD2: G909002-General | TE2: G909003-General | TF2: G909090-General | TG2: H101001-General | TH2: H101002-General | TI2: H101003-General | TJ2: H101004-General | TK2: H101005-General | TL2: H101006-General | TM2: H101007-General | TN2: H101008-General | TO2: H101009-General | TP2: H101010-General | TQ2: H102001-General | TR2: H102002-General | TS2: H102003-General | TT2: H102004-General | TU2: H103001-General | TV2: H103002-General | TW2: H103003-General | TX2: H103004-General | TY2: H103005-General | TZ2: H103006-General | UA2: H103007-General | UB2: H103008-General | UC2: H103009-General | UD2: H103010-General | UE2: H103011-General | UF2: H104001-General | UG2: H104002-General | UH2: H104003-General | UI2: H104004-General | UJ2: H104005-General | UK2: H104006-General | UL2: H301001-General | UM2: H301002-General | UN2: H302001-General | UO2: H302002-General | UP2: H302003-General | UQ2: H402001-General | UR2: H402002-General | US2: H402003-General | UT2: H501001-General | UU2: H501002-General | UV2: H501003-General | UW2: H501004-General | UX2: H501005-General | UY2: H501006-General | UZ2: H501007-General | VA2: H501008-General | VB2: H502001-General | VC2: H502002-General | VD2: H502003-General | VE2: H502004-General | VF2: H502005-General | VG2: H502006-General | VH2: H503001-General | VI2: H503002-General
A3: A101001-General | B3: A101002-Column Pier - Concrete | C3: A101003-Other | D3: A101090-Other | E3: A102001-General | F3: A102002-Other | G3: A102003-Other | H3: A102004-Other | I3: A102005-Other | J3: A102006-Other | K3: A102090-Other | L3: A103001-Other | M3: A103002-Other | N3: A103003-Other | O3: A103004-Other | P3: A103005-Other | Q3: A103090-Other | R3: A201001-Other | S3: A201002-Other | T3: A201003-Other | U3: A201090-Other | V3: A202001-Concrete Block | W3: A202002-Other | X3: A202003-Other | Y3: A202090-Other | Z3: B101001-Beam/Girder - Concrete | AA3: B101002-Concrete | AB3: B101003-Deck - Composite w/Structural Beam | AC3: B101004-Other | AD3: B101005-Other | AE3: B101006-Other | AF3: B101007-Other | AG3: B101090-Other | AH3: B102001-Beam/Girder - Concrete | AI3: B102002-Concrete | AJ3: B102003-Deck - Fiber Cement | AK3: B102004-Other | AL3: B102090-Other | AM3: B201001-Brick Veneer w/CMU Backup | AN3: B201002-Other | AO3: B201003-General | AP3: B201004-Other | AQ3: B201005-Other | AR3: B201006-Handrailing | AS3: B201007-Other | AT3: B201008-Other | AU3: B201009-Other | AV3: B201010-Other | AW3: B201011-Other | AX3: B201012-Other | AY3: B201090-Other | AZ3: B202001-Exterior Glazing | BA3: B202002-Other | BB3: B202003-Other | BC3: B202090-Other | BD3: B203001-General | BE3: B203002-Other | BF3: B203003-General | BG3: B203004-Aluminum/Fiberglass, Manual, 12 FT x 12 Ft | BH3: B203005-Other | BI3: B203006-Other | BJ3: B203007-Other | BK3: B203008-Other | BL3: B203090-General | BM3: B203091-Other | BN3: B301001-Asphalt Shingles | BO3: B301002-General | BP3: B301003-Fiberglass Batts | BQ3: B301004-Flashings - Base | BR3: B301005-General | BS3: B301006-Gravity Ventilator | BT3: B301090-Other | BU3: C101001-Other | BV3: C101002-Other | BW3: C101003-Other | BX3: C101004-Guardrail | BY3: C101005-Interior Windows | BZ3: C101006-Other | CA3: C101007-Other | CB3: C101008-Other | CC3: C101090-Other | CD3: C102001-Metal Door | CE3: C102002-Other | CF3: C102003-Fire Door - Sliding | CG3: C102004-Other | CH3: C102005-Metal | CI3: C102006-Other | CJ3: C102007-Other | CK3: C102090-General | CL3: C102091-General | CM3: C103001-Other | CN3: C103002-Other | CO3: C103003-Other | CP3: C103004-Other | CQ3: C103005-Other | CR3: C103006-Other | CS3: C103007-Other | CT3: C103008-Corian | CU3: C103009-Other | CV3: C103010-Other | CW3: C103011-Other | CX3: C103012-Other | CY3: C103013-Other | CZ3: C103014-General | DA3: C103015-Other | DB3: C103090-Ladder | DC3: C201001-Exterior Stairs - Concrete (12 Riser Flight) | DD3: C201002-Other | DE3: C201090-Other | DF3: C301001-Other | DG3: C301002-Other | DH3: C301003-Other | DI3: C301004-Other | DJ3: C301005-Laminated Plastic | DK3: C301006-Other | DL3: C301090-Other | DM3: C302001-General | DN3: C302002-Other | DO3: C302003-Other | DP3: C302004-Cork Tile | DQ3: C302005-General | DR3: C302006-Other | DS3: C302007-Other | DT3: C302008-Other | DU3: C302009-Other | DV3: C302010-Epoxy | DW3: C302011-Other | DX3: C302090-Other | DY3: C303001-Other | DZ3: C303002-Other | EA3: C303003-Other | EB3: C303004-Other | EC3: C303005-Other | ED3: C303006-Other | EE3: C303090-General | EF3: C304001-Other | EG3: C304002-Other | EH3: C304003-Other | EI3: C304004-Other | EJ3: C304005-Other | EK3: C304006-Other | EL3: C304007-Other | EM3: D101001-Other | EN3: D101002-Hydraulic Elevators - 1500 lb, 2 floors | EO3: D101003-Hydraulic Elevators - (class"B"), 10,000 lb, 2 floors | EP3: D101004-Inclined, stair climber | EQ3: D101005-Electric | ER3: D101090-Correspondence lifts, hand | ES3: D102001-Other | ET3: D102002-Cranes, Bridge girder, 10 ton, 30 Ft span | EU3: D102003-Other | EV3: D103001-10 Ft hieght, 48 In width | EW3: D103002-Flat, 3 Ft-4 In width | EX3: D103090-Other | EY3: D109001-Other | EZ3: D109002-Horizontal belt, 27 Ft length | FA3: D109003-Chute - Personnel | FB3: D109004-Other | FC3: D109005-Other | FD3: D109006-Other | FE3: D109090-Other | FF3: D201001-Other | FG3: D201002-Other | FH3: D201003-Other | FI3: D201004-Group Wash Fountain | FJ3: D201005-Combo Unit (Shower / Tub) | FK3: D201006-General | FL3: D201007-Other | FM3: D201090-Emergency Shower | FN3: D202001-Black / Galvanized Steel 1 In-2 In Pipe | FO3: D202002-Backflow Preventer - 1 In Pipe | FP3: D202003-Booster Pump - 1 HP | FQ3: D202004-Other | FR3: D202005-Other | FS3: D202090-Other | FT3: D203001-Other | FU3: D203002-Other | FV3: D203003-Other | FW3: D203004-Backflow Preventer - > 6 In Pipe | FX3: D203005-Other | FY3: D203090-Other | FZ3: D204001-Other | GA3: D204002-Other | GB3: D204003-Other | GC3: D204004-Other | GD3: D204090-Other | GE3: D209001-Other | GF3: D209002-Other | GG3: D209003-Other | GH3: D209004-Other | GI3: D209005-Other | GJ3: D209090-Other | GK3: D301001-Other | GL3: D301002-Fuel Storage Tank - Fuel Storage Tank, 1000 GAL | GM3: D301003-Other | GN3: D301004-Other | GO3: D301005-Closed Loop, Space/Hot Water Systems | GP3: D301006-Other | GQ3: D301007-Other | GR3: D301090-Ice Bank | GS3: D302001-Electric, Hot Water - <22 KW, <78 MBH | GT3: D302002-Electric, 17.1 MBH | GU3: D302003-Gas - 100 MBH | GV3: D302004-Air Separator - Air control, air separator, 10 In diameter, includes strainer | GW3: D302005-Other | GX3: D302090-Other | GY3: D303001-Chiller, Absorption, Gas, Water Cooled - 800 TN | GZ3: D303002-Condenser, DX, Air Cooled - Belt Drive, 101 ton, R-22 | HA3: D303090-Other | HB3: D304001-Dehumidifier - 1.5 lb./Hr., 50 CFM | HC3: D304002-Other | HD3: D304003-Circulating Pump, Double Suction - 10 In size, 150 HP, to 4000 GPM | HE3: D304004-Other | HF3: D304005-Other | HG3: D304006-Circulating Pump, Double Suction - 10 In size, 150 HP, to 4000 GPM | HH3: D304007-Ceiling Vents, Passive - Passive < 50 CFM | HI3: D304008-Central Station - 2000 CFM | HJ3: D304090-Other | HK3: D305001-Fan System, Axial | HL3: D305002-Hydronic | HM3: D305003-Cab Mount, Four Pipe - 1 ton | HN3: D305004-Baseboard Heating - 1 In Copper Tube | HO3: D305005-208-240 volt, 15 kW | HP3: D305006-A/C Unit, Computer Room - Air Cooled, 10 ton | HQ3: D305090-Other | HR3: D306001-Other | HS3: D306002-analog inputs, sensors (avg. 50 Ft run in 1/2 In EMT), duct humidity, +/- 3% | HT3: D306003-air supply for pneumatic, tank mounted duplex compressor, sterter, alternat | HU3: D306004-Other | HV3: D306005-Other | HW3: D306090-Other | HX3: D307001-Other | HY3: D307002-Other | HZ3: D307003-Other | IA3: D307090-Other | IB3: D309001-Other | IC3: D309002-Other | ID3: D309090-Other | IE3: D401001-Fire Alarm Control Panel, multizone (4) | IF3: D401002-Battery standby power 10 In x 10 In x 17 In | IG3: D402001-Air Dryer | IH3: D402002-5 In pump, 100 HP, 1000 GPM | II3: D403001-Fire Hose Equipment - Fire pump, diesel, with controller, 10 In pump, 300 HP, 3500 GPM, 100 psi | IJ3: D404001-Deluge Systems - extra hazard | IK3: D404002-Other | IL3: D405001-Dispersion nozzle, carbon dioxide 3 In x 5In dispersion nozzle | IM3: D409001-Other | IN3: D409002-Other | IO3: D409003-Other | IP3: D409004-Other | IQ3: D409090-Other | IR3: D501001-Other | IS3: D501002-Electrical Service - 3 Phase, 120/208 V, 1000 A | IT3: D501003-Buck-boost, 120/240 V primary 12/24 V secondary, 0.25 kVA | IU3: D501004-Main lugs, 50 amp | IV3: D501005-Main circuit breaker, 120/208 V, 100 amp, NQOD | IW3: D501006-Motor Control Center - Size 1, 10 HP, 12 In high | IX3: D501090-Capacitor Bank - 240 V, 0.5 kVAR | IY3: D502001-Other | IZ3: D502002-Explosion Proof Lighting | JA3: D502090-Other | JB3: D503001-Other | JC3: D503002-12 outlets | JD3: D503003-12 stations | JE3: D503004-Other | JF3: D503005-Other | JG3: D503006-Other | JH3: D503007-Other | JI3: D503090-Other | JJ3: D509001-Other | JK3: D509002-Emergency Lighting - Lead battery, twin sealed beam light | JL3: D509003-Other | JM3: D509004-Other | JN3: D509005-Other | JO3: D509006-Other | JP3: D509090-Other | JQ3: E101001-Other | JR3: E101002-Other | JS3: E101003-Other | JT3: E101004-Other | JU3: E101005-Other | JV3: E101006-Other | JW3: E101007-Other | JX3: E101008-Other | JY3: E102001-Other | JZ3: E102002-Other | KA3: E102003-Other | KB3: E102004-Other | KC3: E102005-Other | KD3: E102006-Other | KE3: E102007-Other | KF3: E102008-Other | KG3: E102009-Other | KH3: E102010-Other | KI3: E103001-Other | KJ3: E103002-Loading Dock Equipment - Dock Leveler, hydraulic, 7 Ft x 8 Ft, 10 ton | KK3: E103003-Other | KL3: E103004-Automotive lifts (Hydraulic), clear floor, 2 post, 6000 lb | KM3: E109001-Other | KN3: E109002-Other | KO3: E109003-Other | KP3: E109004-Other | KQ3: E109005-Other | KR3: E109006-Other | KS3: E109007-Other | KT3: E109008-Other | KU3: E109009-Other | KV3: E109010-Other | KW3: E109090-Other | KX3: E201001-Other | KY3: E201002-Other | KZ3: E201003-Other | LA3: E201004-Other | LB3: E201090-Other | LC3: E202001-Other | LD3: E202002-Other | LE3: E202003-Other | LF3: E202004-Other | LG3: E202005-Other | LH3: E202006-Other | LI3: E202090-Other | LJ3: F101001-Other | LK3: F101002-Other | LL3: F101003-Other | LM3: F101090-Other | LN3: F102001-General | LO3: F102002-Other | LP3: F102090-Other | LQ3: F103001-Other | LR3: F103002-Other | LS3: F103003-Other | LT3: F103090-Other | LU3: F104001-Other | LV3: F104002-Other | LW3: F104003-Other | LX3: F104004-Other | LY3: F104005-Other | LZ3: F104090-Other | MA3: F105001-Other | MB3: F105002-Other | MC3: F105090-Other | MD3: F201001-Other | ME3: F201002-Other | MF3: F201003-Other | MG3: F201004-Other | MH3: F201005-Other | MI3: F201006-Other | MJ3: F201007-Other | MK3: F201008-Other | ML3: F201090-Other | MM3: F202001-Other | MN3: F202002-Other | MO3: F202003-Other | MP3: F202004-Other | MQ3: F202005-Other | MR3: F202006-Other | MS3: F202007-Other | MT3: F202008-Other | MU3: F202090-Other | MV3: G101001-Other | MW3: G101002-Other | MX3: G101003-Other | MY3: G101004-Other | MZ3: G101005-Other | NA3: G101006-Other | NB3: G101090-Other | NC3: G102001-Other | ND3: G102002-Other | NE3: G102003-Other | NF3: G102004-Other | NG3: G102005-Other | NH3: G102006-Other | NI3: G102007-Other | NJ3: G102090-Other | NK3: G103001-Other | NL3: G103002-Other | NM3: G103003-Other | NN3: G103004-Other | NO3: G103005-Other | NP3: G103006-Other | NQ3: G103007-Other | NR3: G103008-Other | NS3: G103009-Other | NT3: G103010-Other | NU3: G103011-Other | NV3: G103090-Other | NW3: G104001-Other | NX3: G104002-Other | NY3: G104090-Other | NZ3: G201001-Other | OA3: G201002-Other | OB3: G201003-Other | OC3: G201004-Other | OD3: G201005-Other | OE3: G201006-Other | OF3: G201090-Other | OG3: G202001-Other | OH3: G202002-Other | OI3: G202003-Other | OJ3: G202004-Other | OK3: G202005-Other | OL3: G202006-Other | OM3: G202007-Other | ON3: G202090-Other | OO3: G203001-Other | OP3: G203002-Other | OQ3: G203003-Other | OR3: G203004-Other | OS3: G203005-Other | OT3: G203090-Other | OU3: G204001-Fence/Privacy Wall - Concrete | OV3: G204002-General | OW3: G204003-Other | OX3: G204004-Other | OY3: G204005-Other | OZ3: G204006-Other | PA3: G204007-Other | PB3: G204008-Other | PC3: G204009-Other | PD3: G204090-Other | PE3: G205001-Other | PF3: G205002-Other | PG3: G205003-Other | PH3: G205004-Other | PI3: G205005-Other | PJ3: G205006-Other | PK3: G205007-Other | PL3: G205090-Other | PM3: G206001-Other | PN3: G206002-Other | PO3: G206003-Other | PP3: G206004-Other | PQ3: G206005-Other | PR3: G301001-Other | PS3: G301002-Other | PT3: G301003-Other | PU3: G301004-Other | PV3: G301005-Other | PW3: G301006-Other | PX3: G301007-Other | PY3: G301008-Other | PZ3: G301090-Other | QA3: G302001-Other | QB3: G302002-Other | QC3: G302003-Other | QD3: G302004-Other | QE3: G302005-Other | QF3: G302006-Other | QG3: G302090-Other | QH3: G303001-Other | QI3: G303002-Other | QJ3: G303003-Other | QK3: G303004-Other | QL3: G303005-Other | QM3: G303006-Other | QN3: G303007-Other | QO3: G303090-Other | QP3: G304001-Other | QQ3: G304002-Other | QR3: G304003-Other | QS3: G304004-Other | QT3: G304005-Other | QU3: G304006-Other | QV3: G304090-Other | QW3: G305001-Other | QX3: G305002-Other | QY3: G305003-Other | QZ3: G305004-Other | RA3: G305005-Other | RB3: G305006-Other | RC3: G305090-Other | RD3: G306001-Other | RE3: G306002-Other | RF3: G306003-Other | RG3: G306004-Other | RH3: G306005-Other | RI3: G306006-Other | RJ3: G306007-Other | RK3: G306008-Other | RL3: G306009-Other | RM3: G306090-Other | RN3: G309001-Other | RO3: G309002-Other | RP3: G309003-Other | RQ3: G309004-Other | RR3: G309005-Other | RS3: G309090-Other | RT3: G401001-Other | RU3: G401002-Other | RV3: G401003-Other | RW3: G401004-Other | RX3: G401005-Other | RY3: G401006-Other | RZ3: G401007-Other | SA3: G401008-Other | SB3: G401009-Other | SC3: G401010-Other | SD3: G401011-Other | SE3: G401090-Other | SF3: G402001-Other | SG3: G402002-Other | SH3: G402003-Other | SI3: G402004-Other | SJ3: G402005-Other | SK3: G402006-Other | SL3: G402007-Other | SM3: G403001-Other | SN3: G403002-Other | SO3: G403003-Other | SP3: G403004-Other | SQ3: G403005-Other | SR3: G403006-Other | SS3: G403007-Other | ST3: G403008-Other | SU3: G403009-Other | SV3: G403090-Other | SW3: G409001-Other | SX3: G409002-Other | SY3: G409003-Other | SZ3: G409090-Other | TA3: G901001-Other | TB3: G901002-Other | TC3: G909001-Other | TD3: G909002-Other | TE3: G909003-Other | TF3: G909090-Other | TG3: H101001-Other | TH3: H101002-Other | TI3: H101003-Other | TJ3: H101004-Other | TK3: H101005-Other | TL3: H101006-Other | TM3: H101007-Other | TN3: H101008-Other | TO3: H101009-Other | TP3: H101010-Other | TQ3: H102001-Other | TR3: H102002-Other | TS3: H102003-Other | TT3: H102004-Other | TU3: H103001-Other | TV3: H103002-Other | TW3: H103003-Other | TX3: H103004-Other | TY3: H103005-Other | TZ3: H103006-Other | UA3: H103007-Other | UB3: H103008-Other | UC3: H103009-Other | UD3: H103010-Other | UE3: H103011-Other | UF3: H104001-Other | UG3: H104002-Other | UH3: H104003-Other | UI3: H104004-Other | UJ3: H104005-Other | UK3: H104006-Other | UL3: H301001-Other | UM3: H301002-Other | UN3: H302001-Other | UO3: H302002-Other | UP3: H302003-Other | UQ3: H402001-Other | UR3: H402002-Other | US3: H402003-Other | UT3: H501001-Other | UU3: H501002-Other | UV3: H501003-Other | UW3: H501004-Other | UX3: H501005-Other | UY3: H501006-Other | UZ3: H501007-Other | VA3: H501008-Other | VB3: H502001-Other | VC3: H502002-Other | VD3: H502003-Other | VE3: H502004-Other | VF3: H502005-Other | VG3: H502006-Other | VH3: H503001-Other | VI3: H503002-Other
A4: A101001-Grade Beams | B4: A101002-Column Pier - Steel | C4: A101003-Unknown | D4: A101090-Unknown | E4: A102001-Other | F4: A102002-Unknown | G4: A102003-Unknown | H4: A102004-Unknown | I4: A102005-Unknown | J4: A102006-Unknown | K4: A102090-Unknown | L4: A103001-Unknown | M4: A103002-Unknown | N4: A103003-Unknown | O4: A103004-Unknown | P4: A103005-Unknown | Q4: A103090-Unknown | R4: A201001-Unknown | S4: A201002-Unknown | T4: A201003-Unknown | U4: A201090-Unknown | V4: A202001-General | W4: A202002-Unknown | X4: A202003-Unknown | Y4: A202090-Unknown | Z4: B101001-Beam/Girder - Metal | AA4: B101002-General | AB4: B101003-Deck - Light Gauge Steel | AC4: B101004-Unknown | AD4: B101005-Unknown | AE4: B101006-Unknown | AF4: B101007-Unknown | AG4: B101090-Unknown | AH4: B102001-Beam/Girder - Metal | AI4: B102002-General | AJ4: B102003-Deck - Fiberglass | AK4: B102004-Unknown | AL4: B102090-Unknown | AM4: B201001-Brick Veneer w/Stud Backup | AN4: B201002-Unknown | AO4: B201003-Other | AP4: B201004-Unknown | AQ4: B201005-Unknown | AR4: B201006-Ladder | AS4: B201007-Unknown | AT4: B201008-Unknown | AU4: B201009-Unknown | AV4: B201010-Unknown | AW4: B201011-Unknown | AX4: B201012-Unknown | AY4: B201090-Unknown | AZ4: B202001-General | BA4: B202002-Unknown | BB4: B202003-Unknown | BC4: B202090-Unknown | BD4: B203001-Other | BE4: B203002-Unknown | BF4: B203003-Manual | BG4: B203004-General | BH4: B203005-Steel | BI4: B203006-Unknown | BJ4: B203007-Unknown | BK4: B203008-Unknown | BL4: B203090-Other | BM4: B203091-Unknown | BN4: B301001-Clay Tile | BO4: B301002-Liquid Elastomers | BP4: B301003-General | BQ4: B301004-Flashings - Cap | BR4: B301005-Gutters | BS4: B301006-Gravity Ventilator - 12 In Diameter | BT4: B301090-Unknown | BU4: C101001-Security Cage / Wire Mesh | BV4: C101002-Unknown | BW4: C101003-Unknown | BX4: C101004-Other | BY4: C101005-Metal Rollup / Coiling Grille | BZ4: C101006-Unknown | CA4: C101007-Unknown | CB4: C101008-Unknown | CC4: C101090-Unknown | CD4: C102001-Other | CE4: C102002-Unknown | CF4: C102003-Fire Door - Sliding, Metal | CG4: C102004-Rolling, Steel, Electric, 10 FT x 10 Ft | CH4: C102005-Other | CI4: C102006-Unknown | CJ4: C102007-Unknown | CK4: C102090-Other | CL4: C102091-Other | CM4: C103001-Shower Compartment | CN4: C103002-Unknown | CO4: C103003-Unknown | CP4: C103004-Unknown | CQ4: C103005-Unknown | CR4: C103006-Unknown | CS4: C103007-Unknown | CT4: C103008-General | CU4: C103009-Unknown | CV4: C103010-Unknown | CW4: C103011-Unknown | CX4: C103012-Unknown | CY4: C103013-Unknown | CZ4: C103014-Other | DA4: C103015-Unknown | DB4: C103090-Other | DC4: C201001-Exterior Stairs - Concrete (24 Riser Flight) | DD4: C201002-Unknown | DE4: C201090-Unknown | DF4: C301001-Unknown | DG4: C301002-Unknown | DH4: C301003-Unknown | DI4: C301004-Tile | DJ4: C301005-Metal Panel | DK4: C301006-Unknown | DL4: C301090-Unknown | DM4: C302001-Marble Tile | DN4: C302002-Unknown | DO4: C302003-Unknown | DP4: C302004-General | DQ4: C302005-Other | DR4: C302006-Quarry Tile | DS4: C302007-Unknown | DT4: C302008-Unknown | DU4: C302009-Paint | DV4: C302010-General | DW4: C302011-Unknown | DX4: C302090-Unknown | DY4: C303001-Unknown | DZ4: C303002-Unknown | EA4: C303003-Unknown | EB4: C303004-Unknown | EC4: C303005-Unknown | ED4: C303006-Unknown | EE4: C303090-Other | EF4: C304001-Unknown | EG4: C304002-Unknown | EH4: C304003-Unknown | EI4: C304004-Unknown | EJ4: C304005-Unknown | EK4: C304006-Unknown | EL4: C304007-Unknown | EM4: D101001-Unknown | EN4: D101002-Hydraulic Elevators - 1500 lb, 5 floors | EO4: D101003-Hydraulic Elevators - (class"B"), 10,000 lb, 5 floors | EP4: D101004-Inclined, stair lift | EQ4: D101005-General | ER4: D101090-General | ES4: D102001-Unknown | ET4: D102002-Cranes, Bridge girder, 10 ton, 40 Ft span | EU4: D102003-Unknown | EV4: D103001-15 Ft hieght, 32 In width | EW4: D103002-General | EX4: D103090-Unknown | EY4: D109001-Unknown | EZ4: D109002-Horizontal belt, 42 Ft length | FA4: D109003-Chutes | FB4: D109004-Unknown | FC4: D109005-Unknown | FD4: D109006-Unknown | FE4: D109090-Unknown | FF4: D201001-Stainless | FG4: D201002-Stainless | FH4: D201003-Stainless | FI4: D201004-Kitchen Sink | FJ4: D201005-General | FK4: D201006-Other | FL4: D201007-Unknown | FM4: D201090-General | FN4: D202001-Black / Galvanized Steel 2 In-4 In Pipe | FO4: D202002-Backflow Preventer - 1.5 In Pipe | FP4: D202003-Booster Pump - 1.5 HP | FQ4: D202004-Unknown | FR4: D202005-Unknown | FS4: D202090-Unknown | FT4: D203001-Unknown | FU4: D203002-Unknown | FV4: D203003-Unknown | FW4: D203004-Backflow Preventer - 2 In Pipe | FX4: D203005-Unknown | FY4: D203090-Unknown | FZ4: D204001-Unknown | GA4: D204002-Unknown | GB4: D204003-Sump Pump - Duplex | GC4: D204004-Unknown | GD4: D204090-Unknown | GE4: D209001-Unknown | GF4: D209002-Unknown | GG4: D209003-Unknown | GH4: D209004-Unknown | GI4: D209005-Unknown | GJ4: D209090-Unknown | GK4: D301001-Unknown | GL4: D301002-Fuel Storage Tank - Fuel Storage Tank, 2500 GAL | GM4: D301003-Unknown | GN4: D301004-Unknown | GO4: D301005-General | GP4: D301006-Unknown | GQ4: D301007-Unknown | GR4: D301090-Other | GS4: D302001-Electric, Hot Water - 22-45 KW, 78-154 MBH | GT4: D302002-Electric, 27.3 MBH | GU4: D302003-Gas - 160 MBH | GV4: D302004-Air Separator - Air control, air separator, 12 In diameter, includes strainer | GW4: D302005-Unknown | GX4: D302090-Unknown | GY4: D303001-Chiller, Absorption, Gas, Water Cooled - 10 TN | GZ4: D303002-Condenser, DX, Air Cooled - Belt Drive, 159 ton, R-22 | HA4: D303090-Refrigeration Compressor | HB4: D304001-Dehumidifier - 1060 to 1375 lb./Hr., 40,000 CFM | HC4: D304002-Unknown | HD4: D304003-Circulating Pump, Double Suction - 6 In size, 50 HP, to 1200 GPM | HE4: D304004-Unknown | HF4: D304005-Unknown | HG4: D304006-Circulating Pump, Double Suction - 6 In size, 50 HP, to 1200 GPM | HH4: D304007-Ceiling Vents, Passive - Passive > 300 CFM | HI4: D304008-Central Station - 5000 CFM | HJ4: D304090-Unknown | HK4: D305001-Fan System, Centrifugal In-Line | HL4: D305002-Hydronic - 100 MBH | HM4: D305003-Cab Mount, Four Pipe - 1/2 ton | HN4: D305004-Baseboard Heating - 1/2 In Copper Tube | HO4: D305005-208-240 volt, 20 kW | HP4: D305006-A/C Unit, Computer Room - Air Cooled, 15 ton | HQ4: D305090-Unknown | HR4: D306001-Unknown | HS4: D306002-analog inputs, sensors (avg. 50 Ft run in 1/2 In EMT), duct static pressure | HT4: D306003-air supply for pneumatic, tank mounted duplex compressor, sterter, alternat | HU4: D306004-Unknown | HV4: D306005-Unknown | HW4: D306090-Unknown | HX4: D307001-Unknown | HY4: D307002-Unknown | HZ4: D307003-Unknown | IA4: D307090-Unknown | IB4: D309001-Unknown | IC4: D309002-Unknown | ID4: D309090-Unknown | IE4: D401001-Fire Alarm Control Panel, single zone | IF4: D401002-Bell signalling device | IG4: D402001-Backflow Preventer | IH4: D402002-5 In pump, 40 HP, 1000 GPM | II4: D403001-Fire Hose Equipment - Fire pump, diesel, with controller, 6 In pump, 140 HP, 1500 GPM, 100 psi | IJ4: D404001-Deluge Systems - light hazard | IK4: D404002-Unknown | IL4: D405001-Dispersion nozzle, FM200 1-1/2 In dispersion nozzle | IM4: D409001-Unknown | IN4: D409002-Unknown | IO4: D409003-Unknown | IP4: D409004-Unknown | IQ4: D409090-Unknown | IR4: D501001-Unknown | IS4: D501002-Electrical Service - 3 Phase, 120/208 V, 1200 A | IT4: D501003-Buck-boost, 120/240 V primary 12/24 V secondary, 0.50 kVA | IU4: D501004-Main lugs, 120/208 V, 100 amp, NQOD | IV4: D501005-Main circuit breaker, 120/208 V, 225 amp, NQOD | IW4: D501006-Motor Control Center - Size 2, 25 HP, 18 In high | IX4: D501090-Capacitor Bank - 240 V, 1.0 kVAR | IY4: D502001-Unknown | IZ4: D502002-Explosion Proof Lighting - Fluorescent, ceiling mounted, 2-40 W, 4 Ft L | JA4: D502090-Unknown | JB4: D503001-Unknown | JC4: D503002-30 outlets | JD4: D503003-25 stations | JE4: D503004-Unknown | JF4: D503005-Unknown | JG4: D503006-Unknown | JH4: D503007-Unknown | JI4: D503090-Unknown | JJ4: D509001-Unknown | JK4: D509002-Emergency Lighting - Nickel cadmium battery, twin sealed beam light | JL4: D509003-Unknown | JM4: D509004-Unknown | JN4: D509005-Unknown | JO4: D509006-Unknown | JP4: D509090-Unknown | JQ4: E101001-Unknown | JR4: E101002-Unknown | JS4: E101003-Unknown | JT4: E101004-Unknown | JU4: E101005-Security Vault | JV4: E101006-Unknown | JW4: E101007-Unknown | JX4: E101008-Unknown | JY4: E102001-Unknown | JZ4: E102002-Unknown | KA4: E102003-Unknown | KB4: E102004-Unknown | KC4: E102005-Unknown | KD4: E102006-Unknown | KE4: E102007-Unknown | KF4: E102008-Unknown | KG4: E102009-Unknown | KH4: E102010-Unknown | KI4: E103001-Unknown | KJ4: E103002-Loading Dock Equipment - Dock Lift, platform type, 6 Ft x 6 Ft, portable, 3000 lb | KK4: E103003-Unknown | KL4: E103004-Automotive lifts (Hydraulic), clear floor, 2 post, 9000 lb | KM4: E109001-Unknown | KN4: E109002-Unknown | KO4: E109003-Unknown | KP4: E109004-Unknown | KQ4: E109005-Unknown | KR4: E109006-Unknown | KS4: E109007-Unknown | KT4: E109008-Unknown | KU4: E109009-Unknown | KV4: E109010-Unknown | KW4: E109090-Unknown | KX4: E201001-Unknown | KY4: E201002-Unknown | KZ4: E201003-Seating - Auditorium/Stadium | LA4: E201004-Unknown | LB4: E201090-Unknown | LC4: E202001-Unknown | LD4: E202002-Unknown | LE4: E202003-Unknown | LF4: E202004-Unknown | LG4: E202005-Unknown | LH4: E202006-Unknown | LI4: E202090-Unknown | LJ4: F101001-Unknown | LK4: F101002-Unknown | LL4: F101003-Unknown | LM4: F101090-Unknown | LN4: F102001-Other | LO4: F102002-Unknown | LP4: F102090-Unknown | LQ4: F103001-Unknown | LR4: F103002-Unknown | LS4: F103003-Unknown | LT4: F103090-Unknown | LU4: F104001-Unknown | LV4: F104002-Unknown | LW4: F104003-Unknown | LX4: F104004-Unknown | LY4: F104005-Unknown | LZ4: F104090-Unknown | MA4: F105001-Unknown | MB4: F105002-Unknown | MC4: F105090-Unknown | MD4: F201001-Unknown | ME4: F201002-Unknown | MF4: F201003-Unknown | MG4: F201004-Unknown | MH4: F201005-Unknown | MI4: F201006-Unknown | MJ4: F201007-Unknown | MK4: F201008-Unknown | ML4: F201090-Unknown | MM4: F202001-Unknown | MN4: F202002-Unknown | MO4: F202003-Unknown | MP4: F202004-Unknown | MQ4: F202005-Unknown | MR4: F202006-Unknown | MS4: F202007-Unknown | MT4: F202008-Unknown | MU4: F202090-Unknown | MV4: G101001-Unknown | MW4: G101002-Unknown | MX4: G101003-Unknown | MY4: G101004-Unknown | MZ4: G101005-Unknown | NA4: G101006-Unknown | NB4: G101090-Unknown | NC4: G102001-Unknown | ND4: G102002-Unknown | NE4: G102003-Unknown | NF4: G102004-Unknown | NG4: G102005-Unknown | NH4: G102006-Unknown | NI4: G102007-Unknown | NJ4: G102090-Unknown | NK4: G103001-Unknown | NL4: G103002-Unknown | NM4: G103003-Unknown | NN4: G103004-Unknown | NO4: G103005-Unknown | NP4: G103006-Unknown | NQ4: G103007-Unknown | NR4: G103008-Unknown | NS4: G103009-Unknown | NT4: G103010-Unknown | NU4: G103011-Unknown | NV4: G103090-Unknown | NW4: G104001-Unknown | NX4: G104002-Unknown | NY4: G104090-Unknown | NZ4: G201001-Unknown | OA4: G201002-Unknown | OB4: G201003-Unknown | OC4: G201004-Unknown | OD4: G201005-Unknown | OE4: G201006-Unknown | OF4: G201090-Unknown | OG4: G202001-Unknown | OH4: G202002-Unknown | OI4: G202003-Unknown | OJ4: G202004-Unknown | OK4: G202005-Unknown | OL4: G202006-Unknown | OM4: G202007-Unknown | ON4: G202090-Unknown | OO4: G203001-Unknown | OP4: G203002-Unknown | OQ4: G203003-Unknown | OR4: G203004-Unknown | OS4: G203005-Unknown | OT4: G203090-Unknown | OU4: G204001-Fence/Privacy Wall - Masonry | OV4: G204002-Masonry | OW4: G204003-Unknown | OX4: G204004-Unknown | OY4: G204005-Unknown | OZ4: G204006-Unknown | PA4: G204007-Unknown | PB4: G204008-Unknown | PC4: G204009-Unknown | PD4: G204090-Unknown | PE4: G205001-Unknown | PF4: G205002-Unknown | PG4: G205003-Unknown | PH4: G205004-Unknown | PI4: G205005-Unknown | PJ4: G205006-Unknown | PK4: G205007-Unknown | PL4: G205090-Unknown | PM4: G206001-Unknown | PN4: G206002-Unknown | PO4: G206003-Unknown | PP4: G206004-Unknown | PQ4: G206005-Unknown | PR4: G301001-Unknown | PS4: G301002-Unknown | PT4: G301003-Unknown | PU4: G301004-Unknown | PV4: G301005-Unknown | PW4: G301006-Unknown | PX4: G301007-Unknown | PY4: G301008-Unknown | PZ4: G301090-Unknown | QA4: G302001-Unknown | QB4: G302002-Unknown | QC4: G302003-Unknown | QD4: G302004-Unknown | QE4: G302005-Unknown | QF4: G302006-Unknown | QG4: G302090-Unknown | QH4: G303001-Unknown | QI4: G303002-Unknown | QJ4: G303003-Unknown | QK4: G303004-Unknown | QL4: G303005-Unknown | QM4: G303006-Unknown | QN4: G303007-Unknown | QO4: G303090-Unknown | QP4: G304001-Unknown | QQ4: G304002-Unknown | QR4: G304003-Unknown | QS4: G304004-Unknown | QT4: G304005-Unknown | QU4: G304006-Unknown | QV4: G304090-Unknown | QW4: G305001-Unknown | QX4: G305002-Unknown | QY4: G305003-Unknown | QZ4: G305004-Unknown | RA4: G305005-Unknown | RB4: G305006-Unknown | RC4: G305090-Unknown | RD4: G306001-Unknown | RE4: G306002-Unknown | RF4: G306003-Unknown | RG4: G306004-Unknown | RH4: G306005-Unknown | RI4: G306006-Unknown | RJ4: G306007-Unknown | RK4: G306008-Unknown | RL4: G306009-Unknown | RM4: G306090-Unknown | RN4: G309001-Unknown | RP4: G309003-Unknown | RQ4: G309004-Unknown | RR4: G309005-Unknown | RS4: G309090-Unknown | RT4: G401001-Unknown | RU4: G401002-Unknown | RV4: G401003-Unknown | RW4: G401004-Unknown | RX4: G401005-Unknown | RY4: G401006-Unknown | RZ4: G401007-Unknown | SA4: G401008-Unknown | SB4: G401009-Unknown | SC4: G401010-Unknown | SD4: G401011-Unknown | SE4: G401090-Unknown | SF4: G402001-Unknown | SG4: G402002-Unknown | SH4: G402003-Unknown | SI4: G402004-Unknown | SJ4: G402005-Unknown | SK4: G402006-Unknown | SL4: G402007-Unknown | SM4: G403001-Unknown | SN4: G403002-Unknown | SO4: G403003-Unknown | SP4: G403004-Unknown | SQ4: G403005-Unknown | SR4: G403006-Unknown | SS4: G403007-Unknown | ST4: G403008-Unknown | SU4: G403009-Unknown | SV4: G403090-Unknown | SW4: G409001-Unknown | SX4: G409002-Unknown | SY4: G409003-Unknown | SZ4: G409090-Unknown | TA4: G901001-Unknown | TB4: G901002-Unknown | TC4: G909001-Unknown | TD4: G909002-Unknown | TE4: G909003-Unknown | TF4: G909090-Unknown | TG4: H101001-Unknown | TH4: H101002-Unknown | TI4: H101003-Unknown | TJ4: H101004-Unknown | TK4: H101005-Unknown | TL4: H101006-Unknown | TM4: H101007-Unknown | TN4: H101008-Unknown | TO4: H101009-Unknown | TP4: H101010-Unknown | TQ4: H102001-Unknown | TR4: H102002-Unknown | TS4: H102003-Unknown | TT4: H102004-Unknown | TU4: H103001-Unknown | TV4: H103002-Unknown | TW4: H103003-Unknown | TX4: H103004-Unknown | TY4: H103005-Unknown | TZ4: H103006-Unknown | UA4: H103007-Unknown | UB4: H103008-Unknown | UC4: H103009-Unknown | UD4: H103010-Unknown | UE4: H103011-Unknown | UF4: H104001-Unknown | UG4: H104002-Unknown | UH4: H104003-Unknown | UI4: H104004-Unknown | UJ4: H104005-Unknown | UK4: H104006-Unknown | UL4: H301001-Unknown | UM4: H301002-Unknown | UN4: H302001-Unknown | UO4: H302002-Unknown | UP4: H302003-Unknown | UQ4: H402001-Unknown | UR4: H402002-Unknown | US4: H402003-Unknown | UT4: H501001-Unknown | UU4: H501002-Unknown | UV4: H501003-Unknown | UW4: H501004-Unknown | UX4: H501005-Unknown | UY4: H501006-Unknown | UZ4: H501007-Unknown | VA4: H501008-Unknown | VB4: H502001-Unknown | VC4: H502002-Unknown | VD4: H502003-Unknown | VE4: H502004-Unknown | VF4: H502005-Unknown | VG4: H502006-Unknown | VH4: H503001-Unknown | VI4: H503002-Unknown
A5: A101001-Other | B5: A101002-Column Pier - Wood | E5: A102001-PC Concrete | V5: A202001-Other | Z5: B101001-Beam/Girder - Wood | AA5: B101002-Other | AB5: B101003-Deck - Wood Beam and Joist | AH5: B102001-Beam/Girder - Wood | AI5: B102002-Other | AJ5: B102003-Deck - Gypsum | AM5: B201001-Cementitous Boards / Panels | AO5: B201003-Unknown | AR5: B201006-Other | AZ5: B202001-Other | BD5: B203001-Steel | BF5: B203003-Other | BG5: B203004-Other | BH5: B203005-Steel Bi-Fold | BL5: B203090-Unknown | BN5: B301001-Concrete Shingles | BO5: B301002-Modified Bitumen | BP5: B301003-Gypsum Fill | BQ5: B301004-Flashings - Embedded Edge Metal | BR5: B301005-Other | BS5: B301006-Gravity Ventilator - 12 In x 12 In | BT5: B301090-Walkway Protection | BU5: C101001-Unknown | BX5: C101004-Unknown | BY5: C101005-Other | CD5: C102001-Unknown | CF5: C102003-Fire Door - Sliding, Wood | CG5: C102004-Rolling, Steel, Electric, 12 FT x 12 Ft | CH5: C102005-Unknown | CK5: C102090-Rollup Grille, Aluminum, Electric, 10 FT x 10 Ft, bronze anodized | CL5: C102091-Unknown | CM5: C103001-Shower Compartment - Coated Steel | CT5: C103008-Granite | CZ5: C103014-Unknown | DB5: C103090-Unknown | DC5: C201001-Exterior Stairs - Metal (12 Riser Flight) | DI5: C301004-Unknown | DJ5: C301005-Other | DM5: C302001-Other | DP5: C302004-Other | DQ5: C302005-Unknown | DR5: C302006-Unknown | DU5: C302009-Unknown | DV5: C302010-Other | EE5: C303090-Plastic Covered Insulated Batts | EN5: D101002-Hydraulic Elevators - 2000 lb, 2 floors | EO5: D101003-Hydraulic Elevators - (class"B"), 20,000 lb, 2 floors | EP5: D101004-Other | EQ5: D101005-Hydraulic | ER5: D101090-Lifts | ET5: D102002-Cranes, Bridge girder, 10 ton, 50 Ft span | EV5: D103001-15 Ft hieght, 48 In width | EW5: D103002-Other | EZ5: D109002-Horizontal belt, 62 Ft length | FA5: D109003-General | FF5: D201001-Unknown | FG5: D201002-Unknown | FH5: D201003-Unknown | FI5: D201004-Laboratory Sink | FJ5: D201005-Other | FK5: D201006-Unknown | FM5: D201090-Other | FN5: D202001-Black / Galvanized Steel 4 In-6 In Pipe | FO5: D202002-Backflow Preventer - 2 In Pipe | FP5: D202003-Booster Pump - 10 HP | FW5: D203004-Backflow Preventer - 3 In Pipe | GB5: D204003-Sump Pump - Submersible | GL5: D301002-Fuel Storage Tank - Fuel Storage Tank, 5000 GAL | GO5: D301005-Other | GR5: D301090-Thermal Storage Tank | GS5: D302001-Electric, Hot Water - 45-90 KW, 154-308 MB | GT5: D302002-Electric, 34.1 MBH | GU5: D302003-Gas - 20 MBH | GV5: D302004-Air Separator - Air control, air separator, 2 In diameter, includes strainer | GY5: D303001-Chiller, Absorption, Gas, Water Cooled - 100 TN | GZ5: D303002-Condenser, DX, Air Cooled - Belt Drive, 228 ton, R-22 | HA5: D303090-Unknown | HB5: D304001-Dehumidifier - 120 to 155 lb./Hr., 4500 CFM | HD5: D304003-Circulating Pump, Double Suction - 8 In size, 100 HP, to 3000 GPM | HG5: D304006-Circulating Pump, Double Suction - 8 In size, 100 HP, to 3000 GPM | HH5: D304007-Ceiling Vents, Passive - Passive 110-180 CFM | HI5: D304008-Central Station - 5000 CFM, VAV | HK5: D305001-Fan System, Centrifugal In-Line - 10,000 CFM | HL5: D305002-Hydronic - 150 MBH | HM5: D305003-Cab Mount, Four Pipe - 1-1/2 ton | HN5: D305004-Baseboard Heating - 10 Ft long | HO5: D305005-208-240 volt, 25 kW | HP5: D305006-A/C Unit, Computer Room - Air Cooled, 20 ton | HS5: D306002-analog inputs, sensors (avg. 50 Ft run in 1/2 In EMT), duct temperature | HT5: D306003-air supply for pneumatic, tank mounted duplex compressor, sterter, alternat | IE5: D401001-Fire detection systems, 12 detectors | IF5: D401002-Detectors with brackets, fixed temperature heat detector | IG5: D402001-Backflow Preventer - 1 In | IH5: D402002-General | II5: D403001-Fire Hose Equipment - Fire pump, electric, for jockey pump system, add | IJ5: D404001-Deluge Systems - ordinary hazard | IL5: D405001-Extinguisher agent | IS5: D501002-Electrical Service - 3 Phase, 120/208 V, 1600 A | IT5: D501003-Buck-boost, 120/240 V primary 12/24 V secondary, 0.75 kVA | IU5: D501004-Main lugs, 120/208 V, 225 amp, NQOD | IV5: D501005-Main circuit breaker, 120/208 V, 400 amp, NQOD | IW5: D501006-Motor Control Center - Size 3, 50 HP, 24 In high | IX5: D501090-Capacitor Bank - 240 V, 10 kVAR | IZ5: D502002-Explosion Proof Lighting - Fluorescent, ceiling mounted, 3-40 W, 4 Ft L | JC5: D503002-6 outlets | JD5: D503003-50 stations | JK5: D509002-Emergency Lighting - Self-contained, fluorescent lamp pack | JU5: E101005-Unknown | JY5: E102001-Vacuum System | KJ5: E103002-Other | KL5: E103004-Automotive lifts (Hydraulic), clear floor, 2 post,15,000 lb | KZ5: E201003-Seating - Bleachers/Stadium | LN5: F102001-Prison Cell | LO5: F102002-Vehicle Inspection Pit | OU5: G204001-Fence/Privacy Wall - Metal | OV5: G204002-Metal | RS5: G309090-Unknown
A6: A101001-Strip Footing | B6: A101002-General | E6: A102001-Steel H Section | V6: A202001-Unknown | Z6: B101001-Column | AA6: B101002-Unknown | AB6: B101003-General | AH6: B102001-Column | AI6: B102002-Unknown | AJ6: B102003-Deck - Other | AM6: B201001-CIP Concrete | AR6: B201006-Unknown | AZ6: B202001-Steel Windows | BD6: B203001-Unknown | BF6: B203003-Unknown | BG6: B203004-Shutter, Rollup | BH6: B203005-Steel Sliding | BN6: B301001-Concrete Tile | BO6: B301002-Other | BP6: B301003-Lightweight Concrete Fill | BQ6: B301004-Flashings - Flashing Penetrations | BR6: B301005-Unknown | BS6: B301006-Gravity Ventilator - 12 In x 24 In | BU6: C101001-Wall - Brick | BX6: C101004-Wall Screen | BY6: C101005-Unknown | CD6: C102001-Wood Door/Metal Frame | CF6: C102003-Fire Door - Swinging | CG6: C102004-Rolling, Steel, Electric, 20 FT x 10 Ft | CH6: C102005-Wood | CK6: C102090-Rollup Grille, Aluminum, Electric, 10 FT x 10 Ft, mill finish | CM6: C103001-Shower Compartment - Fiberglass | CT6: C103008-Laminated Plastic | DC6: C201001-Exterior Stairs - Metal (24 Riser Flight) | DJ6: C301005-Paint | DM6: C302001-Porcelain Tile | DP6: C302004-Resilient Tile | DV6: C302010-Unknown | EE6: C303090-Unknown | EN6: D101002-Hydraulic Elevators - 2000 lb, 5 floors | EO6: D101003-Hydraulic Elevators - (class"B"), 20,000 lb, 5 floors | EP6: D101004-Unknown | EQ6: D101005-Manual | ER6: D101090-Other | ET6: D102002-Cranes, Bridge girder, 15 ton, 20 Ft span | EV6: D103001-20 Ft hieght, 32 In width | EW6: D103002-Ramp, 3 Ft-4 In width | EZ6: D109002-Inclined belt, 28 Ft length | FA6: D109003-Other | FI6: D201004-Laundry Sink | FJ6: D201005-Shower | FK6: D201006-Water Cooler | FM6: D201090-Stainless Steel Combo Unit (WC/Sink) | FN6: D202001-Black / Galvanized Steel >6 In Pipe | FO6: D202002-Backflow Preventer - 3 In Pipe | FP6: D202003-Booster Pump - 2 HP | FW6: D203004-Backflow Preventer - 4 In Pipe | GB6: D204003-Unknown | GL6: D301002-Gas Meter | GO6: D301005-PV Module | GR6: D301090-Unknown | GS6: D302001-Electric, Hot Water - 90-135 KW, 308-460 M | GT6: D302002-Electric, 51.6 MBH | GU6: D302003-Gas - 200 MBH | GV6: D302004-Air Separator - Air control, air separator, 2-1/2 In diameter, includes strainer | GY6: D303001-Chiller, Absorption, Gas, Water Cooled - 1000 TN | GZ6: D303002-Condenser, DX, Air Cooled - Belt Drive, 314 ton, R-22 | HB6: D304001-Dehumidifier - 16 to 20 lb./Hr., 600 CFM | HD6: D304003-Circulating Pump, Double Suction - 8 In size, 75 HP, to 2500 GPM | HG6: D304006-Circulating Pump, Double Suction - 8 In size, 75 HP, to 2500 GPM | HH6: D304007-Ceiling Vents, Passive - Passive 200-300 CFM | HI6: D304008-Central Station - 10000 CFM | HK6: D305001-Fan System, Centrifugal In-Line - 1300 CFM | HL6: D305002-Hydronic - 20 MBH | HM6: D305003-Cab Mount, Four Pipe - 2 ton | HN6: D305004-Baseboard Heating - 1-1/4 In Copper Tube | HO6: D305005-208-240 volt, 5 kW | HP6: D305006-A/C Unit, Computer Room - Air Cooled, 23 ton | HS6: D306002-analog inputs, sensors (avg. 50 Ft run in 1/2 In EMT), KW/transducer | HT6: D306003-air supply for pneumatic, tank mounted duplex compressor, sterter, alternat | IE6: D401001-Fire detection systems, 25 detectors | IF6: D401002-Detectors with brackets, ion detector (smoke) detector | IG6: D402001-Backflow Preventer - 1-1/2 In | IH6: D402002-Other | II6: D403001-Fire Hose Equipment - Fire pump, electric, w/controller, fittings, relief valve | IJ6: D404001-Dry Pipe Systems | IL6: D405001-Extinguisher agent, 200 lb FM200, container | IS6: D501002-Electrical Service - 3 Phase, 120/208 V, 200 A | IT6: D501003-Buck-boost, 120/240 V primary 12/24 V secondary, 1.0 kVA | IU6: D501004-Main lugs, 120/208 V, 225 amp, NQOD, NEMA 7 | IV6: D501005-Main circuit breaker, 120/208 V, 600 amp, NQOD | IW6: D501006-Motor Control Center - Size 4, 100 HP, 30 In high | IX6: D501090-Capacitor Bank - 240 V, 15 kVAR | IZ6: D502002-Explosion Proof Lighting - Fluorescent, ceiling mounted, 4-40 W, 4 Ft L | JC6: D503002-General | JD6: D503003-6 stations | JK6: D509002-General | KJ6: E103002-Unknown | KL6: E103004-Automotive lifts (Hydraulic), ramp style, 4 post, 25,000 lb | KZ6: E201003-Seating - Classroom | LN6: F102001-Sauna Room | OU6: G204001-Fence/Privacy Wall - Wood | OV6: G204002-Other
A7: A101001-Unknown | B7: A101002-Other | E7: A102001-Steel Pipe | V7: A202001-Wood | Z7: B101001-Column - Concrete | AB7: B101003-Other | AH7: B102001-Column - Concrete | AJ7: B102003-Deck - Steel | AM7: B201001-Concrete Block | AZ7: B202001-Unknown | BD7: B203001-Wood | BG7: B203004-Steel Rolling | BH7: B203005-Steel Vertical | BN7: B301001-Fiberglass Shingles | BO7: B301002-Polyurethane Foam | BP7: B301003-Lightweight Concrete Fill | BQ7: B301004-Flashings - Pitch Pans | BS7: B301006-Gravity Ventilator - 12 In x 36 In | BU7: C101001-Wall - Concrete Block | CD7: C102001-Wood Door/Wood Frame | CF7: C102003-Fire Door - Swinging, Metal | CG7: C102004-Rolling, Steel, Electric, 8 FT x 8 Ft | CK7: C102090-Rollup Grille, Aluminum, Manual, 10 FT x 10 Ft, bronze anodized | CM7: C103001-Shower Compartment - Glass | CT7: C103008-Metal | DC7: C201001-Exterior Stairs - Wood (12 Riser Flight) | DJ7: C301005-Unknown | DM7: C302001-Unknown | DP7: C302004-Rubber Sheet | EN7: D101002-Hydraulic Elevators - 2500 lb, 2 floors | EO7: D101003-Hydraulic Elevators - (class"B"), 3000 lb, 2 floors | EP7: D101004-Vertical | EQ7: D101005-Other | ER7: D101090-Other Hydraulic Elevators | ET7: D102002-Cranes, Bridge girder, 15 ton, 30 Ft span | EV7: D103001-20 Ft hieght, 48 In width | EW7: D103002-Unknown | EZ7: D109002-Other | FA7: D109003-Unknown | FI7: D201004-Other | FJ7: D201005-Unknown | FM7: D201090-Sump | FN7: D202001-Copper < 1 In Pipe | FO7: D202002-Backflow Preventer - 4 In Pipe | FP7: D202003-Booster Pump - 3 HP | FW7: D203004-Backflow Preventer - 6 In Pipe | GL7: D301002-General | GO7: D301005-Solar Inverter | GS7: D302001-Electric, Hot Water - 135-180 KW, 460-613 M | GT7: D302002-Electric, 68.3 MBH | GU7: D302003-Gas - 280 MBH | GV7: D302004-Air Separator - Air control, air separator, 3 In diameter, includes strainer | GY7: D303001-Chiller, Absorption, Gas, Water Cooled - 200 TN | GZ7: D303002-Condenser, DX, Air Cooled - Belt Drive, 45 ton, R-22 | HB7: D304001-Dehumidifier - 240 to 310 lb./Hr., 9000 CFM | HD7: D304003-Circulating Pump, End Suction | HG7: D304006-Circulating Pump, End Suction | HH7: D304007-Ceiling Vents, Passive - Passive 50-110 CFM | HI7: D304008-Central Station - 10000 CFM, VAV | HK7: D305001-Fan System, Centrifugal In-Line - 1500 CFM | HL7: D305002-Hydronic - 200 MBH | HM7: D305003-Cab Mount, Four Pipe - 3 ton | HN7: D305004-Baseboard Heating - 2 Ft long | HO7: D305005-208-240 volt, 7 kW | HP7: D305006-A/C Unit, Computer Room - Air Cooled, 3 ton | HS7: D306002-analog inputs, sensors (avg. 50 Ft run in 1/2 In EMT), KWH totalization ( not i | HT7: D306003-air supply for pneumatic, tank mounted duplex compressor, sterter, alternat | IE7: D401001-Fire detection systems, 50 detectors | IF7: D401002-Detectors with brackets, rate of temperature rise detector | IG7: D402001-Backflow Preventer - 2 In | IH7: D402002-Unknown | II7: D403001-Fire Hose Equipment - Fire pump, electric, with controller, 10 In pump, 300 HP, 3500 GPM, 1770 RPM | IJ7: D404001-Dry Pipe Systems - extra hazard | IL7: D405001-Extinguisher agent, 75 lb carbon dioxide cylinder | IS7: D501002-Electrical Service - 3 Phase, 120/208 V, 2000 A | IT7: D501003-Buck-boost, 120/240 V primary 12/24 V secondary, 1.5 kVA | IU7: D501004-Main lugs, 120/240 V, 100 amp, NQOD | IV7: D501005-Main circuit breaker, 120/240 V, 100 amp, NQOD | IW7: D501006-Motor Control Center - Size 4, 75 HP, 24 In high | IX7: D501090-Capacitor Bank - 240 V, 2.5 kVAR | IZ7: D502002-Explosion Proof Lighting - High pressure sodium, ceiling, pendent mounted, 100 W | JC7: D503002-Other | JD7: D503003-General | JK7: D509002-Generators | KL7: E103004-Automotive lifts (Hydraulic), ramp style, 4 post, 35,000 lb | KZ7: E201003-Unknown | LN7: F102001-Unknown | OU7: G204001-Gate | OV7: G204002-Unknown
B8: A101002-Pile Cap | E8: A102001-Treated Wood | Z8: B101001-Column - Metal | AB8: B101003-Slab - CIP Concrete | AH8: B102001-Column - Metal | AJ8: B102003-Deck - Wood | AM8: B201001-E.I.F.S. | AZ8: B202001-Vinyl Clad Windows | BG8: B203004-Steel Rolling, Electric, 10 FT x 10 Ft | BH8: B203005-Unknown | BN8: B301001-Formed Metal | BO8: B301002-Single Ply Membrane | BP8: B301003-Other | BQ8: B301004-Flashings - Step | BS8: B301006-Gravity Ventilator - 18 In diameter | BU8: C101001-Wall - Drywall w/Stud Framing | CF8: C102003-Fire Door - Swinging, Wood | CG8: C102004-Rolling, Steel, Manual, 10 FT x 10 Ft | CK8: C102090-Rollup Grille, Aluminum, Manual, 10 FT x 10 Ft, mill finish | CM8: C103001-Shower Compartment - Plastic | CT8: C103008-Other | DC8: C201001-Exterior Stairs - Wood (24 Riser Flight) | DJ8: C301005-Wallpaper | DP8: C302004-Unknown | EN8: D101002-Hydraulic Elevators - 2500 lb, 5 floors | EO8: D101003-Hydraulic Elevators - (class"B"), 3000 lb, 5 floors | EQ8: D101005-Unknown | ER8: D101090-Other Traction Geared Elevators | ET8: D102002-Cranes, Bridge girder, 15 ton, 40 Ft span | EV8: D103001-25 Ft hieght, 32 In width | EZ8: D109002-Unknown | FI8: D201004-Service Sink | FM8: D201090-Unknown | FN8: D202001-Copper 1 In-2 In Pipe | FO8: D202002-Backflow Preventer - 6 In pipe | FP8: D202003-Booster Pump - 5 HP | FW8: D203004-General | GL8: D301002-Other | GO8: D301005-Solar Panel - Aluminum Monocrystalline Silicon | GS8: D302001-Electric, Hot Water - 180-253 KW, 613-863 M | GT8: D302002-Electric, 85.3 MBH | GU8: D302003-Gas - 320 MBH | GV8: D302004-Air Separator - Air control, air separator, 4 In diameter, includes strainer | GY8: D303001-Chiller, Absorption, Gas, Water Cooled - 400 TN | GZ8: D303002-Condenser, DX, Air Cooled - Belt Drive, 471 ton, R-22 | HB8: D304001-Dehumidifier - 3 lb./Hr., 150 CFM | HD8: D304003-Circulating Pump, End Suction - 2-1/2 In size, 3 HP, to 150 GPM | HG8: D304006-Circulating Pump, End Suction - 2-1/2 In size, 3 HP, to 150 GPM | HH8: D304007-Commercial/Industrial Vacuum Dust Collection | HI8: D304008-Central Station - 15000 CFM | HK8: D305001-Fan System, Centrifugal In-Line - 2500 CFM | HL8: D305002-Hydronic - 300 MBH | HM8: D305003-Cab Mount, Two Pipe | HN8: D305004-Baseboard Heating - 3/4 In Copper Tube | HO8: D305005-480 volt, 10 kW | HP8: D305006-A/C Unit, Computer Room - Air Cooled, 5 ton | HS8: D306002-analog inputs, sensors (avg. 50 Ft run in 1/2 In EMT), space humidity, +/- 2% | HT8: D306003-boiler room combustion air, damper to 5 SF, controls | IE8: D401001-Fire detection systems, 100 detectors | IF8: D401002-Electric mechanical release | IG8: D402001-Backflow Preventer - 3 In | II8: D403001-Fire Hose Equipment - Fire pump, electric, with controller, 4 In pump, 30 HP, 500 GPM | IJ8: D404001-Dry Pipe Systems - light hazard | IL8: D405001-General | IS8: D501002-Electrical Service - 3 Phase, 120/208 V, 400 A | IT8: D501003-Buck-boost, 120/240 V primary 12/24 V secondary, 2.0 kVA | IU8: D501004-Main lugs, 120/240 V, 225 amp, NQOD | IV8: D501005-Main circuit breaker, 120/240 V, 225 amp, NQOD | IW8: D501006-Motor Control Center - Size 5, 200 HP, 48 In high | IX8: D501090-Capacitor Bank - 240 V, 20 kVAR | IZ8: D502002-Explosion Proof Lighting - Incandescent, ceiling mounted, 200 W | JC8: D503002-Unknown | JD8: D503003-Other | JK8: D509002-Generators - Diesel, 100 kW | KL8: E103004-Automotive lifts (Hydraulic), ramp style, 4 post, 50,000 lb | OU8: G204001-Gate - Metal | OV8: G204002-Wood
B9: A101002-Spread Footing | E9: A102001-Unknown | Z9: B101001-Column - Wood | AB9: B101003-Slab - Precast Concrete | AH9: B102001-Column - Wood | AJ9: B102003-General | AM9: B201001-Fiber Cement Siding | AZ9: B202001-Wood Windows | BG9: B203004-Steel Rolling, Electric, 12 FT x 12 Ft | BH9: B203005-Wood | BN9: B301001-Formed Metal - Metal Standing Seam | BO9: B301002-Unknown | BP9: B301003-Perlite Fill | BQ9: B301004-Flashings - Valley | BS9: B301006-Gravity Ventilator - 20 In x 72 In | BU9: C101001-Wall - Glass Block | CF9: C102003-General | CG9: C102004-Rolling, Steel, Manual, 12 FT x 12 Ft | CK9: C102090-Rollup Grille, Steel, Electric, 10 FT x 10 Ft | CM9: C103001-Shower Compartment - Stainless Steel | CT9: C103008-Stone | DC9: C201001-Exterior Steps | DJ9: C301005-Wood | DP9: C302004-Vinyl Tile | EN9: D101002-Hydraulic Elevators - 3000 lb, 2 floors | EO9: D101003-Hydraulic Elevators - (class"B"), 4000 lb, 2 floors | ER9: D101090-Other Traction Gearless Elevators | ET9: D102002-Cranes, Bridge girder, 15 ton, 50 Ft span | EV9: D103001-25 Ft hieght, 48 In width | FI9: D201004-Stainless | FM9: D201090-Washer / Dryer Hookup | FN9: D202001-Copper 2 In-4 In Pipe | FO9: D202002-Backflow Preventer - 8 In pipe | FP9: D202003-Booster Pump - 7.5 HP | FW9: D203004-Other | GL9: D301002-Unknown | GO9: D301005-Solar Panel - Aluminum Polycrystalline Silicon | GS9: D302001-Electric, Hot Water - 253-370 KW, 863-1263 | GT9: D302002-Gas, 100 MBH | GU9: D302003-Gas - 60 MBH | GV9: D302004-Air Separator - Air control, air separator, 5 In diameter, includes strainer | GY9: D303001-Chiller, Absorption, Gas, Water Cooled - 5 TN | GZ9: D303002-Condenser, DX, Air Cooled - Belt Drive, 50 ton, R-22 | HB9: D304001-Dehumidifier - 30 to 40 lb./Hr., 1125 CFM | HD9: D304003-Circulating Pump, End Suction - 3 In size, 5 HP, to 225 GPM | HG9: D304006-Circulating Pump, End Suction - 3 In size, 5 HP, to 225 GPM | HH9: D304007-Commercial/Industrial Vacuum Dust Collection - 1000 CFM | HI9: D304008-Central Station - 15000 CFM, VAV | HK9: D305001-Fan System, Centrifugal In-Line - 3500 CFM | HL9: D305002-Hydronic - 60 MBH | HM9: D305003-Cab Mount, Two Pipe - 1 ton | HN9: D305004-Baseboard Heating - 6 Ft long | HO9: D305005-480 volt, 13 kW | HP9: D305006-A/C Unit, Computer Room - Air Cooled, 8 ton | HS9: D306002-analog inputs, sensors (avg. 50 Ft run in 1/2 In EMT), space static pressure | HT9: D306003-compensated hot water from boiler, valve control, readout / reset at panel, 120 GPM | IE9: D401001-General | IF9: D401002-General | IG9: D402001-Backflow Preventer - 4 In | II9: D403001-Fire Hose Equipment - Fire pump, electric, with controller, 5 In pump, 100 HP, 1000 GPM | IJ9: D404001-Dry Pipe Systems - ordinary hazard | IL9: D405001-Other | IS9: D501002-Electrical Service - 3 Phase, 120/208 V, 60 A | IT9: D501003-Buck-boost, 120/240 V primary 12/24 V secondary, 3.0 kVA | IU9: D501004-Main lugs, 125 amp | IV9: D501005-Main circuit breaker, 120/240 V, 400 amp, NQOD | IW9: D501006-Motor Control Center - Size 6, 400 HP, 72 In high | IX9: D501090-Capacitor Bank - 240 V, 25 kVAR | IZ9: D502002-Explosion Proof Lighting - Metal halide, ceiling, pendent mounted, 200 W | JD9: D503003-Unknown | JK9: D509002-Generators - Diesel, 1000 kW | KL9: E103004-Automotive lifts (Hydraulic), ramp style, 4 post, 75,000 lb | OU9: G204001-Gate - Wood
