Workbook

Sheet 1-Service Provider Info
A1: ATTACHMENT J-0200000-09 SERVICE PROVIDER INFORMATION
A3: Interface: Service Provider
A4: VERSION #: | B4: v3
A5: Current as of: | B5: 3 December 2015
A9: Version History
A10: v1 - Updated to reflect current interface in MAXIMO
A11: v2 - Update to reflect addition of Utility Outage Reporting information & Support GL Account Import
A12: v3 - Update to reflect addition of additional remarks field.[In sync with NITC R2 Interface Document]
A23: TABS
A24: 1-Service Provider Info | B24: This Sheet
A25: 2-Service Provider Field List | B25: Service Provider Template Data Format Information
A26: 3-Service Provider - Template | B26: Sample Excel Format

Sheet 2-Service Provider Field List
A1: ATTACHMENT J-0200000-09 SERVICE PROVIDER INFORMATION
A3: =+'1-Service Provider Info'!A3 -> Interface: Service Provider
A4: =CONCATENATE('1-Service Provider Info'!A4," ",'1-Service Provider Info'!B4) -> VERSION #: v3
A5: =CONCATENATE('1-Service Provider Info'!A5," ",'1-Service Provider Info'!B5) -> Current as of: 3 December 2015
A6: Service Provider (BOSC1) is a pipe delimited file.
A7: Position | B7: Name | C7: Length Limit | D7: Data Format Note | E7: Field Definition | F7: Content Notes | G7: NAVFAC MAXIMO_FIELD (WORKORDER.)
A8: 1 | B8: Approved Date | C8: 10 | D8: MM/DD/YYYY hh:mm:ss | E8: The Date on which the Work Order was last approved. If the file contains an Approved Date, then this date will be pulled over to the record. If the Approved Date in the file is null, then the Reported Date plus one minute will be displayed in the record. | F8: will default when upload if left blank | G8: APPROVEDDATE
A9: =+A8+1 -> 2 | B9: Work Type | C9: 15 | D9: Must match Value List in Maximo. (Cross-walked field.). Must match Crosswalk | E9: Identifies the work order's type. Example types are: preventive maintenance, corrective maintenance, emergency maintenance, capital project, and event report. | F9: PM is used for all scheduled work PROJECT for IMP repairs | G9: WORKTYPE
A10: =+A9+1 -> 3 | B10: Service Provider Reference Code | C10: 10 | E10: Contractors internal work order tracking number. Will update Record if Value is found in Maximo otherwise new record (Work order) will be created. | F10: * will delete if left blank when a work order is updated or completed. | G10: SERVPRVREFCODE
A11: =+A10+1 -> 4 | B11: Description | C11: 150 | E11: Describes the work order. If the Description is null, in the inbound file, then this field is defaulted to CROSSWALK value. | F11: will create a default entry if left blank on update: "Entered by SP FlatFile BOSC interface. No description provided." Include contractor job plan number in the descriptionInclude PM job plan and frequency. ie QUARTERLY PM JOB PLAN 1234. Or describe work performed ie Replace AHU fan motor and belt. | G11: DESCRIPTION
A12: =+A11+1 -> 5 | B12: Location | C12: 30 | D12: Must match Value List in Maximo | E12: Identifies the work order's location. This is not necessarily the asset's location, however, if an asset is entered, its location will default here. - If the Location is null, in the inbound file, then this field is defaulted to the site's base location. | F12: * Location is not required if the record has an asset #. Most records originating from the contractor system would be for maintenance on an asset # so this field can be left blank. If populated, the location must exist in NAVFAC MAXIMO or the record will be rejected. | G12: LOCATION
A13: =+A12+1 -> 6 | B13: Reported By | C13: 62 | D13: Must match Value List in Maximo | E13: Identifies the person reporting the work order. | F13: Leave blank on flat file; auto-populates by direct entry. | G13: REPORTEDBY
A14: =+A13+1 -> 7 | B14: Master System | C14: N/A | D14: Not used | F14: Will pull from asset number. | G14: N/A
A15: =+A14+1 -> 8 | B15: Status | C15: 16 | D15: (Cross-walked field.) Must match Crosswalk | E15: Status of the work order, for example, in progress, waiting on material, waiting for approval, completed, or closed. | F15: Value list in REFERENCE SPREADSHEET | G15: STATUS
A16: =+A15+1 -> 9 | B16: Status Date | C16: 10 | D16: MM/DD/YYYY hh:mm:ss | F16: Leave blank on flat file; auto-populates by direct entry. | G16: STATUSDATE
A17: =+A16+1 -> 10 | B17: Priority | C17: 12 | D17: (Cross-walked field.) Must match Crosswalk | E17: Identifies the importance of the work order, from 0-999, where 0 is the lowest priority and 999 is the highest. If the Priority is null, in the inbound file, then this field is defaulted. | F17: Leave blank on flat file unless local direction is provided | G17: WOPRIORITY
A18: =+A17+1 -> 11 | B18: Actual Start | C18: 10 | D18: MM/DD/YYYY hh:mm:ss | F18: Format is important | G18: ACTSTART
A19: =+A18+1 -> 12 | B19: Actual Finish | C19: 10 | D19: MM/DD/YYYY hh:mm:ss | F19: Format is important | G19: ACTFINISH
A20: =+A19+1 -> 13 | B20: Supervisor | C20: 30 | D20: Must match Value List in Maximo | F20: Leave blank; if used, must match a MAXIMO user | G20: SUPERVISOR
A21: =+A20+1 -> 14 | B21: Labor Hours(Actual) | C21: 8 | D21: Number (2 decimal places) | F21: required to change status to COMP | G21: ACTLABHRS
A22: =+A21+1 -> 15 | B22: Labor Cost(Actual) | C22: 10 | D22: Number (2 decimal places) | F22: required to change status to COMP | G22: ACTLABCOST
A23: =+A22+1 -> 16 | B23: Material Cost(Actual) | C23: 10 | D23: Number (2 decimal places) | F23: required to change status to COMP | G23: ACTMATCOST
A24: =+A23+1 -> 17 | B24: Duration | C24: 8 | D24: Number (2 decimal places) | E24: Estimated remaining number of hours needed to complete the work. | F24: May be left blank | G24: ESTDUR
A25: =+A24+1 -> 18 | B25: Asset | C25: 25 | D25: Must match an existing ASSETNUM in Maximo | E25: The asset number used must exist in NAVFAC MAXIMO prior to submission, or the record will be rejected. | F25: The asset number used must exist in NAVFAC MAXIMO prior to submission, or the record will be rejected. | G25: ASSETNUM
A26: =+A25+1 -> 19 | B26: Target Finish | C26: 10 | D26: MM/DD/YYYY hh:mm:ss | E26: For contractor scheduled work Target Finish is calculated using the Frequency of Service in J-0200000-01. For IMP system breakdowns the Target Finish is 2 days from the date the work was reported to the Contractor For E/U/R the Target Finish date is calculated from the date the work was reported to the Contractor. | F26: Required to create the work order | G26: TARGCOMPDATE
A27: =+A26+1 -> 20 | B27: Target Start | C27: 10 | D27: MM/DD/YYYY hh:mm:ss | E27: For contractor scheduled work Target Start is calculated using the Frequency of Service in J-0200000-01. For IMP system breakdowns the Target Start is the date the work was reported to the Contractor For E/U/R the Target Start date is calculated from the date the work was reported to the Contractor. | F27: Required to create the work order. | G27: TARGSTARTDATE
A28: =+A27+1 -> 21 | B28: Reported Date | C28: 10 | D28: MM/DD/YYYY hh:mm:ss | F28: Leave blank on flat file; auto-populates by direct entry. | G28: REPORTDATE
A29: =+A28+1 -> 22 | B29: Lead | C29: 30 | D29: Must match Value List in Maximo | E29: Lead person responsible for the work. | F29: Leave blank; if used, must match a MAXIMO user | G29: LEAD
A30: =+A29+1 -> 23 | B30: Scheduled Start | C30: 10 | D30: MM/DD/YYYY hh:mm:ss | E30: Scheduled start should be between the target start and target completion date | F30: Required if status change to inprogress or approved | G30: SCHEDSTART
A31: =+A30+1 -> 24 | B31: Scheduled Finish | C31: 10 | D31: MM/DD/YYYY hh:mm:ss | E31: Scheduled finish should be between the target start and target completion date | F31: Required if status change to inprogress or approved | G31: SCHEDFINISH
A32: =+A31+1 -> 25 | B32: Modified Date | C32: 10 | D32: LEAVE BLANK | E32: Leave blank/Do Not Use | F32: Leave blank/Do Not Use | G32: CHANGEDATE
A33: =+A32+1 -> 26 | B33: Modified By | C33: 30 | D33: LEAVE BLANK | E33: Leave blank/Do Not Use | F33: Leave blank/Do Not Use | G33: CHANGEBY
A34: =+A33+1 -> 27 | B34: N/A | C34: 4 | D34: MM/DD/YYYY hh:mm:ss | E34: N a should be between the target start and target completion date | F34: Placeholder for WORKORDER.PMNEXTDUEDATE. Value is not presently imported. | G34: PMNEXTDUEDATE
A35: =+A34+1 -> 28 | B35: N/A | C35: 1 | E35: Yes or No | F35: Use "N" or leave blank | G35: ISTASK
A36: =+A35+1 -> 29 | B36: N/A | C36: 10 | D36: Length Limit: 250 | E36: Must exist in NAVFAC MAXIMO prior to submission or the record will be rejected. | F36: Must exist in NAVFAC MAXIMO prior to submission or the record will be rejected. | G36: PARENT
A37: =+A36+1 -> 30 | B37: Work Order | C37: 10 | D37: Must match Value List in Maximo | E37: Used in updating record status on existing records. | F37: Not required if the record has a Service Provider Reference Code, otherwise must match the MAXIMO work order | G37: WONUM
A38: =+A37+1 -> 31 | B38: Detail Location | C38: 250 | E38: Detail location should be between the target start and target completion date | F38: leave blank; will pull from asset number | G38: DETAILLOC
A39: =+A38+1 -> 32 | B39: CLIN | C39: 30 | E39: Contract Line Item Number | F39: Value list in ELINs Tab | G39: CLIN
A40: =+A39+1 -> 33 | B40: Customer Ref Code | C40: 8 | D40: Must match Value List in Maximo | E40: Leave blank unless Requirements provides reference list. | F40: May be blank; if used, must match a code in MAXIMO | G40: CUSTOMERCODE
A41: =+A40+1 -> 34 | B41: Sub Work Type | C41: 15 | D41: (Cross-walked field). Must match Crosswalk | E41: Defaulted field based on the value of worktype | F41: FACILITIES for scheduled work in Annex 1502000 UTILITIES for scheduled work in any Annex 16 sub-annex FPCT for IMP repairs under the limit of liability | G41: SUBWORKTYPE
A42: =+A41+1 -> 35 | B42: Work Center | C42: 8 | D42: Must match Value List in Maximo | E42: Work center should be between the target start and target completion date | F42: For this contract use MYP_CTR1 Do not leave blank or will assign to CHR_CTR. | G42: PERSONGROUP
A43: 36 | B43: GL Account | C43: 27 | D43: Must be a complete GL account or will imported as NULL | E43: Only full GL Account, including delimiters, values can be imported. | F43: Use "S.N69450.NX.TRACKNSTXXXXXXXX" for all work orders. changes every FY | G43: GLACCOUNT | H43: This will need the new fiscal year GL account number
A44: 37 | B44: Outage Type | C44: 50 | D44: ALN | E44: Type of utility outage | F44: May be blank. The “Outage Type” value must be a valid value available in the “OUTTYPE” domain. | G44: OUTAGETYPE
A45: 38 | B45: Outage Cause | C45: 50 | D45: ALN | E45: Cause of utility outage | F45: May be blank. The “Outage Cause” value must be a valid value available in the “OUTCAUSE” domain. | G45: OUTAGEREASON
A46: 39 | B46: Num of Bldgs Affected | C46: 12 | D46: Integer | E46: Number of Building affected (whole number) | F46: May be blank | G46: NUMBLDSAFFECTED
A47: 40 | B47: Outage Start Date | C47: 10 | D47: MM/DD/YYYY hh:mm:ss | E47: Outage Start (Date/Time) | F47: May be blank. The “Outage Start Date” value must be m valid value available in the “OUTDATE” domain. | G47: OUTAGESTARTDATE
A48: 41 | B48: Outage End Date | C48: 10 | D48: MM/DD/YYYY hh:mm:ss | E48: Outage End (Date/Time) | F48: May be blank. The “Outage End Date” value must be m valid value available in the “OUTDATE” domain. | G48: OUTAGEENDDATE
A49: 42 | B49: Remarks | C49: 1000 | D49: ALN | E49: Additional remarks. At each submission the remarks are appended to the END of previous remarks. /// Use and Style is a CONTRACT SPECIFIC USE /// | F49: Each remark submission is restricted to 1000 characters, and the DATE will be appended in Maximo prior saving. This can be used (local/contract specific guidance) to provide a chronology to the work order. Resulting format would be: DATE1 - Remark1; DATE2 - Remark2; etc. The total field length is restricted to <2000 characters - or a maximum of 11-12 remarks on a single Work Order. The following information shall be provided if it is relevant: 1. Name and phone number of all Government personnel with whom the work was coordinated or provided clarificaiton to the technician, and date KO was notified of any problems scheduling the work or accessing the location. 2. A narrative of work performed and technicians observations. 3. The estimated cost and date notification of work exceeding LOL was submitted to the KO. | G49: LONGDESCRIPTION

Sheet 3-Service Provider-Template
A1: ATTACHMENT J-0200000-09 SERVICE PROVIDER INFORMATION | T1: ATTACHMENT J-0200000-XX SERVICE PROVIDER INFORMATION
A3: =+'1-Service Provider Info'!A3 -> Interface: Service Provider
A4: =CONCATENATE('1-Service Provider Info'!A4," ",'1-Service Provider Info'!B4) -> VERSION #: v3
A5: =CONCATENATE('1-Service Provider Info'!A5," ",'1-Service Provider Info'!B5) -> Current as of: 3 December 2015
A7: Position | B7: 1 | C7: 2 | D7: 3 | E7: 4 | F7: 5 | G7: 6 | H7: 7 | I7: 8 | J7: 9 | K7: 10 | L7: 11 | M7: 12 | N7: 13 | O7: 14 | P7: 15 | Q7: 16 | R7: 17 | S7: 18 | T7: 19 | U7: 20 | V7: 21 | W7: 22 | X7: 23 | Y7: 24 | Z7: 25 | AA7: 26 | AB7: 27 | AC7: 28 | AD7: 29 | AE7: 30 | AF7: 31 | AG7: 32 | AH7: 33 | AI7: 34 | AJ7: 35 | AK7: 36 | AL7: 37 | AM7: 38 | AN7: 39 | AO7: 40 | AP7: 41 | AQ7: 42
A8: Name | B8: Approved Date | C8: Work Type | D8: Service Provider Reference Code | E8: Description | F8: Location | G8: Reported By | H8: Master System | I8: Status | J8: Status Date | K8: Priority | L8: Actual Start | M8: Actual Finish | N8: Supervisor | O8: Labor Hours (Actual) | P8: Labor Cost (Actual) | Q8: Material Cost (Actual) | R8: Duration | S8: Asset | T8: Target Finish | U8: Target Start | V8: Reported Date | W8: Lead | X8: Scheduled Start | Y8: Scheduled Finish | Z8: Modified Date | AA8: Modified By | AB8: PMNEXTDUEDATE | AC8: Is Task? | AD8: Parent WO | AE8: Work Order | AF8: Detail Location | AG8: CLIN | AH8: Customer Ref Code | AI8: Sub Work Type | AJ8: Work Center | AK8: GL Account | AL8: Outage Type | AM8: Outage Cause | AN8: Num of Bldgs Affected | AO8: Outage Start Date | AP8: Outage End Date | AQ8: Remarks
A9: Validation tool | F9: Y | I9: Y | S9: Y | AG9: Y | AH9: Y
A10: REQUIRED TO CREATE WO | B10: N | C10: Y* | D10: Y | E10: Y | F10: Y* | G10: N | H10: N | I10: Y | J10: N | K10: N | L10: N | M10: N | N10: N | O10: N | P10: N | Q10: N | R10: N | S10: Y | T10: Y | U10: Y | V10: N | W10: N | X10: N | Y10: N | Z10: N | AA10: N | AB10: N | AC10: N | AD10: N | AE10: N | AF10: N | AG10: Y | AH10: N | AI10: Y* | AJ10: Y | AK10: Y | AL10: N | AM10: N | AN10: N | AO10: N | AP10: N | AQ10: N*
A11: REQUIRED TO UPDATE WO | B11: N | C11: Y* | D11: Y* | E11: Y | F11: N | G11: N | H11: N | I11: N | J11: N | K11: N | L11: N | M11: N | N11: N | O11: N | P11: N | Q11: N | R11: N | S11: Y | T11: N | U11: N | V11: N | W11: N | X11: Y* | Y11: Y* | Z11: N | AA11: N | AB11: N | AC11: N | AD11: N | AE11: N | AF11: N | AG11: N | AH11: N | AI11: Y* | AJ11: Y | AK11: Y | AL11: N | AM11: N | AN11: N | AO11: N | AP11: N | AQ11: N*
A12: REQUIRED TO COMP WO | B12: N | C12: Y* | D12: Y* | E12: Y | F12: N | G12: N | H12: N | I12: Y | J12: N | K12: N | L12: Y | M12: Y | N12: N | O12: Y* | P12: Y* | Q12: Y* | R12: N | S12: Y | T12: N | U12: N | V12: N | W12: N | X12: N | Y12: N | Z12: N | AA12: N | AB12: N | AC12: N | AD12: N | AE12: N | AF12: N | AG12: N | AH12: N | AI12: Y* | AJ12: Y | AK12: Y | AL12: N | AM12: N | AN12: N | AO12: N | AP12: N | AQ12: Y*
